; Auto-generated by icon_emit_jvm.c — Tiny-ICON Byrd Box JVM
.bytecode 45.0
.class public queens
.super java/lang/Object

.field public static icn_failed B
.field public static icn_suspended B
.field public static icn_suspend_id I
.field public static icn_retval_obj Ljava/lang/Object;
.field public static icn_retval J
.field public static icn_retval_str Ljava/lang/String;
.field public static icn_pv_show_sep Ljava/lang/String;
.field public static icn_gvar_sep Ljava/lang/String;
.field public static icn_pv_show_line Ljava/lang/String;
.field public static icn_gvar_line Ljava/lang/String;
.field public static icn_3_relop_lc Ljava/lang/String;
.field public static icn_3_relop_rc Ljava/lang/String;
.field public static icn_5_sub_s Ljava/lang/String;
.field public static icn_5_sub_i I
.field public static icn_6_binop_lc J
.field public static icn_6_binop_rc J
.field public static icn_6_binop_bf I
.field public static icn_8_binop_lc J
.field public static icn_8_binop_rc J
.field public static icn_8_binop_bf I
.field public static icn_pv_safe_c J
.field public static icn_pv_safe_r J
.field public static icn_gvar_down J
.field public static icn_14_relop_lc Ljava/lang/String;
.field public static icn_14_relop_rc Ljava/lang/String;
.field public static icn_16_sub_s Ljava/lang/String;
.field public static icn_16_sub_i I
.field public static icn_17_binop_lc J
.field public static icn_17_binop_rc J
.field public static icn_17_binop_bf I
.field public static icn_19_binop_lc J
.field public static icn_19_binop_rc J
.field public static icn_19_binop_bf I
.field public static icn_gvar_n J
.field public static icn_gvar_up J
.field public static icn_25_relop_lc Ljava/lang/String;
.field public static icn_25_relop_rc Ljava/lang/String;
.field public static icn_27_sub_s Ljava/lang/String;
.field public static icn_27_sub_i I
.field public static icn_gvar_rows J
.field public static icn_39_lc Ljava/lang/String;
.field public static icn_39_rc Ljava/lang/String;
.field public static icn_46_lsa_l Ljava/util/ArrayList;
.field public static icn_46_lsa_i J
.field public static icn_46_lsa_v Ljava/lang/String;
.field public static icn_47_binop_lc J
.field public static icn_47_binop_rc J
.field public static icn_47_binop_bf I
.field public static icn_49_binop_lc J
.field public static icn_49_binop_rc J
.field public static icn_49_binop_bf I
.field public static icn_50_binop_lc J
.field public static icn_50_binop_rc J
.field public static icn_50_binop_bf I
.field public static icn_52_sub_s Ljava/lang/String;
.field public static icn_52_sub_i I
.field public static icn_pv_show_col J
.field public static icn_gvar_placed J
.field public static icn_60_I J
.field public static icn_60_bound J
.field public static icn_60_e1cur J
.field public static icn_60_e2seen I
.field public static icn_60_e1val J
.field public static icn_60_e2val J
.field public static icn_gvar_qcount J
.field public static icn_70_binop_lc J
.field public static icn_70_binop_rc J
.field public static icn_70_binop_bf I
.field public static icn_72_binop_lc J
.field public static icn_72_binop_rc J
.field public static icn_72_binop_bf I
.field public static icn_75_augtemp J
.field public static icn_pv_try_col_r J
.field public static icn_82_lsa_l Ljava/util/ArrayList;
.field public static icn_82_lsa_i J
.field public static icn_82_lsa_v J
.field public static icn_pv_try_col_c J
.field public static icn_86_lsa_l Ljava/util/ArrayList;
.field public static icn_86_lsa_i J
.field public static icn_86_lsa_v J
.field public static icn_90_lsa_l Ljava/util/ArrayList;
.field public static icn_90_lsa_i J
.field public static icn_90_lsa_v J
.field public static icn_91_binop_lc J
.field public static icn_91_binop_rc J
.field public static icn_91_binop_bf I
.field public static icn_93_binop_lc J
.field public static icn_93_binop_rc J
.field public static icn_93_binop_bf I
.field public static icn_98_lsa_l Ljava/util/ArrayList;
.field public static icn_98_lsa_i J
.field public static icn_98_lsa_v J
.field public static icn_99_binop_lc J
.field public static icn_99_binop_rc J
.field public static icn_99_binop_bf I
.field public static icn_101_binop_lc J
.field public static icn_101_binop_rc J
.field public static icn_101_binop_bf I
.field public static icn_105_binop_lc J
.field public static icn_105_binop_rc J
.field public static icn_105_binop_bf I
.field public static icn_arg_0 J
.field public static icn_110_lsa_l Ljava/util/ArrayList;
.field public static icn_110_lsa_i J
.field public static icn_110_lsa_v J
.field public static icn_114_lsa_l Ljava/util/ArrayList;
.field public static icn_114_lsa_i J
.field public static icn_114_lsa_v J
.field public static icn_115_binop_lc J
.field public static icn_115_binop_rc J
.field public static icn_115_binop_bf I
.field public static icn_117_binop_lc J
.field public static icn_117_binop_rc J
.field public static icn_117_binop_bf I
.field public static icn_122_lsa_l Ljava/util/ArrayList;
.field public static icn_122_lsa_i J
.field public static icn_122_lsa_v J
.field public static icn_123_binop_lc J
.field public static icn_123_binop_rc J
.field public static icn_123_binop_bf I
.field public static icn_125_binop_lc J
.field public static icn_125_binop_rc J
.field public static icn_125_binop_bf I
.field public static icn_arg_1 J
.field public static icn_132_I J
.field public static icn_132_bound J
.field public static icn_132_e1cur J
.field public static icn_132_e2seen I
.field public static icn_132_e1val J
.field public static icn_132_e2val J
.field public static icn_139_relop_lc J
.field public static icn_139_relop_rc J
.field public static icn_153_ln J
.field public static icn_153_lx Ljava/lang/Object;
.field public static icn_153_ll Ljava/util/ArrayList;
.field public static icn_153_lc I
.field public static icn_154_binop_lc J
.field public static icn_154_binop_rc J
.field public static icn_154_binop_bf I
.field public static icn_156_binop_lc J
.field public static icn_156_binop_rc J
.field public static icn_156_binop_bf I
.field public static icn_161_ln J
.field public static icn_161_lx Ljava/lang/Object;
.field public static icn_161_ll Ljava/util/ArrayList;
.field public static icn_161_lc I
.field public static icn_162_binop_lc J
.field public static icn_162_binop_rc J
.field public static icn_162_binop_bf I
.field public static icn_164_binop_lc J
.field public static icn_164_binop_rc J
.field public static icn_164_binop_bf I
.field public static icn_169_ln J
.field public static icn_169_lx Ljava/lang/Object;
.field public static icn_169_ll Ljava/util/ArrayList;
.field public static icn_169_lc I
.field public static icn_173_ln J
.field public static icn_173_lx Ljava/lang/Object;
.field public static icn_173_ll Ljava/util/ArrayList;
.field public static icn_173_lc I
.field public static icn_177_alt_gate I
.field public static icn_180_sub_s Ljava/lang/String;
.field public static icn_180_sub_i I
.field public static icn_pv_main_args J
.field public static icn_177_alt_val J

.method public static main([Ljava/lang/String;)V
    .limit stack 4
    .limit locals 1
    invokestatic queens/icn_main()V
    return
.end method

.method public static icn_builtin_left(Ljava/lang/String;ILjava/lang/String;)Ljava/lang/String;
    .limit stack 4
    .limit locals 5
    aload_0
    invokevirtual java/lang/String/length()I
    iload_1
    if_icmplt icn_left_pad
    aload_0
    iconst_0
    iload_1
    invokevirtual java/lang/String/substring(II)Ljava/lang/String;
    areturn
icn_left_pad:
    new java/lang/StringBuilder
    dup
    aload_0
    invokespecial java/lang/StringBuilder/<init>(Ljava/lang/String;)V
    astore_3
icn_left_loop:
    aload_3
    invokevirtual java/lang/StringBuilder/length()I
    iload_1
    if_icmpge icn_left_done
    aload_3
    aload_2
    iconst_0
    invokevirtual java/lang/String/charAt(I)C
    invokevirtual java/lang/StringBuilder/append(C)Ljava/lang/StringBuilder;
    pop
    goto icn_left_loop
icn_left_done:
    aload_3
    invokevirtual java/lang/StringBuilder/toString()Ljava/lang/String;
    areturn
.end method

.method public static icn_builtin_right(Ljava/lang/String;ILjava/lang/String;)Ljava/lang/String;
    .limit stack 4
    .limit locals 5
    aload_0
    invokevirtual java/lang/String/length()I
    iload_1
    if_icmplt icn_right_pad
    aload_0
    invokevirtual java/lang/String/length()I
    iload_1
    isub
    aload_0
    swap
    invokevirtual java/lang/String/substring(I)Ljava/lang/String;
    areturn
icn_right_pad:
    new java/lang/StringBuilder
    dup
    invokespecial java/lang/StringBuilder/<init>()V
    astore_3
    iload_1
    aload_0
    invokevirtual java/lang/String/length()I
    isub
    istore 4
    iconst_0
icn_right_loop:
    dup
    iload 4
    if_icmpge icn_right_append
    aload_3
    aload_2
    iconst_0
    invokevirtual java/lang/String/charAt(I)C
    invokevirtual java/lang/StringBuilder/append(C)Ljava/lang/StringBuilder;
    pop
    iconst_1
    iadd
    goto icn_right_loop
icn_right_append:
    pop
    aload_3
    aload_0
    invokevirtual java/lang/StringBuilder/append(Ljava/lang/String;)Ljava/lang/StringBuilder;
    pop
    aload_3
    invokevirtual java/lang/StringBuilder/toString()Ljava/lang/String;
    areturn
.end method

.method public static icn_builtin_center(Ljava/lang/String;ILjava/lang/String;)Ljava/lang/String;
    .limit stack 5
    .limit locals 7
    aload_0
    invokevirtual java/lang/String/length()I
    iload_1
    if_icmplt icn_ctr_pad
    aload_0
    iconst_0
    iload_1
    invokevirtual java/lang/String/substring(II)Ljava/lang/String;
    areturn
icn_ctr_pad:
    iload_1
    aload_0
    invokevirtual java/lang/String/length()I
    isub
    istore_3
    iload_3
    iconst_2
    idiv
    istore 4
    iload_3
    iload 4
    isub
    istore 5
    new java/lang/StringBuilder
    dup
    invokespecial java/lang/StringBuilder/<init>()V
    astore 6
    iconst_0
icn_ctr_lloop:
    dup
    iload 4
    if_icmpge icn_ctr_mid
    aload 6
    aload_2
    iconst_0
    invokevirtual java/lang/String/charAt(I)C
    invokevirtual java/lang/StringBuilder/append(C)Ljava/lang/StringBuilder;
    pop
    iconst_1
    iadd
    goto icn_ctr_lloop
icn_ctr_mid:
    pop
    aload 6
    aload_0
    invokevirtual java/lang/StringBuilder/append(Ljava/lang/String;)Ljava/lang/StringBuilder;
    pop
    iconst_0
icn_ctr_rloop:
    dup
    iload 5
    if_icmpge icn_ctr_done
    aload 6
    aload_2
    iconst_0
    invokevirtual java/lang/String/charAt(I)C
    invokevirtual java/lang/StringBuilder/append(C)Ljava/lang/StringBuilder;
    pop
    iconst_1
    iadd
    goto icn_ctr_rloop
icn_ctr_done:
    pop
    aload 6
    invokevirtual java/lang/StringBuilder/toString()Ljava/lang/String;
    areturn
.end method

.method public static icn_builtin_trim(Ljava/lang/String;Ljava/lang/String;)Ljava/lang/String;
    .limit stack 4
    .limit locals 3
    aload_0
    invokevirtual java/lang/String/length()I
    istore_2
icn_trim_loop:
    iload_2
    ifle icn_trim_done
    aload_1
    aload_0
    iload_2
    iconst_1
    isub
    invokevirtual java/lang/String/charAt(I)C
    invokevirtual java/lang/String/indexOf(I)I
    iflt icn_trim_done
    iinc 2 -1
    goto icn_trim_loop
icn_trim_done:
    aload_0
    iconst_0
    iload_2
    invokevirtual java/lang/String/substring(II)Ljava/lang/String;
    areturn
.end method

.method public static icn_builtin_map(Ljava/lang/String;Ljava/lang/String;Ljava/lang/String;)Ljava/lang/String;
    .limit stack 5
    .limit locals 7
    new java/lang/StringBuilder
    dup
    invokespecial java/lang/StringBuilder/<init>()V
    astore_3
    iconst_0
    istore 4
icn_map_loop:
    iload 4
    aload_0
    invokevirtual java/lang/String/length()I
    if_icmpge icn_map_done
    aload_0
    iload 4
    invokevirtual java/lang/String/charAt(I)C
    istore 5
    aload_1
    iload 5
    invokevirtual java/lang/String/indexOf(I)I
    istore 6
    iload 6
    iflt icn_map_notfound
    iload 6
    aload_2
    invokevirtual java/lang/String/length()I
    if_icmpge icn_map_notfound
    aload_3
    aload_2
    iload 6
    invokevirtual java/lang/String/charAt(I)C
    invokevirtual java/lang/StringBuilder/append(C)Ljava/lang/StringBuilder;
    pop
    goto icn_map_next
icn_map_notfound:
    aload_3
    iload 5
    invokevirtual java/lang/StringBuilder/append(C)Ljava/lang/StringBuilder;
    pop
icn_map_next:
    iinc 4 1
    goto icn_map_loop
icn_map_done:
    aload_3
    invokevirtual java/lang/StringBuilder/toString()Ljava/lang/String;
    areturn
.end method

.method public static icn_builtin_parse_long(Ljava/lang/String;)J
    .limit stack 4
    .limit locals 4
    .catch java/lang/Exception from icn_plong_L0 to icn_plong_L1 using icn_plong_catch
icn_plong_L0:
    aload_0
    invokevirtual java/lang/String/trim()Ljava/lang/String;
    astore_1
    aload_1
    ldc "r"
    invokevirtual java/lang/String/contains(Ljava/lang/CharSequence;)Z
    ifeq icn_plong_plain
    aload_1
    ldc "r"
    iconst_2
    invokevirtual java/lang/String/split(Ljava/lang/String;I)[Ljava/lang/String;
    astore_2
    aload_2
    iconst_0
    aaload
    invokestatic java/lang/Integer/parseInt(Ljava/lang/String;)I
    istore_3
    aload_2
    iconst_1
    aaload
    iload_3
    invokestatic java/lang/Long/parseLong(Ljava/lang/String;I)J
    goto icn_plong_L1
icn_plong_plain:
    aload_1
    invokestatic java/lang/Long/parseLong(Ljava/lang/String;)J
icn_plong_L1:
    lreturn
icn_plong_catch:
    pop
    ldc2_w -9223372036854775808
    lreturn
.end method

.method public static icn_builtin_numeric(Ljava/lang/String;)J
    .limit stack 2
    .limit locals 2
    aload_0
    invokestatic queens/icn_builtin_parse_long(Ljava/lang/String;)J
    lreturn
.end method

.method public static icn_builtin_sort(Ljava/util/ArrayList;)Ljava/util/ArrayList;
    .limit stack 6
    .limit locals 8
    new java/util/ArrayList
    dup
    aload_0
    invokespecial java/util/ArrayList/<init>(Ljava/util/Collection;)V
    astore_1
    iconst_1
    istore_2
icn_sort_outer:
    aload_1
    invokevirtual java/util/ArrayList/size()I
    iload_2
    if_icmple icn_sort_done
    aload_1
    iload_2
    invokevirtual java/util/ArrayList/get(I)Ljava/lang/Object;
    checkcast java/lang/Long
    invokevirtual java/lang/Long/longValue()J
    lstore 4
    iload_2
    iconst_1
    isub
    istore_3
icn_sort_inner:
    iload_3
    iflt icn_sort_insert
    aload_1
    iload_3
    invokevirtual java/util/ArrayList/get(I)Ljava/lang/Object;
    checkcast java/lang/Long
    invokevirtual java/lang/Long/longValue()J
    lload 4
    lcmp
    ifle icn_sort_insert
    aload_1
    iload_3
    iconst_1
    iadd
    aload_1
    iload_3
    invokevirtual java/util/ArrayList/get(I)Ljava/lang/Object;
    invokevirtual java/util/ArrayList/set(ILjava/lang/Object;)Ljava/lang/Object;
    pop
    iinc 3 -1
    goto icn_sort_inner
icn_sort_insert:
    aload_1
    iload_3
    iconst_1
    iadd
    lload 4
    invokestatic java/lang/Long/valueOf(J)Ljava/lang/Long;
    invokevirtual java/util/ArrayList/set(ILjava/lang/Object;)Ljava/lang/Object;
    pop
    iinc 2 1
    goto icn_sort_outer
icn_sort_done:
    aload_1
    areturn
.end method

.method public static icn_builtin_sortf(Ljava/util/ArrayList;I)Ljava/util/ArrayList;
    .limit stack 8
    .limit locals 10
    new java/util/ArrayList
    dup
    aload_0
    invokespecial java/util/ArrayList/<init>(Ljava/util/Collection;)V
    astore_2
    iconst_1
    istore_3
icn_sortf_outer:
    aload_2
    invokevirtual java/util/ArrayList/size()I
    iload_3
    if_icmple icn_sortf_done
    aload_2
    iload_3
    invokevirtual java/util/ArrayList/get(I)Ljava/lang/Object;
    astore 5
    iload_3
    iconst_1
    isub
    istore 4
icn_sortf_inner:
    iload 4
    iflt icn_sortf_insert
    aload_2
    iload 4
    invokevirtual java/util/ArrayList/get(I)Ljava/lang/Object;
    astore 6
    aload 6
    invokevirtual java/lang/Object/getClass()Ljava/lang/Class;
    invokevirtual java/lang/Class/getDeclaredFields()[Ljava/lang/reflect/Field;
    iload_1
    iconst_1
    isub
    aaload
    aload 6
    invokevirtual java/lang/reflect/Field/get(Ljava/lang/Object;)Ljava/lang/Object;
    astore 7
    aload 5
    invokevirtual java/lang/Object/getClass()Ljava/lang/Class;
    invokevirtual java/lang/Class/getDeclaredFields()[Ljava/lang/reflect/Field;
    iload_1
    iconst_1
    isub
    aaload
    aload 5
    invokevirtual java/lang/reflect/Field/get(Ljava/lang/Object;)Ljava/lang/Object;
    astore 8
    aload 7
    checkcast java/lang/Long
    aload 8
    checkcast java/lang/Long
    invokevirtual java/lang/Long/compareTo(Ljava/lang/Long;)I
    ifle icn_sortf_insert
    aload_2
    iload 4
    iconst_1
    iadd
    aload_2
    iload 4
    invokevirtual java/util/ArrayList/get(I)Ljava/lang/Object;
    invokevirtual java/util/ArrayList/set(ILjava/lang/Object;)Ljava/lang/Object;
    pop
    iinc 4 -1
    goto icn_sortf_inner
icn_sortf_insert:
    aload_2
    iload 4
    iconst_1
    iadd
    aload 5
    invokevirtual java/util/ArrayList/set(ILjava/lang/Object;)Ljava/lang/Object;
    pop
    iinc 3 1
    goto icn_sortf_outer
icn_sortf_done:
    aload_2
    areturn
.end method

.method public static icn_safe()V
    .limit stack 16
    .limit locals 230
    lconst_0
    lstore 0
    lconst_0
    lstore 2
    lconst_0
    lstore 4
    lconst_0
    lstore 6
    lconst_0
    lstore 8
    lconst_0
    lstore 10
    lconst_0
    lstore 12
    lconst_0
    lstore 14
    lconst_0
    lstore 16
    lconst_0
    lstore 18
    lconst_0
    lstore 20
    lconst_0
    lstore 22
    lconst_0
    lstore 24
    lconst_0
    lstore 26
    lconst_0
    lstore 28
    lconst_0
    lstore 30
    lconst_0
    lstore 32
    lconst_0
    lstore 34
    lconst_0
    lstore 36
    lconst_0
    lstore 38
    lconst_0
    lstore 40
    lconst_0
    lstore 42
    lconst_0
    lstore 44
    lconst_0
    lstore 46
    lconst_0
    lstore 48
    lconst_0
    lstore 50
    lconst_0
    lstore 52
    lconst_0
    lstore 54
    lconst_0
    lstore 56
    lconst_0
    lstore 58
    lconst_0
    lstore 60
    lconst_0
    lstore 62
    iconst_0
    istore 84
    iconst_0
    istore 85
    iconst_0
    istore 86
    iconst_0
    istore 87
    iconst_0
    istore 88
    iconst_0
    istore 89
    iconst_0
    istore 90
    aconst_null
    astore 148
    aconst_null
    astore 149
    aconst_null
    astore 150
    aconst_null
    astore 151
    getstatic queens/icn_arg_0 J
    putstatic queens/icn_pv_safe_c J
    getstatic queens/icn_arg_1 J
    putstatic queens/icn_pv_safe_r J
    goto icn_23_α
icn_0_α:
    lconst_0
    putstatic queens/icn_retval J
    iconst_0
    putstatic queens/icn_failed B
    goto icn_safe_ret
icn_0_β:
    goto icn_safe_ret
icn_2_α:
    iconst_1
    putstatic queens/icn_failed B
    goto icn_safe_done
icn_2_β:
    goto icn_0_α
;  INT
icn_4_α:
    ldc2_w 0
    goto icn_3_rrelay
icn_4_β:
    goto icn_3_lb
;  INT
icn_7_α:
    ldc2_w 1
    goto icn_6_rrelay
icn_7_β:
    goto icn_6_lb
;  VAR
icn_9_α:
    getstatic queens/icn_pv_safe_c J
    goto icn_8_rrelay
icn_9_β:
    goto icn_8_lb
;  VAR
icn_10_α:
    getstatic queens/icn_pv_safe_r J
    goto icn_8_lrelay
icn_10_β:
    goto icn_1_else
icn_8_lrelay:
    putstatic queens/icn_8_binop_lc J
    goto icn_8_lstore
icn_8_rrelay:
    putstatic queens/icn_8_binop_rc J
    goto icn_8_compute
icn_8_lb:
    goto icn_10_β
icn_8_α:
    iconst_0
    putstatic queens/icn_8_binop_bf I
    goto icn_10_α
icn_8_β:
    iconst_1
    putstatic queens/icn_8_binop_bf I
    goto icn_10_α
icn_8_lstore:
    getstatic queens/icn_8_binop_bf I
    ifeq icn_9_α
    goto icn_9_β
icn_8_compute:
    getstatic queens/icn_8_binop_lc J
    getstatic queens/icn_8_binop_rc J
    ladd
    goto icn_6_lrelay
icn_6_lrelay:
    putstatic queens/icn_6_binop_lc J
    goto icn_6_lstore
icn_6_rrelay:
    putstatic queens/icn_6_binop_rc J
    goto icn_6_compute
icn_6_lb:
    goto icn_8_β
icn_6_α:
    iconst_0
    putstatic queens/icn_6_binop_bf I
    goto icn_8_α
icn_6_β:
    goto icn_7_β
icn_6_lstore:
    getstatic queens/icn_6_binop_bf I
    ifeq icn_7_α
    goto icn_7_β
icn_6_compute:
    getstatic queens/icn_6_binop_lc J
    getstatic queens/icn_6_binop_rc J
    lsub
    goto icn_5_sub_irelay
;  VAR
icn_11_α:
    getstatic queens/icn_gvar_down J
    goto icn_5_sub_srelay
icn_11_β:
    goto icn_1_else
icn_5_sub_srelay:
    putstatic queens/icn_5_sub_s Ljava/lang/String;
    goto icn_6_α
icn_5_sub_irelay:
    l2i
    istore 84
    iload 84
    ifgt icn_5_sub_pos
    iload 84
    iflt icn_5_sub_neg
icn_5_sub_z:
    goto icn_1_else
icn_5_sub_pos:
    iload 84
    iconst_1
    isub
    putstatic queens/icn_5_sub_i I
    goto icn_5_sub_check
icn_5_sub_neg:
    getstatic queens/icn_5_sub_s Ljava/lang/String;
    invokevirtual java/lang/String/length()I
    iload 84
    iadd
    putstatic queens/icn_5_sub_i I
    goto icn_5_sub_check
icn_5_sub_check:
    getstatic queens/icn_5_sub_i I
    iflt icn_1_else
    getstatic queens/icn_5_sub_s Ljava/lang/String;
    invokevirtual java/lang/String/length()I
    getstatic queens/icn_5_sub_i I
    if_icmple icn_1_else
    getstatic queens/icn_5_sub_s Ljava/lang/String;
    getstatic queens/icn_5_sub_i I
    getstatic queens/icn_5_sub_i I
    iconst_1
    iadd
    invokevirtual java/lang/String/substring(II)Ljava/lang/String;
    goto icn_3_lrelay
icn_5_α:
    goto icn_11_α
icn_5_β:
    goto icn_6_β
icn_3_lrelay:
    putstatic queens/icn_3_relop_lc Ljava/lang/String;
    goto icn_3_lstore
icn_3_rrelay:
    putstatic queens/icn_3_relop_rc Ljava/lang/String;
    goto icn_3_check
icn_3_lb:
    goto icn_5_β
icn_3_α:
    goto icn_5_α
icn_3_β:
    goto icn_4_β
icn_3_lstore:
    goto icn_4_α
icn_3_check:
    getstatic queens/icn_3_relop_lc Ljava/lang/String;
    getstatic queens/icn_3_relop_rc Ljava/lang/String;
    invokevirtual java/lang/String/compareTo(Ljava/lang/String;)I
    ifeq icn_4_β
    getstatic queens/icn_3_relop_rc Ljava/lang/String;
    goto icn_1_then
icn_1_then:
    pop
    goto icn_2_α
icn_1_else:
    goto icn_0_α
icn_1_α:
    goto icn_3_α
icn_1_β:
    goto icn_3_β
icn_13_α:
    iconst_1
    putstatic queens/icn_failed B
    goto icn_safe_done
icn_13_β:
    goto icn_1_α
;  INT
icn_15_α:
    ldc2_w 0
    goto icn_14_rrelay
icn_15_β:
    goto icn_14_lb
;  VAR
icn_18_α:
    getstatic queens/icn_pv_safe_c J
    goto icn_17_rrelay
icn_18_β:
    goto icn_17_lb
;  VAR
icn_20_α:
    getstatic queens/icn_pv_safe_r J
    goto icn_19_rrelay
icn_20_β:
    goto icn_19_lb
;  VAR
icn_21_α:
    getstatic queens/icn_gvar_n J
    goto icn_19_lrelay
icn_21_β:
    goto icn_12_else
icn_19_lrelay:
    putstatic queens/icn_19_binop_lc J
    goto icn_19_lstore
icn_19_rrelay:
    putstatic queens/icn_19_binop_rc J
    goto icn_19_compute
icn_19_lb:
    goto icn_21_β
icn_19_α:
    iconst_0
    putstatic queens/icn_19_binop_bf I
    goto icn_21_α
icn_19_β:
    iconst_1
    putstatic queens/icn_19_binop_bf I
    goto icn_21_α
icn_19_lstore:
    getstatic queens/icn_19_binop_bf I
    ifeq icn_20_α
    goto icn_20_β
icn_19_compute:
    getstatic queens/icn_19_binop_lc J
    getstatic queens/icn_19_binop_rc J
    ladd
    goto icn_17_lrelay
icn_17_lrelay:
    putstatic queens/icn_17_binop_lc J
    goto icn_17_lstore
icn_17_rrelay:
    putstatic queens/icn_17_binop_rc J
    goto icn_17_compute
icn_17_lb:
    goto icn_19_β
icn_17_α:
    iconst_0
    putstatic queens/icn_17_binop_bf I
    goto icn_19_α
icn_17_β:
    goto icn_18_β
icn_17_lstore:
    getstatic queens/icn_17_binop_bf I
    ifeq icn_18_α
    goto icn_18_β
icn_17_compute:
    getstatic queens/icn_17_binop_lc J
    getstatic queens/icn_17_binop_rc J
    lsub
    goto icn_16_sub_irelay
;  VAR
icn_22_α:
    getstatic queens/icn_gvar_up J
    goto icn_16_sub_srelay
icn_22_β:
    goto icn_12_else
icn_16_sub_srelay:
    putstatic queens/icn_16_sub_s Ljava/lang/String;
    goto icn_17_α
icn_16_sub_irelay:
    l2i
    istore 85
    iload 85
    ifgt icn_16_sub_pos
    iload 85
    iflt icn_16_sub_neg
icn_16_sub_z:
    goto icn_12_else
icn_16_sub_pos:
    iload 85
    iconst_1
    isub
    putstatic queens/icn_16_sub_i I
    goto icn_16_sub_check
icn_16_sub_neg:
    getstatic queens/icn_16_sub_s Ljava/lang/String;
    invokevirtual java/lang/String/length()I
    iload 85
    iadd
    putstatic queens/icn_16_sub_i I
    goto icn_16_sub_check
icn_16_sub_check:
    getstatic queens/icn_16_sub_i I
    iflt icn_12_else
    getstatic queens/icn_16_sub_s Ljava/lang/String;
    invokevirtual java/lang/String/length()I
    getstatic queens/icn_16_sub_i I
    if_icmple icn_12_else
    getstatic queens/icn_16_sub_s Ljava/lang/String;
    getstatic queens/icn_16_sub_i I
    getstatic queens/icn_16_sub_i I
    iconst_1
    iadd
    invokevirtual java/lang/String/substring(II)Ljava/lang/String;
    goto icn_14_lrelay
icn_16_α:
    goto icn_22_α
icn_16_β:
    goto icn_17_β
icn_14_lrelay:
    putstatic queens/icn_14_relop_lc Ljava/lang/String;
    goto icn_14_lstore
icn_14_rrelay:
    putstatic queens/icn_14_relop_rc Ljava/lang/String;
    goto icn_14_check
icn_14_lb:
    goto icn_16_β
icn_14_α:
    goto icn_16_α
icn_14_β:
    goto icn_15_β
icn_14_lstore:
    goto icn_15_α
icn_14_check:
    getstatic queens/icn_14_relop_lc Ljava/lang/String;
    getstatic queens/icn_14_relop_rc Ljava/lang/String;
    invokevirtual java/lang/String/compareTo(Ljava/lang/String;)I
    ifeq icn_15_β
    getstatic queens/icn_14_relop_rc Ljava/lang/String;
    goto icn_12_then
icn_12_then:
    pop
    goto icn_13_α
icn_12_else:
    goto icn_1_α
icn_12_α:
    goto icn_14_α
icn_12_β:
    goto icn_14_β
icn_24_α:
    iconst_1
    putstatic queens/icn_failed B
    goto icn_safe_done
icn_24_β:
    goto icn_12_α
;  INT
icn_26_α:
    ldc2_w 0
    goto icn_25_rrelay
icn_26_β:
    goto icn_25_lb
;  VAR
icn_28_α:
    getstatic queens/icn_pv_safe_r J
    goto icn_27_sub_irelay
icn_28_β:
    goto icn_23_else
;  VAR
icn_29_α:
    getstatic queens/icn_gvar_rows J
    goto icn_27_sub_srelay
icn_29_β:
    goto icn_23_else
icn_27_sub_srelay:
    putstatic queens/icn_27_sub_s Ljava/lang/String;
    goto icn_28_α
icn_27_sub_irelay:
    l2i
    istore 86
    iload 86
    ifgt icn_27_sub_pos
    iload 86
    iflt icn_27_sub_neg
icn_27_sub_z:
    goto icn_23_else
icn_27_sub_pos:
    iload 86
    iconst_1
    isub
    putstatic queens/icn_27_sub_i I
    goto icn_27_sub_check
icn_27_sub_neg:
    getstatic queens/icn_27_sub_s Ljava/lang/String;
    invokevirtual java/lang/String/length()I
    iload 86
    iadd
    putstatic queens/icn_27_sub_i I
    goto icn_27_sub_check
icn_27_sub_check:
    getstatic queens/icn_27_sub_i I
    iflt icn_23_else
    getstatic queens/icn_27_sub_s Ljava/lang/String;
    invokevirtual java/lang/String/length()I
    getstatic queens/icn_27_sub_i I
    if_icmple icn_23_else
    getstatic queens/icn_27_sub_s Ljava/lang/String;
    getstatic queens/icn_27_sub_i I
    getstatic queens/icn_27_sub_i I
    iconst_1
    iadd
    invokevirtual java/lang/String/substring(II)Ljava/lang/String;
    goto icn_25_lrelay
icn_27_α:
    goto icn_29_α
icn_27_β:
    goto icn_28_β
icn_25_lrelay:
    putstatic queens/icn_25_relop_lc Ljava/lang/String;
    goto icn_25_lstore
icn_25_rrelay:
    putstatic queens/icn_25_relop_rc Ljava/lang/String;
    goto icn_25_check
icn_25_lb:
    goto icn_27_β
icn_25_α:
    goto icn_27_α
icn_25_β:
    goto icn_26_β
icn_25_lstore:
    goto icn_26_α
icn_25_check:
    getstatic queens/icn_25_relop_lc Ljava/lang/String;
    getstatic queens/icn_25_relop_rc Ljava/lang/String;
    invokevirtual java/lang/String/compareTo(Ljava/lang/String;)I
    ifeq icn_26_β
    getstatic queens/icn_25_relop_rc Ljava/lang/String;
    goto icn_23_then
icn_23_then:
    pop
    goto icn_24_α
icn_23_else:
    goto icn_12_α
icn_23_α:
    goto icn_25_α
icn_23_β:
    goto icn_25_β
icn_safe_done:
    iconst_0
    putstatic queens/icn_suspended B
    iconst_0
    putstatic queens/icn_suspend_id I
    iconst_1
    putstatic queens/icn_failed B
    return
icn_safe_ret:
    iconst_0
    putstatic queens/icn_failed B
    return
icn_safe_sret:
    return
.end method

.method public static icn_show()V
    .limit stack 16
    .limit locals 306
    lconst_0
    lstore 0
    lconst_0
    lstore 2
    lconst_0
    lstore 4
    lconst_0
    lstore 6
    lconst_0
    lstore 8
    lconst_0
    lstore 10
    lconst_0
    lstore 12
    lconst_0
    lstore 14
    lconst_0
    lstore 16
    lconst_0
    lstore 18
    lconst_0
    lstore 20
    lconst_0
    lstore 22
    lconst_0
    lstore 24
    lconst_0
    lstore 26
    lconst_0
    lstore 28
    lconst_0
    lstore 30
    lconst_0
    lstore 32
    lconst_0
    lstore 34
    lconst_0
    lstore 36
    lconst_0
    lstore 38
    lconst_0
    lstore 40
    lconst_0
    lstore 42
    lconst_0
    lstore 44
    lconst_0
    lstore 46
    lconst_0
    lstore 48
    lconst_0
    lstore 50
    lconst_0
    lstore 52
    lconst_0
    lstore 54
    lconst_0
    lstore 56
    lconst_0
    lstore 58
    lconst_0
    lstore 60
    lconst_0
    lstore 62
    iconst_0
    istore 84
    iconst_0
    istore 85
    iconst_0
    istore 86
    iconst_0
    istore 87
    iconst_0
    istore 88
    iconst_0
    istore 89
    iconst_0
    istore 90
    iconst_0
    istore 91
    aconst_null
    astore 148
    aconst_null
    astore 149
    aconst_null
    astore 150
    aconst_null
    astore 151
    aconst_null
    astore 152
    aconst_null
    astore 153
    aconst_null
    astore 154
    aconst_null
    astore 155
    aconst_null
    astore 156
    aconst_null
    astore 157
    aconst_null
    astore 158
    aconst_null
    astore 159
    aconst_null
    astore 160
    aconst_null
    astore 161
    aconst_null
    astore 162
    aconst_null
    astore 163
    goto icn_75_α
;  STR
icn_31_α:
    ldc "  "
    goto icn_30_waft_0
icn_31_β:
    goto icn_show_done
;  VAR
icn_32_α:
    getstatic queens/icn_pv_show_sep Ljava/lang/String;
    goto icn_30_waft_1
icn_32_β:
    goto icn_show_done
icn_30_α:
    goto icn_31_α
icn_30_β:
    goto icn_31_β
    goto icn_30_wentry
icn_30_waft_0:
    astore 148
    getstatic java/lang/System/out Ljava/io/PrintStream;
    aload 148
    invokevirtual java/io/PrintStream/print(Ljava/lang/String;)V
    goto icn_32_α
icn_30_waft_1:
    astore 149
    getstatic java/lang/System/out Ljava/io/PrintStream;
    aload 149
    invokevirtual java/io/PrintStream/print(Ljava/lang/String;)V
    getstatic java/lang/System/out Ljava/io/PrintStream;
    ldc ""
    invokevirtual java/io/PrintStream/println(Ljava/lang/String;)V
    aload 149
    goto icn_show_s5_sdrain
icn_30_wentry:
    goto icn_31_α
icn_show_s5_sdrain:
    pop
    goto icn_show_done
;  STR
icn_36_α:
    ldc "  "
    goto icn_35_waft_0
icn_36_β:
    goto icn_34_seq_rf_0
;  VAR
icn_37_α:
    getstatic queens/icn_pv_show_sep Ljava/lang/String;
    goto icn_35_waft_1
icn_37_β:
    goto icn_34_seq_rf_0
icn_35_α:
    goto icn_36_α
icn_35_β:
    goto icn_36_β
    goto icn_35_wentry
icn_35_waft_0:
    astore 150
    getstatic java/lang/System/out Ljava/io/PrintStream;
    aload 150
    invokevirtual java/io/PrintStream/print(Ljava/lang/String;)V
    goto icn_37_α
icn_35_waft_1:
    astore 151
    getstatic java/lang/System/out Ljava/io/PrintStream;
    aload 151
    invokevirtual java/io/PrintStream/print(Ljava/lang/String;)V
    getstatic java/lang/System/out Ljava/io/PrintStream;
    ldc ""
    invokevirtual java/io/PrintStream/println(Ljava/lang/String;)V
    aload 151
    goto icn_34_seq_rg_0
icn_35_wentry:
    goto icn_36_α
;  STR
icn_40_α:
    ldc "|"
    goto icn_39_rrelay
icn_40_β:
    goto icn_39_lb
;  STR
icn_42_α:
    ldc "|   "
    goto icn_41_repl_mid
icn_42_β:
    goto icn_34_seq_rf_1
;  VAR
icn_43_α:
    getstatic queens/icn_gvar_n J
    goto icn_41_repl_after
icn_43_β:
    goto icn_34_seq_rf_1
icn_41_α:
    goto icn_42_α
icn_41_β:
    goto icn_42_β
icn_41_repl_mid:
    astore 152
    goto icn_43_α
icn_41_repl_after:
    l2i
    istore 85
    new java/lang/StringBuilder
    dup
    invokespecial java/lang/StringBuilder/<init>()V
    astore 153
    iconst_0
    istore 6
icn_41_repl_loop:
    iload 6
    iload 85
    if_icmpge icn_41_repl_done
    aload 153
    aload 152
    invokevirtual java/lang/StringBuilder/append(Ljava/lang/String;)Ljava/lang/StringBuilder;
    pop
    iinc 6 1
    goto icn_41_repl_loop
icn_41_repl_done:
    aload 153
    invokevirtual java/lang/StringBuilder/toString()Ljava/lang/String;
    goto icn_39_lrelay
icn_39_lrelay:
    putstatic queens/icn_39_lc Ljava/lang/String;
    goto icn_39_lstore
icn_39_rrelay:
    putstatic queens/icn_39_rc Ljava/lang/String;
    goto icn_39_compute
icn_39_lb:
    goto icn_41_β
icn_39_α:
    iconst_0
    istore 84
    goto icn_41_α
icn_39_β:
    iconst_1
    istore 84
    goto icn_41_α
icn_39_lstore:
    iload 84
    ifeq icn_40_α
    goto icn_40_β
icn_39_compute:
    getstatic queens/icn_39_lc Ljava/lang/String;
    getstatic queens/icn_39_rc Ljava/lang/String;
    invokevirtual java/lang/String/concat(Ljava/lang/String;)Ljava/lang/String;
    goto icn_38_store
icn_38_α:
    goto icn_39_α
icn_38_β:
    goto icn_39_β
icn_38_store:
    putstatic queens/icn_pv_show_line Ljava/lang/String;
    getstatic queens/icn_pv_show_line Ljava/lang/String;
    goto icn_34_seq_rg_1
;  STR
icn_45_α:
    ldc "Q"
    goto icn_44_store
icn_45_β:
    goto icn_34_seq_rf_2
icn_44_α:
    goto icn_45_α
icn_44_β:
    goto icn_45_β
icn_44_store:
    putstatic queens/icn_46_lsa_v Ljava/lang/String;
    getstatic queens/icn_pv_show_line Ljava/util/ArrayList;
    putstatic queens/icn_46_lsa_l Ljava/util/ArrayList;
;  INT
icn_48_α:
    ldc2_w 3
    goto icn_47_rrelay
icn_48_β:
    goto icn_47_lb
;  INT
icn_51_α:
    ldc2_w 1
    goto icn_50_rrelay
icn_51_β:
    goto icn_50_lb
;  VAR
icn_53_α:
    getstatic queens/icn_pv_show_col J
    goto icn_52_sub_irelay
icn_53_β:
    goto icn_49_lb
;  VAR
icn_54_α:
    getstatic queens/icn_gvar_placed J
    goto icn_52_sub_srelay
icn_54_β:
    goto icn_49_lb
icn_52_sub_srelay:
    putstatic queens/icn_52_sub_s Ljava/lang/String;
    goto icn_53_α
icn_52_sub_irelay:
    l2i
    istore 86
    iload 86
    ifgt icn_52_sub_pos
    iload 86
    iflt icn_52_sub_neg
icn_52_sub_z:
    goto icn_49_lb
icn_52_sub_pos:
    iload 86
    iconst_1
    isub
    putstatic queens/icn_52_sub_i I
    goto icn_52_sub_check
icn_52_sub_neg:
    getstatic queens/icn_52_sub_s Ljava/lang/String;
    invokevirtual java/lang/String/length()I
    iload 86
    iadd
    putstatic queens/icn_52_sub_i I
    goto icn_52_sub_check
icn_52_sub_check:
    getstatic queens/icn_52_sub_i I
    iflt icn_49_lb
    getstatic queens/icn_52_sub_s Ljava/lang/String;
    invokevirtual java/lang/String/length()I
    getstatic queens/icn_52_sub_i I
    if_icmple icn_49_lb
    getstatic queens/icn_52_sub_s Ljava/lang/String;
    getstatic queens/icn_52_sub_i I
    getstatic queens/icn_52_sub_i I
    iconst_1
    iadd
    invokevirtual java/lang/String/substring(II)Ljava/lang/String;
    goto icn_50_lrelay
icn_52_α:
    goto icn_54_α
icn_52_β:
    goto icn_53_β
icn_50_lrelay:
    putstatic queens/icn_50_binop_lc J
    goto icn_50_lstore
icn_50_rrelay:
    putstatic queens/icn_50_binop_rc J
    goto icn_50_compute
icn_50_lb:
    goto icn_52_β
icn_50_α:
    iconst_0
    putstatic queens/icn_50_binop_bf I
    goto icn_52_α
icn_50_β:
    goto icn_51_β
icn_50_lstore:
    getstatic queens/icn_50_binop_bf I
    ifeq icn_51_α
    goto icn_51_β
icn_50_compute:
    getstatic queens/icn_50_binop_lc J
    getstatic queens/icn_50_binop_rc J
    lsub
    goto icn_49_rrelay
;  INT
icn_55_α:
    ldc2_w 4
    goto icn_49_lrelay
icn_55_β:
    goto icn_34_seq_rf_2
icn_49_lrelay:
    putstatic queens/icn_49_binop_lc J
    goto icn_49_lstore
icn_49_rrelay:
    putstatic queens/icn_49_binop_rc J
    goto icn_49_compute
icn_49_lb:
    goto icn_55_β
icn_49_α:
    iconst_0
    putstatic queens/icn_49_binop_bf I
    goto icn_55_α
icn_49_β:
    iconst_1
    putstatic queens/icn_49_binop_bf I
    goto icn_55_α
icn_49_lstore:
    getstatic queens/icn_49_binop_bf I
    ifeq icn_50_α
    goto icn_50_β
icn_49_compute:
    getstatic queens/icn_49_binop_lc J
    getstatic queens/icn_49_binop_rc J
    lmul
    goto icn_47_lrelay
icn_47_lrelay:
    putstatic queens/icn_47_binop_lc J
    goto icn_47_lstore
icn_47_rrelay:
    putstatic queens/icn_47_binop_rc J
    goto icn_47_compute
icn_47_lb:
    goto icn_49_β
icn_47_α:
    iconst_0
    putstatic queens/icn_47_binop_bf I
    goto icn_49_α
icn_47_β:
    goto icn_48_β
icn_47_lstore:
    getstatic queens/icn_47_binop_bf I
    ifeq icn_48_α
    goto icn_48_β
icn_47_compute:
    getstatic queens/icn_47_binop_lc J
    getstatic queens/icn_47_binop_rc J
    ladd
    goto icn_46_lsa_ir
    goto icn_47_α
icn_46_lsa_ir:
    lconst_1
    lsub
    putstatic queens/icn_46_lsa_i J
    goto icn_46_lsa_do
icn_46_lsa_do:
    getstatic queens/icn_46_lsa_l Ljava/util/ArrayList;
    getstatic queens/icn_46_lsa_i J
    l2i
    getstatic queens/icn_46_lsa_v Ljava/lang/String;
    invokevirtual java/util/ArrayList/set(ILjava/lang/Object;)Ljava/lang/Object;
    pop
    getstatic queens/icn_46_lsa_v Ljava/lang/String;
    goto icn_34_seq_rg_2
;  STR
icn_57_α:
    ldc "  "
    goto icn_56_waft_0
icn_57_β:
    goto icn_33_pump
;  VAR
icn_58_α:
    getstatic queens/icn_pv_show_line Ljava/lang/String;
    goto icn_56_waft_1
icn_58_β:
    goto icn_33_pump
icn_56_α:
    goto icn_57_α
icn_56_β:
    goto icn_57_β
    goto icn_56_wentry
icn_56_waft_0:
    astore 154
    getstatic java/lang/System/out Ljava/io/PrintStream;
    aload 154
    invokevirtual java/io/PrintStream/print(Ljava/lang/String;)V
    goto icn_58_α
icn_56_waft_1:
    astore 155
    getstatic java/lang/System/out Ljava/io/PrintStream;
    aload 155
    invokevirtual java/io/PrintStream/print(Ljava/lang/String;)V
    getstatic java/lang/System/out Ljava/io/PrintStream;
    ldc ""
    invokevirtual java/io/PrintStream/println(Ljava/lang/String;)V
    aload 155
    goto icn_33_bdrain
icn_56_wentry:
    goto icn_57_α
    goto icn_34_α
icn_34_seq_rg_0:
    pop
    goto icn_38_α
icn_34_seq_rg_1:
    pop
    goto icn_44_α
icn_34_seq_rg_2:
    pop
    goto icn_56_α
icn_34_seq_rf_0:
    goto icn_38_α
icn_34_seq_rf_1:
    goto icn_44_α
icn_34_seq_rf_2:
    goto icn_56_α
icn_34_α:
    goto icn_35_α
icn_34_β:
    goto icn_56_β
;  VAR
icn_61_α:
    getstatic queens/icn_gvar_n J
    goto icn_60_e2relay
icn_61_β:
    goto icn_60_e1b
;  INT
icn_62_α:
    ldc2_w 1
    goto icn_60_e1relay
icn_62_β:
    goto icn_30_α
icn_60_e1relay:
    putstatic queens/icn_60_e1val J
    goto icn_61_α
icn_60_e2relay:
    putstatic queens/icn_60_e2val J
    goto icn_60_init
icn_60_e1b:
    iconst_0
    putstatic queens/icn_60_e2seen I
    goto icn_62_β
icn_60_e2b:
    goto icn_61_β
icn_60_α:
    iconst_0
    putstatic queens/icn_60_e2seen I
    goto icn_62_α
icn_60_β:
    getstatic queens/icn_60_I J
    lconst_1
    ladd
    putstatic queens/icn_60_I J
    goto icn_60_code
icn_60_init:
    getstatic queens/icn_60_e2val J
    putstatic queens/icn_60_bound J
    getstatic queens/icn_60_e2seen I
    ifne icn_60_init_e2adv
    getstatic queens/icn_60_e1val J
    putstatic queens/icn_60_e1cur J
    getstatic queens/icn_60_e1cur J
    putstatic queens/icn_60_I J
    iconst_1
    putstatic queens/icn_60_e2seen I
    goto icn_60_code
icn_60_init_e2adv:
    getstatic queens/icn_60_e1cur J
    putstatic queens/icn_60_I J
    goto icn_60_code
icn_60_code:
    getstatic queens/icn_60_I J
    getstatic queens/icn_60_bound J
    lcmp
    ifgt icn_60_e2b
    getstatic queens/icn_60_I J
    goto icn_59_store
icn_59_α:
    goto icn_60_α
icn_59_β:
    goto icn_60_β
icn_59_store:
    putstatic queens/icn_pv_show_col J
    getstatic queens/icn_pv_show_col J
    goto icn_33_gdrain
icn_33_gdrain:
    pop2
    goto icn_34_α
icn_33_bdrain:
    pop
icn_33_pump:
    goto icn_59_β
icn_33_α:
    goto icn_59_α
icn_33_β:
    goto icn_30_α
;  STR
icn_64_α:
    ldc "solution "
    goto icn_63_waft_0
icn_64_β:
    goto icn_33_α
;  VAR
icn_65_α:
    getstatic queens/icn_gvar_qcount J
    goto icn_63_waft_1
icn_65_β:
    goto icn_33_α
;  STR
icn_66_α:
    ldc ":"
    goto icn_63_waft_2
icn_66_β:
    goto icn_33_α
icn_63_α:
    goto icn_64_α
icn_63_β:
    goto icn_64_β
    goto icn_63_wentry
icn_63_waft_0:
    astore 156
    getstatic java/lang/System/out Ljava/io/PrintStream;
    aload 156
    invokevirtual java/io/PrintStream/print(Ljava/lang/String;)V
    goto icn_65_α
icn_63_waft_1:
    lstore 8
    getstatic java/lang/System/out Ljava/io/PrintStream;
    lload 8
    invokevirtual java/io/PrintStream/print(J)V
    goto icn_66_α
icn_63_waft_2:
    astore 157
    getstatic java/lang/System/out Ljava/io/PrintStream;
    aload 157
    invokevirtual java/io/PrintStream/print(Ljava/lang/String;)V
    getstatic java/lang/System/out Ljava/io/PrintStream;
    ldc ""
    invokevirtual java/io/PrintStream/println(Ljava/lang/String;)V
    aload 157
    goto icn_show_s3_sdrain
icn_63_wentry:
    goto icn_64_α
icn_show_s3_sdrain:
    pop
    goto icn_33_α
;  STR
icn_69_α:
    ldc "-"
    goto icn_68_repl_mid
icn_69_β:
    goto icn_63_α
;  INT
icn_71_α:
    ldc2_w 1
    goto icn_70_rrelay
icn_71_β:
    goto icn_70_lb
;  VAR
icn_73_α:
    getstatic queens/icn_gvar_n J
    goto icn_72_rrelay
icn_73_β:
    goto icn_72_lb
;  INT
icn_74_α:
    ldc2_w 4
    goto icn_72_lrelay
icn_74_β:
    goto icn_63_α
icn_72_lrelay:
    putstatic queens/icn_72_binop_lc J
    goto icn_72_lstore
icn_72_rrelay:
    putstatic queens/icn_72_binop_rc J
    goto icn_72_compute
icn_72_lb:
    goto icn_74_β
icn_72_α:
    iconst_0
    putstatic queens/icn_72_binop_bf I
    goto icn_74_α
icn_72_β:
    iconst_1
    putstatic queens/icn_72_binop_bf I
    goto icn_74_α
icn_72_lstore:
    getstatic queens/icn_72_binop_bf I
    ifeq icn_73_α
    goto icn_73_β
icn_72_compute:
    getstatic queens/icn_72_binop_lc J
    getstatic queens/icn_72_binop_rc J
    lmul
    goto icn_70_lrelay
icn_70_lrelay:
    putstatic queens/icn_70_binop_lc J
    goto icn_70_lstore
icn_70_rrelay:
    putstatic queens/icn_70_binop_rc J
    goto icn_70_compute
icn_70_lb:
    goto icn_72_β
icn_70_α:
    iconst_0
    putstatic queens/icn_70_binop_bf I
    goto icn_72_α
icn_70_β:
    goto icn_71_β
icn_70_lstore:
    getstatic queens/icn_70_binop_bf I
    ifeq icn_71_α
    goto icn_71_β
icn_70_compute:
    getstatic queens/icn_70_binop_lc J
    getstatic queens/icn_70_binop_rc J
    ladd
    goto icn_68_repl_after
icn_68_α:
    goto icn_69_α
icn_68_β:
    goto icn_69_β
icn_68_repl_mid:
    astore 158
    goto icn_70_α
icn_68_repl_after:
    l2i
    istore 87
    new java/lang/StringBuilder
    dup
    invokespecial java/lang/StringBuilder/<init>()V
    astore 159
    iconst_0
    istore 10
icn_68_repl_loop:
    iload 10
    iload 87
    if_icmpge icn_68_repl_done
    aload 159
    aload 158
    invokevirtual java/lang/StringBuilder/append(Ljava/lang/String;)Ljava/lang/StringBuilder;
    pop
    iinc 10 1
    goto icn_68_repl_loop
icn_68_repl_done:
    aload 159
    invokevirtual java/lang/StringBuilder/toString()Ljava/lang/String;
    goto icn_67_store
icn_67_α:
    goto icn_68_α
icn_67_β:
    goto icn_68_β
icn_67_store:
    putstatic queens/icn_pv_show_sep Ljava/lang/String;
    getstatic queens/icn_pv_show_sep Ljava/lang/String;
    goto icn_show_s2_sdrain
icn_show_s2_sdrain:
    pop
    goto icn_63_α
;  INT
icn_76_α:
    ldc2_w 1
    goto icn_75_rhsok
icn_76_β:
    goto icn_67_α
icn_75_α:
    goto icn_76_α
icn_75_β:
    goto icn_76_β
icn_75_rhsok:
    putstatic queens/icn_75_augtemp J
    getstatic queens/icn_gvar_qcount J
    getstatic queens/icn_75_augtemp J
    ladd
    dup2
    putstatic queens/icn_gvar_qcount J
    goto icn_show_s1_sdrain
icn_show_s1_sdrain:
    pop2
    goto icn_67_α
icn_show_done:
    iconst_0
    putstatic queens/icn_suspended B
    iconst_0
    putstatic queens/icn_suspend_id I
    iconst_1
    putstatic queens/icn_failed B
    return
icn_show_ret:
    iconst_0
    putstatic queens/icn_failed B
    return
icn_show_sret:
    return
.end method

.method public static icn_try_col()V
    .limit stack 16
    .limit locals 414
    lconst_0
    lstore 0
    lconst_0
    lstore 2
    lconst_0
    lstore 4
    lconst_0
    lstore 6
    lconst_0
    lstore 8
    lconst_0
    lstore 10
    lconst_0
    lstore 12
    lconst_0
    lstore 14
    lconst_0
    lstore 16
    lconst_0
    lstore 18
    lconst_0
    lstore 20
    lconst_0
    lstore 22
    lconst_0
    lstore 24
    lconst_0
    lstore 26
    lconst_0
    lstore 28
    lconst_0
    lstore 30
    lconst_0
    lstore 32
    lconst_0
    lstore 34
    lconst_0
    lstore 36
    lconst_0
    lstore 38
    lconst_0
    lstore 40
    lconst_0
    lstore 42
    lconst_0
    lstore 44
    lconst_0
    lstore 46
    lconst_0
    lstore 48
    lconst_0
    lstore 50
    lconst_0
    lstore 52
    lconst_0
    lstore 54
    lconst_0
    lstore 56
    lconst_0
    lstore 58
    lconst_0
    lstore 60
    lconst_0
    lstore 62
    iconst_0
    istore 84
    iconst_0
    istore 85
    iconst_0
    istore 86
    iconst_0
    istore 87
    aconst_null
    astore 148
    aconst_null
    astore 149
    aconst_null
    astore 150
    aconst_null
    astore 151
    getstatic queens/icn_arg_0 J
    putstatic queens/icn_pv_try_col_c J
    goto icn_135_α
;  VAR
icn_81_α:
    getstatic queens/icn_pv_try_col_r J
    goto icn_80_store
icn_81_β:
    goto icn_79_seq_rf_0
icn_80_α:
    goto icn_81_α
icn_80_β:
    goto icn_81_β
icn_80_store:
    putstatic queens/icn_82_lsa_v J
    getstatic queens/icn_gvar_placed Ljava/util/ArrayList;
    putstatic queens/icn_82_lsa_l Ljava/util/ArrayList;
;  VAR
icn_83_α:
    getstatic queens/icn_pv_try_col_c J
    goto icn_82_lsa_ir
icn_83_β:
    goto icn_79_seq_rf_0
    goto icn_83_α
icn_82_lsa_ir:
    lconst_1
    lsub
    putstatic queens/icn_82_lsa_i J
    goto icn_82_lsa_do
icn_82_lsa_do:
    getstatic queens/icn_82_lsa_l Ljava/util/ArrayList;
    getstatic queens/icn_82_lsa_i J
    l2i
    getstatic queens/icn_82_lsa_v J
    invokestatic java/lang/Long/valueOf(J)Ljava/lang/Long;
    invokevirtual java/util/ArrayList/set(ILjava/lang/Object;)Ljava/lang/Object;
    pop
    getstatic queens/icn_82_lsa_v J
    goto icn_79_seq_rg_0
;  INT
icn_85_α:
    ldc2_w 1
    goto icn_84_store
icn_85_β:
    goto icn_79_seq_rf_1
icn_84_α:
    goto icn_85_α
icn_84_β:
    goto icn_85_β
icn_84_store:
    putstatic queens/icn_86_lsa_v J
    getstatic queens/icn_gvar_rows Ljava/util/ArrayList;
    putstatic queens/icn_86_lsa_l Ljava/util/ArrayList;
;  VAR
icn_87_α:
    getstatic queens/icn_pv_try_col_r J
    goto icn_86_lsa_ir
icn_87_β:
    goto icn_79_seq_rf_1
    goto icn_87_α
icn_86_lsa_ir:
    lconst_1
    lsub
    putstatic queens/icn_86_lsa_i J
    goto icn_86_lsa_do
icn_86_lsa_do:
    getstatic queens/icn_86_lsa_l Ljava/util/ArrayList;
    getstatic queens/icn_86_lsa_i J
    l2i
    getstatic queens/icn_86_lsa_v J
    invokestatic java/lang/Long/valueOf(J)Ljava/lang/Long;
    invokevirtual java/util/ArrayList/set(ILjava/lang/Object;)Ljava/lang/Object;
    pop
    getstatic queens/icn_86_lsa_v J
    goto icn_79_seq_rg_1
;  INT
icn_89_α:
    ldc2_w 1
    goto icn_88_store
icn_89_β:
    goto icn_79_seq_rf_2
icn_88_α:
    goto icn_89_α
icn_88_β:
    goto icn_89_β
icn_88_store:
    putstatic queens/icn_90_lsa_v J
    getstatic queens/icn_gvar_up Ljava/util/ArrayList;
    putstatic queens/icn_90_lsa_l Ljava/util/ArrayList;
;  VAR
icn_92_α:
    getstatic queens/icn_pv_try_col_c J
    goto icn_91_rrelay
icn_92_β:
    goto icn_91_lb
;  VAR
icn_94_α:
    getstatic queens/icn_pv_try_col_r J
    goto icn_93_rrelay
icn_94_β:
    goto icn_93_lb
;  VAR
icn_95_α:
    getstatic queens/icn_gvar_n J
    goto icn_93_lrelay
icn_95_β:
    goto icn_79_seq_rf_2
icn_93_lrelay:
    putstatic queens/icn_93_binop_lc J
    goto icn_93_lstore
icn_93_rrelay:
    putstatic queens/icn_93_binop_rc J
    goto icn_93_compute
icn_93_lb:
    goto icn_95_β
icn_93_α:
    iconst_0
    putstatic queens/icn_93_binop_bf I
    goto icn_95_α
icn_93_β:
    iconst_1
    putstatic queens/icn_93_binop_bf I
    goto icn_95_α
icn_93_lstore:
    getstatic queens/icn_93_binop_bf I
    ifeq icn_94_α
    goto icn_94_β
icn_93_compute:
    getstatic queens/icn_93_binop_lc J
    getstatic queens/icn_93_binop_rc J
    ladd
    goto icn_91_lrelay
icn_91_lrelay:
    putstatic queens/icn_91_binop_lc J
    goto icn_91_lstore
icn_91_rrelay:
    putstatic queens/icn_91_binop_rc J
    goto icn_91_compute
icn_91_lb:
    goto icn_93_β
icn_91_α:
    iconst_0
    putstatic queens/icn_91_binop_bf I
    goto icn_93_α
icn_91_β:
    goto icn_92_β
icn_91_lstore:
    getstatic queens/icn_91_binop_bf I
    ifeq icn_92_α
    goto icn_92_β
icn_91_compute:
    getstatic queens/icn_91_binop_lc J
    getstatic queens/icn_91_binop_rc J
    lsub
    goto icn_90_lsa_ir
    goto icn_91_α
icn_90_lsa_ir:
    lconst_1
    lsub
    putstatic queens/icn_90_lsa_i J
    goto icn_90_lsa_do
icn_90_lsa_do:
    getstatic queens/icn_90_lsa_l Ljava/util/ArrayList;
    getstatic queens/icn_90_lsa_i J
    l2i
    getstatic queens/icn_90_lsa_v J
    invokestatic java/lang/Long/valueOf(J)Ljava/lang/Long;
    invokevirtual java/util/ArrayList/set(ILjava/lang/Object;)Ljava/lang/Object;
    pop
    getstatic queens/icn_90_lsa_v J
    goto icn_79_seq_rg_2
;  INT
icn_97_α:
    ldc2_w 1
    goto icn_96_store
icn_97_β:
    goto icn_79_seq_rf_3
icn_96_α:
    goto icn_97_α
icn_96_β:
    goto icn_97_β
icn_96_store:
    putstatic queens/icn_98_lsa_v J
    getstatic queens/icn_gvar_down Ljava/util/ArrayList;
    putstatic queens/icn_98_lsa_l Ljava/util/ArrayList;
;  INT
icn_100_α:
    ldc2_w 1
    goto icn_99_rrelay
icn_100_β:
    goto icn_99_lb
;  VAR
icn_102_α:
    getstatic queens/icn_pv_try_col_c J
    goto icn_101_rrelay
icn_102_β:
    goto icn_101_lb
;  VAR
icn_103_α:
    getstatic queens/icn_pv_try_col_r J
    goto icn_101_lrelay
icn_103_β:
    goto icn_79_seq_rf_3
icn_101_lrelay:
    putstatic queens/icn_101_binop_lc J
    goto icn_101_lstore
icn_101_rrelay:
    putstatic queens/icn_101_binop_rc J
    goto icn_101_compute
icn_101_lb:
    goto icn_103_β
icn_101_α:
    iconst_0
    putstatic queens/icn_101_binop_bf I
    goto icn_103_α
icn_101_β:
    iconst_1
    putstatic queens/icn_101_binop_bf I
    goto icn_103_α
icn_101_lstore:
    getstatic queens/icn_101_binop_bf I
    ifeq icn_102_α
    goto icn_102_β
icn_101_compute:
    getstatic queens/icn_101_binop_lc J
    getstatic queens/icn_101_binop_rc J
    ladd
    goto icn_99_lrelay
icn_99_lrelay:
    putstatic queens/icn_99_binop_lc J
    goto icn_99_lstore
icn_99_rrelay:
    putstatic queens/icn_99_binop_rc J
    goto icn_99_compute
icn_99_lb:
    goto icn_101_β
icn_99_α:
    iconst_0
    putstatic queens/icn_99_binop_bf I
    goto icn_101_α
icn_99_β:
    goto icn_100_β
icn_99_lstore:
    getstatic queens/icn_99_binop_bf I
    ifeq icn_100_α
    goto icn_100_β
icn_99_compute:
    getstatic queens/icn_99_binop_lc J
    getstatic queens/icn_99_binop_rc J
    lsub
    goto icn_98_lsa_ir
    goto icn_99_α
icn_98_lsa_ir:
    lconst_1
    lsub
    putstatic queens/icn_98_lsa_i J
    goto icn_98_lsa_do
icn_98_lsa_do:
    getstatic queens/icn_98_lsa_l Ljava/util/ArrayList;
    getstatic queens/icn_98_lsa_i J
    l2i
    getstatic queens/icn_98_lsa_v J
    invokestatic java/lang/Long/valueOf(J)Ljava/lang/Long;
    invokevirtual java/util/ArrayList/set(ILjava/lang/Object;)Ljava/lang/Object;
    pop
    getstatic queens/icn_98_lsa_v J
    goto icn_79_seq_rg_3
;  INT
icn_106_α:
    ldc2_w 1
    goto icn_105_rrelay
icn_106_β:
    goto icn_105_lb
;  VAR
icn_107_α:
    getstatic queens/icn_pv_try_col_c J
    goto icn_105_lrelay
icn_107_β:
    goto icn_79_seq_rf_4
icn_105_lrelay:
    putstatic queens/icn_105_binop_lc J
    goto icn_105_lstore
icn_105_rrelay:
    putstatic queens/icn_105_binop_rc J
    goto icn_105_compute
icn_105_lb:
    goto icn_107_β
icn_105_α:
    iconst_0
    putstatic queens/icn_105_binop_bf I
    goto icn_107_α
icn_105_β:
    iconst_1
    putstatic queens/icn_105_binop_bf I
    goto icn_107_α
icn_105_lstore:
    getstatic queens/icn_105_binop_bf I
    ifeq icn_106_α
    goto icn_106_β
icn_105_compute:
    getstatic queens/icn_105_binop_lc J
    getstatic queens/icn_105_binop_rc J
    ladd
    goto icn_104_arg0
icn_104_arg0:
    putstatic queens/icn_arg_0 J
    goto icn_104_docall
icn_104_α:
    goto icn_105_α
icn_104_β:
    goto icn_105_β
icn_104_docall:
    getstatic queens/icn_6_binop_lc J
    lstore 152
    getstatic queens/icn_6_binop_rc J
    lstore 154
    getstatic queens/icn_8_binop_lc J
    lstore 156
    getstatic queens/icn_8_binop_rc J
    lstore 158
    getstatic queens/icn_17_binop_lc J
    lstore 160
    getstatic queens/icn_17_binop_rc J
    lstore 162
    getstatic queens/icn_19_binop_lc J
    lstore 164
    getstatic queens/icn_19_binop_rc J
    lstore 166
    getstatic queens/icn_46_lsa_i J
    lstore 168
    getstatic queens/icn_47_binop_lc J
    lstore 170
    getstatic queens/icn_47_binop_rc J
    lstore 172
    getstatic queens/icn_49_binop_lc J
    lstore 174
    getstatic queens/icn_49_binop_rc J
    lstore 176
    getstatic queens/icn_50_binop_lc J
    lstore 178
    getstatic queens/icn_50_binop_rc J
    lstore 180
    getstatic queens/icn_60_I J
    lstore 182
    getstatic queens/icn_60_bound J
    lstore 184
    getstatic queens/icn_60_e1cur J
    lstore 186
    getstatic queens/icn_60_e1val J
    lstore 188
    getstatic queens/icn_60_e2val J
    lstore 190
    getstatic queens/icn_70_binop_lc J
    lstore 192
    getstatic queens/icn_70_binop_rc J
    lstore 194
    getstatic queens/icn_72_binop_lc J
    lstore 196
    getstatic queens/icn_72_binop_rc J
    lstore 198
    getstatic queens/icn_75_augtemp J
    lstore 200
    getstatic queens/icn_pv_try_col_r J
    lstore 202
    getstatic queens/icn_82_lsa_i J
    lstore 204
    getstatic queens/icn_82_lsa_v J
    lstore 206
    getstatic queens/icn_pv_try_col_c J
    lstore 208
    getstatic queens/icn_86_lsa_i J
    lstore 210
    getstatic queens/icn_86_lsa_v J
    lstore 212
    getstatic queens/icn_90_lsa_i J
    lstore 214
    getstatic queens/icn_90_lsa_v J
    lstore 216
    getstatic queens/icn_91_binop_lc J
    lstore 218
    getstatic queens/icn_91_binop_rc J
    lstore 220
    getstatic queens/icn_93_binop_lc J
    lstore 222
    getstatic queens/icn_93_binop_rc J
    lstore 224
    getstatic queens/icn_98_lsa_i J
    lstore 226
    getstatic queens/icn_98_lsa_v J
    lstore 228
    getstatic queens/icn_99_binop_lc J
    lstore 230
    getstatic queens/icn_99_binop_rc J
    lstore 232
    getstatic queens/icn_101_binop_lc J
    lstore 234
    getstatic queens/icn_101_binop_rc J
    lstore 236
    getstatic queens/icn_105_binop_lc J
    lstore 238
    getstatic queens/icn_105_binop_rc J
    lstore 240
    invokestatic queens/icn_try_col()V
    lload 152
    putstatic queens/icn_6_binop_lc J
    lload 154
    putstatic queens/icn_6_binop_rc J
    lload 156
    putstatic queens/icn_8_binop_lc J
    lload 158
    putstatic queens/icn_8_binop_rc J
    lload 160
    putstatic queens/icn_17_binop_lc J
    lload 162
    putstatic queens/icn_17_binop_rc J
    lload 164
    putstatic queens/icn_19_binop_lc J
    lload 166
    putstatic queens/icn_19_binop_rc J
    lload 168
    putstatic queens/icn_46_lsa_i J
    lload 170
    putstatic queens/icn_47_binop_lc J
    lload 172
    putstatic queens/icn_47_binop_rc J
    lload 174
    putstatic queens/icn_49_binop_lc J
    lload 176
    putstatic queens/icn_49_binop_rc J
    lload 178
    putstatic queens/icn_50_binop_lc J
    lload 180
    putstatic queens/icn_50_binop_rc J
    lload 182
    putstatic queens/icn_60_I J
    lload 184
    putstatic queens/icn_60_bound J
    lload 186
    putstatic queens/icn_60_e1cur J
    lload 188
    putstatic queens/icn_60_e1val J
    lload 190
    putstatic queens/icn_60_e2val J
    lload 192
    putstatic queens/icn_70_binop_lc J
    lload 194
    putstatic queens/icn_70_binop_rc J
    lload 196
    putstatic queens/icn_72_binop_lc J
    lload 198
    putstatic queens/icn_72_binop_rc J
    lload 200
    putstatic queens/icn_75_augtemp J
    lload 202
    putstatic queens/icn_pv_try_col_r J
    lload 204
    putstatic queens/icn_82_lsa_i J
    lload 206
    putstatic queens/icn_82_lsa_v J
    lload 208
    putstatic queens/icn_pv_try_col_c J
    lload 210
    putstatic queens/icn_86_lsa_i J
    lload 212
    putstatic queens/icn_86_lsa_v J
    lload 214
    putstatic queens/icn_90_lsa_i J
    lload 216
    putstatic queens/icn_90_lsa_v J
    lload 218
    putstatic queens/icn_91_binop_lc J
    lload 220
    putstatic queens/icn_91_binop_rc J
    lload 222
    putstatic queens/icn_93_binop_lc J
    lload 224
    putstatic queens/icn_93_binop_rc J
    lload 226
    putstatic queens/icn_98_lsa_i J
    lload 228
    putstatic queens/icn_98_lsa_v J
    lload 230
    putstatic queens/icn_99_binop_lc J
    lload 232
    putstatic queens/icn_99_binop_rc J
    lload 234
    putstatic queens/icn_101_binop_lc J
    lload 236
    putstatic queens/icn_101_binop_rc J
    lload 238
    putstatic queens/icn_105_binop_lc J
    lload 240
    putstatic queens/icn_105_binop_rc J
    getstatic queens/icn_failed B
    ifne icn_104_after_call
    getstatic queens/icn_retval J
    goto icn_79_seq_rg_4
icn_104_after_call:
    goto icn_79_seq_rf_4
;  INT
icn_109_α:
    ldc2_w 0
    goto icn_108_store
icn_109_β:
    goto icn_79_seq_rf_5
icn_108_α:
    goto icn_109_α
icn_108_β:
    goto icn_109_β
icn_108_store:
    putstatic queens/icn_110_lsa_v J
    getstatic queens/icn_gvar_rows Ljava/util/ArrayList;
    putstatic queens/icn_110_lsa_l Ljava/util/ArrayList;
;  VAR
icn_111_α:
    getstatic queens/icn_pv_try_col_r J
    goto icn_110_lsa_ir
icn_111_β:
    goto icn_79_seq_rf_5
    goto icn_111_α
icn_110_lsa_ir:
    lconst_1
    lsub
    putstatic queens/icn_110_lsa_i J
    goto icn_110_lsa_do
icn_110_lsa_do:
    getstatic queens/icn_110_lsa_l Ljava/util/ArrayList;
    getstatic queens/icn_110_lsa_i J
    l2i
    getstatic queens/icn_110_lsa_v J
    invokestatic java/lang/Long/valueOf(J)Ljava/lang/Long;
    invokevirtual java/util/ArrayList/set(ILjava/lang/Object;)Ljava/lang/Object;
    pop
    getstatic queens/icn_110_lsa_v J
    goto icn_79_seq_rg_5
;  INT
icn_113_α:
    ldc2_w 0
    goto icn_112_store
icn_113_β:
    goto icn_79_seq_rf_6
icn_112_α:
    goto icn_113_α
icn_112_β:
    goto icn_113_β
icn_112_store:
    putstatic queens/icn_114_lsa_v J
    getstatic queens/icn_gvar_up Ljava/util/ArrayList;
    putstatic queens/icn_114_lsa_l Ljava/util/ArrayList;
;  VAR
icn_116_α:
    getstatic queens/icn_pv_try_col_c J
    goto icn_115_rrelay
icn_116_β:
    goto icn_115_lb
;  VAR
icn_118_α:
    getstatic queens/icn_pv_try_col_r J
    goto icn_117_rrelay
icn_118_β:
    goto icn_117_lb
;  VAR
icn_119_α:
    getstatic queens/icn_gvar_n J
    goto icn_117_lrelay
icn_119_β:
    goto icn_79_seq_rf_6
icn_117_lrelay:
    putstatic queens/icn_117_binop_lc J
    goto icn_117_lstore
icn_117_rrelay:
    putstatic queens/icn_117_binop_rc J
    goto icn_117_compute
icn_117_lb:
    goto icn_119_β
icn_117_α:
    iconst_0
    putstatic queens/icn_117_binop_bf I
    goto icn_119_α
icn_117_β:
    iconst_1
    putstatic queens/icn_117_binop_bf I
    goto icn_119_α
icn_117_lstore:
    getstatic queens/icn_117_binop_bf I
    ifeq icn_118_α
    goto icn_118_β
icn_117_compute:
    getstatic queens/icn_117_binop_lc J
    getstatic queens/icn_117_binop_rc J
    ladd
    goto icn_115_lrelay
icn_115_lrelay:
    putstatic queens/icn_115_binop_lc J
    goto icn_115_lstore
icn_115_rrelay:
    putstatic queens/icn_115_binop_rc J
    goto icn_115_compute
icn_115_lb:
    goto icn_117_β
icn_115_α:
    iconst_0
    putstatic queens/icn_115_binop_bf I
    goto icn_117_α
icn_115_β:
    goto icn_116_β
icn_115_lstore:
    getstatic queens/icn_115_binop_bf I
    ifeq icn_116_α
    goto icn_116_β
icn_115_compute:
    getstatic queens/icn_115_binop_lc J
    getstatic queens/icn_115_binop_rc J
    lsub
    goto icn_114_lsa_ir
    goto icn_115_α
icn_114_lsa_ir:
    lconst_1
    lsub
    putstatic queens/icn_114_lsa_i J
    goto icn_114_lsa_do
icn_114_lsa_do:
    getstatic queens/icn_114_lsa_l Ljava/util/ArrayList;
    getstatic queens/icn_114_lsa_i J
    l2i
    getstatic queens/icn_114_lsa_v J
    invokestatic java/lang/Long/valueOf(J)Ljava/lang/Long;
    invokevirtual java/util/ArrayList/set(ILjava/lang/Object;)Ljava/lang/Object;
    pop
    getstatic queens/icn_114_lsa_v J
    goto icn_79_seq_rg_6
;  INT
icn_121_α:
    ldc2_w 0
    goto icn_120_store
icn_121_β:
    goto icn_77_pump
icn_120_α:
    goto icn_121_α
icn_120_β:
    goto icn_121_β
icn_120_store:
    putstatic queens/icn_122_lsa_v J
    getstatic queens/icn_gvar_down Ljava/util/ArrayList;
    putstatic queens/icn_122_lsa_l Ljava/util/ArrayList;
;  INT
icn_124_α:
    ldc2_w 1
    goto icn_123_rrelay
icn_124_β:
    goto icn_123_lb
;  VAR
icn_126_α:
    getstatic queens/icn_pv_try_col_c J
    goto icn_125_rrelay
icn_126_β:
    goto icn_125_lb
;  VAR
icn_127_α:
    getstatic queens/icn_pv_try_col_r J
    goto icn_125_lrelay
icn_127_β:
    goto icn_77_pump
icn_125_lrelay:
    putstatic queens/icn_125_binop_lc J
    goto icn_125_lstore
icn_125_rrelay:
    putstatic queens/icn_125_binop_rc J
    goto icn_125_compute
icn_125_lb:
    goto icn_127_β
icn_125_α:
    iconst_0
    putstatic queens/icn_125_binop_bf I
    goto icn_127_α
icn_125_β:
    iconst_1
    putstatic queens/icn_125_binop_bf I
    goto icn_127_α
icn_125_lstore:
    getstatic queens/icn_125_binop_bf I
    ifeq icn_126_α
    goto icn_126_β
icn_125_compute:
    getstatic queens/icn_125_binop_lc J
    getstatic queens/icn_125_binop_rc J
    ladd
    goto icn_123_lrelay
icn_123_lrelay:
    putstatic queens/icn_123_binop_lc J
    goto icn_123_lstore
icn_123_rrelay:
    putstatic queens/icn_123_binop_rc J
    goto icn_123_compute
icn_123_lb:
    goto icn_125_β
icn_123_α:
    iconst_0
    putstatic queens/icn_123_binop_bf I
    goto icn_125_α
icn_123_β:
    goto icn_124_β
icn_123_lstore:
    getstatic queens/icn_123_binop_bf I
    ifeq icn_124_α
    goto icn_124_β
icn_123_compute:
    getstatic queens/icn_123_binop_lc J
    getstatic queens/icn_123_binop_rc J
    lsub
    goto icn_122_lsa_ir
    goto icn_123_α
icn_122_lsa_ir:
    lconst_1
    lsub
    putstatic queens/icn_122_lsa_i J
    goto icn_122_lsa_do
icn_122_lsa_do:
    getstatic queens/icn_122_lsa_l Ljava/util/ArrayList;
    getstatic queens/icn_122_lsa_i J
    l2i
    getstatic queens/icn_122_lsa_v J
    invokestatic java/lang/Long/valueOf(J)Ljava/lang/Long;
    invokevirtual java/util/ArrayList/set(ILjava/lang/Object;)Ljava/lang/Object;
    pop
    getstatic queens/icn_122_lsa_v J
    goto icn_77_bdrain
    goto icn_79_α
icn_79_seq_rg_0:
    pop2
    goto icn_84_α
icn_79_seq_rg_1:
    pop2
    goto icn_88_α
icn_79_seq_rg_2:
    pop2
    goto icn_96_α
icn_79_seq_rg_3:
    pop2
    goto icn_104_α
icn_79_seq_rg_4:
    pop2
    goto icn_108_α
icn_79_seq_rg_5:
    pop2
    goto icn_112_α
icn_79_seq_rg_6:
    pop2
    goto icn_120_α
icn_79_seq_rf_0:
    goto icn_84_α
icn_79_seq_rf_1:
    goto icn_88_α
icn_79_seq_rf_2:
    goto icn_96_α
icn_79_seq_rf_3:
    goto icn_104_α
icn_79_seq_rf_4:
    goto icn_108_α
icn_79_seq_rf_5:
    goto icn_112_α
icn_79_seq_rf_6:
    goto icn_120_α
icn_79_α:
    goto icn_80_α
icn_79_β:
    goto icn_120_β
;  VAR
icn_129_α:
    getstatic queens/icn_pv_try_col_r J
    goto icn_128_arg1
icn_129_β:
    goto icn_78_else
icn_128_arg1:
    putstatic queens/icn_arg_1 J
    goto icn_128_docall
;  VAR
icn_130_α:
    getstatic queens/icn_pv_try_col_c J
    goto icn_128_arg0
icn_130_β:
    goto icn_78_else
icn_128_arg0:
    putstatic queens/icn_arg_0 J
    goto icn_129_α
icn_128_α:
    goto icn_130_α
icn_128_β:
    goto icn_129_β
icn_128_docall:
    getstatic queens/icn_6_binop_lc J
    lstore 152
    getstatic queens/icn_6_binop_rc J
    lstore 154
    getstatic queens/icn_8_binop_lc J
    lstore 156
    getstatic queens/icn_8_binop_rc J
    lstore 158
    getstatic queens/icn_17_binop_lc J
    lstore 160
    getstatic queens/icn_17_binop_rc J
    lstore 162
    getstatic queens/icn_19_binop_lc J
    lstore 164
    getstatic queens/icn_19_binop_rc J
    lstore 166
    getstatic queens/icn_46_lsa_i J
    lstore 168
    getstatic queens/icn_47_binop_lc J
    lstore 170
    getstatic queens/icn_47_binop_rc J
    lstore 172
    getstatic queens/icn_49_binop_lc J
    lstore 174
    getstatic queens/icn_49_binop_rc J
    lstore 176
    getstatic queens/icn_50_binop_lc J
    lstore 178
    getstatic queens/icn_50_binop_rc J
    lstore 180
    getstatic queens/icn_60_I J
    lstore 182
    getstatic queens/icn_60_bound J
    lstore 184
    getstatic queens/icn_60_e1cur J
    lstore 186
    getstatic queens/icn_60_e1val J
    lstore 188
    getstatic queens/icn_60_e2val J
    lstore 190
    getstatic queens/icn_70_binop_lc J
    lstore 192
    getstatic queens/icn_70_binop_rc J
    lstore 194
    getstatic queens/icn_72_binop_lc J
    lstore 196
    getstatic queens/icn_72_binop_rc J
    lstore 198
    getstatic queens/icn_75_augtemp J
    lstore 200
    getstatic queens/icn_pv_try_col_r J
    lstore 202
    getstatic queens/icn_82_lsa_i J
    lstore 204
    getstatic queens/icn_82_lsa_v J
    lstore 206
    getstatic queens/icn_pv_try_col_c J
    lstore 208
    getstatic queens/icn_86_lsa_i J
    lstore 210
    getstatic queens/icn_86_lsa_v J
    lstore 212
    getstatic queens/icn_90_lsa_i J
    lstore 214
    getstatic queens/icn_90_lsa_v J
    lstore 216
    getstatic queens/icn_91_binop_lc J
    lstore 218
    getstatic queens/icn_91_binop_rc J
    lstore 220
    getstatic queens/icn_93_binop_lc J
    lstore 222
    getstatic queens/icn_93_binop_rc J
    lstore 224
    getstatic queens/icn_98_lsa_i J
    lstore 226
    getstatic queens/icn_98_lsa_v J
    lstore 228
    getstatic queens/icn_99_binop_lc J
    lstore 230
    getstatic queens/icn_99_binop_rc J
    lstore 232
    getstatic queens/icn_101_binop_lc J
    lstore 234
    getstatic queens/icn_101_binop_rc J
    lstore 236
    getstatic queens/icn_105_binop_lc J
    lstore 238
    getstatic queens/icn_105_binop_rc J
    lstore 240
    getstatic queens/icn_110_lsa_i J
    lstore 242
    getstatic queens/icn_110_lsa_v J
    lstore 244
    getstatic queens/icn_114_lsa_i J
    lstore 246
    getstatic queens/icn_114_lsa_v J
    lstore 248
    getstatic queens/icn_115_binop_lc J
    lstore 250
    getstatic queens/icn_115_binop_rc J
    lstore 252
    getstatic queens/icn_117_binop_lc J
    lstore 254
    getstatic queens/icn_117_binop_rc J
    lstore 256
    getstatic queens/icn_122_lsa_i J
    lstore 258
    getstatic queens/icn_122_lsa_v J
    lstore 260
    getstatic queens/icn_123_binop_lc J
    lstore 262
    getstatic queens/icn_123_binop_rc J
    lstore 264
    getstatic queens/icn_125_binop_lc J
    lstore 266
    getstatic queens/icn_125_binop_rc J
    lstore 268
    invokestatic queens/icn_safe()V
    lload 152
    putstatic queens/icn_6_binop_lc J
    lload 154
    putstatic queens/icn_6_binop_rc J
    lload 156
    putstatic queens/icn_8_binop_lc J
    lload 158
    putstatic queens/icn_8_binop_rc J
    lload 160
    putstatic queens/icn_17_binop_lc J
    lload 162
    putstatic queens/icn_17_binop_rc J
    lload 164
    putstatic queens/icn_19_binop_lc J
    lload 166
    putstatic queens/icn_19_binop_rc J
    lload 168
    putstatic queens/icn_46_lsa_i J
    lload 170
    putstatic queens/icn_47_binop_lc J
    lload 172
    putstatic queens/icn_47_binop_rc J
    lload 174
    putstatic queens/icn_49_binop_lc J
    lload 176
    putstatic queens/icn_49_binop_rc J
    lload 178
    putstatic queens/icn_50_binop_lc J
    lload 180
    putstatic queens/icn_50_binop_rc J
    lload 182
    putstatic queens/icn_60_I J
    lload 184
    putstatic queens/icn_60_bound J
    lload 186
    putstatic queens/icn_60_e1cur J
    lload 188
    putstatic queens/icn_60_e1val J
    lload 190
    putstatic queens/icn_60_e2val J
    lload 192
    putstatic queens/icn_70_binop_lc J
    lload 194
    putstatic queens/icn_70_binop_rc J
    lload 196
    putstatic queens/icn_72_binop_lc J
    lload 198
    putstatic queens/icn_72_binop_rc J
    lload 200
    putstatic queens/icn_75_augtemp J
    lload 202
    putstatic queens/icn_pv_try_col_r J
    lload 204
    putstatic queens/icn_82_lsa_i J
    lload 206
    putstatic queens/icn_82_lsa_v J
    lload 208
    putstatic queens/icn_pv_try_col_c J
    lload 210
    putstatic queens/icn_86_lsa_i J
    lload 212
    putstatic queens/icn_86_lsa_v J
    lload 214
    putstatic queens/icn_90_lsa_i J
    lload 216
    putstatic queens/icn_90_lsa_v J
    lload 218
    putstatic queens/icn_91_binop_lc J
    lload 220
    putstatic queens/icn_91_binop_rc J
    lload 222
    putstatic queens/icn_93_binop_lc J
    lload 224
    putstatic queens/icn_93_binop_rc J
    lload 226
    putstatic queens/icn_98_lsa_i J
    lload 228
    putstatic queens/icn_98_lsa_v J
    lload 230
    putstatic queens/icn_99_binop_lc J
    lload 232
    putstatic queens/icn_99_binop_rc J
    lload 234
    putstatic queens/icn_101_binop_lc J
    lload 236
    putstatic queens/icn_101_binop_rc J
    lload 238
    putstatic queens/icn_105_binop_lc J
    lload 240
    putstatic queens/icn_105_binop_rc J
    lload 242
    putstatic queens/icn_110_lsa_i J
    lload 244
    putstatic queens/icn_110_lsa_v J
    lload 246
    putstatic queens/icn_114_lsa_i J
    lload 248
    putstatic queens/icn_114_lsa_v J
    lload 250
    putstatic queens/icn_115_binop_lc J
    lload 252
    putstatic queens/icn_115_binop_rc J
    lload 254
    putstatic queens/icn_117_binop_lc J
    lload 256
    putstatic queens/icn_117_binop_rc J
    lload 258
    putstatic queens/icn_122_lsa_i J
    lload 260
    putstatic queens/icn_122_lsa_v J
    lload 262
    putstatic queens/icn_123_binop_lc J
    lload 264
    putstatic queens/icn_123_binop_rc J
    lload 266
    putstatic queens/icn_125_binop_lc J
    lload 268
    putstatic queens/icn_125_binop_rc J
    getstatic queens/icn_failed B
    ifne icn_128_after_call
    getstatic queens/icn_retval J
    goto icn_78_then
icn_128_after_call:
    goto icn_78_else
icn_78_then:
    pop2
    goto icn_79_α
icn_78_else:
    goto icn_77_pump
icn_78_α:
    goto icn_128_α
icn_78_β:
    goto icn_128_β
;  VAR
icn_133_α:
    getstatic queens/icn_gvar_n J
    goto icn_132_e2relay
icn_133_β:
    goto icn_132_e1b
;  INT
icn_134_α:
    ldc2_w 1
    goto icn_132_e1relay
icn_134_β:
    goto icn_try_col_done
icn_132_e1relay:
    putstatic queens/icn_132_e1val J
    goto icn_133_α
icn_132_e2relay:
    putstatic queens/icn_132_e2val J
    goto icn_132_init
icn_132_e1b:
    iconst_0
    putstatic queens/icn_132_e2seen I
    goto icn_134_β
icn_132_e2b:
    goto icn_133_β
icn_132_α:
    iconst_0
    putstatic queens/icn_132_e2seen I
    goto icn_134_α
icn_132_β:
    getstatic queens/icn_132_I J
    lconst_1
    ladd
    putstatic queens/icn_132_I J
    goto icn_132_code
icn_132_init:
    getstatic queens/icn_132_e2val J
    putstatic queens/icn_132_bound J
    getstatic queens/icn_132_e2seen I
    ifne icn_132_init_e2adv
    getstatic queens/icn_132_e1val J
    putstatic queens/icn_132_e1cur J
    getstatic queens/icn_132_e1cur J
    putstatic queens/icn_132_I J
    iconst_1
    putstatic queens/icn_132_e2seen I
    goto icn_132_code
icn_132_init_e2adv:
    getstatic queens/icn_132_e1cur J
    putstatic queens/icn_132_I J
    goto icn_132_code
icn_132_code:
    getstatic queens/icn_132_I J
    getstatic queens/icn_132_bound J
    lcmp
    ifgt icn_132_e2b
    getstatic queens/icn_132_I J
    goto icn_131_store
icn_131_α:
    goto icn_132_α
icn_131_β:
    goto icn_132_β
icn_131_store:
    putstatic queens/icn_pv_try_col_r J
    getstatic queens/icn_pv_try_col_r J
    goto icn_77_gdrain
icn_77_gdrain:
    pop2
    goto icn_78_α
icn_77_bdrain:
    pop2
icn_77_pump:
    goto icn_131_β
icn_77_α:
    goto icn_131_α
icn_77_β:
    goto icn_try_col_done
icn_137_α:
    goto icn_137_docall
icn_137_β:
    goto icn_136_seq_rf_0
icn_137_docall:
    getstatic queens/icn_6_binop_lc J
    lstore 152
    getstatic queens/icn_6_binop_rc J
    lstore 154
    getstatic queens/icn_8_binop_lc J
    lstore 156
    getstatic queens/icn_8_binop_rc J
    lstore 158
    getstatic queens/icn_17_binop_lc J
    lstore 160
    getstatic queens/icn_17_binop_rc J
    lstore 162
    getstatic queens/icn_19_binop_lc J
    lstore 164
    getstatic queens/icn_19_binop_rc J
    lstore 166
    getstatic queens/icn_46_lsa_i J
    lstore 168
    getstatic queens/icn_47_binop_lc J
    lstore 170
    getstatic queens/icn_47_binop_rc J
    lstore 172
    getstatic queens/icn_49_binop_lc J
    lstore 174
    getstatic queens/icn_49_binop_rc J
    lstore 176
    getstatic queens/icn_50_binop_lc J
    lstore 178
    getstatic queens/icn_50_binop_rc J
    lstore 180
    getstatic queens/icn_60_I J
    lstore 182
    getstatic queens/icn_60_bound J
    lstore 184
    getstatic queens/icn_60_e1cur J
    lstore 186
    getstatic queens/icn_60_e1val J
    lstore 188
    getstatic queens/icn_60_e2val J
    lstore 190
    getstatic queens/icn_70_binop_lc J
    lstore 192
    getstatic queens/icn_70_binop_rc J
    lstore 194
    getstatic queens/icn_72_binop_lc J
    lstore 196
    getstatic queens/icn_72_binop_rc J
    lstore 198
    getstatic queens/icn_75_augtemp J
    lstore 200
    getstatic queens/icn_pv_try_col_r J
    lstore 202
    getstatic queens/icn_82_lsa_i J
    lstore 204
    getstatic queens/icn_82_lsa_v J
    lstore 206
    getstatic queens/icn_pv_try_col_c J
    lstore 208
    getstatic queens/icn_86_lsa_i J
    lstore 210
    getstatic queens/icn_86_lsa_v J
    lstore 212
    getstatic queens/icn_90_lsa_i J
    lstore 214
    getstatic queens/icn_90_lsa_v J
    lstore 216
    getstatic queens/icn_91_binop_lc J
    lstore 218
    getstatic queens/icn_91_binop_rc J
    lstore 220
    getstatic queens/icn_93_binop_lc J
    lstore 222
    getstatic queens/icn_93_binop_rc J
    lstore 224
    getstatic queens/icn_98_lsa_i J
    lstore 226
    getstatic queens/icn_98_lsa_v J
    lstore 228
    getstatic queens/icn_99_binop_lc J
    lstore 230
    getstatic queens/icn_99_binop_rc J
    lstore 232
    getstatic queens/icn_101_binop_lc J
    lstore 234
    getstatic queens/icn_101_binop_rc J
    lstore 236
    getstatic queens/icn_105_binop_lc J
    lstore 238
    getstatic queens/icn_105_binop_rc J
    lstore 240
    getstatic queens/icn_110_lsa_i J
    lstore 242
    getstatic queens/icn_110_lsa_v J
    lstore 244
    getstatic queens/icn_114_lsa_i J
    lstore 246
    getstatic queens/icn_114_lsa_v J
    lstore 248
    getstatic queens/icn_115_binop_lc J
    lstore 250
    getstatic queens/icn_115_binop_rc J
    lstore 252
    getstatic queens/icn_117_binop_lc J
    lstore 254
    getstatic queens/icn_117_binop_rc J
    lstore 256
    getstatic queens/icn_122_lsa_i J
    lstore 258
    getstatic queens/icn_122_lsa_v J
    lstore 260
    getstatic queens/icn_123_binop_lc J
    lstore 262
    getstatic queens/icn_123_binop_rc J
    lstore 264
    getstatic queens/icn_125_binop_lc J
    lstore 266
    getstatic queens/icn_125_binop_rc J
    lstore 268
    getstatic queens/icn_132_I J
    lstore 270
    getstatic queens/icn_132_bound J
    lstore 272
    getstatic queens/icn_132_e1cur J
    lstore 274
    getstatic queens/icn_132_e1val J
    lstore 276
    getstatic queens/icn_132_e2val J
    lstore 278
    invokestatic queens/icn_show()V
    lload 152
    putstatic queens/icn_6_binop_lc J
    lload 154
    putstatic queens/icn_6_binop_rc J
    lload 156
    putstatic queens/icn_8_binop_lc J
    lload 158
    putstatic queens/icn_8_binop_rc J
    lload 160
    putstatic queens/icn_17_binop_lc J
    lload 162
    putstatic queens/icn_17_binop_rc J
    lload 164
    putstatic queens/icn_19_binop_lc J
    lload 166
    putstatic queens/icn_19_binop_rc J
    lload 168
    putstatic queens/icn_46_lsa_i J
    lload 170
    putstatic queens/icn_47_binop_lc J
    lload 172
    putstatic queens/icn_47_binop_rc J
    lload 174
    putstatic queens/icn_49_binop_lc J
    lload 176
    putstatic queens/icn_49_binop_rc J
    lload 178
    putstatic queens/icn_50_binop_lc J
    lload 180
    putstatic queens/icn_50_binop_rc J
    lload 182
    putstatic queens/icn_60_I J
    lload 184
    putstatic queens/icn_60_bound J
    lload 186
    putstatic queens/icn_60_e1cur J
    lload 188
    putstatic queens/icn_60_e1val J
    lload 190
    putstatic queens/icn_60_e2val J
    lload 192
    putstatic queens/icn_70_binop_lc J
    lload 194
    putstatic queens/icn_70_binop_rc J
    lload 196
    putstatic queens/icn_72_binop_lc J
    lload 198
    putstatic queens/icn_72_binop_rc J
    lload 200
    putstatic queens/icn_75_augtemp J
    lload 202
    putstatic queens/icn_pv_try_col_r J
    lload 204
    putstatic queens/icn_82_lsa_i J
    lload 206
    putstatic queens/icn_82_lsa_v J
    lload 208
    putstatic queens/icn_pv_try_col_c J
    lload 210
    putstatic queens/icn_86_lsa_i J
    lload 212
    putstatic queens/icn_86_lsa_v J
    lload 214
    putstatic queens/icn_90_lsa_i J
    lload 216
    putstatic queens/icn_90_lsa_v J
    lload 218
    putstatic queens/icn_91_binop_lc J
    lload 220
    putstatic queens/icn_91_binop_rc J
    lload 222
    putstatic queens/icn_93_binop_lc J
    lload 224
    putstatic queens/icn_93_binop_rc J
    lload 226
    putstatic queens/icn_98_lsa_i J
    lload 228
    putstatic queens/icn_98_lsa_v J
    lload 230
    putstatic queens/icn_99_binop_lc J
    lload 232
    putstatic queens/icn_99_binop_rc J
    lload 234
    putstatic queens/icn_101_binop_lc J
    lload 236
    putstatic queens/icn_101_binop_rc J
    lload 238
    putstatic queens/icn_105_binop_lc J
    lload 240
    putstatic queens/icn_105_binop_rc J
    lload 242
    putstatic queens/icn_110_lsa_i J
    lload 244
    putstatic queens/icn_110_lsa_v J
    lload 246
    putstatic queens/icn_114_lsa_i J
    lload 248
    putstatic queens/icn_114_lsa_v J
    lload 250
    putstatic queens/icn_115_binop_lc J
    lload 252
    putstatic queens/icn_115_binop_rc J
    lload 254
    putstatic queens/icn_117_binop_lc J
    lload 256
    putstatic queens/icn_117_binop_rc J
    lload 258
    putstatic queens/icn_122_lsa_i J
    lload 260
    putstatic queens/icn_122_lsa_v J
    lload 262
    putstatic queens/icn_123_binop_lc J
    lload 264
    putstatic queens/icn_123_binop_rc J
    lload 266
    putstatic queens/icn_125_binop_lc J
    lload 268
    putstatic queens/icn_125_binop_rc J
    lload 270
    putstatic queens/icn_132_I J
    lload 272
    putstatic queens/icn_132_bound J
    lload 274
    putstatic queens/icn_132_e1cur J
    lload 276
    putstatic queens/icn_132_e1val J
    lload 278
    putstatic queens/icn_132_e2val J
    getstatic queens/icn_failed B
    ifne icn_137_after_call
    getstatic queens/icn_retval J
    goto icn_136_seq_rg_0
icn_137_after_call:
    goto icn_136_seq_rf_0
icn_138_α:
    lconst_0
    putstatic queens/icn_retval J
    iconst_0
    putstatic queens/icn_failed B
    goto icn_try_col_ret
icn_138_β:
    goto icn_try_col_ret
    goto icn_136_α
icn_136_seq_rg_0:
    pop2
    goto icn_138_α
icn_136_seq_rf_0:
    goto icn_138_α
icn_136_α:
    goto icn_137_α
icn_136_β:
    goto icn_138_β
;  VAR
icn_140_α:
    getstatic queens/icn_gvar_n J
    goto icn_139_rrelay
icn_140_β:
    goto icn_139_lb
;  VAR
icn_141_α:
    getstatic queens/icn_pv_try_col_c J
    goto icn_139_lrelay
icn_141_β:
    goto icn_135_else
icn_139_lrelay:
    putstatic queens/icn_139_relop_lc J
    goto icn_139_lstore
icn_139_rrelay:
    putstatic queens/icn_139_relop_rc J
    goto icn_139_check
icn_139_lb:
    goto icn_141_β
icn_139_α:
    goto icn_141_α
icn_139_β:
    goto icn_140_β
icn_139_lstore:
    goto icn_140_α
icn_139_check:
    getstatic queens/icn_139_relop_lc J
    getstatic queens/icn_139_relop_rc J
    lcmp
    ifle icn_140_β
    getstatic queens/icn_139_relop_rc J
    goto icn_135_then
icn_135_then:
    pop2
    goto icn_136_α
icn_135_else:
    goto icn_77_α
icn_135_α:
    goto icn_139_α
icn_135_β:
    goto icn_139_β
icn_try_col_s1_sdrain:
    pop2
    goto icn_77_α
icn_try_col_done:
    iconst_0
    putstatic queens/icn_suspended B
    iconst_0
    putstatic queens/icn_suspend_id I
    iconst_1
    putstatic queens/icn_failed B
    return
icn_try_col_ret:
    iconst_0
    putstatic queens/icn_failed B
    return
icn_try_col_sret:
    return
.end method

.method public static icn_main()V
    .limit stack 16
    .limit locals 483
    lconst_0
    lstore 0
    lconst_0
    lstore 2
    lconst_0
    lstore 4
    lconst_0
    lstore 6
    lconst_0
    lstore 8
    lconst_0
    lstore 10
    lconst_0
    lstore 12
    lconst_0
    lstore 14
    lconst_0
    lstore 16
    lconst_0
    lstore 18
    lconst_0
    lstore 20
    lconst_0
    lstore 22
    lconst_0
    lstore 24
    lconst_0
    lstore 26
    lconst_0
    lstore 28
    lconst_0
    lstore 30
    lconst_0
    lstore 32
    lconst_0
    lstore 34
    lconst_0
    lstore 36
    lconst_0
    lstore 38
    lconst_0
    lstore 40
    lconst_0
    lstore 42
    lconst_0
    lstore 44
    lconst_0
    lstore 46
    lconst_0
    lstore 48
    lconst_0
    lstore 50
    lconst_0
    lstore 52
    lconst_0
    lstore 54
    lconst_0
    lstore 56
    lconst_0
    lstore 58
    lconst_0
    lstore 60
    lconst_0
    lstore 62
    iconst_0
    istore 84
    iconst_0
    istore 85
    iconst_0
    istore 86
    iconst_0
    istore 87
    iconst_0
    istore 88
    aconst_null
    astore 148
    aconst_null
    astore 149
    aconst_null
    astore 150
    aconst_null
    astore 151
    aconst_null
    astore 152
    aconst_null
    astore 153
    aconst_null
    astore 154
    goto icn_176_α
;  VAR
icn_143_α:
    getstatic queens/icn_gvar_qcount J
    goto icn_142_waft_0
icn_143_β:
    goto icn_main_done
;  STR
icn_144_α:
    ldc " solutions total."
    goto icn_142_waft_1
icn_144_β:
    goto icn_main_done
icn_142_α:
    goto icn_143_α
icn_142_β:
    goto icn_143_β
    goto icn_142_wentry
icn_142_waft_0:
    lstore 2
    getstatic java/lang/System/out Ljava/io/PrintStream;
    lload 2
    invokevirtual java/io/PrintStream/print(J)V
    goto icn_144_α
icn_142_waft_1:
    astore 148
    getstatic java/lang/System/out Ljava/io/PrintStream;
    aload 148
    invokevirtual java/io/PrintStream/print(Ljava/lang/String;)V
    getstatic java/lang/System/out Ljava/io/PrintStream;
    ldc ""
    invokevirtual java/io/PrintStream/println(Ljava/lang/String;)V
    aload 148
    goto icn_main_s8_sdrain
icn_142_wentry:
    goto icn_143_α
icn_main_s8_sdrain:
    pop
    goto icn_main_done
;  INT
icn_146_α:
    ldc2_w 1
    goto icn_145_arg0
icn_146_β:
    goto icn_142_α
icn_145_arg0:
    putstatic queens/icn_arg_0 J
    goto icn_145_docall
icn_145_α:
    goto icn_146_α
icn_145_β:
    goto icn_146_β
icn_145_docall:
    getstatic queens/icn_6_binop_lc J
    lstore 153
    getstatic queens/icn_6_binop_rc J
    lstore 155
    getstatic queens/icn_8_binop_lc J
    lstore 157
    getstatic queens/icn_8_binop_rc J
    lstore 159
    getstatic queens/icn_17_binop_lc J
    lstore 161
    getstatic queens/icn_17_binop_rc J
    lstore 163
    getstatic queens/icn_19_binop_lc J
    lstore 165
    getstatic queens/icn_19_binop_rc J
    lstore 167
    getstatic queens/icn_46_lsa_i J
    lstore 169
    getstatic queens/icn_47_binop_lc J
    lstore 171
    getstatic queens/icn_47_binop_rc J
    lstore 173
    getstatic queens/icn_49_binop_lc J
    lstore 175
    getstatic queens/icn_49_binop_rc J
    lstore 177
    getstatic queens/icn_50_binop_lc J
    lstore 179
    getstatic queens/icn_50_binop_rc J
    lstore 181
    getstatic queens/icn_60_I J
    lstore 183
    getstatic queens/icn_60_bound J
    lstore 185
    getstatic queens/icn_60_e1cur J
    lstore 187
    getstatic queens/icn_60_e1val J
    lstore 189
    getstatic queens/icn_60_e2val J
    lstore 191
    getstatic queens/icn_70_binop_lc J
    lstore 193
    getstatic queens/icn_70_binop_rc J
    lstore 195
    getstatic queens/icn_72_binop_lc J
    lstore 197
    getstatic queens/icn_72_binop_rc J
    lstore 199
    getstatic queens/icn_75_augtemp J
    lstore 201
    getstatic queens/icn_82_lsa_i J
    lstore 203
    getstatic queens/icn_82_lsa_v J
    lstore 205
    getstatic queens/icn_86_lsa_i J
    lstore 207
    getstatic queens/icn_86_lsa_v J
    lstore 209
    getstatic queens/icn_90_lsa_i J
    lstore 211
    getstatic queens/icn_90_lsa_v J
    lstore 213
    getstatic queens/icn_91_binop_lc J
    lstore 215
    getstatic queens/icn_91_binop_rc J
    lstore 217
    getstatic queens/icn_93_binop_lc J
    lstore 219
    getstatic queens/icn_93_binop_rc J
    lstore 221
    getstatic queens/icn_98_lsa_i J
    lstore 223
    getstatic queens/icn_98_lsa_v J
    lstore 225
    getstatic queens/icn_99_binop_lc J
    lstore 227
    getstatic queens/icn_99_binop_rc J
    lstore 229
    getstatic queens/icn_101_binop_lc J
    lstore 231
    getstatic queens/icn_101_binop_rc J
    lstore 233
    getstatic queens/icn_105_binop_lc J
    lstore 235
    getstatic queens/icn_105_binop_rc J
    lstore 237
    getstatic queens/icn_110_lsa_i J
    lstore 239
    getstatic queens/icn_110_lsa_v J
    lstore 241
    getstatic queens/icn_114_lsa_i J
    lstore 243
    getstatic queens/icn_114_lsa_v J
    lstore 245
    getstatic queens/icn_115_binop_lc J
    lstore 247
    getstatic queens/icn_115_binop_rc J
    lstore 249
    getstatic queens/icn_117_binop_lc J
    lstore 251
    getstatic queens/icn_117_binop_rc J
    lstore 253
    getstatic queens/icn_122_lsa_i J
    lstore 255
    getstatic queens/icn_122_lsa_v J
    lstore 257
    getstatic queens/icn_123_binop_lc J
    lstore 259
    getstatic queens/icn_123_binop_rc J
    lstore 261
    getstatic queens/icn_125_binop_lc J
    lstore 263
    getstatic queens/icn_125_binop_rc J
    lstore 265
    getstatic queens/icn_132_I J
    lstore 267
    getstatic queens/icn_132_bound J
    lstore 269
    getstatic queens/icn_132_e1cur J
    lstore 271
    getstatic queens/icn_132_e1val J
    lstore 273
    getstatic queens/icn_132_e2val J
    lstore 275
    getstatic queens/icn_139_relop_lc J
    lstore 277
    getstatic queens/icn_139_relop_rc J
    lstore 279
    invokestatic queens/icn_try_col()V
    lload 153
    putstatic queens/icn_6_binop_lc J
    lload 155
    putstatic queens/icn_6_binop_rc J
    lload 157
    putstatic queens/icn_8_binop_lc J
    lload 159
    putstatic queens/icn_8_binop_rc J
    lload 161
    putstatic queens/icn_17_binop_lc J
    lload 163
    putstatic queens/icn_17_binop_rc J
    lload 165
    putstatic queens/icn_19_binop_lc J
    lload 167
    putstatic queens/icn_19_binop_rc J
    lload 169
    putstatic queens/icn_46_lsa_i J
    lload 171
    putstatic queens/icn_47_binop_lc J
    lload 173
    putstatic queens/icn_47_binop_rc J
    lload 175
    putstatic queens/icn_49_binop_lc J
    lload 177
    putstatic queens/icn_49_binop_rc J
    lload 179
    putstatic queens/icn_50_binop_lc J
    lload 181
    putstatic queens/icn_50_binop_rc J
    lload 183
    putstatic queens/icn_60_I J
    lload 185
    putstatic queens/icn_60_bound J
    lload 187
    putstatic queens/icn_60_e1cur J
    lload 189
    putstatic queens/icn_60_e1val J
    lload 191
    putstatic queens/icn_60_e2val J
    lload 193
    putstatic queens/icn_70_binop_lc J
    lload 195
    putstatic queens/icn_70_binop_rc J
    lload 197
    putstatic queens/icn_72_binop_lc J
    lload 199
    putstatic queens/icn_72_binop_rc J
    lload 201
    putstatic queens/icn_75_augtemp J
    lload 203
    putstatic queens/icn_82_lsa_i J
    lload 205
    putstatic queens/icn_82_lsa_v J
    lload 207
    putstatic queens/icn_86_lsa_i J
    lload 209
    putstatic queens/icn_86_lsa_v J
    lload 211
    putstatic queens/icn_90_lsa_i J
    lload 213
    putstatic queens/icn_90_lsa_v J
    lload 215
    putstatic queens/icn_91_binop_lc J
    lload 217
    putstatic queens/icn_91_binop_rc J
    lload 219
    putstatic queens/icn_93_binop_lc J
    lload 221
    putstatic queens/icn_93_binop_rc J
    lload 223
    putstatic queens/icn_98_lsa_i J
    lload 225
    putstatic queens/icn_98_lsa_v J
    lload 227
    putstatic queens/icn_99_binop_lc J
    lload 229
    putstatic queens/icn_99_binop_rc J
    lload 231
    putstatic queens/icn_101_binop_lc J
    lload 233
    putstatic queens/icn_101_binop_rc J
    lload 235
    putstatic queens/icn_105_binop_lc J
    lload 237
    putstatic queens/icn_105_binop_rc J
    lload 239
    putstatic queens/icn_110_lsa_i J
    lload 241
    putstatic queens/icn_110_lsa_v J
    lload 243
    putstatic queens/icn_114_lsa_i J
    lload 245
    putstatic queens/icn_114_lsa_v J
    lload 247
    putstatic queens/icn_115_binop_lc J
    lload 249
    putstatic queens/icn_115_binop_rc J
    lload 251
    putstatic queens/icn_117_binop_lc J
    lload 253
    putstatic queens/icn_117_binop_rc J
    lload 255
    putstatic queens/icn_122_lsa_i J
    lload 257
    putstatic queens/icn_122_lsa_v J
    lload 259
    putstatic queens/icn_123_binop_lc J
    lload 261
    putstatic queens/icn_123_binop_rc J
    lload 263
    putstatic queens/icn_125_binop_lc J
    lload 265
    putstatic queens/icn_125_binop_rc J
    lload 267
    putstatic queens/icn_132_I J
    lload 269
    putstatic queens/icn_132_bound J
    lload 271
    putstatic queens/icn_132_e1cur J
    lload 273
    putstatic queens/icn_132_e1val J
    lload 275
    putstatic queens/icn_132_e2val J
    lload 277
    putstatic queens/icn_139_relop_lc J
    lload 279
    putstatic queens/icn_139_relop_rc J
    getstatic queens/icn_failed B
    ifne icn_145_after_call
    getstatic queens/icn_retval J
    goto icn_main_s7_sdrain
icn_145_after_call:
    goto icn_142_α
icn_main_s7_sdrain:
    pop2
    goto icn_142_α
;  VAR
icn_148_α:
    getstatic queens/icn_gvar_n J
    goto icn_147_waft_0
icn_148_β:
    goto icn_145_α
;  STR
icn_149_α:
    ldc "-Queens:"
    goto icn_147_waft_1
icn_149_β:
    goto icn_145_α
icn_147_α:
    goto icn_148_α
icn_147_β:
    goto icn_148_β
    goto icn_147_wentry
icn_147_waft_0:
    lstore 4
    getstatic java/lang/System/out Ljava/io/PrintStream;
    lload 4
    invokevirtual java/io/PrintStream/print(J)V
    goto icn_149_α
icn_147_waft_1:
    astore 149
    getstatic java/lang/System/out Ljava/io/PrintStream;
    aload 149
    invokevirtual java/io/PrintStream/print(Ljava/lang/String;)V
    getstatic java/lang/System/out Ljava/io/PrintStream;
    ldc ""
    invokevirtual java/io/PrintStream/println(Ljava/lang/String;)V
    aload 149
    goto icn_main_s6_sdrain
icn_147_wentry:
    goto icn_148_α
icn_main_s6_sdrain:
    pop
    goto icn_145_α
;  INT
icn_151_α:
    ldc2_w 0
    goto icn_150_store
icn_151_β:
    goto icn_147_α
icn_150_α:
    goto icn_151_α
icn_150_β:
    goto icn_151_β
icn_150_store:
    putstatic queens/icn_gvar_qcount J
    getstatic queens/icn_gvar_qcount J
    goto icn_main_s5_sdrain
icn_main_s5_sdrain:
    pop2
    goto icn_147_α
;  INT
icn_155_α:
    ldc2_w 1
    goto icn_154_rrelay
icn_155_β:
    goto icn_154_lb
;  VAR
icn_157_α:
    getstatic queens/icn_gvar_n J
    goto icn_156_rrelay
icn_157_β:
    goto icn_156_lb
;  INT
icn_158_α:
    ldc2_w 2
    goto icn_156_lrelay
icn_158_β:
    goto icn_150_α
icn_156_lrelay:
    putstatic queens/icn_156_binop_lc J
    goto icn_156_lstore
icn_156_rrelay:
    putstatic queens/icn_156_binop_rc J
    goto icn_156_compute
icn_156_lb:
    goto icn_158_β
icn_156_α:
    iconst_0
    putstatic queens/icn_156_binop_bf I
    goto icn_158_α
icn_156_β:
    iconst_1
    putstatic queens/icn_156_binop_bf I
    goto icn_158_α
icn_156_lstore:
    getstatic queens/icn_156_binop_bf I
    ifeq icn_157_α
    goto icn_157_β
icn_156_compute:
    getstatic queens/icn_156_binop_lc J
    getstatic queens/icn_156_binop_rc J
    lmul
    goto icn_154_lrelay
icn_154_lrelay:
    putstatic queens/icn_154_binop_lc J
    goto icn_154_lstore
icn_154_rrelay:
    putstatic queens/icn_154_binop_rc J
    goto icn_154_compute
icn_154_lb:
    goto icn_156_β
icn_154_α:
    iconst_0
    putstatic queens/icn_154_binop_bf I
    goto icn_156_α
icn_154_β:
    goto icn_155_β
icn_154_lstore:
    getstatic queens/icn_154_binop_bf I
    ifeq icn_155_α
    goto icn_155_β
icn_154_compute:
    getstatic queens/icn_154_binop_lc J
    getstatic queens/icn_154_binop_rc J
    lsub
    goto icn_153_nlr
;  INT
icn_159_α:
    ldc2_w 0
    goto icn_153_xlr
icn_159_β:
    goto icn_150_α
icn_153_α:
    goto icn_154_α
icn_153_β:
    goto icn_150_α
icn_153_nlr:
    putstatic queens/icn_153_ln J
    goto icn_159_α
icn_153_xlr:
    invokestatic java/lang/Long/valueOf(J)Ljava/lang/Long;
    putstatic queens/icn_153_lx Ljava/lang/Object;
    new java/util/ArrayList
    dup
    invokespecial java/util/ArrayList/<init>()V
    putstatic queens/icn_153_ll Ljava/util/ArrayList;
    getstatic queens/icn_153_ln J
    l2i
    putstatic queens/icn_153_lc I
icn_153_llp:
    getstatic queens/icn_153_lc I
    ifeq icn_153_lld
    getstatic queens/icn_153_ll Ljava/util/ArrayList;
    getstatic queens/icn_153_lx Ljava/lang/Object;
    invokevirtual java/util/ArrayList/add(Ljava/lang/Object;)Z
    pop
    getstatic queens/icn_153_lc I
    iconst_1
    isub
    putstatic queens/icn_153_lc I
    goto icn_153_llp
icn_153_lld:
    getstatic queens/icn_153_ll Ljava/util/ArrayList;
    goto icn_152_store
icn_152_α:
    goto icn_153_α
icn_152_β:
    goto icn_153_β
icn_152_store:
    putstatic queens/icn_gvar_down Ljava/util/ArrayList;
    getstatic queens/icn_gvar_down Ljava/util/ArrayList;
    goto icn_main_s4_sdrain
icn_main_s4_sdrain:
    pop
    goto icn_150_α
;  INT
icn_163_α:
    ldc2_w 1
    goto icn_162_rrelay
icn_163_β:
    goto icn_162_lb
;  VAR
icn_165_α:
    getstatic queens/icn_gvar_n J
    goto icn_164_rrelay
icn_165_β:
    goto icn_164_lb
;  INT
icn_166_α:
    ldc2_w 2
    goto icn_164_lrelay
icn_166_β:
    goto icn_152_α
icn_164_lrelay:
    putstatic queens/icn_164_binop_lc J
    goto icn_164_lstore
icn_164_rrelay:
    putstatic queens/icn_164_binop_rc J
    goto icn_164_compute
icn_164_lb:
    goto icn_166_β
icn_164_α:
    iconst_0
    putstatic queens/icn_164_binop_bf I
    goto icn_166_α
icn_164_β:
    iconst_1
    putstatic queens/icn_164_binop_bf I
    goto icn_166_α
icn_164_lstore:
    getstatic queens/icn_164_binop_bf I
    ifeq icn_165_α
    goto icn_165_β
icn_164_compute:
    getstatic queens/icn_164_binop_lc J
    getstatic queens/icn_164_binop_rc J
    lmul
    goto icn_162_lrelay
icn_162_lrelay:
    putstatic queens/icn_162_binop_lc J
    goto icn_162_lstore
icn_162_rrelay:
    putstatic queens/icn_162_binop_rc J
    goto icn_162_compute
icn_162_lb:
    goto icn_164_β
icn_162_α:
    iconst_0
    putstatic queens/icn_162_binop_bf I
    goto icn_164_α
icn_162_β:
    goto icn_163_β
icn_162_lstore:
    getstatic queens/icn_162_binop_bf I
    ifeq icn_163_α
    goto icn_163_β
icn_162_compute:
    getstatic queens/icn_162_binop_lc J
    getstatic queens/icn_162_binop_rc J
    lsub
    goto icn_161_nlr
;  INT
icn_167_α:
    ldc2_w 0
    goto icn_161_xlr
icn_167_β:
    goto icn_152_α
icn_161_α:
    goto icn_162_α
icn_161_β:
    goto icn_152_α
icn_161_nlr:
    putstatic queens/icn_161_ln J
    goto icn_167_α
icn_161_xlr:
    invokestatic java/lang/Long/valueOf(J)Ljava/lang/Long;
    putstatic queens/icn_161_lx Ljava/lang/Object;
    new java/util/ArrayList
    dup
    invokespecial java/util/ArrayList/<init>()V
    putstatic queens/icn_161_ll Ljava/util/ArrayList;
    getstatic queens/icn_161_ln J
    l2i
    putstatic queens/icn_161_lc I
icn_161_llp:
    getstatic queens/icn_161_lc I
    ifeq icn_161_lld
    getstatic queens/icn_161_ll Ljava/util/ArrayList;
    getstatic queens/icn_161_lx Ljava/lang/Object;
    invokevirtual java/util/ArrayList/add(Ljava/lang/Object;)Z
    pop
    getstatic queens/icn_161_lc I
    iconst_1
    isub
    putstatic queens/icn_161_lc I
    goto icn_161_llp
icn_161_lld:
    getstatic queens/icn_161_ll Ljava/util/ArrayList;
    goto icn_160_store
icn_160_α:
    goto icn_161_α
icn_160_β:
    goto icn_161_β
icn_160_store:
    putstatic queens/icn_gvar_up Ljava/util/ArrayList;
    getstatic queens/icn_gvar_up Ljava/util/ArrayList;
    goto icn_main_s3_sdrain
icn_main_s3_sdrain:
    pop
    goto icn_152_α
;  VAR
icn_170_α:
    getstatic queens/icn_gvar_n J
    goto icn_169_nlr
icn_170_β:
    goto icn_160_α
;  INT
icn_171_α:
    ldc2_w 0
    goto icn_169_xlr
icn_171_β:
    goto icn_160_α
icn_169_α:
    goto icn_170_α
icn_169_β:
    goto icn_160_α
icn_169_nlr:
    putstatic queens/icn_169_ln J
    goto icn_171_α
icn_169_xlr:
    invokestatic java/lang/Long/valueOf(J)Ljava/lang/Long;
    putstatic queens/icn_169_lx Ljava/lang/Object;
    new java/util/ArrayList
    dup
    invokespecial java/util/ArrayList/<init>()V
    putstatic queens/icn_169_ll Ljava/util/ArrayList;
    getstatic queens/icn_169_ln J
    l2i
    putstatic queens/icn_169_lc I
icn_169_llp:
    getstatic queens/icn_169_lc I
    ifeq icn_169_lld
    getstatic queens/icn_169_ll Ljava/util/ArrayList;
    getstatic queens/icn_169_lx Ljava/lang/Object;
    invokevirtual java/util/ArrayList/add(Ljava/lang/Object;)Z
    pop
    getstatic queens/icn_169_lc I
    iconst_1
    isub
    putstatic queens/icn_169_lc I
    goto icn_169_llp
icn_169_lld:
    getstatic queens/icn_169_ll Ljava/util/ArrayList;
    goto icn_168_store
icn_168_α:
    goto icn_169_α
icn_168_β:
    goto icn_169_β
icn_168_store:
    putstatic queens/icn_gvar_rows Ljava/util/ArrayList;
    getstatic queens/icn_gvar_rows Ljava/util/ArrayList;
    goto icn_main_s2_sdrain
icn_main_s2_sdrain:
    pop
    goto icn_160_α
;  VAR
icn_174_α:
    getstatic queens/icn_gvar_n J
    goto icn_173_nlr
icn_174_β:
    goto icn_168_α
;  INT
icn_175_α:
    ldc2_w 0
    goto icn_173_xlr
icn_175_β:
    goto icn_168_α
icn_173_α:
    goto icn_174_α
icn_173_β:
    goto icn_168_α
icn_173_nlr:
    putstatic queens/icn_173_ln J
    goto icn_175_α
icn_173_xlr:
    invokestatic java/lang/Long/valueOf(J)Ljava/lang/Long;
    putstatic queens/icn_173_lx Ljava/lang/Object;
    new java/util/ArrayList
    dup
    invokespecial java/util/ArrayList/<init>()V
    putstatic queens/icn_173_ll Ljava/util/ArrayList;
    getstatic queens/icn_173_ln J
    l2i
    putstatic queens/icn_173_lc I
icn_173_llp:
    getstatic queens/icn_173_lc I
    ifeq icn_173_lld
    getstatic queens/icn_173_ll Ljava/util/ArrayList;
    getstatic queens/icn_173_lx Ljava/lang/Object;
    invokevirtual java/util/ArrayList/add(Ljava/lang/Object;)Z
    pop
    getstatic queens/icn_173_lc I
    iconst_1
    isub
    putstatic queens/icn_173_lc I
    goto icn_173_llp
icn_173_lld:
    getstatic queens/icn_173_ll Ljava/util/ArrayList;
    goto icn_172_store
icn_172_α:
    goto icn_173_α
icn_172_β:
    goto icn_173_β
icn_172_store:
    putstatic queens/icn_gvar_placed Ljava/util/ArrayList;
    getstatic queens/icn_gvar_placed Ljava/util/ArrayList;
    goto icn_main_s1_sdrain
icn_main_s1_sdrain:
    pop
    goto icn_168_α
;  INT
icn_178_α:
    ldc2_w 6
    goto icn_177_alt_g1
icn_178_β:
    goto icn_172_α
;  INT
icn_181_α:
    ldc2_w 1
    goto icn_180_sub_irelay
icn_181_β:
    goto icn_178_α
;  VAR
icn_182_α:
    getstatic queens/icn_pv_main_args J
    goto icn_180_sub_srelay
icn_182_β:
    goto icn_178_α
icn_180_sub_srelay:
    putstatic queens/icn_180_sub_s Ljava/lang/String;
    goto icn_181_α
icn_180_sub_irelay:
    l2i
    istore 84
    iload 84
    ifgt icn_180_sub_pos
    iload 84
    iflt icn_180_sub_neg
icn_180_sub_z:
    goto icn_178_α
icn_180_sub_pos:
    iload 84
    iconst_1
    isub
    putstatic queens/icn_180_sub_i I
    goto icn_180_sub_check
icn_180_sub_neg:
    getstatic queens/icn_180_sub_s Ljava/lang/String;
    invokevirtual java/lang/String/length()I
    iload 84
    iadd
    putstatic queens/icn_180_sub_i I
    goto icn_180_sub_check
icn_180_sub_check:
    getstatic queens/icn_180_sub_i I
    iflt icn_178_α
    getstatic queens/icn_180_sub_s Ljava/lang/String;
    invokevirtual java/lang/String/length()I
    getstatic queens/icn_180_sub_i I
    if_icmple icn_178_α
    getstatic queens/icn_180_sub_s Ljava/lang/String;
    getstatic queens/icn_180_sub_i I
    getstatic queens/icn_180_sub_i I
    iconst_1
    iadd
    invokevirtual java/lang/String/substring(II)Ljava/lang/String;
    goto icn_179_int_after
icn_180_α:
    goto icn_182_α
icn_180_β:
    goto icn_181_β
icn_179_α:
    goto icn_180_α
icn_179_β:
    goto icn_180_β
icn_179_int_after:
    astore 150
    aload 150
    invokestatic queens/icn_builtin_parse_long(Ljava/lang/String;)J
    lstore 6
    lload 6
    ldc2_w -9223372036854775808
    lcmp
    ifeq icn_179_int_fail
    lload 6
    goto icn_177_alt_g0
icn_179_int_fail:
    goto icn_178_α
icn_177_alt_g0:
    putstatic queens/icn_177_alt_val J
    sipush 1
    putstatic queens/icn_177_alt_gate I
    getstatic queens/icn_177_alt_val J
    goto icn_176_store
icn_177_alt_g1:
    putstatic queens/icn_177_alt_val J
    sipush 2
    putstatic queens/icn_177_alt_gate I
    getstatic queens/icn_177_alt_val J
    goto icn_176_store
icn_177_α:
    iconst_0
    putstatic queens/icn_177_alt_gate I
    goto icn_179_α
icn_177_β:
    getstatic queens/icn_177_alt_gate I
    tableswitch 1 2
        icn_179_β
        icn_178_β
        default: icn_172_α
icn_176_α:
    goto icn_177_α
icn_176_β:
    goto icn_177_β
icn_176_store:
    putstatic queens/icn_gvar_n J
    getstatic queens/icn_gvar_n J
    goto icn_main_s0_sdrain
icn_main_s0_sdrain:
    pop2
    goto icn_172_α
icn_main_done:
    return
.end method

