; Generated by scrip-cc Prolog JVM emitter (prolog_emit_jvm.c)
; Source: /home/claude/one4all/test/prolog/queens.pl

.class public queens
.super java/lang/Object

; Trail field
.field static pj_trail Ljava/util/ArrayList;

; M-PJ-EXCEPTIONS — throw/catch term carrier
.field static pj_throw_term Ljava/lang/Object;

; Dynamic DB field: HashMap<String, ArrayList<Object[]>>
.field static pj_db Ljava/util/HashMap;

; Global nb_setval/nb_getval store: HashMap<String, Object[]>
.field static pj_nb Ljava/util/HashMap;

.method static <clinit>()V
    .limit stack 3
    .limit locals 0
    new java/util/ArrayList
    dup
    invokespecial java/util/ArrayList/<init>()V
    putstatic queens/pj_trail Ljava/util/ArrayList;
    new java/util/HashMap
    dup
    invokespecial java/util/HashMap/<init>()V
    putstatic queens/pj_db Ljava/util/HashMap;
    new java/util/HashMap
    dup
    invokespecial java/util/HashMap/<init>()V
    putstatic queens/pj_nb Ljava/util/HashMap;
    return
.end method

; === Runtime helpers =================================================
.method static pj_trail_mark()I
    .limit stack 2
    .limit locals 0
    getstatic queens/pj_trail Ljava/util/ArrayList;
    invokevirtual java/util/ArrayList/size()I
    ireturn
.end method

.method static pj_trail_push([Ljava/lang/Object;)V
    .limit stack 4
    .limit locals 1
    getstatic queens/pj_trail Ljava/util/ArrayList;
    aload_0
    invokevirtual java/util/ArrayList/add(Ljava/lang/Object;)Z
    pop
    return
.end method

.method static pj_trail_unwind(I)V
    .limit stack 4
    .limit locals 2
pj_unwind_loop:
    getstatic queens/pj_trail Ljava/util/ArrayList;
    invokevirtual java/util/ArrayList/size()I
    iload_0
    if_icmple pj_unwind_done
    getstatic queens/pj_trail Ljava/util/ArrayList;
    getstatic queens/pj_trail Ljava/util/ArrayList;
    invokevirtual java/util/ArrayList/size()I
    iconst_1
    isub
    invokevirtual java/util/ArrayList/remove(I)Ljava/lang/Object;
    checkcast [Ljava/lang/Object;
    dup
    iconst_0
    ldc "var"
    aastore
    iconst_1
    aconst_null
    aastore
    goto pj_unwind_loop
pj_unwind_done:
    return
.end method

.method static pj_deref(Ljava/lang/Object;)Ljava/lang/Object;
    .limit stack 3
    .limit locals 2
    aload_0
    astore_1
pj_deref_loop:
    aload_1
    ifnull pj_deref_done
    aload_1
    checkcast [Ljava/lang/Object;
    iconst_0
    aaload
    ldc "ref"
    invokevirtual java/lang/Object/equals(Ljava/lang/Object;)Z
    ifeq pj_deref_done
    aload_1
    checkcast [Ljava/lang/Object;
    iconst_1
    aaload
    astore_1
    goto pj_deref_loop
pj_deref_done:
    aload_1
    areturn
.end method

.method static pj_term_atom(Ljava/lang/String;)[Ljava/lang/Object;
    .limit stack 5
    .limit locals 1
    iconst_2
    anewarray java/lang/Object
    dup
    iconst_0
    ldc "atom"
    aastore
    dup
    iconst_1
    aload_0
    aastore
    areturn
.end method

.method static pj_term_int(J)[Ljava/lang/Object;
    .limit stack 5
    .limit locals 2
    iconst_2
    anewarray java/lang/Object
    dup
    iconst_0
    ldc "int"
    aastore
    dup
    iconst_1
    lload_0
    invokestatic java/lang/Long/toString(J)Ljava/lang/String;
    aastore
    areturn
.end method

.method static pj_term_float(D)[Ljava/lang/Object;
    .limit stack 5
    .limit locals 2
    iconst_2
    anewarray java/lang/Object
    dup
    iconst_0
    ldc "float"
    aastore
    dup
    iconst_1
    dload_0
    invokestatic java/lang/Double/toString(D)Ljava/lang/String;
    aastore
    areturn
.end method

.method static pj_term_var()[Ljava/lang/Object;
    .limit stack 4
    .limit locals 0
    iconst_2
    anewarray java/lang/Object
    dup
    iconst_0
    ldc "var"
    aastore
    areturn
.end method

.method static pj_unify(Ljava/lang/Object;Ljava/lang/Object;)Z
    .limit stack 6
    .limit locals 4
    aload_0
    invokestatic queens/pj_deref(Ljava/lang/Object;)Ljava/lang/Object;
    astore_0
    aload_1
    invokestatic queens/pj_deref(Ljava/lang/Object;)Ljava/lang/Object;
    astore_1
    aload_0
    aload_1
    if_acmpeq pj_unify_true
    aload_0
    ifnull pj_unify_check_b_var
    aload_0
    checkcast [Ljava/lang/Object;
    iconst_0
    aaload
    ldc "var"
    invokevirtual java/lang/Object/equals(Ljava/lang/Object;)Z
    ifeq pj_unify_check_b_var
    aload_0
    checkcast [Ljava/lang/Object;
    iconst_1
    aaload
    ifnonnull pj_unify_check_b_var
    aload_0
    checkcast [Ljava/lang/Object;
    dup
    iconst_0
    ldc "ref"
    aastore
    iconst_1
    aload_1
    aastore
    aload_0
    checkcast [Ljava/lang/Object;
    invokestatic queens/pj_trail_push([Ljava/lang/Object;)V
    goto pj_unify_true
pj_unify_check_b_var:
    aload_1
    ifnull pj_unify_check_atoms
    aload_1
    checkcast [Ljava/lang/Object;
    iconst_0
    aaload
    ldc "var"
    invokevirtual java/lang/Object/equals(Ljava/lang/Object;)Z
    ifeq pj_unify_check_atoms
    aload_1
    checkcast [Ljava/lang/Object;
    iconst_1
    aaload
    ifnonnull pj_unify_check_atoms
    aload_1
    checkcast [Ljava/lang/Object;
    dup
    iconst_0
    ldc "ref"
    aastore
    iconst_1
    aload_0
    aastore
    aload_1
    checkcast [Ljava/lang/Object;
    invokestatic queens/pj_trail_push([Ljava/lang/Object;)V
    goto pj_unify_true
pj_unify_check_atoms:
    aload_0
    ifnull pj_unify_false
    aload_1
    ifnull pj_unify_false
    aload_0
    checkcast [Ljava/lang/Object;
    iconst_0
    aaload
    ldc "atom"
    invokevirtual java/lang/Object/equals(Ljava/lang/Object;)Z
    ifeq pj_unify_check_int
    aload_1
    checkcast [Ljava/lang/Object;
    iconst_0
    aaload
    ldc "atom"
    invokevirtual java/lang/Object/equals(Ljava/lang/Object;)Z
    ifeq pj_unify_false
    aload_0
    checkcast [Ljava/lang/Object;
    iconst_1
    aaload
    aload_1
    checkcast [Ljava/lang/Object;
    iconst_1
    aaload
    invokevirtual java/lang/Object/equals(Ljava/lang/Object;)Z
    ifeq pj_unify_false
    goto pj_unify_true
pj_unify_check_int:
    aload_0
    checkcast [Ljava/lang/Object;
    iconst_0
    aaload
    ldc "int"
    invokevirtual java/lang/Object/equals(Ljava/lang/Object;)Z
    ifeq pj_unify_check_float
    aload_1
    checkcast [Ljava/lang/Object;
    iconst_0
    aaload
    ldc "int"
    invokevirtual java/lang/Object/equals(Ljava/lang/Object;)Z
    ifeq pj_unify_false
    aload_0
    checkcast [Ljava/lang/Object;
    iconst_1
    aaload
    aload_1
    checkcast [Ljava/lang/Object;
    iconst_1
    aaload
    invokevirtual java/lang/Object/equals(Ljava/lang/Object;)Z
    ifeq pj_unify_check_compound
    goto pj_unify_true
pj_unify_check_float:
    aload_0
    checkcast [Ljava/lang/Object;
    iconst_0
    aaload
    ldc "float"
    invokevirtual java/lang/Object/equals(Ljava/lang/Object;)Z
    ifeq pj_unify_check_compound
    aload_1
    checkcast [Ljava/lang/Object;
    iconst_0
    aaload
    ldc "float"
    invokevirtual java/lang/Object/equals(Ljava/lang/Object;)Z
    ifeq pj_unify_false
    aload_0
    checkcast [Ljava/lang/Object;
    iconst_1
    aaload
    checkcast java/lang/String
    invokestatic java/lang/Double/parseDouble(Ljava/lang/String;)D
    aload_1
    checkcast [Ljava/lang/Object;
    iconst_1
    aaload
    checkcast java/lang/String
    invokestatic java/lang/Double/parseDouble(Ljava/lang/String;)D
    dcmpl
    ifne pj_unify_false
    goto pj_unify_true
pj_unify_check_compound:
    aload_0
    checkcast [Ljava/lang/Object;
    iconst_0
    aaload
    ldc "compound"
    invokevirtual java/lang/Object/equals(Ljava/lang/Object;)Z
    ifeq pj_unify_false
    aload_1
    checkcast [Ljava/lang/Object;
    iconst_0
    aaload
    ldc "compound"
    invokevirtual java/lang/Object/equals(Ljava/lang/Object;)Z
    ifeq pj_unify_false
    aload_0
    checkcast [Ljava/lang/Object;
    iconst_1
    aaload
    aload_1
    checkcast [Ljava/lang/Object;
    iconst_1
    aaload
    invokevirtual java/lang/Object/equals(Ljava/lang/Object;)Z
    ifeq pj_unify_false
    aload_0
    checkcast [Ljava/lang/Object;
    arraylength
    aload_1
    checkcast [Ljava/lang/Object;
    arraylength
    if_icmpne pj_unify_false
    aload_0
    checkcast [Ljava/lang/Object;
    arraylength
    iconst_2
    isub
    istore_2
    iconst_0
    istore_3
pj_unify_cmp_loop:
    iload_3
    iload_2
    if_icmpge pj_unify_true
    aload_0
    checkcast [Ljava/lang/Object;
    iload_3
    iconst_2
    iadd
    aaload
    aload_1
    checkcast [Ljava/lang/Object;
    iload_3
    iconst_2
    iadd
    aaload
    invokestatic queens/pj_unify(Ljava/lang/Object;Ljava/lang/Object;)Z
    ifeq pj_unify_false
    iinc 3 1
    goto pj_unify_cmp_loop
pj_unify_true:
    iconst_1
    ireturn
pj_unify_false:
    iconst_0
    ireturn
.end method

.method static pj_term_str(Ljava/lang/Object;)Ljava/lang/String;
    .limit stack 8
    .limit locals 4
    aload_0
    invokestatic queens/pj_deref(Ljava/lang/Object;)Ljava/lang/Object;
    astore_0
    aload_0
    ifnonnull pts_notnull
    ldc "_"
    areturn
pts_notnull:
    aload_0
    checkcast [Ljava/lang/Object;
    iconst_0
    aaload
    astore_1
    aload_1
    ldc "atom"
    invokevirtual java/lang/Object/equals(Ljava/lang/Object;)Z
    ifne pts_scalar
    aload_1
    ldc "int"
    invokevirtual java/lang/Object/equals(Ljava/lang/Object;)Z
    ifne pts_scalar
    aload_1
    ldc "float"
    invokevirtual java/lang/Object/equals(Ljava/lang/Object;)Z
    ifne pts_scalar
    aload_1
    ldc "compound"
    invokevirtual java/lang/Object/equals(Ljava/lang/Object;)Z
    ifeq pts_var
    aload_0
    checkcast [Ljava/lang/Object;
    iconst_1
    aaload
    ldc "."
    invokevirtual java/lang/Object/equals(Ljava/lang/Object;)Z
    ifeq pts_plain_compound
    aload_0
    checkcast [Ljava/lang/Object;
    arraylength
    iconst_4
    if_icmpne pts_plain_compound
    new java/lang/StringBuilder
    dup
    invokespecial java/lang/StringBuilder/<init>()V
    ldc "["
    invokevirtual java/lang/StringBuilder/append(Ljava/lang/String;)Ljava/lang/StringBuilder;
    astore_2
    aload_0
    astore_3
pts_list_loop:
    aload_2
    aload_3
    checkcast [Ljava/lang/Object;
    iconst_2
    aaload
    invokestatic queens/pj_term_str(Ljava/lang/Object;)Ljava/lang/String;
    invokevirtual java/lang/StringBuilder/append(Ljava/lang/String;)Ljava/lang/StringBuilder;
    pop
    aload_3
    checkcast [Ljava/lang/Object;
    iconst_3
    aaload
    invokestatic queens/pj_deref(Ljava/lang/Object;)Ljava/lang/Object;
    astore_3
    aload_3
    ifnull pts_list_close
    aload_3
    checkcast [Ljava/lang/Object;
    iconst_0
    aaload
    ldc "atom"
    invokevirtual java/lang/Object/equals(Ljava/lang/Object;)Z
    ifeq pts_list_tail_check
    aload_3
    checkcast [Ljava/lang/Object;
    iconst_1
    aaload
    ldc "[]"
    invokevirtual java/lang/Object/equals(Ljava/lang/Object;)Z
    ifne pts_list_close
pts_list_tail_check:
    aload_3
    checkcast [Ljava/lang/Object;
    iconst_0
    aaload
    ldc "compound"
    invokevirtual java/lang/Object/equals(Ljava/lang/Object;)Z
    ifeq pts_list_improper
    aload_3
    checkcast [Ljava/lang/Object;
    iconst_1
    aaload
    ldc "."
    invokevirtual java/lang/Object/equals(Ljava/lang/Object;)Z
    ifeq pts_list_improper
    aload_2
    ldc ","
    invokevirtual java/lang/StringBuilder/append(Ljava/lang/String;)Ljava/lang/StringBuilder;
    pop
    goto pts_list_loop
pts_list_improper:
    aload_2
    ldc "|"
    invokevirtual java/lang/StringBuilder/append(Ljava/lang/String;)Ljava/lang/StringBuilder;
    pop
    aload_2
    aload_3
    invokestatic queens/pj_term_str(Ljava/lang/Object;)Ljava/lang/String;
    invokevirtual java/lang/StringBuilder/append(Ljava/lang/String;)Ljava/lang/StringBuilder;
    pop
pts_list_close:
    aload_2
    ldc "]"
    invokevirtual java/lang/StringBuilder/append(Ljava/lang/String;)Ljava/lang/StringBuilder;
    pop
    aload_2
    invokevirtual java/lang/StringBuilder/toString()Ljava/lang/String;
    areturn
pts_plain_compound:
    aload_0
    checkcast [Ljava/lang/Object;
    arraylength
    iconst_3
    if_icmpne pts_not_var_term
    aload_0
    checkcast [Ljava/lang/Object;
    iconst_1
    aaload
    ldc "$VAR"
    invokevirtual java/lang/Object/equals(Ljava/lang/Object;)Z
    ifeq pts_not_var_term
    aload_0
    checkcast [Ljava/lang/Object;
    iconst_2
    aaload
    invokestatic queens/pj_deref(Ljava/lang/Object;)Ljava/lang/Object;
    invokestatic queens/pj_int_val(Ljava/lang/Object;)J
    l2i
    istore_1
    iload_1
    bipush 26
    irem
    bipush 65
    iadd
    i2c
    invokestatic java/lang/Character/toString(C)Ljava/lang/String;
    astore_2
    iload_1
    bipush 26
    idiv
    istore_3
    iload_3
    ifne pts_var_suffix
    aload_2
    areturn
pts_var_suffix:
    new java/lang/StringBuilder
    dup
    invokespecial java/lang/StringBuilder/<init>()V
    aload_2
    invokevirtual java/lang/StringBuilder/append(Ljava/lang/String;)Ljava/lang/StringBuilder;
    iload_3
    invokevirtual java/lang/StringBuilder/append(I)Ljava/lang/StringBuilder;
    invokevirtual java/lang/StringBuilder/toString()Ljava/lang/String;
    areturn
pts_not_var_term:
    aload_0
    checkcast [Ljava/lang/Object;
    iconst_1
    aaload
    checkcast java/lang/String
    astore_1
    aload_0
    checkcast [Ljava/lang/Object;
    arraylength
    ldc 4
    if_icmpne pts_plain_noninfix
    aload_1
    ldc "-"
    invokevirtual java/lang/Object/equals(Ljava/lang/Object;)Z
    ifne pts_infix
    aload_1
    ldc "+"
    invokevirtual java/lang/Object/equals(Ljava/lang/Object;)Z
    ifne pts_infix
    aload_1
    ldc "*"
    invokevirtual java/lang/Object/equals(Ljava/lang/Object;)Z
    ifne pts_infix
    aload_1
    ldc "/"
    invokevirtual java/lang/Object/equals(Ljava/lang/Object;)Z
    ifne pts_infix
    goto pts_plain_noninfix
pts_infix:
    new java/lang/StringBuilder
    dup
    invokespecial java/lang/StringBuilder/<init>()V
    astore_2
    aload_2
    aload_0
    checkcast [Ljava/lang/Object;
    iconst_2
    aaload
    invokestatic queens/pj_term_str(Ljava/lang/Object;)Ljava/lang/String;
    invokevirtual java/lang/StringBuilder/append(Ljava/lang/String;)Ljava/lang/StringBuilder;
    pop
    aload_2
    aload_1
    invokevirtual java/lang/StringBuilder/append(Ljava/lang/String;)Ljava/lang/StringBuilder;
    pop
    aload_2
    aload_0
    checkcast [Ljava/lang/Object;
    iconst_3
    aaload
    invokestatic queens/pj_term_str(Ljava/lang/Object;)Ljava/lang/String;
    invokevirtual java/lang/StringBuilder/append(Ljava/lang/String;)Ljava/lang/StringBuilder;
    pop
    aload_2
    invokevirtual java/lang/StringBuilder/toString()Ljava/lang/String;
    areturn
pts_plain_noninfix:
    new java/lang/StringBuilder
    dup
    invokespecial java/lang/StringBuilder/<init>()V
    astore_2
    aload_2
    aload_1
    invokevirtual java/lang/StringBuilder/append(Ljava/lang/String;)Ljava/lang/StringBuilder;
    pop
    aload_0
    checkcast [Ljava/lang/Object;
    arraylength
    iconst_2
    isub
    istore_3
    iload_3
    ifeq pts_compound_done
    aload_2
    ldc "("
    invokevirtual java/lang/StringBuilder/append(Ljava/lang/String;)Ljava/lang/StringBuilder;
    pop
    iconst_0
    istore_1
pts_compound_loop:
    iload_1
    iload_3
    if_icmpge pts_compound_close
    iload_1
    ifeq pts_compound_nocomma
    aload_2
    ldc ","
    invokevirtual java/lang/StringBuilder/append(Ljava/lang/String;)Ljava/lang/StringBuilder;
    pop
pts_compound_nocomma:
    aload_2
    aload_0
    checkcast [Ljava/lang/Object;
    iload_1
    iconst_2
    iadd
    aaload
    invokestatic queens/pj_term_str(Ljava/lang/Object;)Ljava/lang/String;
    invokevirtual java/lang/StringBuilder/append(Ljava/lang/String;)Ljava/lang/StringBuilder;
    pop
    iinc 1 1
    goto pts_compound_loop
pts_compound_close:
    aload_2
    ldc ")"
    invokevirtual java/lang/StringBuilder/append(Ljava/lang/String;)Ljava/lang/StringBuilder;
    pop
pts_compound_done:
    aload_2
    invokevirtual java/lang/StringBuilder/toString()Ljava/lang/String;
    areturn
pts_var:
    ldc "_"
    areturn
pts_scalar:
    aload_0
    checkcast [Ljava/lang/Object;
    iconst_1
    aaload
    checkcast java/lang/String
    areturn
.end method

.method static pj_write(Ljava/lang/Object;)V
    .limit stack 3
    .limit locals 1
    aload_0
    invokestatic queens/pj_term_str(Ljava/lang/Object;)Ljava/lang/String;
    getstatic java/lang/System/out Ljava/io/PrintStream;
    swap
    invokevirtual java/io/PrintStream/print(Ljava/lang/String;)V
    return
.end method

.method static pj_needs_quote(Ljava/lang/String;)Z
    .limit stack 4
    .limit locals 4
    aload_0
    invokevirtual java/lang/String/length()I
    istore_1
    iload_1
    ifne pjnq_check_first
    iconst_1
    ireturn
pjnq_check_first:
    aload_0
    ldc "[]"
    invokevirtual java/lang/Object/equals(Ljava/lang/Object;)Z
    ifne pjnq_no
    aload_0
    ldc "{}"
    invokevirtual java/lang/Object/equals(Ljava/lang/Object;)Z
    ifne pjnq_no
    aload_0
    ldc ","
    invokevirtual java/lang/Object/equals(Ljava/lang/Object;)Z
    ifne pjnq_no
    aload_0
    ldc "|"
    invokevirtual java/lang/Object/equals(Ljava/lang/Object;)Z
    ifne pjnq_no
    aload_0
    ldc "!"
    invokevirtual java/lang/Object/equals(Ljava/lang/Object;)Z
    ifne pjnq_no
    aload_0
    ldc ";"
    invokevirtual java/lang/Object/equals(Ljava/lang/Object;)Z
    ifne pjnq_no
    aload_0
    iconst_0
    invokevirtual java/lang/String/charAt(I)C
    istore_2
    iload_2
    invokestatic java/lang/Character/isLowerCase(C)Z
    ifne pjnq_alphaid
    iload_2
    invokestatic queens/pj_is_sym_char(I)Z
    ifne pjnq_symbolic
    iconst_1
    ireturn
pjnq_alphaid:
    iconst_1
    istore_2
pjnq_ai_loop:
    iload_2
    iload_1
    if_icmpge pjnq_no
    aload_0
    iload_2
    invokevirtual java/lang/String/charAt(I)C
    istore_3
    iload_3
    invokestatic java/lang/Character/isLetterOrDigit(C)Z
    ifne pjnq_ai_next
    iload_3
    bipush 95
    if_icmpeq pjnq_ai_next
    goto pjnq_yes
pjnq_ai_next:
    iinc 2 1
    goto pjnq_ai_loop
pjnq_symbolic:
    iconst_1
    istore_2
pjnq_sym_loop:
    iload_2
    iload_1
    if_icmpge pjnq_no
    aload_0
    iload_2
    invokevirtual java/lang/String/charAt(I)C
    istore_3
    iload_3
    invokestatic queens/pj_is_sym_char(I)Z
    ifeq pjnq_yes
    iinc 2 1
    goto pjnq_sym_loop
pjnq_yes:
    iconst_1
    ireturn
pjnq_no:
    iconst_0
    ireturn
.end method

.method static pj_is_sym_char(I)Z
    .limit stack 2
    .limit locals 1
    iload_0
    bipush 35
    if_icmpeq pjsc_yes
    iload_0
    bipush 38
    if_icmpeq pjsc_yes
    iload_0
    bipush 42
    if_icmpeq pjsc_yes
    iload_0
    bipush 43
    if_icmpeq pjsc_yes
    iload_0
    bipush 45
    if_icmpeq pjsc_yes
    iload_0
    bipush 46
    if_icmpeq pjsc_yes
    iload_0
    bipush 47
    if_icmpeq pjsc_yes
    iload_0
    bipush 58
    if_icmpeq pjsc_yes
    iload_0
    bipush 60
    if_icmpeq pjsc_yes
    iload_0
    bipush 61
    if_icmpeq pjsc_yes
    iload_0
    bipush 62
    if_icmpeq pjsc_yes
    iload_0
    bipush 63
    if_icmpeq pjsc_yes
    iload_0
    bipush 64
    if_icmpeq pjsc_yes
    iload_0
    bipush 92
    if_icmpeq pjsc_yes
    iload_0
    bipush 94
    if_icmpeq pjsc_yes
    iload_0
    bipush 126
    if_icmpeq pjsc_yes
    iconst_0
    ireturn
pjsc_yes:
    iconst_1
    ireturn
.end method

.method static pj_quoted_atom_str(Ljava/lang/String;)Ljava/lang/String;
    .limit stack 4
    .limit locals 5
    new java/lang/StringBuilder
    dup
    invokespecial java/lang/StringBuilder/<init>()V
    astore_1
    aload_1
    ldc "'"
    invokevirtual java/lang/StringBuilder/append(Ljava/lang/String;)Ljava/lang/StringBuilder;
    pop
    aload_0
    invokevirtual java/lang/String/length()I
    istore_2
    iconst_0
    istore_3
pjqa_loop:
    iload_3
    iload_2
    if_icmpge pjqa_close
    aload_0
    iload_3
    invokevirtual java/lang/String/charAt(I)C
    istore 4
    iload 4
    bipush 39
    if_icmpne pjqa_append
    aload_1
    ldc "''"
    invokevirtual java/lang/StringBuilder/append(Ljava/lang/String;)Ljava/lang/StringBuilder;
    pop
    iinc 3 1
    goto pjqa_loop
pjqa_append:
    aload_1
    iload 4
    i2c
    invokevirtual java/lang/StringBuilder/append(C)Ljava/lang/StringBuilder;
    pop
    iinc 3 1
    goto pjqa_loop
pjqa_close:
    aload_1
    ldc "'"
    invokevirtual java/lang/StringBuilder/append(Ljava/lang/String;)Ljava/lang/StringBuilder;
    pop
    aload_1
    invokevirtual java/lang/StringBuilder/toString()Ljava/lang/String;
    areturn
.end method

.method static pj_term_str_q(Ljava/lang/Object;)Ljava/lang/String;
    .limit stack 8
    .limit locals 5
    aload_0
    invokestatic queens/pj_deref(Ljava/lang/Object;)Ljava/lang/Object;
    astore_0
    aload_0
    ifnonnull ptsq_notnull
    ldc "_"
    areturn
ptsq_notnull:
    aload_0
    checkcast [Ljava/lang/Object;
    iconst_0
    aaload
    astore_1
    aload_1
    ldc "int"
    invokevirtual java/lang/Object/equals(Ljava/lang/Object;)Z
    ifne ptsq_scalar
    aload_1
    ldc "float"
    invokevirtual java/lang/Object/equals(Ljava/lang/Object;)Z
    ifne ptsq_scalar
    aload_1
    ldc "atom"
    invokevirtual java/lang/Object/equals(Ljava/lang/Object;)Z
    ifeq ptsq_compound_or_var
    aload_0
    checkcast [Ljava/lang/Object;
    iconst_1
    aaload
    checkcast java/lang/String
    astore_2
    aload_2
    invokestatic queens/pj_needs_quote(Ljava/lang/String;)Z
    ifeq ptsq_atom_plain
    aload_2
    invokestatic queens/pj_quoted_atom_str(Ljava/lang/String;)Ljava/lang/String;
    areturn
ptsq_atom_plain:
    aload_2
    areturn
ptsq_scalar:
    aload_0
    checkcast [Ljava/lang/Object;
    iconst_1
    aaload
    checkcast java/lang/String
    areturn
ptsq_compound_or_var:
    aload_1
    ldc "var"
    invokevirtual java/lang/Object/equals(Ljava/lang/Object;)Z
    ifne ptsq_var
    aload_0
    checkcast [Ljava/lang/Object;
    arraylength
    iconst_2
    isub
    istore_3
    new java/lang/StringBuilder
    dup
    invokespecial java/lang/StringBuilder/<init>()V
    astore_2
    aload_0
    checkcast [Ljava/lang/Object;
    iconst_1
    aaload
    checkcast java/lang/String
    astore 4
    aload 4
    ldc "."
    invokevirtual java/lang/Object/equals(Ljava/lang/Object;)Z
    ifeq ptsq_not_list
    iload_3
    bipush 2
    if_icmpne ptsq_not_list
    aload_0
    invokestatic queens/pj_term_str(Ljava/lang/Object;)Ljava/lang/String;
    areturn
ptsq_not_list:
    aload 4
    invokestatic queens/pj_needs_quote(Ljava/lang/String;)Z
    ifeq ptsq_fn_plain
    aload 4
    invokestatic queens/pj_quoted_atom_str(Ljava/lang/String;)Ljava/lang/String;
    goto ptsq_fn_app
ptsq_fn_plain:
    aload 4
ptsq_fn_app:
    aload_2
    swap
    invokevirtual java/lang/StringBuilder/append(Ljava/lang/String;)Ljava/lang/StringBuilder;
    pop
    iload_3
    ifne ptsq_open_p
    aload_2
    invokevirtual java/lang/StringBuilder/toString()Ljava/lang/String;
    areturn
ptsq_open_p:
    aload_2
    ldc "("
    invokevirtual java/lang/StringBuilder/append(Ljava/lang/String;)Ljava/lang/StringBuilder;
    pop
    iconst_0
    istore 4
ptsq_arg_loop:
    iload 4
    iload_3
    if_icmpge ptsq_close_p
    iload 4
    ifle ptsq_no_c
    aload_2
    ldc ","
    invokevirtual java/lang/StringBuilder/append(Ljava/lang/String;)Ljava/lang/StringBuilder;
    pop
ptsq_no_c:
    aload_0
    checkcast [Ljava/lang/Object;
    iload 4
    iconst_2
    iadd
    aaload
    invokestatic queens/pj_term_str_q(Ljava/lang/Object;)Ljava/lang/String;
    aload_2
    swap
    invokevirtual java/lang/StringBuilder/append(Ljava/lang/String;)Ljava/lang/StringBuilder;
    pop
    iinc 4 1
    goto ptsq_arg_loop
ptsq_close_p:
    aload_2
    ldc ")"
    invokevirtual java/lang/StringBuilder/append(Ljava/lang/String;)Ljava/lang/StringBuilder;
    pop
    aload_2
    invokevirtual java/lang/StringBuilder/toString()Ljava/lang/String;
    areturn
ptsq_var:
    ldc "_"
    areturn
.end method

.method static pj_term_str_canonical(Ljava/lang/Object;)Ljava/lang/String;
    .limit stack 8
    .limit locals 5
    aload_0
    invokestatic queens/pj_deref(Ljava/lang/Object;)Ljava/lang/Object;
    astore_0
    aload_0
    ifnonnull ptsc_notnull
    ldc "_"
    areturn
ptsc_notnull:
    aload_0
    checkcast [Ljava/lang/Object;
    iconst_0
    aaload
    astore_1
    aload_1
    ldc "int"
    invokevirtual java/lang/Object/equals(Ljava/lang/Object;)Z
    ifne ptsc_scalar
    aload_1
    ldc "float"
    invokevirtual java/lang/Object/equals(Ljava/lang/Object;)Z
    ifne ptsc_scalar
    aload_1
    ldc "atom"
    invokevirtual java/lang/Object/equals(Ljava/lang/Object;)Z
    ifeq ptsc_compound_or_var
    aload_0
    checkcast [Ljava/lang/Object;
    iconst_1
    aaload
    checkcast java/lang/String
    astore_2
    aload_2
    invokestatic queens/pj_needs_quote(Ljava/lang/String;)Z
    ifeq ptsc_atom_plain
    aload_2
    invokestatic queens/pj_quoted_atom_str(Ljava/lang/String;)Ljava/lang/String;
    areturn
ptsc_atom_plain:
    aload_2
    areturn
ptsc_scalar:
    aload_0
    checkcast [Ljava/lang/Object;
    iconst_1
    aaload
    checkcast java/lang/String
    areturn
ptsc_compound_or_var:
    aload_1
    ldc "var"
    invokevirtual java/lang/Object/equals(Ljava/lang/Object;)Z
    ifne ptsc_var
    aload_0
    checkcast [Ljava/lang/Object;
    iconst_1
    aaload
    ldc "."
    invokevirtual java/lang/Object/equals(Ljava/lang/Object;)Z
    ifeq ptsc_plain_compound
    aload_0
    checkcast [Ljava/lang/Object;
    arraylength
    iconst_4
    if_icmpne ptsc_plain_compound
    aload_0
    invokestatic queens/pj_term_str(Ljava/lang/Object;)Ljava/lang/String;
    areturn
ptsc_plain_compound:
    aload_0
    checkcast [Ljava/lang/Object;
    arraylength
    iconst_2
    isub
    istore_3
    new java/lang/StringBuilder
    dup
    invokespecial java/lang/StringBuilder/<init>()V
    astore_2
    aload_0
    checkcast [Ljava/lang/Object;
    iconst_1
    aaload
    checkcast java/lang/String
    astore 4
    aload 4
    invokestatic queens/pj_needs_quote(Ljava/lang/String;)Z
    ifeq ptsc_fn_plain
    aload 4
    invokestatic queens/pj_quoted_atom_str(Ljava/lang/String;)Ljava/lang/String;
    goto ptsc_fn_append
ptsc_fn_plain:
    aload 4
ptsc_fn_append:
    aload_2
    swap
    invokevirtual java/lang/StringBuilder/append(Ljava/lang/String;)Ljava/lang/StringBuilder;
    pop
    iload_3
    ifne ptsc_open_paren
    aload_2
    invokevirtual java/lang/StringBuilder/toString()Ljava/lang/String;
    areturn
ptsc_open_paren:
    aload_2
    ldc "("
    invokevirtual java/lang/StringBuilder/append(Ljava/lang/String;)Ljava/lang/StringBuilder;
    pop
    iconst_0
    istore 4
ptsc_arg_loop:
    iload 4
    iload_3
    if_icmpge ptsc_close_paren
    iload 4
    ifle ptsc_no_comma
    aload_2
    ldc ","
    invokevirtual java/lang/StringBuilder/append(Ljava/lang/String;)Ljava/lang/StringBuilder;
    pop
ptsc_no_comma:
    aload_0
    checkcast [Ljava/lang/Object;
    iload 4
    iconst_2
    iadd
    aaload
    invokestatic queens/pj_term_str_canonical(Ljava/lang/Object;)Ljava/lang/String;
    aload_2
    swap
    invokevirtual java/lang/StringBuilder/append(Ljava/lang/String;)Ljava/lang/StringBuilder;
    pop
    iinc 4 1
    goto ptsc_arg_loop
ptsc_close_paren:
    aload_2
    ldc ")"
    invokevirtual java/lang/StringBuilder/append(Ljava/lang/String;)Ljava/lang/StringBuilder;
    pop
    aload_2
    invokevirtual java/lang/StringBuilder/toString()Ljava/lang/String;
    areturn
ptsc_var:
    ldc "_"
    areturn
.end method

.method static pj_writeq(Ljava/lang/Object;)V
    .limit stack 3
    .limit locals 1
    aload_0
    invokestatic queens/pj_term_str_q(Ljava/lang/Object;)Ljava/lang/String;
    getstatic java/lang/System/out Ljava/io/PrintStream;
    swap
    invokevirtual java/io/PrintStream/print(Ljava/lang/String;)V
    return
.end method

.method static pj_write_canonical(Ljava/lang/Object;)V
    .limit stack 3
    .limit locals 1
    aload_0
    invokestatic queens/pj_term_str_canonical(Ljava/lang/Object;)Ljava/lang/String;
    getstatic java/lang/System/out Ljava/io/PrintStream;
    swap
    invokevirtual java/io/PrintStream/print(Ljava/lang/String;)V
    return
.end method

.method static pj_term_to_list(Ljava/lang/Object;)[Ljava/lang/Object;
    .limit stack 8
    .limit locals 5
    aload_0
    invokestatic queens/pj_deref(Ljava/lang/Object;)Ljava/lang/Object;
    checkcast [Ljava/lang/Object;
    astore_0
    aload_0
    iconst_0
    aaload
    astore_1
    ldc "[]"
    invokestatic queens/pj_term_atom(Ljava/lang/String;)[Ljava/lang/Object;
    astore_3
    aload_1
    ldc "atom"
    invokevirtual java/lang/Object/equals(Ljava/lang/Object;)Z
    ifeq ttl_compound
    aload_0
    iconst_1
    aaload
    checkcast java/lang/String
    invokestatic queens/pj_term_atom(Ljava/lang/String;)[Ljava/lang/Object;
    bipush 4
    anewarray java/lang/Object
    dup
    iconst_0
    ldc "compound"
    aastore
    dup
    iconst_1
    ldc "."
    aastore
    dup
    iconst_2
    aload_0
    iconst_1
    aaload
    checkcast java/lang/String
    invokestatic queens/pj_term_atom(Ljava/lang/String;)[Ljava/lang/Object;
    aastore
    dup
    bipush 3
    aload_3
    aastore
    areturn
ttl_compound:
    aload_0
    arraylength
    iconst_2
    isub
    istore_1
    iload_1
    iconst_1
    isub
    istore_2
ttl_arg_loop:
    iload_2
    iflt ttl_prepend_functor
    bipush 4
    anewarray java/lang/Object
    dup
    iconst_0
    ldc "compound"
    aastore
    dup
    iconst_1
    ldc "."
    aastore
    dup
    iconst_2
    aload_0
    iload_2
    iconst_2
    iadd
    aaload
    aastore
    dup
    bipush 3
    aload_3
    aastore
    astore_3
    iinc 2 -1
    goto ttl_arg_loop
ttl_prepend_functor:
    bipush 4
    anewarray java/lang/Object
    dup
    iconst_0
    ldc "compound"
    aastore
    dup
    iconst_1
    ldc "."
    aastore
    dup
    iconst_2
    aload_0
    iconst_1
    aaload
    checkcast java/lang/String
    invokestatic queens/pj_term_atom(Ljava/lang/String;)[Ljava/lang/Object;
    aastore
    dup
    bipush 3
    aload_3
    aastore
    areturn
.end method

.method static pj_list_to_term(Ljava/lang/Object;)[Ljava/lang/Object;
    .limit stack 8
    .limit locals 6
    aload_0
    invokestatic queens/pj_deref(Ljava/lang/Object;)Ljava/lang/Object;
    astore_0
    aload_0
    ifnull ltl_fail
    aload_0
    checkcast [Ljava/lang/Object;
    iconst_0
    aaload
    ldc "compound"
    invokevirtual java/lang/Object/equals(Ljava/lang/Object;)Z
    ifeq ltl_fail
    aload_0
    checkcast [Ljava/lang/Object;
    iconst_1
    aaload
    ldc "."
    invokevirtual java/lang/Object/equals(Ljava/lang/Object;)Z
    ifeq ltl_fail
    aload_0
    checkcast [Ljava/lang/Object;
    iconst_2
    aaload
    invokestatic queens/pj_deref(Ljava/lang/Object;)Ljava/lang/Object;
    astore 4
    aload_0
    checkcast [Ljava/lang/Object;
    bipush 3
    aaload
    invokestatic queens/pj_deref(Ljava/lang/Object;)Ljava/lang/Object;
    astore_0
    bipush 34
    anewarray java/lang/Object
    astore_1
    iconst_0
    istore_2
ltl_loop:
    aload_0
    ifnull ltl_build
    aload_0
    checkcast [Ljava/lang/Object;
    iconst_0
    aaload
    ldc "atom"
    invokevirtual java/lang/Object/equals(Ljava/lang/Object;)Z
    ifne ltl_build
    iload_2
    bipush 32
    if_icmpge ltl_fail
    aload_1
    iload_2
    aload_0
    checkcast [Ljava/lang/Object;
    iconst_2
    aaload
    aastore
    iinc 2 1
    aload_0
    checkcast [Ljava/lang/Object;
    bipush 3
    aaload
    invokestatic queens/pj_deref(Ljava/lang/Object;)Ljava/lang/Object;
    astore_0
    goto ltl_loop
ltl_build:
    iload_2
    ifne ltl_compound
    aload 4
    checkcast [Ljava/lang/Object;
    areturn
ltl_compound:
    iload_2
    iconst_2
    iadd
    anewarray java/lang/Object
    astore_3
    aload_3
    iconst_0
    ldc "compound"
    aastore
    aload_3
    iconst_1
    aload 4
    invokestatic queens/pj_atom_name(Ljava/lang/Object;)Ljava/lang/String;
    aastore
    iconst_0
    istore 5
ltl_copy:
    iload 5
    iload_2
    if_icmpge ltl_ret
    aload_3
    iload 5
    iconst_2
    iadd
    aload_1
    iload 5
    aaload
    aastore
    iinc 5 1
    goto ltl_copy
ltl_ret:
    aload_3
    areturn
ltl_fail:
    aconst_null
    areturn
.end method

.method static pj_univ(Ljava/lang/Object;Ljava/lang/Object;)Z
    .limit stack 4
    .limit locals 4
    aload_0
    invokestatic queens/pj_deref(Ljava/lang/Object;)Ljava/lang/Object;
    astore_2
    aload_2
    ifnull univ_compose
    aload_2
    checkcast [Ljava/lang/Object;
    iconst_0
    aaload
    ldc "var"
    invokevirtual java/lang/Object/equals(Ljava/lang/Object;)Z
    ifne univ_compose
    aload_2
    invokestatic queens/pj_term_to_list(Ljava/lang/Object;)[Ljava/lang/Object;
    aload_1
    invokestatic queens/pj_unify(Ljava/lang/Object;Ljava/lang/Object;)Z
    ireturn
univ_compose:
    aload_1
    invokestatic queens/pj_list_to_term(Ljava/lang/Object;)[Ljava/lang/Object;
    astore_3
    aload_3
    ifnull univ_fail
    aload_0
    aload_3
    invokestatic queens/pj_unify(Ljava/lang/Object;Ljava/lang/Object;)Z
    ireturn
univ_fail:
    iconst_0
    ireturn
.end method

.method static pj_atom_name(Ljava/lang/Object;)Ljava/lang/String;
    .limit stack 4
    .limit locals 2
    aload_0
    invokestatic queens/pj_deref(Ljava/lang/Object;)Ljava/lang/Object;
    checkcast [Ljava/lang/Object;
    astore_0
    aload_0
    iconst_0
    aaload
    ldc "int"
    invokevirtual java/lang/Object/equals(Ljava/lang/Object;)Z
    ifeq pan_atom
    aload_0
    iconst_1
    aaload
    checkcast java/lang/String
    areturn
pan_atom:
    aload_0
    iconst_1
    aaload
    checkcast java/lang/String
    areturn
.end method

.method static pj_int_val(Ljava/lang/Object;)J
    .limit stack 3
    .limit locals 2
    aload_0
    invokestatic queens/pj_deref(Ljava/lang/Object;)Ljava/lang/Object;
    checkcast [Ljava/lang/Object;
    iconst_1
    aaload
    checkcast java/lang/String
    invokestatic java/lang/Long/parseLong(Ljava/lang/String;)J
    lreturn
.end method

.method static pj_string_to_char_list(Ljava/lang/String;)[Ljava/lang/Object;
    .limit stack 8
    .limit locals 5
    aload_0
    invokevirtual java/lang/String/length()I
    istore_1
    ldc "[]"
    invokestatic queens/pj_term_atom(Ljava/lang/String;)[Ljava/lang/Object;
    astore_3
    iload_1
    iconst_1
    isub
    istore_2
scl_loop:
    iload_2
    iflt scl_done
    aload_0
    iload_2
    invokevirtual java/lang/String/charAt(I)C
    invokestatic java/lang/String/valueOf(C)Ljava/lang/String;
    invokestatic queens/pj_term_atom(Ljava/lang/String;)[Ljava/lang/Object;
    astore 4
    bipush 4
    anewarray java/lang/Object
    dup
    iconst_0
    ldc "compound"
    aastore
    dup
    iconst_1
    ldc "."
    aastore
    dup
    iconst_2
    aload 4
    aastore
    dup
    bipush 3
    aload_3
    aastore
    astore_3
    iinc 2 -1
    goto scl_loop
scl_done:
    aload_3
    areturn
.end method

.method static pj_string_to_code_list(Ljava/lang/String;)[Ljava/lang/Object;
    .limit stack 8
    .limit locals 5
    aload_0
    invokevirtual java/lang/String/length()I
    istore_1
    ldc "[]"
    invokestatic queens/pj_term_atom(Ljava/lang/String;)[Ljava/lang/Object;
    astore_3
    iload_1
    iconst_1
    isub
    istore_2
scol_loop:
    iload_2
    iflt scol_done
    aload_0
    iload_2
    invokevirtual java/lang/String/charAt(I)C
    i2l
    invokestatic queens/pj_term_int(J)[Ljava/lang/Object;
    astore 4
    bipush 4
    anewarray java/lang/Object
    dup
    iconst_0
    ldc "compound"
    aastore
    dup
    iconst_1
    ldc "."
    aastore
    dup
    iconst_2
    aload 4
    aastore
    dup
    bipush 3
    aload_3
    aastore
    astore_3
    iinc 2 -1
    goto scol_loop
scol_done:
    aload_3
    areturn
.end method

.method static pj_atom_chars_2(Ljava/lang/Object;Ljava/lang/Object;)Z
    .limit stack 8
    .limit locals 6
    aload_0
    invokestatic queens/pj_deref(Ljava/lang/Object;)Ljava/lang/Object;
    checkcast [Ljava/lang/Object;
    astore_2
    aload_2
    iconst_0
    aaload
    ldc "var"
    invokevirtual java/lang/Object/equals(Ljava/lang/Object;)Z
    ifne ac2_reverse
    aload_2
    invokestatic queens/pj_atom_name(Ljava/lang/Object;)Ljava/lang/String;
    invokestatic queens/pj_string_to_char_list(Ljava/lang/String;)[Ljava/lang/Object;
    aload_1
    invokestatic queens/pj_unify(Ljava/lang/Object;Ljava/lang/Object;)Z
    ireturn
ac2_reverse:
    aload_1
    invokestatic queens/pj_char_list_to_string(Ljava/lang/Object;)Ljava/lang/String;
    invokestatic queens/pj_term_atom(Ljava/lang/String;)[Ljava/lang/Object;
    aload_0
    invokestatic queens/pj_unify(Ljava/lang/Object;Ljava/lang/Object;)Z
    ireturn
.end method

.method static pj_atom_codes_2(Ljava/lang/Object;Ljava/lang/Object;)Z
    .limit stack 8
    .limit locals 4
    aload_0
    invokestatic queens/pj_deref(Ljava/lang/Object;)Ljava/lang/Object;
    checkcast [Ljava/lang/Object;
    astore_2
    aload_2
    iconst_0
    aaload
    ldc "var"
    invokevirtual java/lang/Object/equals(Ljava/lang/Object;)Z
    ifne acd2_reverse
    aload_2
    invokestatic queens/pj_atom_name(Ljava/lang/Object;)Ljava/lang/String;
    invokestatic queens/pj_string_to_code_list(Ljava/lang/String;)[Ljava/lang/Object;
    aload_1
    invokestatic queens/pj_unify(Ljava/lang/Object;Ljava/lang/Object;)Z
    ireturn
acd2_reverse:
    aload_1
    invokestatic queens/pj_code_list_to_string(Ljava/lang/Object;)Ljava/lang/String;
    invokestatic queens/pj_term_atom(Ljava/lang/String;)[Ljava/lang/Object;
    aload_0
    invokestatic queens/pj_unify(Ljava/lang/Object;Ljava/lang/Object;)Z
    ireturn
.end method

.method static pj_char_code_2(Ljava/lang/Object;Ljava/lang/Object;)Z
    .limit stack 8
    .limit locals 4
    aload_0
    invokestatic queens/pj_deref(Ljava/lang/Object;)Ljava/lang/Object;
    checkcast [Ljava/lang/Object;
    astore_2
    aload_2
    iconst_0
    aaload
    ldc "var"
    invokevirtual java/lang/Object/equals(Ljava/lang/Object;)Z
    ifne cc2_reverse
    aload_2
    invokestatic queens/pj_atom_name(Ljava/lang/Object;)Ljava/lang/String;
    iconst_0
    invokevirtual java/lang/String/charAt(I)C
    i2l
    invokestatic queens/pj_term_int(J)[Ljava/lang/Object;
    aload_1
    invokestatic queens/pj_unify(Ljava/lang/Object;Ljava/lang/Object;)Z
    ireturn
cc2_reverse:
    aload_1
    invokestatic queens/pj_deref(Ljava/lang/Object;)Ljava/lang/Object;
    invokestatic queens/pj_int_val(Ljava/lang/Object;)J
    l2i
    invokestatic java/lang/String/valueOf(C)Ljava/lang/String;
    invokestatic queens/pj_term_atom(Ljava/lang/String;)[Ljava/lang/Object;
    aload_0
    invokestatic queens/pj_unify(Ljava/lang/Object;Ljava/lang/Object;)Z
    ireturn
.end method

.method static pj_char_list_to_string(Ljava/lang/Object;)Ljava/lang/String;
    .limit stack 6
    .limit locals 3
    new java/lang/StringBuilder
    dup
    invokespecial java/lang/StringBuilder/<init>()V
    astore_1
    aload_0
    invokestatic queens/pj_deref(Ljava/lang/Object;)Ljava/lang/Object;
    astore_2
clts_loop:
    aload_2
    checkcast [Ljava/lang/Object;
    iconst_1
    aaload
    ldc "[]"
    invokevirtual java/lang/Object/equals(Ljava/lang/Object;)Z
    ifne clts_done
    aload_2
    checkcast [Ljava/lang/Object;
    iconst_2
    aaload
    invokestatic queens/pj_deref(Ljava/lang/Object;)Ljava/lang/Object;
    invokestatic queens/pj_atom_name(Ljava/lang/Object;)Ljava/lang/String;
    aload_1
    swap
    invokevirtual java/lang/StringBuilder/append(Ljava/lang/String;)Ljava/lang/StringBuilder;
    pop
    aload_2
    checkcast [Ljava/lang/Object;
    bipush 3
    aaload
    invokestatic queens/pj_deref(Ljava/lang/Object;)Ljava/lang/Object;
    astore_2
    goto clts_loop
clts_done:
    aload_1
    invokevirtual java/lang/StringBuilder/toString()Ljava/lang/String;
    areturn
.end method

.method static pj_code_list_to_string(Ljava/lang/Object;)Ljava/lang/String;
    .limit stack 6
    .limit locals 3
    new java/lang/StringBuilder
    dup
    invokespecial java/lang/StringBuilder/<init>()V
    astore_1
    aload_0
    invokestatic queens/pj_deref(Ljava/lang/Object;)Ljava/lang/Object;
    astore_2
colts_loop:
    aload_2
    checkcast [Ljava/lang/Object;
    iconst_1
    aaload
    ldc "[]"
    invokevirtual java/lang/Object/equals(Ljava/lang/Object;)Z
    ifne colts_done
    aload_2
    checkcast [Ljava/lang/Object;
    iconst_2
    aaload
    invokestatic queens/pj_deref(Ljava/lang/Object;)Ljava/lang/Object;
    invokestatic queens/pj_int_val(Ljava/lang/Object;)J
    l2i
    i2c
    aload_1
    swap
    invokevirtual java/lang/StringBuilder/append(C)Ljava/lang/StringBuilder;
    pop
    aload_2
    checkcast [Ljava/lang/Object;
    bipush 3
    aaload
    invokestatic queens/pj_deref(Ljava/lang/Object;)Ljava/lang/Object;
    astore_2
    goto colts_loop
colts_done:
    aload_1
    invokevirtual java/lang/StringBuilder/toString()Ljava/lang/String;
    areturn
.end method

; === Dynamic DB helpers: pj_db_assert_key, pj_db_assert, pj_db_query =
; pj_db_assert_key(Object) -> String
.method static pj_db_assert_key(Ljava/lang/Object;)Ljava/lang/String;
    .limit stack 6
    .limit locals 3
    aload_0
    dup
    instanceof [Ljava/lang/Object;
    ifeq pj_db_key_atom
    checkcast [Ljava/lang/Object;
    iconst_1
    aaload
    checkcast java/lang/String
    astore_1
    aload_0
    checkcast [Ljava/lang/Object;
    arraylength
    iconst_2
    isub
    istore_2
    new java/lang/StringBuilder
    dup
    invokespecial java/lang/StringBuilder/<init>()V
    aload_1
    invokevirtual java/lang/StringBuilder/append(Ljava/lang/String;)Ljava/lang/StringBuilder;
    ldc "/"
    invokevirtual java/lang/StringBuilder/append(Ljava/lang/String;)Ljava/lang/StringBuilder;
    iload_2
    invokevirtual java/lang/StringBuilder/append(I)Ljava/lang/StringBuilder;
    invokevirtual java/lang/StringBuilder/toString()Ljava/lang/String;
    areturn
pj_db_key_atom:
    aload_0
    checkcast java/lang/String
    astore_1
    new java/lang/StringBuilder
    dup
    invokespecial java/lang/StringBuilder/<init>()V
    aload_1
    invokevirtual java/lang/StringBuilder/append(Ljava/lang/String;)Ljava/lang/StringBuilder;
    ldc "/0"
    invokevirtual java/lang/StringBuilder/append(Ljava/lang/String;)Ljava/lang/StringBuilder;
    invokevirtual java/lang/StringBuilder/toString()Ljava/lang/String;
    areturn
.end method

; pj_db_assert(String key, Object term, int prepend) -> void
.method static pj_db_assert(Ljava/lang/String;Ljava/lang/Object;I)V
    .limit stack 6
    .limit locals 4
    getstatic queens/pj_db Ljava/util/HashMap;
    aload_0
    invokevirtual java/util/HashMap/get(Ljava/lang/Object;)Ljava/lang/Object;
    dup
    ifnonnull pj_db_assert_have_list
    pop
    new java/util/ArrayList
    dup
    invokespecial java/util/ArrayList/<init>()V
    astore_3
    getstatic queens/pj_db Ljava/util/HashMap;
    aload_0
    aload_3
    invokevirtual java/util/HashMap/put(Ljava/lang/Object;Ljava/lang/Object;)Ljava/lang/Object;
    pop
    goto pj_db_assert_join
pj_db_assert_have_list:
    checkcast java/util/ArrayList
    astore_3
pj_db_assert_join:
    aload_1
    invokestatic queens/pj_copy_term_ground(Ljava/lang/Object;)Ljava/lang/Object;
    astore_1
    iload_2
    ifeq pj_db_assert_append
    aload_3
    iconst_0
    aload_1
    invokevirtual java/util/ArrayList/add(ILjava/lang/Object;)V
    return
pj_db_assert_append:
    aload_3
    aload_1
    invokevirtual java/util/ArrayList/add(Ljava/lang/Object;)Z
    pop
    return
.end method

; pj_db_query(String key, int idx) -> Object | null
.method static pj_db_query(Ljava/lang/String;I)Ljava/lang/Object;
    .limit stack 4
    .limit locals 3
    getstatic queens/pj_db Ljava/util/HashMap;
    aload_0
    invokevirtual java/util/HashMap/get(Ljava/lang/Object;)Ljava/lang/Object;
    dup
    ifnonnull pj_db_query_have
    areturn
pj_db_query_have:
    checkcast java/util/ArrayList
    astore_2
    aload_2
    invokevirtual java/util/ArrayList/size()I
    iload_1
    if_icmpgt pj_db_query_ok
    aconst_null
    areturn
pj_db_query_ok:
    aload_2
    iload_1
    invokevirtual java/util/ArrayList/get(I)Ljava/lang/Object;
    areturn
.end method

; pj_db_retract(String key, int idx) -> Object | null
.method static pj_db_retract(Ljava/lang/String;I)Ljava/lang/Object;
    .limit stack 4
    .limit locals 3
    getstatic queens/pj_db Ljava/util/HashMap;
    aload_0
    invokevirtual java/util/HashMap/get(Ljava/lang/Object;)Ljava/lang/Object;
    dup
    ifnonnull pj_db_retract_have
    areturn
pj_db_retract_have:
    checkcast java/util/ArrayList
    astore_2
    aload_2
    invokevirtual java/util/ArrayList/size()I
    iload_1
    if_icmpgt pj_db_retract_ok
    aconst_null
    areturn
pj_db_retract_ok:
    aload_2
    iload_1
    invokevirtual java/util/ArrayList/remove(I)Ljava/lang/Object;
    areturn
.end method

; pj_db_abolish(String key) -> void
.method static pj_db_abolish(Ljava/lang/String;)V
    .limit stack 2
    .limit locals 1
    getstatic queens/pj_db Ljava/util/HashMap;
    aload_0
    invokevirtual java/util/HashMap/remove(Ljava/lang/Object;)Ljava/lang/Object;
    pop
    return
.end method

; pj_db_abolish_key(Object) -> String
.method static pj_db_abolish_key(Ljava/lang/Object;)Ljava/lang/String;
    .limit stack 6
    .limit locals 4
    aload_0
    checkcast [Ljava/lang/Object;
    iconst_2
    aaload
    invokestatic queens/pj_atom_name(Ljava/lang/Object;)Ljava/lang/String;
    astore_1
    aload_0
    checkcast [Ljava/lang/Object;
    iconst_3
    aaload
    invokestatic queens/pj_int_val(Ljava/lang/Object;)J
    l2i
    istore_2
    new java/lang/StringBuilder
    dup
    invokespecial java/lang/StringBuilder/<init>()V
    aload_1
    invokevirtual java/lang/StringBuilder/append(Ljava/lang/String;)Ljava/lang/StringBuilder;
    ldc "/"
    invokevirtual java/lang/StringBuilder/append(Ljava/lang/String;)Ljava/lang/StringBuilder;
    iload_2
    invokevirtual java/lang/StringBuilder/append(I)Ljava/lang/StringBuilder;
    invokevirtual java/lang/StringBuilder/toString()Ljava/lang/String;
    areturn
.end method

; pj_copy_term_ground(Object) -> Object
.method static pj_copy_term_ground(Ljava/lang/Object;)Ljava/lang/Object;
    .limit stack 8
    .limit locals 5
    aload_0
    dup
    instanceof [Ljava/lang/Object;
    ifne pj_ctg_compound
    areturn
pj_ctg_compound:
    checkcast [Ljava/lang/Object;
    astore_1
    aload_1
    arraylength
    istore_2
    iload_2
    anewarray java/lang/Object
    astore_3
    aload_3
    iconst_0
    aload_1
    iconst_0
    aaload
    aastore
    iconst_1
    istore 4
pj_ctg_loop:
    iload 4
    iload_2
    if_icmpge pj_ctg_done
    aload_3
    iload 4
    aload_1
    iload 4
    aaload
    invokestatic queens/pj_copy_term_ground(Ljava/lang/Object;)Ljava/lang/Object;
    aastore
    iinc 4 1
    goto pj_ctg_loop
pj_ctg_done:
    aload_3
    areturn
.end method

; pj_list_to_arraylist(Object) -> ArrayList
.method static pj_list_to_arraylist(Ljava/lang/Object;)Ljava/util/ArrayList;
    .limit stack 4
    .limit locals 3
    new java/util/ArrayList
    dup
    invokespecial java/util/ArrayList/<init>()V
    astore_1
    aload_0
    invokestatic queens/pj_deref(Ljava/lang/Object;)Ljava/lang/Object;
    astore_2
pj_lta_loop:
    aload_2
    instanceof [Ljava/lang/Object;
    ifeq pj_lta_done
    aload_2
    checkcast [Ljava/lang/Object;
    iconst_1
    aaload
    checkcast java/lang/String
    astore_0
    aload_0
    ldc "[]"
    invokevirtual java/lang/Object/equals(Ljava/lang/Object;)Z
    ifne pj_lta_done
    aload_1
    aload_2
    checkcast [Ljava/lang/Object;
    iconst_2
    aaload
    invokevirtual java/util/ArrayList/add(Ljava/lang/Object;)Z
    pop
    aload_2
    checkcast [Ljava/lang/Object;
    iconst_3
    aaload
    invokestatic queens/pj_deref(Ljava/lang/Object;)Ljava/lang/Object;
    astore_2
    goto pj_lta_loop
pj_lta_done:
    aload_1
    areturn
.end method

; pj_length_2(Object list, Object n) -> Z
.method static pj_length_2(Ljava/lang/Object;Ljava/lang/Object;)Z
    .limit stack 6
    .limit locals 4
    aload_0
    invokestatic queens/pj_deref(Ljava/lang/Object;)Ljava/lang/Object;
    astore_2
    iconst_0
    istore_3
pj_len_loop:
    aload_2
    instanceof [Ljava/lang/Object;
    ifeq pj_len_done
    aload_2
    checkcast [Ljava/lang/Object;
    iconst_1
    aaload
    ldc "[]"
    invokevirtual java/lang/Object/equals(Ljava/lang/Object;)Z
    ifne pj_len_done
    iinc 3 1
    aload_2
    checkcast [Ljava/lang/Object;
    iconst_3
    aaload
    invokestatic queens/pj_deref(Ljava/lang/Object;)Ljava/lang/Object;
    astore_2
    goto pj_len_loop
pj_len_done:
    iload_3
    i2l
    invokestatic queens/pj_term_int(J)[Ljava/lang/Object;
    aload_1
    invokestatic queens/pj_unify(Ljava/lang/Object;Ljava/lang/Object;)Z
    ireturn
.end method

; pj_arraylist_to_list(ArrayList) -> Object
.method static pj_arraylist_to_list(Ljava/util/ArrayList;)Ljava/lang/Object;
    .limit stack 8
    .limit locals 4
    ldc "[]"
    invokestatic queens/pj_term_atom(Ljava/lang/String;)[Ljava/lang/Object;
    astore_1
    aload_0
    invokevirtual java/util/ArrayList/size()I
    iconst_1
    isub
    istore_2
pj_atl_loop:
    iload_2
    iflt pj_atl_done
    bipush 4
    anewarray java/lang/Object
    dup
    iconst_0
    ldc "compound"
    aastore
    dup
    iconst_1
    ldc "."
    aastore
    dup
    iconst_2
    aload_0
    iload_2
    invokevirtual java/util/ArrayList/get(I)Ljava/lang/Object;
    aastore
    dup
    iconst_3
    aload_1
    aastore
    astore_1
    iinc 2 -1
    goto pj_atl_loop
pj_atl_done:
    aload_1
    areturn
.end method

; pj_sort_list(Object list, int dedup) -> Object
.method static pj_sort_list(Ljava/lang/Object;I)Ljava/lang/Object;
    .limit stack 8
    .limit locals 8
    aload_0
    invokestatic queens/pj_list_to_arraylist(Ljava/lang/Object;)Ljava/util/ArrayList;
    astore_2
    aload_2
    invokevirtual java/util/ArrayList/size()I
    istore_3
    iconst_1
    istore 4
pj_sl_outer:
    iload 4
    iload_3
    if_icmpge pj_sl_sorted
    aload_2
    iload 4
    invokevirtual java/util/ArrayList/get(I)Ljava/lang/Object;
    astore 5
    iload 4
    iconst_1
    isub
    istore 6
pj_sl_inner:
    iload 6
    iflt pj_sl_insert
    aload_2
    iload 6
    invokevirtual java/util/ArrayList/get(I)Ljava/lang/Object;
    invokestatic queens/pj_term_str(Ljava/lang/Object;)Ljava/lang/String;
    aload 5
    invokestatic queens/pj_term_str(Ljava/lang/Object;)Ljava/lang/String;
    invokevirtual java/lang/String/compareTo(Ljava/lang/String;)I
    ifle pj_sl_insert
    aload_2
    iload 6
    iconst_1
    iadd
    aload_2
    iload 6
    invokevirtual java/util/ArrayList/get(I)Ljava/lang/Object;
    invokevirtual java/util/ArrayList/set(ILjava/lang/Object;)Ljava/lang/Object;
    pop
    iinc 6 -1
    goto pj_sl_inner
pj_sl_insert:
    aload_2
    iload 6
    iconst_1
    iadd
    aload 5
    invokevirtual java/util/ArrayList/set(ILjava/lang/Object;)Ljava/lang/Object;
    pop
    iinc 4 1
    goto pj_sl_outer
pj_sl_sorted:
    iload_1
    ifeq pj_sl_build
    iconst_0
    istore 4
pj_sl_dedup:
    iload 4
    aload_2
    invokevirtual java/util/ArrayList/size()I
    iconst_1
    isub
    if_icmpge pj_sl_build
    aload_2
    iload 4
    invokevirtual java/util/ArrayList/get(I)Ljava/lang/Object;
    invokestatic queens/pj_term_str(Ljava/lang/Object;)Ljava/lang/String;
    aload_2
    iload 4
    iconst_1
    iadd
    invokevirtual java/util/ArrayList/get(I)Ljava/lang/Object;
    invokestatic queens/pj_term_str(Ljava/lang/Object;)Ljava/lang/String;
    invokevirtual java/lang/String/compareTo(Ljava/lang/String;)I
    ifne pj_sl_dedup_next
    aload_2
    iload 4
    iconst_1
    iadd
    invokevirtual java/util/ArrayList/remove(I)Ljava/lang/Object;
    pop
    goto pj_sl_dedup
pj_sl_dedup_next:
    iinc 4 1
    goto pj_sl_dedup
pj_sl_build:
    aload_2
    invokestatic queens/pj_arraylist_to_list(Ljava/util/ArrayList;)Ljava/lang/Object;
    areturn
.end method

; pj_is_var(Object) -> Z
.method static pj_is_var(Ljava/lang/Object;)Z
    .limit stack 3
    .limit locals 1
    aload_0
    ifnull pj_isvar_true
    aload_0
    checkcast [Ljava/lang/Object;
    iconst_0
    aaload
    ldc "var"
    invokevirtual java/lang/Object/equals(Ljava/lang/Object;)Z
    ifeq pj_isvar_false
    aload_0
    checkcast [Ljava/lang/Object;
    iconst_1
    aaload
    ifnonnull pj_isvar_false
pj_isvar_true:
    iconst_1
    ireturn
pj_isvar_false:
    iconst_0
    ireturn
.end method

; pj_succ_2(Object x, Object y) -> Z
.method static pj_succ_2(Ljava/lang/Object;Ljava/lang/Object;)Z
    .limit stack 6
    .limit locals 6
    aload_0
    invokestatic queens/pj_deref(Ljava/lang/Object;)Ljava/lang/Object;
    astore_0
    aload_1
    invokestatic queens/pj_deref(Ljava/lang/Object;)Ljava/lang/Object;
    astore_1
    aload_0
    invokestatic queens/pj_is_var(Ljava/lang/Object;)Z
    ifne pj_succ2_x_unbound
    aload_0
    invokestatic queens/pj_int_val(Ljava/lang/Object;)J
    lconst_1
    ladd
    invokestatic queens/pj_term_int(J)[Ljava/lang/Object;
    aload_1
    invokestatic queens/pj_unify(Ljava/lang/Object;Ljava/lang/Object;)Z
    ireturn
pj_succ2_x_unbound:
    aload_1
    invokestatic queens/pj_int_val(Ljava/lang/Object;)J
    lconst_1
    lsub
    dup2
    lstore_2
    lconst_0
    lcmp
    iflt pj_succ2_neg
    lload_2
    invokestatic queens/pj_term_int(J)[Ljava/lang/Object;
    aload_0
    invokestatic queens/pj_unify(Ljava/lang/Object;Ljava/lang/Object;)Z
    ireturn
pj_succ2_neg:
    lload_2
    invokestatic queens/pj_term_int(J)[Ljava/lang/Object;
    pop
    aload_1
    invokestatic queens/pj_deref(Ljava/lang/Object;)Ljava/lang/Object;
    bipush 4
    anewarray java/lang/Object
    dup
    iconst_0
    ldc "compound"
    aastore
    dup
    iconst_1
    ldc "domain_error"
    aastore
    dup
    iconst_2
    ldc "not_less_than_zero"
    invokestatic queens/pj_term_atom(Ljava/lang/String;)[Ljava/lang/Object;
    aastore
    dup
    bipush 3
    aload_1
    invokestatic queens/pj_deref(Ljava/lang/Object;)Ljava/lang/Object;
    aastore
    astore 4
    bipush 4
    anewarray java/lang/Object
    dup
    iconst_0
    ldc "compound"
    aastore
    dup
    iconst_1
    ldc "error"
    aastore
    dup
    iconst_2
    aload 4
    aastore
    dup
    bipush 3
    ldc "succ/2"
    invokestatic queens/pj_term_atom(Ljava/lang/String;)[Ljava/lang/Object;
    aastore
    putstatic queens/pj_throw_term Ljava/lang/Object;
    new java/lang/RuntimeException
    dup
    ldc "PROLOG_THROW"
    invokespecial java/lang/RuntimeException/<init>(Ljava/lang/String;)V
    athrow
.end method

; pj_plus_3(Object x, Object y, Object z) -> Z
.method static pj_plus_3(Ljava/lang/Object;Ljava/lang/Object;Ljava/lang/Object;)Z
    .limit stack 8
    .limit locals 8
    aload_0
    invokestatic queens/pj_deref(Ljava/lang/Object;)Ljava/lang/Object;
    astore_0
    aload_1
    invokestatic queens/pj_deref(Ljava/lang/Object;)Ljava/lang/Object;
    astore_1
    aload_2
    invokestatic queens/pj_deref(Ljava/lang/Object;)Ljava/lang/Object;
    astore_2
    aload_0
    invokestatic queens/pj_is_var(Ljava/lang/Object;)Z
    ifne pj_plus3_x_var
    aload_1
    invokestatic queens/pj_is_var(Ljava/lang/Object;)Z
    ifne pj_plus3_y_var
    aload_0
    invokestatic queens/pj_int_val(Ljava/lang/Object;)J
    aload_1
    invokestatic queens/pj_int_val(Ljava/lang/Object;)J
    ladd
    invokestatic queens/pj_term_int(J)[Ljava/lang/Object;
    aload_2
    invokestatic queens/pj_unify(Ljava/lang/Object;Ljava/lang/Object;)Z
    ireturn
pj_plus3_y_var:
    aload_2
    invokestatic queens/pj_int_val(Ljava/lang/Object;)J
    aload_0
    invokestatic queens/pj_int_val(Ljava/lang/Object;)J
    lsub
    invokestatic queens/pj_term_int(J)[Ljava/lang/Object;
    aload_1
    invokestatic queens/pj_unify(Ljava/lang/Object;Ljava/lang/Object;)Z
    ireturn
pj_plus3_x_var:
    aload_2
    invokestatic queens/pj_int_val(Ljava/lang/Object;)J
    aload_1
    invokestatic queens/pj_int_val(Ljava/lang/Object;)J
    lsub
    invokestatic queens/pj_term_int(J)[Ljava/lang/Object;
    aload_0
    invokestatic queens/pj_unify(Ljava/lang/Object;Ljava/lang/Object;)Z
    ireturn
.end method

; pj_nb_setval_2(Object name, Object value) -> V
.method static pj_nb_setval_2(Ljava/lang/Object;Ljava/lang/Object;)V
    .limit stack 4
    .limit locals 2
    aload_0
    invokestatic queens/pj_deref(Ljava/lang/Object;)Ljava/lang/Object;
    invokestatic queens/pj_atom_name(Ljava/lang/Object;)Ljava/lang/String;
    aload_1
    invokestatic queens/pj_deref(Ljava/lang/Object;)Ljava/lang/Object;
    getstatic queens/pj_nb Ljava/util/HashMap;
    dup_x2
    pop
    invokevirtual java/util/HashMap/put(Ljava/lang/Object;Ljava/lang/Object;)Ljava/lang/Object;
    pop
    return
.end method

; pj_nb_getval_2(Object name, Object var) -> Z
.method static pj_nb_getval_2(Ljava/lang/Object;Ljava/lang/Object;)Z
    .limit stack 4
    .limit locals 3
    aload_0
    invokestatic queens/pj_deref(Ljava/lang/Object;)Ljava/lang/Object;
    invokestatic queens/pj_atom_name(Ljava/lang/Object;)Ljava/lang/String;
    astore_2
    getstatic queens/pj_nb Ljava/util/HashMap;
    aload_2
    invokevirtual java/util/HashMap/get(Ljava/lang/Object;)Ljava/lang/Object;
    dup
    ifnonnull pj_nb_getval_found
    pop
    iconst_0
    ireturn
pj_nb_getval_found:
    aload_1
    invokestatic queens/pj_unify(Ljava/lang/Object;Ljava/lang/Object;)Z
    ireturn
.end method

; pj_succ_or_zero_2(Object x, Object y) -> Z
.method static pj_succ_or_zero_2(Ljava/lang/Object;Ljava/lang/Object;)Z
    .limit stack 6
    .limit locals 4
    aload_0
    invokestatic queens/pj_deref(Ljava/lang/Object;)Ljava/lang/Object;
    invokestatic queens/pj_int_val(Ljava/lang/Object;)J
    lstore_2
    lload_2
    lconst_0
    lcmp
    ifle pj_soz_zero
    lload_2
    lconst_1
    lsub
    invokestatic queens/pj_term_int(J)[Ljava/lang/Object;
    aload_1
    invokestatic queens/pj_unify(Ljava/lang/Object;Ljava/lang/Object;)Z
    ireturn
pj_soz_zero:
    lconst_0
    invokestatic queens/pj_term_int(J)[Ljava/lang/Object;
    aload_1
    invokestatic queens/pj_unify(Ljava/lang/Object;Ljava/lang/Object;)Z
    ireturn
.end method

; pj_format_2(Object fmt, Object arglist) -> V
.method static pj_format_2(Ljava/lang/Object;Ljava/lang/Object;)V
    .limit stack 6
    .limit locals 7
    aload_0
    invokestatic queens/pj_deref(Ljava/lang/Object;)Ljava/lang/Object;
    astore_0
    aload_0
    invokestatic queens/pj_atom_name(Ljava/lang/Object;)Ljava/lang/String;
    astore_2
    aload_2
    invokevirtual java/lang/String/length()I
    istore_3
    iconst_0
    istore 4
pjfmt_loop:
    iload 4
    iload_3
    if_icmpge pjfmt_done
    aload_2
    iload 4
    invokevirtual java/lang/String/charAt(I)C
    istore 5
    iload 5
    bipush 126
    if_icmpne pjfmt_plain
    iinc 4 1
    iload 4
    iload_3
    if_icmpge pjfmt_done
    aload_2
    iload 4
    invokevirtual java/lang/String/charAt(I)C
    istore 5
    iload 5
    bipush 119
    if_icmpeq pjfmt_write
    iload 5
    bipush 97
    if_icmpeq pjfmt_write
    iload 5
    bipush 100
    if_icmpeq pjfmt_write
    iload 5
    bipush 105
    if_icmpeq pjfmt_ignore
    iload 5
    bipush 110
    if_icmpeq pjfmt_nl
    iinc 4 1
    goto pjfmt_loop
pjfmt_write:
    aload_1
    invokestatic queens/pj_deref(Ljava/lang/Object;)Ljava/lang/Object;
    checkcast [Ljava/lang/Object;
    iconst_2
    aaload
    astore 6
    aload_1
    invokestatic queens/pj_deref(Ljava/lang/Object;)Ljava/lang/Object;
    checkcast [Ljava/lang/Object;
    bipush 3
    aaload
    astore_1
    aload 6
    invokestatic queens/pj_write(Ljava/lang/Object;)V
    iinc 4 1
    goto pjfmt_loop
pjfmt_ignore:
    aload_1
    invokestatic queens/pj_deref(Ljava/lang/Object;)Ljava/lang/Object;
    checkcast [Ljava/lang/Object;
    bipush 3
    aaload
    astore_1
    iinc 4 1
    goto pjfmt_loop
pjfmt_nl:
    getstatic java/lang/System/out Ljava/io/PrintStream;
    invokevirtual java/io/PrintStream/println()V
    iinc 4 1
    goto pjfmt_loop
pjfmt_plain:
    getstatic java/lang/System/out Ljava/io/PrintStream;
    iload 5
    i2c
    invokestatic java/lang/Character/toString(C)Ljava/lang/String;
    invokevirtual java/io/PrintStream/print(Ljava/lang/String;)V
    iinc 4 1
    goto pjfmt_loop
pjfmt_done:
    return
.end method

; pj_numbervars_walk(Object term, int[] counter) -> V
.method static pj_numbervars_walk(Ljava/lang/Object;[I)V
    .limit stack 8
    .limit locals 6
    aload_0
    invokestatic queens/pj_deref(Ljava/lang/Object;)Ljava/lang/Object;
    astore_0
    aload_0
    checkcast [Ljava/lang/Object;
    iconst_0
    aaload
    astore_2
    aload_2
    ldc "var"
    invokevirtual java/lang/Object/equals(Ljava/lang/Object;)Z
    ifeq pjnv_not_var
    aload_0
    checkcast [Ljava/lang/Object;
    iconst_1
    aaload
    ifnonnull pjnv_done
    aload_1
    iconst_0
    iaload
    istore_3
    iload_3
    i2l
    invokestatic queens/pj_term_int(J)[Ljava/lang/Object;
    astore 4
    bipush 3
    anewarray java/lang/Object
    dup
    iconst_0
    ldc "compound"
    aastore
    dup
    iconst_1
    ldc "$VAR"
    aastore
    dup
    iconst_2
    aload 4
    aastore
    astore 5
    aload_0
    checkcast [Ljava/lang/Object;
    iconst_0
    ldc "ref"
    aastore
    aload_0
    checkcast [Ljava/lang/Object;
    iconst_1
    aload 5
    aastore
    aload_1
    iconst_0
    aload_1
    iconst_0
    iaload
    iconst_1
    iadd
    iastore
    goto pjnv_done
pjnv_not_var:
    aload_2
    ldc "compound"
    invokevirtual java/lang/Object/equals(Ljava/lang/Object;)Z
    ifeq pjnv_done
    aload_0
    checkcast [Ljava/lang/Object;
    arraylength
    iconst_2
    isub
    istore_3
    iconst_0
    istore 4
pjnv_arg_loop:
    iload 4
    iload_3
    if_icmpge pjnv_done
    aload_0
    checkcast [Ljava/lang/Object;
    iload 4
    iconst_2
    iadd
    aaload
    aload_1
    invokestatic queens/pj_numbervars_walk(Ljava/lang/Object;[I)V
    iinc 4 1
    goto pjnv_arg_loop
pjnv_done:
    return
.end method

; pj_numbervars_3(Object term, Object start, Object end) -> Z
.method static pj_numbervars_3(Ljava/lang/Object;Ljava/lang/Object;Ljava/lang/Object;)Z
    .limit stack 6
    .limit locals 5
    aload_1
    invokestatic queens/pj_deref(Ljava/lang/Object;)Ljava/lang/Object;
    invokestatic queens/pj_int_val(Ljava/lang/Object;)J
    l2i
    iconst_1
    newarray int
    dup_x1
    swap
    iconst_0
    swap
    iastore
    astore_3
    aload_0
    aload_3
    invokestatic queens/pj_numbervars_walk(Ljava/lang/Object;[I)V
    aload_3
    iconst_0
    iaload
    i2l
    invokestatic queens/pj_term_int(J)[Ljava/lang/Object;
    aload_2
    invokestatic queens/pj_unify(Ljava/lang/Object;Ljava/lang/Object;)Z
    ireturn
.end method

; pj_char_type_2(Object ch, Object type) -> Z
.method static pj_char_type_2(Ljava/lang/Object;Ljava/lang/Object;)Z
    .limit stack 6
    .limit locals 6
    aload_0
    invokestatic queens/pj_deref(Ljava/lang/Object;)Ljava/lang/Object;
    astore_0
    aload_0
    invokestatic queens/pj_atom_name(Ljava/lang/Object;)Ljava/lang/String;
    astore_2
    aload_2
    iconst_0
    invokevirtual java/lang/String/charAt(I)C
    istore_3
    aload_1
    invokestatic queens/pj_deref(Ljava/lang/Object;)Ljava/lang/Object;
    astore_1
    aload_1
    checkcast [Ljava/lang/Object;
    iconst_0
    aaload
    ldc "compound"
    invokevirtual java/lang/Object/equals(Ljava/lang/Object;)Z
    ifne pjct_compound_type
    aload_1
    invokestatic queens/pj_atom_name(Ljava/lang/Object;)Ljava/lang/String;
    astore 4
    aload 4
    ldc "alpha"
    invokevirtual java/lang/Object/equals(Ljava/lang/Object;)Z
    ifeq pjct_try_alnum
    iload_3
    invokestatic java/lang/Character/isLetter(C)Z
    ireturn
pjct_try_alnum:
    aload 4
    ldc "alnum"
    invokevirtual java/lang/Object/equals(Ljava/lang/Object;)Z
    ifeq pjct_try_digit
    iload_3
    invokestatic java/lang/Character/isLetterOrDigit(C)Z
    ireturn
pjct_try_digit:
    aload 4
    ldc "digit"
    invokevirtual java/lang/Object/equals(Ljava/lang/Object;)Z
    ifeq pjct_try_space
    iload_3
    invokestatic java/lang/Character/isDigit(C)Z
    ireturn
pjct_try_space:
    aload 4
    ldc "space"
    invokevirtual java/lang/Object/equals(Ljava/lang/Object;)Z
    ifeq pjct_try_white
    iload_3
    invokestatic java/lang/Character/isWhitespace(C)Z
    ireturn
pjct_try_white:
    aload 4
    ldc "white"
    invokevirtual java/lang/Object/equals(Ljava/lang/Object;)Z
    ifeq pjct_try_eol
    iload_3
    invokestatic java/lang/Character/isWhitespace(C)Z
    ireturn
pjct_try_eol:
    aload 4
    ldc "end_of_line"
    invokevirtual java/lang/Object/equals(Ljava/lang/Object;)Z
    ifeq pjct_try_upper
    iload_3
    bipush 10
    if_icmpeq pjct_true
    iload_3
    bipush 13
    if_icmpeq pjct_true
    iconst_0
    ireturn
pjct_try_upper:
    aload 4
    ldc "upper"
    invokevirtual java/lang/Object/equals(Ljava/lang/Object;)Z
    ifeq pjct_try_lower
    iload_3
    invokestatic java/lang/Character/isUpperCase(C)Z
    ireturn
pjct_try_lower:
    aload 4
    ldc "lower"
    invokevirtual java/lang/Object/equals(Ljava/lang/Object;)Z
    ifeq pjct_fail
    iload_3
    invokestatic java/lang/Character/isLowerCase(C)Z
    ireturn
pjct_true:
    iconst_1
    ireturn
pjct_fail:
    iconst_0
    ireturn
pjct_compound_type:
    aload_1
    checkcast [Ljava/lang/Object;
    iconst_1
    aaload
    checkcast java/lang/String
    astore 4
    aload 4
    ldc "digit"
    invokevirtual java/lang/Object/equals(Ljava/lang/Object;)Z
    ifeq pjct_try_upper_l
    iload_3
    invokestatic java/lang/Character/isDigit(C)Z
    ifeq pjct_fail
    iload_3
    bipush 48
    isub
    i2l
    invokestatic queens/pj_term_int(J)[Ljava/lang/Object;
    aload_1
    checkcast [Ljava/lang/Object;
    iconst_2
    aaload
    invokestatic queens/pj_unify(Ljava/lang/Object;Ljava/lang/Object;)Z
    ireturn
pjct_try_upper_l:
    aload 4
    ldc "upper"
    invokevirtual java/lang/Object/equals(Ljava/lang/Object;)Z
    ifeq pjct_try_lower_u
    iload_3
    invokestatic java/lang/Character/isUpperCase(C)Z
    ifeq pjct_fail
    iload_3
    invokestatic java/lang/Character/toLowerCase(C)C
    invokestatic java/lang/Character/toString(C)Ljava/lang/String;
    invokestatic queens/pj_term_atom(Ljava/lang/String;)[Ljava/lang/Object;
    aload_1
    checkcast [Ljava/lang/Object;
    iconst_2
    aaload
    invokestatic queens/pj_unify(Ljava/lang/Object;Ljava/lang/Object;)Z
    ireturn
pjct_try_lower_u:
    aload 4
    ldc "lower"
    invokevirtual java/lang/Object/equals(Ljava/lang/Object;)Z
    ifeq pjct_try_to_upper
    iload_3
    invokestatic java/lang/Character/isLowerCase(C)Z
    ifeq pjct_fail
    iload_3
    invokestatic java/lang/Character/toUpperCase(C)C
    invokestatic java/lang/Character/toString(C)Ljava/lang/String;
    invokestatic queens/pj_term_atom(Ljava/lang/String;)[Ljava/lang/Object;
    aload_1
    checkcast [Ljava/lang/Object;
    iconst_2
    aaload
    invokestatic queens/pj_unify(Ljava/lang/Object;Ljava/lang/Object;)Z
    ireturn
pjct_try_to_upper:
    aload 4
    ldc "to_upper"
    invokevirtual java/lang/Object/equals(Ljava/lang/Object;)Z
    ifeq pjct_try_to_lower
    iload_3
    invokestatic java/lang/Character/toUpperCase(C)C
    invokestatic java/lang/Character/toString(C)Ljava/lang/String;
    invokestatic queens/pj_term_atom(Ljava/lang/String;)[Ljava/lang/Object;
    aload_1
    checkcast [Ljava/lang/Object;
    iconst_2
    aaload
    invokestatic queens/pj_unify(Ljava/lang/Object;Ljava/lang/Object;)Z
    ireturn
pjct_try_to_lower:
    aload 4
    ldc "to_lower"
    invokevirtual java/lang/Object/equals(Ljava/lang/Object;)Z
    ifeq pjct_try_ascii
    iload_3
    invokestatic java/lang/Character/toLowerCase(C)C
    invokestatic java/lang/Character/toString(C)Ljava/lang/String;
    invokestatic queens/pj_term_atom(Ljava/lang/String;)[Ljava/lang/Object;
    aload_1
    checkcast [Ljava/lang/Object;
    iconst_2
    aaload
    invokestatic queens/pj_unify(Ljava/lang/Object;Ljava/lang/Object;)Z
    ireturn
pjct_try_ascii:
    aload 4
    ldc "ascii"
    invokevirtual java/lang/Object/equals(Ljava/lang/Object;)Z
    ifeq pjct_fail
    iload_3
    i2l
    invokestatic queens/pj_term_int(J)[Ljava/lang/Object;
    aload_1
    checkcast [Ljava/lang/Object;
    iconst_2
    aaload
    invokestatic queens/pj_unify(Ljava/lang/Object;Ljava/lang/Object;)Z
    ireturn
.end method

; pj_atom_string_2
.method static pj_atom_string_2(Ljava/lang/Object;Ljava/lang/Object;)Z
    .limit stack 4
    .limit locals 4
    aload_0
    invokestatic queens/pj_deref(Ljava/lang/Object;)Ljava/lang/Object;
    checkcast [Ljava/lang/Object;
    astore_2
    aload_2
    iconst_0
    aaload
    ldc "var"
    invokevirtual java/lang/Object/equals(Ljava/lang/Object;)Z
    ifne as2_rev
    aload_2
    invokestatic queens/pj_atom_name(Ljava/lang/Object;)Ljava/lang/String;
    invokestatic queens/pj_term_atom(Ljava/lang/String;)[Ljava/lang/Object;
    aload_1
    invokestatic queens/pj_unify(Ljava/lang/Object;Ljava/lang/Object;)Z
    ireturn
as2_rev:
    aload_1
    invokestatic queens/pj_deref(Ljava/lang/Object;)Ljava/lang/Object;
    checkcast [Ljava/lang/Object;
    astore_3
    aload_3
    invokestatic queens/pj_atom_name(Ljava/lang/Object;)Ljava/lang/String;
    invokestatic queens/pj_term_atom(Ljava/lang/String;)[Ljava/lang/Object;
    aload_0
    invokestatic queens/pj_unify(Ljava/lang/Object;Ljava/lang/Object;)Z
    ireturn
.end method

; pj_number_string_2
.method static pj_number_string_2(Ljava/lang/Object;Ljava/lang/Object;)Z
    .limit stack 4
    .limit locals 5
    aload_0
    invokestatic queens/pj_deref(Ljava/lang/Object;)Ljava/lang/Object;
    checkcast [Ljava/lang/Object;
    astore_2
    aload_2
    iconst_0
    aaload
    ldc "var"
    invokevirtual java/lang/Object/equals(Ljava/lang/Object;)Z
    ifne ns2_rev
    aload_2
    invokestatic queens/pj_atom_name(Ljava/lang/Object;)Ljava/lang/String;
    invokestatic queens/pj_term_atom(Ljava/lang/String;)[Ljava/lang/Object;
    aload_1
    invokestatic queens/pj_unify(Ljava/lang/Object;Ljava/lang/Object;)Z
    ireturn
ns2_rev:
    aload_1
    invokestatic queens/pj_deref(Ljava/lang/Object;)Ljava/lang/Object;
    astore_3
    aload_3
    invokestatic queens/pj_atom_name(Ljava/lang/Object;)Ljava/lang/String;
    astore 4
    aload 4
    invokestatic java/lang/Long/parseLong(Ljava/lang/String;)J
    invokestatic queens/pj_term_int(J)[Ljava/lang/Object;
    aload_0
    invokestatic queens/pj_unify(Ljava/lang/Object;Ljava/lang/Object;)Z
    ireturn
.end method

; pj_term_to_atom_2
.method static pj_term_to_atom_2(Ljava/lang/Object;Ljava/lang/Object;)Z
    .limit stack 4
    .limit locals 2
    aload_0
    invokestatic queens/pj_term_str(Ljava/lang/Object;)Ljava/lang/String;
    invokestatic queens/pj_term_atom(Ljava/lang/String;)[Ljava/lang/Object;
    aload_1
    invokestatic queens/pj_unify(Ljava/lang/Object;Ljava/lang/Object;)Z
    ireturn
.end method

; pj_alc_sep(Object list, String sep) -> String
.method static pj_alc_sep(Ljava/lang/Object;Ljava/lang/String;)Ljava/lang/String;
    .limit stack 6
    .limit locals 5
    new java/lang/StringBuilder
    dup
    invokespecial java/lang/StringBuilder/<init>()V
    astore_2
    iconst_1
    istore 4
    aload_0
    invokestatic queens/pj_deref(Ljava/lang/Object;)Ljava/lang/Object;
    astore_3
alcs_loop:
    aload_3
    checkcast [Ljava/lang/Object;
    iconst_1
    aaload
    ldc "[]"
    invokevirtual java/lang/Object/equals(Ljava/lang/Object;)Z
    ifne alcs_done
    iload 4
    ifne alcs_skip_sep
    aload_2
    aload_1
    invokevirtual java/lang/StringBuilder/append(Ljava/lang/String;)Ljava/lang/StringBuilder;
    pop
alcs_skip_sep:
    iconst_0
    istore 4
    aload_3
    checkcast [Ljava/lang/Object;
    iconst_2
    aaload
    invokestatic queens/pj_deref(Ljava/lang/Object;)Ljava/lang/Object;
    invokestatic queens/pj_atom_name(Ljava/lang/Object;)Ljava/lang/String;
    aload_2
    swap
    invokevirtual java/lang/StringBuilder/append(Ljava/lang/String;)Ljava/lang/StringBuilder;
    pop
    aload_3
    checkcast [Ljava/lang/Object;
    bipush 3
    aaload
    invokestatic queens/pj_deref(Ljava/lang/Object;)Ljava/lang/Object;
    astore_3
    goto alcs_loop
alcs_done:
    aload_2
    invokevirtual java/lang/StringBuilder/toString()Ljava/lang/String;
    areturn
.end method

; === forall/2 synthetic predicate =========================================
.method static p_forall_2([Ljava/lang/Object;[Ljava/lang/Object;I)[Ljava/lang/Object;
    .limit stack 6
    .limit locals 6
    aload_0
    invokestatic queens/pj_deref(Ljava/lang/Object;)Ljava/lang/Object;
    iconst_0
    istore 3
p_forall_2_loop:
    dup
    iload 3
    invokestatic queens/pj_call_goal(Ljava/lang/Object;I)I
    istore 4
    iload 4
    ldc -1
    if_icmpeq p_forall_2_done
    iload 4
    istore 3
    aload_1
    invokestatic queens/pj_deref(Ljava/lang/Object;)Ljava/lang/Object;
    iconst_0
    invokestatic queens/pj_call_goal(Ljava/lang/Object;I)I
    ldc -1
    if_icmpeq p_forall_2_fail
    goto p_forall_2_loop
p_forall_2_done:
    pop
    iconst_1
    anewarray java/lang/Object
    dup
    iconst_0
    iconst_0
    invokestatic java/lang/Integer/valueOf(I)Ljava/lang/Integer;
    aastore
    areturn
p_forall_2_fail:
    pop
    aconst_null
    areturn
.end method

; === between/3 synthetic predicate ========================================
.method static p_between_3([Ljava/lang/Object;[Ljava/lang/Object;[Ljava/lang/Object;I)[Ljava/lang/Object;
    .limit stack 8
    .limit locals 10
    iload_3
    ifne p_between_3_generate
    aload_2
    invokestatic queens/pj_deref(Ljava/lang/Object;)Ljava/lang/Object;
    checkcast [Ljava/lang/Object;
    iconst_0
    aaload
    ldc "var"
    invokevirtual java/lang/Object/equals(Ljava/lang/Object;)Z
    ifne p_between_3_generate
    aload_0
    invokestatic queens/pj_deref(Ljava/lang/Object;)Ljava/lang/Object;
    checkcast [Ljava/lang/Object;
    iconst_1
    aaload
    checkcast java/lang/String
    invokestatic java/lang/Long/parseLong(Ljava/lang/String;)J
    lstore 4
    aload_1
    invokestatic queens/pj_deref(Ljava/lang/Object;)Ljava/lang/Object;
    checkcast [Ljava/lang/Object;
    iconst_1
    aaload
    checkcast java/lang/String
    invokestatic java/lang/Long/parseLong(Ljava/lang/String;)J
    lstore 6
    aload_2
    invokestatic queens/pj_deref(Ljava/lang/Object;)Ljava/lang/Object;
    checkcast [Ljava/lang/Object;
    iconst_1
    aaload
    checkcast java/lang/String
    invokestatic java/lang/Long/parseLong(Ljava/lang/String;)J
    lstore 8
    lload 4
    lload 8
    lcmp
    ifgt p_between_3_fail
    lload 8
    lload 6
    lcmp
    ifgt p_between_3_fail
    iconst_1
    anewarray java/lang/Object
    dup
    iconst_0
    ldc 2147483647
    invokestatic java/lang/Integer/valueOf(I)Ljava/lang/Integer;
    aastore
    areturn
p_between_3_generate:
    aload_0
    invokestatic queens/pj_deref(Ljava/lang/Object;)Ljava/lang/Object;
    checkcast [Ljava/lang/Object;
    iconst_1
    aaload
    checkcast java/lang/String
    invokestatic java/lang/Long/parseLong(Ljava/lang/String;)J
    iload_3
    i2l
    ladd
    lstore 8
    aload_1
    invokestatic queens/pj_deref(Ljava/lang/Object;)Ljava/lang/Object;
    checkcast [Ljava/lang/Object;
    iconst_1
    aaload
    checkcast java/lang/String
    invokestatic java/lang/Long/parseLong(Ljava/lang/String;)J
    lstore 6
    lload 8
    lload 6
    lcmp
    ifgt p_between_3_fail
    lload 8
    invokestatic queens/pj_term_int(J)[Ljava/lang/Object;
    aload_2
    invokestatic queens/pj_unify(Ljava/lang/Object;Ljava/lang/Object;)Z
    ifeq p_between_3_fail
    iconst_1
    anewarray java/lang/Object
    dup
    iconst_0
    iload_3
    iconst_1
    iadd
    invokestatic java/lang/Integer/valueOf(I)Ljava/lang/Integer;
    aastore
    areturn
p_between_3_fail:
    aconst_null
    areturn
.end method

; === pj_copy_term (deep copy for findall) ===========================
.method static pj_copy_term(Ljava/lang/Object;)Ljava/lang/Object;
    .limit stack 10
    .limit locals 6
    aload_0
    invokestatic queens/pj_deref(Ljava/lang/Object;)Ljava/lang/Object;
    astore_0
    aload_0
    ifnonnull pj_ct_notnull
    aconst_null
    areturn
pj_ct_notnull:
    aload_0
    checkcast [Ljava/lang/Object;
    astore_1
    aload_1
    iconst_0
    aaload
    astore_2
    aload_2
    ldc "var"
    invokevirtual java/lang/Object/equals(Ljava/lang/Object;)Z
    ifeq pj_ct_not_var
    invokestatic queens/pj_term_var()[Ljava/lang/Object;
    areturn
pj_ct_not_var:
    aload_2
    ldc "atom"
    invokevirtual java/lang/Object/equals(Ljava/lang/Object;)Z
    ifeq pj_ct_not_atom
    aload_1
    areturn
pj_ct_not_atom:
    aload_2
    ldc "int"
    invokevirtual java/lang/Object/equals(Ljava/lang/Object;)Z
    ifeq pj_ct_not_int
    aload_1
    areturn
pj_ct_not_int:
    aload_1
    arraylength
    istore_3
    iload_3
    anewarray java/lang/Object
    astore 4
    aload 4
    iconst_0
    aload_1
    iconst_0
    aaload
    aastore
    aload 4
    iconst_1
    aload_1
    iconst_1
    aaload
    aastore
    iconst_2
    istore 5
pj_ct_arg_loop:
    iload 5
    iload_3
    if_icmpge pj_ct_done
    aload 4
    iload 5
    aload_1
    iload 5
    aaload
    invokestatic queens/pj_copy_term(Ljava/lang/Object;)Ljava/lang/Object;
    aastore
    iinc 5 1
    goto pj_ct_arg_loop
pj_ct_done:
    aload 4
    areturn
.end method

; === pj_is_ground (recursive ground check) ===========================
.method static pj_is_ground(Ljava/lang/Object;)Z
    .limit stack 8
    .limit locals 5
    aload_0
    invokestatic queens/pj_deref(Ljava/lang/Object;)Ljava/lang/Object;
    astore_0
    aload_0
    ifnull pj_isg_false
    aload_0
    instanceof [Ljava/lang/Object;
    ifeq pj_isg_string
    aload_0
    checkcast [Ljava/lang/Object;
    astore 1
    aload 1
    iconst_0
    aaload
    checkcast java/lang/String
    astore 2
    aload 2
    ldc "var"
    invokevirtual java/lang/Object/equals(Ljava/lang/Object;)Z
    ifne pj_isg_false
    aload 2
    ldc "ref"
    invokevirtual java/lang/Object/equals(Ljava/lang/Object;)Z
    ifeq pj_isg_not_ref
    aload 1
    iconst_1
    aaload
    invokestatic queens/pj_is_ground(Ljava/lang/Object;)Z
    ireturn
pj_isg_not_ref:
    aload 2
    ldc "atom"
    invokevirtual java/lang/Object/equals(Ljava/lang/Object;)Z
    ifne pj_isg_true
    aload 2
    ldc "int"
    invokevirtual java/lang/Object/equals(Ljava/lang/Object;)Z
    ifne pj_isg_true
    aload 2
    ldc "float"
    invokevirtual java/lang/Object/equals(Ljava/lang/Object;)Z
    ifne pj_isg_true
    aload 1
    arraylength
    iconst_2
    isub
    istore 3
    iconst_0
    istore 4
pj_isg_compound_loop:
    iload 4
    iload 3
    if_icmpge pj_isg_true
    aload 1
    iload 4
    iconst_2
    iadd
    aaload
    invokestatic queens/pj_is_ground(Ljava/lang/Object;)Z
    ifeq pj_isg_false
    iinc 4 1
    goto pj_isg_compound_loop
pj_isg_string:
pj_isg_true:
    iconst_1
    ireturn
pj_isg_false:
    iconst_0
    ireturn
.end method

; === pj_can_compare (?= operator) ====================================
.method static pj_can_compare(Ljava/lang/Object;Ljava/lang/Object;)Z
    .limit stack 4
    .limit locals 2
    aload_0
    invokestatic queens/pj_is_ground(Ljava/lang/Object;)Z
    ifeq pj_cc_false
    aload_1
    invokestatic queens/pj_is_ground(Ljava/lang/Object;)Z
    ifeq pj_cc_false
    iconst_1
    ireturn
pj_cc_false:
    iconst_0
    ireturn
.end method

; === pj_call_goal (goal interpreter for findall) ====================
.method static pj_call_goal(Ljava/lang/Object;I)I
    .limit stack 20
    .limit locals 16
    aload_0
    invokestatic queens/pj_deref(Ljava/lang/Object;)Ljava/lang/Object;
    astore_0
    aload_0
    ifnull pj_cg_fail
    aload_0
    checkcast [Ljava/lang/Object;
    astore 2
    aload 2
    iconst_0
    aaload
    checkcast java/lang/String
    astore 3
    aload 3
    ldc "atom"
    invokevirtual java/lang/Object/equals(Ljava/lang/Object;)Z
    ifeq pj_cg_not_atom
    aload 2
    iconst_1
    aaload
    checkcast java/lang/String
    astore 4
    aload 4
    ldc "fail"
    invokevirtual java/lang/Object/equals(Ljava/lang/Object;)Z
    ifeq pj_cg_not_fail_atom
    ldc -1
    ireturn
pj_cg_not_fail_atom:
    aload 4
    ldc "true"
    invokevirtual java/lang/Object/equals(Ljava/lang/Object;)Z
    ifeq pj_cg_atom_user
    iconst_0
    ireturn
pj_cg_atom_user:
    aload 4
    iconst_0
    aconst_null
    iload_1
    invokestatic queens/pj_reflect_call(Ljava/lang/String;I[Ljava/lang/Object;I)[Ljava/lang/Object;
    astore 5
    aload 5
    ifnull pj_cg_fail
    aload 5
    iconst_0
    aaload
    checkcast java/lang/Integer
    invokevirtual java/lang/Integer/intValue()I
    ireturn
pj_cg_not_atom:
    aload 3
    ldc "compound"
    invokevirtual java/lang/Object/equals(Ljava/lang/Object;)Z
    ifeq pj_cg_fail
    aload 2
    iconst_1
    aaload
    checkcast java/lang/String
    astore 4
    aload 2
    arraylength
    iconst_2
    isub
    istore 5
    aload 4
    ldc ","
    invokevirtual java/lang/Object/equals(Ljava/lang/Object;)Z
    ifeq pj_cg_not_conj
    aload 2
    iconst_2
    aaload
    iload_1
    invokestatic queens/pj_call_goal(Ljava/lang/Object;I)I
    istore 9
    iload 9
    ldc -1
    if_icmpeq pj_cg_fail
    aload 2
    iconst_3
    aaload
    iconst_0
    invokestatic queens/pj_call_goal(Ljava/lang/Object;I)I
    ldc -1
    if_icmpeq pj_cg_fail
    iload 9
    ireturn
pj_cg_not_conj:
    aload 4
    ldc "is"
    invokevirtual java/lang/Object/equals(Ljava/lang/Object;)Z
    ifeq pj_cg_not_is
    aload 2
    iconst_2
    aaload
    astore 6
    aload 2
    iconst_3
    aaload
    astore 7
    aload 7
    invokestatic queens/pj_eval_arith(Ljava/lang/Object;)J
    invokestatic queens/pj_term_int(J)[Ljava/lang/Object;
    astore 8
    aload 6
    aload 8
    invokestatic queens/pj_unify(Ljava/lang/Object;Ljava/lang/Object;)Z
    ifeq pj_cg_fail
    iconst_0
    ireturn
pj_cg_not_is:
    aload 4
    ldc "phrase"
    invokevirtual java/lang/Object/equals(Ljava/lang/Object;)Z
    ifeq pj_cg_not_phrase
    aload 2
    arraylength
    iconst_2
    isub
    istore 5
    iload 5
    iconst_2
    if_icmplt pj_cg_not_phrase
    iload 5
    iconst_3
    if_icmpgt pj_cg_not_phrase
    aload 2
    iconst_2
    aaload
    invokestatic queens/pj_deref(Ljava/lang/Object;)Ljava/lang/Object;
    astore 6
    aload 6
    instanceof [Ljava/lang/Object;
    ifeq pj_cg_phrase_atom_nt
    aload 6
    checkcast [Ljava/lang/Object;
    astore 7
    aload 7
    iconst_1
    aaload
    checkcast java/lang/String
    astore 8
    aload 7
    arraylength
    iconst_2
    isub
    istore 9
    goto pj_cg_phrase_have_nt
pj_cg_phrase_atom_nt:
    aconst_null
    astore 7
    aload 6
    checkcast java/lang/String
    astore 8
    iconst_0
    istore 9
pj_cg_phrase_have_nt:
    aload 8
    ldc "[]"
    invokevirtual java/lang/Object/equals(Ljava/lang/Object;)Z
    ifeq pj_cg_phrase_not_nil_nt
    aload 2
    iconst_3
    aaload
    iload 5
    iconst_3
    if_icmpeq pj_cg_phrase_nil_has_rest
    ldc "[]"
    invokestatic queens/pj_term_atom(Ljava/lang/String;)[Ljava/lang/Object;
    goto pj_cg_phrase_nil_do_unify
pj_cg_phrase_nil_has_rest:
    aload 2
    bipush 4
    aaload
pj_cg_phrase_nil_do_unify:
    invokestatic queens/pj_unify(Ljava/lang/Object;Ljava/lang/Object;)Z
    ifeq pj_cg_fail
    iconst_0
    ireturn
pj_cg_phrase_not_nil_nt:
    iload 9
    iconst_2
    iadd
    istore 10
    iload 10
    anewarray java/lang/Object
    astore 11
    iconst_0
    istore 12
pj_cg_phrase_nt_args_loop:
    iload 12
    iload 9
    if_icmpge pj_cg_phrase_nt_args_done
    aload 11
    iload 12
    aload 7
    iload 12
    iconst_2
    iadd
    aaload
    aastore
    iinc 12 1
    goto pj_cg_phrase_nt_args_loop
pj_cg_phrase_nt_args_done:
    aload 11
    iload 9
    aload 2
    iconst_3
    aaload
    aastore
    aload 11
    iload 9
    iconst_1
    iadd
    iload 5
    iconst_3
    if_icmpeq pj_cg_phrase_has_rest
    ldc "[]"
    invokestatic queens/pj_term_atom(Ljava/lang/String;)[Ljava/lang/Object;
    goto pj_cg_phrase_store_rest
pj_cg_phrase_has_rest:
    aload 2
    bipush 4
    aaload
pj_cg_phrase_store_rest:
    aastore
    aload 8
    iload 10
    aload 11
    iload_1
    invokestatic queens/pj_reflect_call(Ljava/lang/String;I[Ljava/lang/Object;I)[Ljava/lang/Object;
    astore 13
    aload 13
    ifnull pj_cg_fail
    aload 13
    iconst_0
    aaload
    checkcast java/lang/Integer
    invokevirtual java/lang/Integer/intValue()I
    ireturn
pj_cg_not_phrase:
    aload 4
    ldc "assertz"
    invokevirtual java/lang/String/equals(Ljava/lang/Object;)Z
    ifeq pj_cg_not_assertz
    aload 2
    iconst_2
    aaload
    invokestatic queens/pj_deref(Ljava/lang/Object;)Ljava/lang/Object;
    dup
    invokestatic queens/pj_db_assert_key(Ljava/lang/Object;)Ljava/lang/String;
    swap
    iconst_0
    invokestatic queens/pj_db_assert(Ljava/lang/String;Ljava/lang/Object;I)V
    iconst_0
    ireturn
pj_cg_not_assertz:
    aload 2
    arraylength
    iconst_2
    isub
    istore 5
    iload 5
    anewarray java/lang/Object
    astore 6
    iconst_0
    istore 7
pj_cg_args_loop:
    iload 7
    iload 5
    if_icmpge pj_cg_args_done
    aload 6
    iload 7
    aload 2
    iload 7
    iconst_2
    iadd
    aaload
    aastore
    iinc 7 1
    goto pj_cg_args_loop
pj_cg_args_done:
    aload 4
    iload 5
    aload 6
    iload_1
    invokestatic queens/pj_reflect_call(Ljava/lang/String;I[Ljava/lang/Object;I)[Ljava/lang/Object;
    astore 8
    aload 8
    ifnull pj_cg_fail
    aload 8
    iconst_0
    aaload
    checkcast java/lang/Integer
    invokevirtual java/lang/Integer/intValue()I
    ireturn
pj_cg_fail:
    ldc -1
    ireturn
.end method

; === pj_eval_arith (arithmetic evaluator for findall/is) ============
.method static pj_eval_arith(Ljava/lang/Object;)J
    .limit stack 10
    .limit locals 8
    aload_0
    invokestatic queens/pj_deref(Ljava/lang/Object;)Ljava/lang/Object;
    astore_0
    aload_0
    checkcast [Ljava/lang/Object;
    astore_1
    aload_1
    iconst_0
    aaload
    checkcast java/lang/String
    astore_2
    aload_2
    ldc "int"
    invokevirtual java/lang/Object/equals(Ljava/lang/Object;)Z
    ifeq pj_ea_not_int
    aload_1
    iconst_1
    aaload
    checkcast java/lang/String
    invokestatic java/lang/Long/parseLong(Ljava/lang/String;)J
    lreturn
pj_ea_not_int:
    aload_1
    iconst_1
    aaload
    checkcast java/lang/String
    astore_3
    aload_1
    iconst_2
    aaload
    invokestatic queens/pj_eval_arith(Ljava/lang/Object;)J
    lstore 4
    aload_1
    arraylength
    iconst_3
    if_icmplt pj_ea_unary
    aload_1
    iconst_3
    aaload
    invokestatic queens/pj_eval_arith(Ljava/lang/Object;)J
    lstore 6
    aload_3
    ldc "+"
    invokevirtual java/lang/Object/equals(Ljava/lang/Object;)Z
    ifeq pj_ea_not_add
    lload 4
    lload 6
    ladd
    lreturn
pj_ea_not_add:
    aload_3
    ldc "-"
    invokevirtual java/lang/Object/equals(Ljava/lang/Object;)Z
    ifeq pj_ea_not_sub
    lload 4
    lload 6
    lsub
    lreturn
pj_ea_not_sub:
    aload_3
    ldc "*"
    invokevirtual java/lang/Object/equals(Ljava/lang/Object;)Z
    ifeq pj_ea_not_mul
    lload 4
    lload 6
    lmul
    lreturn
pj_ea_not_mul:
    aload_3
    ldc "/"
    invokevirtual java/lang/Object/equals(Ljava/lang/Object;)Z
    ifeq pj_ea_not_div
    lload 4
    lload 6
    ldiv
    lreturn
pj_ea_not_div:
    aload_3
    ldc "mod"
    invokevirtual java/lang/Object/equals(Ljava/lang/Object;)Z
    ifeq pj_ea_not_mod
    lload 4
    lload 6
    lrem
    lreturn
pj_ea_not_mod:
    lload 4
    lreturn
pj_ea_unary:
    aload_3
    ldc "-"
    invokevirtual java/lang/Object/equals(Ljava/lang/Object;)Z
    ifeq pj_ea_unary_other
    lload 4
    lneg
    lreturn
pj_ea_unary_other:
    lload 4
    lreturn
.end method

; === pj_reflect_call (reflection dispatch for findall) ==============
.method static pj_reflect_call(Ljava/lang/String;I[Ljava/lang/Object;I)[Ljava/lang/Object;
    .limit stack 20
    .limit locals 15
    .catch java/lang/Exception from pj_rc_try_start to pj_rc_try_end using pj_rc_catch
pj_rc_try_start:
    ldc "p_"
    aload_0
    invokevirtual java/lang/String/concat(Ljava/lang/String;)Ljava/lang/String;
    ldc "_"
    invokevirtual java/lang/String/concat(Ljava/lang/String;)Ljava/lang/String;
    iload_1
    invokestatic java/lang/Integer/toString(I)Ljava/lang/String;
    invokevirtual java/lang/String/concat(Ljava/lang/String;)Ljava/lang/String;
    astore 4
    iload_1
    iconst_1
    iadd
    anewarray java/lang/Class
    astore 5
    iconst_0
    istore 6
pj_rc_param_loop:
    iload 6
    iload_1
    if_icmpge pj_rc_param_done
    aload 5
    iload 6
    iconst_0
    anewarray java/lang/Object
    invokevirtual java/lang/Object/getClass()Ljava/lang/Class;
    aastore
    iinc 6 1
    goto pj_rc_param_loop
pj_rc_param_done:
    aload 5
    iload_1
    getstatic java/lang/Integer/TYPE Ljava/lang/Class;
    aastore
    ldc "queens"
    invokestatic java/lang/Class/forName(Ljava/lang/String;)Ljava/lang/Class;
    astore 7
    aload 7
    aload 4
    aload 5
    invokevirtual java/lang/Class/getDeclaredMethod(Ljava/lang/String;[Ljava/lang/Class;)Ljava/lang/reflect/Method;
    astore 8
    aload 8
    iconst_1
    invokevirtual java/lang/reflect/Method/setAccessible(Z)V
    iload_1
    iconst_1
    iadd
    anewarray java/lang/Object
    astore 9
    iconst_0
    istore 6
pj_rc_invoke_loop:
    iload 6
    iload_1
    if_icmpge pj_rc_invoke_done
    aload 9
    iload 6
    aload_2
    iload 6
    aaload
    aastore
    iinc 6 1
    goto pj_rc_invoke_loop
pj_rc_invoke_done:
    aload 9
    iload_1
    iload_3
    invokestatic java/lang/Integer/valueOf(I)Ljava/lang/Integer;
    aastore
    aload 8
    aconst_null
    aload 9
    invokevirtual java/lang/reflect/Method/invoke(Ljava/lang/Object;[Ljava/lang/Object;)Ljava/lang/Object;
pj_rc_try_end:
    checkcast [Ljava/lang/Object;
    areturn
pj_rc_catch:
    astore 10
    aload 10
    instanceof java/lang/reflect/InvocationTargetException
    ifeq pj_rc_not_ite
    aload 10
    checkcast java/lang/reflect/InvocationTargetException
    invokevirtual java/lang/reflect/InvocationTargetException/getCause()Ljava/lang/Throwable;
    dup
    ifnull pj_rc_ite_null
    astore 10
    goto pj_rc_not_ite
pj_rc_ite_null:
    pop
    goto pj_rc_swallow
pj_rc_not_ite:
    aload 10
    invokevirtual java/lang/Throwable/getMessage()Ljava/lang/String;
    ifnull pj_rc_swallow
    aload 10
    invokevirtual java/lang/Throwable/getMessage()Ljava/lang/String;
    ldc "PROLOG_THROW"
    invokevirtual java/lang/String/equals(Ljava/lang/Object;)Z
    ifeq pj_rc_swallow
    aload 10
    athrow
pj_rc_swallow:
    new java/lang/StringBuilder
    dup
    invokespecial java/lang/StringBuilder/<init>()V
    aload_0
    invokevirtual java/lang/StringBuilder/append(Ljava/lang/String;)Ljava/lang/StringBuilder;
    ldc "/"
    invokevirtual java/lang/StringBuilder/append(Ljava/lang/String;)Ljava/lang/StringBuilder;
    iload_1
    invokevirtual java/lang/StringBuilder/append(I)Ljava/lang/StringBuilder;
    invokevirtual java/lang/StringBuilder/toString()Ljava/lang/String;
    iload_3
    invokestatic queens/pj_db_query(Ljava/lang/String;I)Ljava/lang/Object;
    dup
    ifnull pj_rc_db_miss
    checkcast [Ljava/lang/Object;
    astore 11
    aconst_null
    astore 12
    iconst_0
    istore 13
    iconst_0
    istore 14
pj_rc_db_unify_loop:
    iload 14
    iload_1
    if_icmpge pj_rc_db_unify_done
    aload_2
    iload 14
    aaload
    aload 11
    iload 14
    iconst_2
    iadd
    aaload
    invokestatic queens/pj_unify(Ljava/lang/Object;Ljava/lang/Object;)Z
    ifeq pj_rc_db_unify_fail
    iinc 14 1
    goto pj_rc_db_unify_loop
pj_rc_db_unify_done:
    iconst_1
    anewarray java/lang/Object
    dup
    iconst_0
    iload_3
    iconst_1
    iadd
    invokestatic java/lang/Integer/valueOf(I)Ljava/lang/Integer;
    aastore
    areturn
pj_rc_db_unify_fail:
    aconst_null
    areturn
pj_rc_db_miss:
    pop
    aconst_null
    areturn
.end method

; === findall/3 synthetic predicate ===================================
.method static p_findall_3([Ljava/lang/Object;[Ljava/lang/Object;[Ljava/lang/Object;I)[Ljava/lang/Object;
    .limit stack 20
    .limit locals 16
    new java/util/ArrayList
    dup
    invokespecial java/util/ArrayList/<init>()V
    astore 4
    invokestatic queens/pj_trail_mark()I
    istore 5
    iconst_0
    istore 6
pj_fa_loop:
    aload_1
    iload 6
    invokestatic queens/pj_call_goal(Ljava/lang/Object;I)I
    istore 6
    iload 6
    ldc -1
    if_icmpeq pj_fa_done
    aload_0
    invokestatic queens/pj_copy_term(Ljava/lang/Object;)Ljava/lang/Object;
    astore 8
    aload 4
    aload 8
    invokevirtual java/util/ArrayList/add(Ljava/lang/Object;)Z
    pop
    iload 5
    invokestatic queens/pj_trail_unwind(I)V
    goto pj_fa_loop
pj_fa_done:
    iload 5
    invokestatic queens/pj_trail_unwind(I)V
    ldc "[]"
    invokestatic queens/pj_term_atom(Ljava/lang/String;)[Ljava/lang/Object;
    astore 9
    aload 4
    invokevirtual java/util/ArrayList/size()I
    iconst_1
    isub
    istore 10
pj_fa_list_loop:
    iload 10
    iflt pj_fa_list_done
    bipush 4
    anewarray java/lang/Object
    astore 11
    aload 11
    iconst_0
    ldc "compound"
    aastore
    aload 11
    iconst_1
    ldc "."
    aastore
    aload 11
    iconst_2
    aload 4
    iload 10
    invokevirtual java/util/ArrayList/get(I)Ljava/lang/Object;
    aastore
    aload 11
    iconst_3
    aload 9
    aastore
    aload 11
    astore 9
    iinc 10 -1
    goto pj_fa_list_loop
pj_fa_list_done:
    aload_2
    aload 9
    invokestatic queens/pj_unify(Ljava/lang/Object;Ljava/lang/Object;)Z
    ifeq pj_fa_fail
    iconst_1
    anewarray java/lang/Object
    dup
    iconst_0
    iconst_1
    invokestatic java/lang/Integer/valueOf(I)Ljava/lang/Integer;
    aastore
    areturn
pj_fa_fail:
    aconst_null
    areturn
.end method

; === aggregate_all/3 synthetic predicate ============================
.method static p_aggregate_all_3([Ljava/lang/Object;[Ljava/lang/Object;[Ljava/lang/Object;I)[Ljava/lang/Object;
    .limit stack 20
    .limit locals 20
    aload_0
    invokestatic queens/pj_deref(Ljava/lang/Object;)Ljava/lang/Object;
    astore_0
    new java/util/ArrayList
    dup
    invokespecial java/util/ArrayList/<init>()V
    astore 4
    invokestatic queens/pj_trail_mark()I
    istore 5
    iconst_0
    istore 6
pj_agg_loop:
    aload_1
    iload 6
    invokestatic queens/pj_call_goal(Ljava/lang/Object;I)I
    istore 6
    iload 6
    ldc -1
    if_icmpeq pj_agg_done
    aload_0
    invokestatic queens/pj_copy_term(Ljava/lang/Object;)Ljava/lang/Object;
    astore 9
    aload 4
    aload 9
    invokevirtual java/util/ArrayList/add(Ljava/lang/Object;)Z
    pop
    iload 5
    invokestatic queens/pj_trail_unwind(I)V
    goto pj_agg_loop
pj_agg_done:
    iload 5
    invokestatic queens/pj_trail_unwind(I)V
    aload_0
    checkcast [Ljava/lang/Object;
    iconst_1
    aaload
    invokevirtual java/lang/Object/toString()Ljava/lang/String;
    astore 7
    aload 7
    ldc "count"
    invokevirtual java/lang/String/equals(Ljava/lang/Object;)Z
    ifeq pj_agg_not_count
    aload 4
    invokevirtual java/util/ArrayList/size()I
    i2l
    invokestatic queens/pj_term_int(J)[Ljava/lang/Object;
    aload_2
    invokestatic queens/pj_unify(Ljava/lang/Object;Ljava/lang/Object;)Z
    ifeq pj_agg_fail
    goto pj_agg_succeed
pj_agg_not_count:
    aload 7
    ldc "bag"
    invokevirtual java/lang/String/equals(Ljava/lang/Object;)Z
    ifne pj_agg_build_list
    aload 7
    ldc "set"
    invokevirtual java/lang/String/equals(Ljava/lang/Object;)Z
    ifne pj_agg_build_sorted_list
    goto pj_agg_not_bag
pj_agg_build_list:
    ldc "[]"
    invokestatic queens/pj_term_atom(Ljava/lang/String;)[Ljava/lang/Object;
    astore 10
    aload 4
    invokevirtual java/util/ArrayList/size()I
    iconst_1
    isub
    istore 11
pj_agg_bag_loop:
    iload 11
    iflt pj_agg_bag_done
    aload 4
    iload 11
    invokevirtual java/util/ArrayList/get(I)Ljava/lang/Object;
    checkcast [Ljava/lang/Object;
    iconst_2
    aaload
    astore 12
    bipush 4
    anewarray java/lang/Object
    astore 13
    aload 13
    iconst_0
    ldc "compound"
    aastore
    aload 13
    iconst_1
    ldc "."
    aastore
    aload 13
    iconst_2
    aload 12
    aastore
    aload 13
    iconst_3
    aload 10
    aastore
    aload 13
    astore 10
    iinc 11 -1
    goto pj_agg_bag_loop
pj_agg_bag_done:
    aload_2
    aload 10
    invokestatic queens/pj_unify(Ljava/lang/Object;Ljava/lang/Object;)Z
    ifeq pj_agg_fail
    goto pj_agg_succeed
pj_agg_build_sorted_list:
    ldc "[]"
    invokestatic queens/pj_term_atom(Ljava/lang/String;)[Ljava/lang/Object;
    astore 10
    aload 4
    invokevirtual java/util/ArrayList/size()I
    iconst_1
    isub
    istore 11
pj_agg_set_bld_loop:
    iload 11
    iflt pj_agg_set_bld_done
    bipush 4
    anewarray java/lang/Object
    astore 12
    aload 12
    iconst_0
    ldc "compound"
    aastore
    aload 12
    iconst_1
    ldc "."
    aastore
    aload 12
    iconst_2
    aload 4
    iload 11
    invokevirtual java/util/ArrayList/get(I)Ljava/lang/Object;
    aastore
    aload 12
    iconst_3
    aload 10
    aastore
    aload 12
    astore 10
    iinc 11 -1
    goto pj_agg_set_bld_loop
pj_agg_set_bld_done:
    aload 10
    iconst_1
    invokestatic queens/pj_sort_list(Ljava/lang/Object;I)Ljava/lang/Object;
    astore 10
    aload_2
    aload 10
    invokestatic queens/pj_unify(Ljava/lang/Object;Ljava/lang/Object;)Z
    ifeq pj_agg_fail
    goto pj_agg_succeed
pj_agg_not_bag:
    lconst_0
    lstore 11
    lconst_0
    lstore 13
    iconst_0
    istore 15
    aload 7
    ldc "sum"
    invokevirtual java/lang/String/equals(Ljava/lang/Object;)Z
    ifne pj_agg_sum
    aload 7
    ldc "max"
    invokevirtual java/lang/String/equals(Ljava/lang/Object;)Z
    ifne pj_agg_max
    aload 7
    ldc "min"
    invokevirtual java/lang/String/equals(Ljava/lang/Object;)Z
    ifne pj_agg_min
    goto pj_agg_unknown
pj_agg_sum:
    iconst_0
    istore 10
pj_agg_sum_loop:
    iload 10
    aload 4
    invokevirtual java/util/ArrayList/size()I
    if_icmpge pj_agg_sum_done
    aload 4
    iload 10
    invokevirtual java/util/ArrayList/get(I)Ljava/lang/Object;
    checkcast [Ljava/lang/Object;
    iconst_2
    aaload
    invokestatic queens/pj_deref(Ljava/lang/Object;)Ljava/lang/Object;
    invokestatic queens/pj_int_val(Ljava/lang/Object;)J
    lload 11
    ladd
    lstore 11
    iinc 10 1
    goto pj_agg_sum_loop
pj_agg_sum_done:
    lload 11
    invokestatic queens/pj_term_int(J)[Ljava/lang/Object;
    aload_2
    invokestatic queens/pj_unify(Ljava/lang/Object;Ljava/lang/Object;)Z
    ifeq pj_agg_fail
    goto pj_agg_succeed
pj_agg_max:
    iconst_0
    istore 10
pj_agg_max_loop:
    iload 10
    aload 4
    invokevirtual java/util/ArrayList/size()I
    if_icmpge pj_agg_max_done
    aload 4
    iload 10
    invokevirtual java/util/ArrayList/get(I)Ljava/lang/Object;
    checkcast [Ljava/lang/Object;
    iconst_2
    aaload
    invokestatic queens/pj_deref(Ljava/lang/Object;)Ljava/lang/Object;
    invokestatic queens/pj_int_val(Ljava/lang/Object;)J
    lstore 13
    iload 15
    ifne pj_agg_max_cmp
    lload 13
    lstore 11
    iconst_1
    istore 15
    goto pj_agg_max_next
pj_agg_max_cmp:
    lload 13
    lload 11
    lcmp
    ifle pj_agg_max_next
    lload 13
    lstore 11
pj_agg_max_next:
    iinc 10 1
    goto pj_agg_max_loop
pj_agg_max_done:
    iload 15
    ifeq pj_agg_fail
    lload 11
    invokestatic queens/pj_term_int(J)[Ljava/lang/Object;
    aload_2
    invokestatic queens/pj_unify(Ljava/lang/Object;Ljava/lang/Object;)Z
    ifeq pj_agg_fail
    goto pj_agg_succeed
pj_agg_min:
    iconst_0
    istore 10
pj_agg_min_loop:
    iload 10
    aload 4
    invokevirtual java/util/ArrayList/size()I
    if_icmpge pj_agg_min_done
    aload 4
    iload 10
    invokevirtual java/util/ArrayList/get(I)Ljava/lang/Object;
    checkcast [Ljava/lang/Object;
    iconst_2
    aaload
    invokestatic queens/pj_deref(Ljava/lang/Object;)Ljava/lang/Object;
    invokestatic queens/pj_int_val(Ljava/lang/Object;)J
    lstore 13
    iload 15
    ifne pj_agg_min_cmp
    lload 13
    lstore 11
    iconst_1
    istore 15
    goto pj_agg_min_next
pj_agg_min_cmp:
    lload 13
    lload 11
    lcmp
    ifge pj_agg_min_next
    lload 13
    lstore 11
pj_agg_min_next:
    iinc 10 1
    goto pj_agg_min_loop
pj_agg_min_done:
    iload 15
    ifeq pj_agg_fail
    lload 11
    invokestatic queens/pj_term_int(J)[Ljava/lang/Object;
    aload_2
    invokestatic queens/pj_unify(Ljava/lang/Object;Ljava/lang/Object;)Z
    ifeq pj_agg_fail
    goto pj_agg_succeed
pj_agg_unknown:
    aconst_null
    areturn
pj_agg_succeed:
    iconst_1
    anewarray java/lang/Object
    dup
    iconst_0
    iconst_1
    invokestatic java/lang/Integer/valueOf(I)Ljava/lang/Integer;
    aastore
    areturn
pj_agg_fail:
    aconst_null
    areturn
.end method

; === reverse/2 synthetic predicate ========================================
.method static p_reverse_2([Ljava/lang/Object;[Ljava/lang/Object;I)[Ljava/lang/Object;
    .limit stack 8
    .limit locals 8
    iload_2
    ifne p_reverse_2_fail
    new java/util/ArrayList
    dup
    invokespecial java/util/ArrayList/<init>()V
    astore_3
    aload_0
    invokestatic queens/pj_deref(Ljava/lang/Object;)Ljava/lang/Object;
    astore 4
p_rev_walk:
    aload 4
    checkcast [Ljava/lang/Object;
    iconst_1
    aaload
    ldc "[]"
    invokevirtual java/lang/Object/equals(Ljava/lang/Object;)Z
    ifne p_rev_build
    aload_3
    aload 4
    checkcast [Ljava/lang/Object;
    iconst_2
    aaload
    invokevirtual java/util/ArrayList/add(Ljava/lang/Object;)Z
    pop
    aload 4
    checkcast [Ljava/lang/Object;
    iconst_3
    aaload
    invokestatic queens/pj_deref(Ljava/lang/Object;)Ljava/lang/Object;
    astore 4
    goto p_rev_walk
p_rev_build:
    ldc "[]"
    invokestatic queens/pj_term_atom(Ljava/lang/String;)[Ljava/lang/Object;
    astore 5
    iconst_0
    istore 6
p_rev_loop:
    iload 6
    aload_3
    invokevirtual java/util/ArrayList/size()I
    if_icmpge p_rev_unify
    bipush 4
    anewarray java/lang/Object
    dup
    iconst_0
    ldc "compound"
    aastore
    dup
    iconst_1
    ldc "."
    aastore
    dup
    iconst_2
    aload_3
    iload 6
    invokevirtual java/util/ArrayList/get(I)Ljava/lang/Object;
    aastore
    dup
    iconst_3
    aload 5
    aastore
    astore 5
    iinc 6 1
    goto p_rev_loop
p_rev_unify:
    aload 5
    aload_1
    invokestatic queens/pj_unify(Ljava/lang/Object;Ljava/lang/Object;)Z
    ifeq p_reverse_2_fail
    iconst_1
    anewarray java/lang/Object
    dup
    iconst_0
    iconst_1
    invokestatic java/lang/Integer/valueOf(I)Ljava/lang/Integer;
    aastore
    areturn
p_reverse_2_fail:
    aconst_null
    areturn
.end method

.method static pj_gcd(JJ)J
    .limit stack 4
    .limit locals 4
    lload_0
    invokestatic java/lang/Math/abs(J)J
    lstore_0
    lload_2
    invokestatic java/lang/Math/abs(J)J
    lstore_2
pj_gcd_loop:
    lload_2
    lconst_0
    lcmp
    ifeq pj_gcd_done
    lload_0
    lload_2
    lrem
    lload_2
    lstore_0
    lstore_2
    goto pj_gcd_loop
pj_gcd_done:
    lload_0
    lreturn
.end method

.method static pj_shr(JJ)J
    .limit stack 4
    .limit locals 4
    lload_2
    ldc2_w 63
    lcmp
    ifle pj_shr_ok
    lload_0
    ldc2_w 63
    l2i
    lshr
    lreturn
pj_shr_ok:
    lload_0
    lload_2
    l2i
    lshr
    lreturn
.end method

.method static pj_shl(JJ)J
    .limit stack 4
    .limit locals 4
    lload_2
    ldc2_w 63
    lcmp
    ifle pj_shl_ok
    lconst_0
    lreturn
pj_shl_ok:
    lload_0
    lload_2
    l2i
    lshl
    lreturn
.end method

.method static pj_mod(JJ)J
    .limit stack 6
    .limit locals 6
    lload_0
    lload_2
    lrem
    lstore 4
    lload 4
    lconst_0
    lcmp
    ifeq pj_mod_done
    lload 4
    lload_2
    lxor
    lconst_0
    lcmp
    ifge pj_mod_done
    lload 4
    lload_2
    ladd
    lstore 4
pj_mod_done:
    lload 4
    lreturn
.end method

.method static pj_asinh(D)D
    .limit stack 6
    .limit locals 2
    dload_0
    dload_0
    dload_0
    dmul
    dconst_1
    dadd
    invokestatic java/lang/Math/sqrt(D)D
    dadd
    invokestatic java/lang/Math/log(D)D
    dreturn
.end method

.method static pj_acosh(D)D
    .limit stack 6
    .limit locals 2
    dload_0
    dload_0
    dload_0
    dmul
    dconst_1
    dsub
    invokestatic java/lang/Math/sqrt(D)D
    dadd
    invokestatic java/lang/Math/log(D)D
    dreturn
.end method

.method static pj_atanh(D)D
    .limit stack 6
    .limit locals 2
    dconst_1
    dload_0
    dadd
    dconst_1
    dload_0
    dsub
    ddiv
    invokestatic java/lang/Math/log(D)D
    ldc2_w 4602678819172646912
    invokestatic java/lang/Double/longBitsToDouble(J)D
    dmul
    dreturn
.end method

.method static pj_num_as_double([Ljava/lang/Object;)D
    .limit stack 4
    .limit locals 1
    aload_0
    iconst_0
    aaload
    ldc "float"
    invokevirtual java/lang/Object/equals(Ljava/lang/Object;)Z
    ifeq pj_num_as_double_int
    aload_0
    iconst_1
    aaload
    checkcast java/lang/String
    invokestatic java/lang/Double/parseDouble(Ljava/lang/String;)D
    dreturn
pj_num_as_double_int:
    aload_0
    iconst_1
    aaload
    checkcast java/lang/String
    invokestatic java/lang/Long/parseLong(Ljava/lang/String;)J
    l2d
    dreturn
.end method

.method static pj_num_cmp([Ljava/lang/Object;[Ljava/lang/Object;)I
    .limit stack 6
    .limit locals 2
    aload_0
    invokestatic queens/pj_num_as_double([Ljava/lang/Object;)D
    aload_1
    invokestatic queens/pj_num_as_double([Ljava/lang/Object;)D
    dcmpl
    ireturn
.end method

.method static pj_min_mixed(JJ)[Ljava/lang/Object;
    .limit stack 8
    .limit locals 4
    lload_0
    l2d
    lload_2
    invokestatic java/lang/Double/longBitsToDouble(J)D
    dcmpl
    ifgt pj_min_mixed_float
    lload_0
    invokestatic queens/pj_term_int(J)[Ljava/lang/Object;
    areturn
pj_min_mixed_float:
    lload_2
    invokestatic java/lang/Double/longBitsToDouble(J)D
    invokestatic queens/pj_term_float(D)[Ljava/lang/Object;
    areturn
.end method

.method static pj_max_mixed(JJ)[Ljava/lang/Object;
    .limit stack 8
    .limit locals 4
    lload_0
    l2d
    lload_2
    invokestatic java/lang/Double/longBitsToDouble(J)D
    dcmpl
    iflt pj_max_mixed_float
    lload_0
    invokestatic queens/pj_term_int(J)[Ljava/lang/Object;
    areturn
pj_max_mixed_float:
    lload_2
    invokestatic java/lang/Double/longBitsToDouble(J)D
    invokestatic queens/pj_term_float(D)[Ljava/lang/Object;
    areturn
.end method

.method static pj_obj_to_double([Ljava/lang/Object;)D
    .limit stack 4
    .limit locals 2
    aload_0
    iconst_0
    aaload
    ldc "float"
    invokevirtual java/lang/Object/equals(Ljava/lang/Object;)Z
    ifeq pj_o2d_int
    aload_0
    iconst_1
    aaload
    checkcast java/lang/String
    invokestatic java/lang/Double/parseDouble(Ljava/lang/String;)D
    dreturn
pj_o2d_int:
    aload_0
    iconst_1
    aaload
    checkcast java/lang/String
    invokestatic java/lang/Long/parseLong(Ljava/lang/String;)J
    l2d
    dreturn
.end method

.method static pj_obj_is_float([Ljava/lang/Object;)Z
    .limit stack 3
    .limit locals 1
    aload_0
    iconst_0
    aaload
    ldc "float"
    invokevirtual java/lang/Object/equals(Ljava/lang/Object;)Z
    ireturn
.end method

.method static pj_varnum_mul([Ljava/lang/Object;[Ljava/lang/Object;)[Ljava/lang/Object;
    .limit stack 8
    .limit locals 2
    aload_0
    invokestatic queens/pj_obj_is_float([Ljava/lang/Object;)Z
    aload_1
    invokestatic queens/pj_obj_is_float([Ljava/lang/Object;)Z
    ior
    ifeq pj_vn_mul_int
    aload_0
    invokestatic queens/pj_obj_to_double([Ljava/lang/Object;)D
    aload_1
    invokestatic queens/pj_obj_to_double([Ljava/lang/Object;)D
    dmul
    invokestatic queens/pj_term_float(D)[Ljava/lang/Object;
    areturn
pj_vn_mul_int:
    aload_0
    iconst_1
    aaload
    checkcast java/lang/String
    invokestatic java/lang/Long/parseLong(Ljava/lang/String;)J
    aload_1
    iconst_1
    aaload
    checkcast java/lang/String
    invokestatic java/lang/Long/parseLong(Ljava/lang/String;)J
    lmul
    invokestatic queens/pj_term_int(J)[Ljava/lang/Object;
    areturn
.end method

.method static pj_varnum_add([Ljava/lang/Object;[Ljava/lang/Object;)[Ljava/lang/Object;
    .limit stack 8
    .limit locals 2
    aload_0
    invokestatic queens/pj_obj_is_float([Ljava/lang/Object;)Z
    aload_1
    invokestatic queens/pj_obj_is_float([Ljava/lang/Object;)Z
    ior
    ifeq pj_vn_add_int
    aload_0
    invokestatic queens/pj_obj_to_double([Ljava/lang/Object;)D
    aload_1
    invokestatic queens/pj_obj_to_double([Ljava/lang/Object;)D
    dadd
    invokestatic queens/pj_term_float(D)[Ljava/lang/Object;
    areturn
pj_vn_add_int:
    aload_0
    iconst_1
    aaload
    checkcast java/lang/String
    invokestatic java/lang/Long/parseLong(Ljava/lang/String;)J
    aload_1
    iconst_1
    aaload
    checkcast java/lang/String
    invokestatic java/lang/Long/parseLong(Ljava/lang/String;)J
    ladd
    invokestatic queens/pj_term_int(J)[Ljava/lang/Object;
    areturn
.end method

.method static pj_varnum_sub([Ljava/lang/Object;[Ljava/lang/Object;)[Ljava/lang/Object;
    .limit stack 8
    .limit locals 2
    aload_0
    invokestatic queens/pj_obj_is_float([Ljava/lang/Object;)Z
    aload_1
    invokestatic queens/pj_obj_is_float([Ljava/lang/Object;)Z
    ior
    ifeq pj_vn_sub_int
    aload_0
    invokestatic queens/pj_obj_to_double([Ljava/lang/Object;)D
    aload_1
    invokestatic queens/pj_obj_to_double([Ljava/lang/Object;)D
    dsub
    invokestatic queens/pj_term_float(D)[Ljava/lang/Object;
    areturn
pj_vn_sub_int:
    aload_0
    iconst_1
    aaload
    checkcast java/lang/String
    invokestatic java/lang/Long/parseLong(Ljava/lang/String;)J
    aload_1
    iconst_1
    aaload
    checkcast java/lang/String
    invokestatic java/lang/Long/parseLong(Ljava/lang/String;)J
    lsub
    invokestatic queens/pj_term_int(J)[Ljava/lang/Object;
    areturn
.end method

.method static pj_varnum_div([Ljava/lang/Object;[Ljava/lang/Object;)[Ljava/lang/Object;
    .limit stack 8
    .limit locals 2
    aload_0
    invokestatic queens/pj_obj_is_float([Ljava/lang/Object;)Z
    aload_1
    invokestatic queens/pj_obj_is_float([Ljava/lang/Object;)Z
    ior
    ifeq pj_vn_div_int
    aload_0
    invokestatic queens/pj_obj_to_double([Ljava/lang/Object;)D
    aload_1
    invokestatic queens/pj_obj_to_double([Ljava/lang/Object;)D
    ddiv
    invokestatic queens/pj_term_float(D)[Ljava/lang/Object;
    areturn
pj_vn_div_int:
    aload_0
    iconst_1
    aaload
    checkcast java/lang/String
    invokestatic java/lang/Long/parseLong(Ljava/lang/String;)J
    aload_1
    iconst_1
    aaload
    checkcast java/lang/String
    invokestatic java/lang/Long/parseLong(Ljava/lang/String;)J
    ldiv
    invokestatic queens/pj_term_int(J)[Ljava/lang/Object;
    areturn
.end method

.method static pj_obj_to_bits([Ljava/lang/Object;)J
    .limit stack 4
    .limit locals 1
    aload_0
    iconst_0
    aaload
    ldc "float"
    invokevirtual java/lang/Object/equals(Ljava/lang/Object;)Z
    ifeq pj_otb_int
    aload_0
    iconst_1
    aaload
    checkcast java/lang/String
    invokestatic java/lang/Double/parseDouble(Ljava/lang/String;)D
    invokestatic java/lang/Double/doubleToRawLongBits(D)J
    lreturn
pj_otb_int:
    aload_0
    iconst_1
    aaload
    checkcast java/lang/String
    invokestatic java/lang/Long/parseLong(Ljava/lang/String;)J
    lreturn
.end method

; === member/2 ========================================================
; Predicate method: p_FUNCTOR_ARITY(args..., cs) -> Object[]|null
; cs = continuation state: 0=first try, N=retry from clause N
.method static p_member_2([Ljava/lang/Object;[Ljava/lang/Object;I)[Ljava/lang/Object;
    .limit stack 512
    .limit locals 71
    iconst_0
    istore 69
    iload 2
    istore 4
    iload 2 ; cs >= 1? → clause1
    ldc 1
    if_icmpge p_member_2_clause1
    iload 2 ; cs >= 0? → clause0
    ldc 0
    if_icmpge p_member_2_clause0
    goto p_member_2_omega
p_member_2_clause0:
    iload 2
    ldc 0
    isub
    dup
    ifge p_member_2_initcs_clamp_0
    pop
    iconst_0
p_member_2_initcs_clamp_0:
    istore 4
    iconst_0
    istore 5
    invokestatic queens/pj_trail_mark()I
    istore 3
    aload 0
    astore 6
    aload 1
    bipush 4
    anewarray java/lang/Object
    dup
    iconst_0
    ldc "compound"
    aastore
    dup
    iconst_1
    ldc "."
    aastore
    dup
    bipush 2
    aload 6
    aastore
    dup
    bipush 3
    invokestatic queens/pj_term_var()[Ljava/lang/Object;
    aastore
    invokestatic queens/pj_unify(Ljava/lang/Object;Ljava/lang/Object;)Z
    ifeq p_member_2_alphafail_0
    goto p_member_2_beta_0
p_member_2_alphafail_0:
    iload 3
    invokestatic queens/pj_trail_unwind(I)V
    goto p_member_2_clause1
p_member_2_alpha_0:
    iload 3
    invokestatic queens/pj_trail_unwind(I)V
    aload 0
    astore 6
    aload 1
    bipush 4
    anewarray java/lang/Object
    dup
    iconst_0
    ldc "compound"
    aastore
    dup
    iconst_1
    ldc "."
    aastore
    dup
    bipush 2
    aload 6
    aastore
    dup
    bipush 3
    invokestatic queens/pj_term_var()[Ljava/lang/Object;
    aastore
    invokestatic queens/pj_unify(Ljava/lang/Object;Ljava/lang/Object;)Z
    ifeq p_member_2_clause1
p_member_2_beta_0:
    goto p_member_2_gamma_0
p_member_2_bodyfail_0:
    iload 3
    invokestatic queens/pj_trail_unwind(I)V
    goto p_member_2_clause1
p_member_2_gamma_0:
    iconst_1
    anewarray java/lang/Object
    dup
    iconst_0
    ldc 0
    iload 4
    iadd
    iconst_1
    iadd
    invokestatic java/lang/Integer/valueOf(I)Ljava/lang/Integer;
    aastore
    areturn
p_member_2_cutgamma_0:
    iconst_1
    anewarray java/lang/Object
    dup
    iconst_0
    ldc 2147483647
    invokestatic java/lang/Integer/valueOf(I)Ljava/lang/Integer;
    aastore
    areturn
p_member_2_clause1:
    iload 2
    ldc 1
    isub
    dup
    ifge p_member_2_initcs_clamp_1
    pop
    iconst_0
p_member_2_initcs_clamp_1:
    istore 4
    iconst_0
    istore 5
    invokestatic queens/pj_trail_mark()I
    istore 3
    aload 0
    astore 6
    invokestatic queens/pj_term_var()[Ljava/lang/Object;
    astore 7
    aload 1
    bipush 4
    anewarray java/lang/Object
    dup
    iconst_0
    ldc "compound"
    aastore
    dup
    iconst_1
    ldc "."
    aastore
    dup
    bipush 2
    invokestatic queens/pj_term_var()[Ljava/lang/Object;
    aastore
    dup
    bipush 3
    aload 7
    aastore
    invokestatic queens/pj_unify(Ljava/lang/Object;Ljava/lang/Object;)Z
    ifeq p_member_2_alphafail_1
    goto p_member_2_beta_1
p_member_2_alphafail_1:
    iload 3
    invokestatic queens/pj_trail_unwind(I)V
    goto p_member_2_omega
p_member_2_alpha_1:
    iload 3
    invokestatic queens/pj_trail_unwind(I)V
    aload 0
    astore 6
    invokestatic queens/pj_term_var()[Ljava/lang/Object;
    astore 7
    aload 1
    bipush 4
    anewarray java/lang/Object
    dup
    iconst_0
    ldc "compound"
    aastore
    dup
    iconst_1
    ldc "."
    aastore
    dup
    bipush 2
    invokestatic queens/pj_term_var()[Ljava/lang/Object;
    aastore
    dup
    bipush 3
    aload 7
    aastore
    invokestatic queens/pj_unify(Ljava/lang/Object;Ljava/lang/Object;)Z
    ifeq p_member_2_omega
p_member_2_beta_1:
    iload 4
    istore 8
call0_alpha:
    invokestatic queens/pj_trail_mark()I
    istore 10
    aload 6
    aload 7
    iload 8
    invokestatic queens/p_member_2([Ljava/lang/Object;[Ljava/lang/Object;I)[Ljava/lang/Object;
    dup
    astore 9
    ifnull call0_omega
    aload 9
    iconst_0
    aaload
    checkcast java/lang/Integer
    invokevirtual java/lang/Integer/intValue()I
    dup
    istore 5
    istore 8
    iconst_0
    istore 11
    iconst_0
    istore 12
    goto p_member_2_gamma_1
call0_beta:
    iload 10
    invokestatic queens/pj_trail_unwind(I)V
    goto call0_alpha
call0_omega:
    iconst_0
    istore 8
    goto p_member_2_bodyfail_1
p_member_2_bodyfail_1:
    iload 3
    invokestatic queens/pj_trail_unwind(I)V
    goto p_member_2_omega
p_member_2_gamma_1:
    iconst_1
    anewarray java/lang/Object
    dup
    iconst_0
    ldc 1
    iload 4
    iadd
    iconst_1
    iadd
    invokestatic java/lang/Integer/valueOf(I)Ljava/lang/Integer;
    aastore
    areturn
p_member_2_cutgamma_1:
    iconst_1
    anewarray java/lang/Object
    dup
    iconst_0
    ldc 2147483647
    invokestatic java/lang/Integer/valueOf(I)Ljava/lang/Integer;
    aastore
    areturn
p_member_2_omega:
    iload 2
    ldc 2
    isub
    dup
    ifge pj_db1_store
    pop
    iconst_0
pj_db1_store:
    istore 69
pj_db1_loop:
    ldc "member/2"
    iload 69
    invokestatic queens/pj_db_query(Ljava/lang/String;I)Ljava/lang/Object;
    dup
    ifnonnull pj_db1_hit
    pop
    goto pj_db1_miss
pj_db1_hit:
    checkcast [Ljava/lang/Object;
    astore 70
    invokestatic queens/pj_trail_mark()I
    istore 3
    aload 0
    aload 70
    ldc 2
    aaload
    invokestatic queens/pj_unify(Ljava/lang/Object;Ljava/lang/Object;)Z
    ifeq pj_dbu2_fail
    aload 1
    aload 70
    ldc 3
    aaload
    invokestatic queens/pj_unify(Ljava/lang/Object;Ljava/lang/Object;)Z
    ifeq pj_dbu2_fail
    goto pj_dbu2_ok
pj_dbu2_fail:
    iload 3
    invokestatic queens/pj_trail_unwind(I)V
    iinc 69 1
    goto pj_db1_loop
pj_dbu2_ok:
    ldc 3
    anewarray java/lang/Object
    dup
    iconst_0
    ldc 2
    iload 69
    iadd
    iconst_1
    iadd
    invokestatic java/lang/Integer/valueOf(I)Ljava/lang/Integer;
    aastore
    dup
    ldc 1
    aload 0
    aastore
    dup
    ldc 2
    aload 1
    aastore
    areturn
pj_db1_miss:
    aconst_null
    areturn
.end method

; === memberchk/2 =====================================================
; Predicate method: p_FUNCTOR_ARITY(args..., cs) -> Object[]|null
; cs = continuation state: 0=first try, N=retry from clause N
.method static p_memberchk_2([Ljava/lang/Object;[Ljava/lang/Object;I)[Ljava/lang/Object;
    .limit stack 512
    .limit locals 71
    iconst_0
    istore 69
    iload 2 ; cs == 0x7fffffff (cutgamma sentinel)? -> omega
    ldc 2147483647
    if_icmpeq p_memberchk_2_omega
    iload 2
    istore 4
    iload 2 ; cs >= 1? → clause1
    ldc 1
    if_icmpge p_memberchk_2_clause1
    iload 2 ; cs >= 0? → clause0
    ldc 0
    if_icmpge p_memberchk_2_clause0
    goto p_memberchk_2_omega
p_memberchk_2_clause0:
    iload 2
    ldc 0
    isub
    dup
    ifge p_memberchk_2_initcs_clamp_0
    pop
    iconst_0
p_memberchk_2_initcs_clamp_0:
    istore 4
    iconst_0
    istore 5
    invokestatic queens/pj_trail_mark()I
    istore 3
    aload 0
    astore 6
    aload 1
    bipush 4
    anewarray java/lang/Object
    dup
    iconst_0
    ldc "compound"
    aastore
    dup
    iconst_1
    ldc "."
    aastore
    dup
    bipush 2
    aload 6
    aastore
    dup
    bipush 3
    invokestatic queens/pj_term_var()[Ljava/lang/Object;
    aastore
    invokestatic queens/pj_unify(Ljava/lang/Object;Ljava/lang/Object;)Z
    ifeq p_memberchk_2_alphafail_0
    goto p_memberchk_2_beta_0
p_memberchk_2_alphafail_0:
    iload 3
    invokestatic queens/pj_trail_unwind(I)V
    goto p_memberchk_2_clause1
p_memberchk_2_alpha_0:
    iload 3
    invokestatic queens/pj_trail_unwind(I)V
    aload 0
    astore 6
    aload 1
    bipush 4
    anewarray java/lang/Object
    dup
    iconst_0
    ldc "compound"
    aastore
    dup
    iconst_1
    ldc "."
    aastore
    dup
    bipush 2
    aload 6
    aastore
    dup
    bipush 3
    invokestatic queens/pj_term_var()[Ljava/lang/Object;
    aastore
    invokestatic queens/pj_unify(Ljava/lang/Object;Ljava/lang/Object;)Z
    ifeq p_memberchk_2_clause1
p_memberchk_2_beta_0:
    ldc 2
    istore 2
    goto p_memberchk_2_cutgamma_0
p_memberchk_2_bodyfail_0:
    iload 3
    invokestatic queens/pj_trail_unwind(I)V
    goto p_memberchk_2_clause1
p_memberchk_2_gamma_0:
    iconst_1
    anewarray java/lang/Object
    dup
    iconst_0
    ldc 0
    iload 4
    iadd
    iconst_1
    iadd
    invokestatic java/lang/Integer/valueOf(I)Ljava/lang/Integer;
    aastore
    areturn
p_memberchk_2_cutgamma_0:
    iconst_1
    anewarray java/lang/Object
    dup
    iconst_0
    ldc 2147483647
    invokestatic java/lang/Integer/valueOf(I)Ljava/lang/Integer;
    aastore
    areturn
p_memberchk_2_clause1:
    iload 2
    ldc 1
    isub
    dup
    ifge p_memberchk_2_initcs_clamp_1
    pop
    iconst_0
p_memberchk_2_initcs_clamp_1:
    istore 4
    iconst_0
    istore 5
    invokestatic queens/pj_trail_mark()I
    istore 3
    aload 0
    astore 6
    invokestatic queens/pj_term_var()[Ljava/lang/Object;
    astore 7
    aload 1
    bipush 4
    anewarray java/lang/Object
    dup
    iconst_0
    ldc "compound"
    aastore
    dup
    iconst_1
    ldc "."
    aastore
    dup
    bipush 2
    invokestatic queens/pj_term_var()[Ljava/lang/Object;
    aastore
    dup
    bipush 3
    aload 7
    aastore
    invokestatic queens/pj_unify(Ljava/lang/Object;Ljava/lang/Object;)Z
    ifeq p_memberchk_2_alphafail_1
    goto p_memberchk_2_beta_1
p_memberchk_2_alphafail_1:
    iload 3
    invokestatic queens/pj_trail_unwind(I)V
    goto p_memberchk_2_omega
p_memberchk_2_alpha_1:
    iload 3
    invokestatic queens/pj_trail_unwind(I)V
    aload 0
    astore 6
    invokestatic queens/pj_term_var()[Ljava/lang/Object;
    astore 7
    aload 1
    bipush 4
    anewarray java/lang/Object
    dup
    iconst_0
    ldc "compound"
    aastore
    dup
    iconst_1
    ldc "."
    aastore
    dup
    bipush 2
    invokestatic queens/pj_term_var()[Ljava/lang/Object;
    aastore
    dup
    bipush 3
    aload 7
    aastore
    invokestatic queens/pj_unify(Ljava/lang/Object;Ljava/lang/Object;)Z
    ifeq p_memberchk_2_omega
p_memberchk_2_beta_1:
    iload 4
    istore 8
call3_alpha:
    invokestatic queens/pj_trail_mark()I
    istore 10
    aload 6
    aload 7
    iload 8
    invokestatic queens/p_memberchk_2([Ljava/lang/Object;[Ljava/lang/Object;I)[Ljava/lang/Object;
    dup
    astore 9
    ifnull call3_omega
    aload 9
    iconst_0
    aaload
    checkcast java/lang/Integer
    invokevirtual java/lang/Integer/intValue()I
    dup
    istore 5
    istore 8
    iconst_0
    istore 11
    iconst_0
    istore 12
    goto p_memberchk_2_gamma_1
call3_beta:
    iload 10
    invokestatic queens/pj_trail_unwind(I)V
    goto call3_alpha
call3_omega:
    iconst_0
    istore 8
    goto p_memberchk_2_bodyfail_1
p_memberchk_2_bodyfail_1:
    iload 3
    invokestatic queens/pj_trail_unwind(I)V
    goto p_memberchk_2_omega
p_memberchk_2_gamma_1:
    iconst_1
    anewarray java/lang/Object
    dup
    iconst_0
    ldc 1
    iload 4
    iadd
    iconst_1
    iadd
    invokestatic java/lang/Integer/valueOf(I)Ljava/lang/Integer;
    aastore
    areturn
p_memberchk_2_cutgamma_1:
    iconst_1
    anewarray java/lang/Object
    dup
    iconst_0
    ldc 2147483647
    invokestatic java/lang/Integer/valueOf(I)Ljava/lang/Integer;
    aastore
    areturn
p_memberchk_2_omega:
    iload 2
    ldc 2
    isub
    dup
    ifge pj_db4_store
    pop
    iconst_0
pj_db4_store:
    istore 69
pj_db4_loop:
    ldc "memberchk/2"
    iload 69
    invokestatic queens/pj_db_query(Ljava/lang/String;I)Ljava/lang/Object;
    dup
    ifnonnull pj_db4_hit
    pop
    goto pj_db4_miss
pj_db4_hit:
    checkcast [Ljava/lang/Object;
    astore 70
    invokestatic queens/pj_trail_mark()I
    istore 3
    aload 0
    aload 70
    ldc 2
    aaload
    invokestatic queens/pj_unify(Ljava/lang/Object;Ljava/lang/Object;)Z
    ifeq pj_dbu5_fail
    aload 1
    aload 70
    ldc 3
    aaload
    invokestatic queens/pj_unify(Ljava/lang/Object;Ljava/lang/Object;)Z
    ifeq pj_dbu5_fail
    goto pj_dbu5_ok
pj_dbu5_fail:
    iload 3
    invokestatic queens/pj_trail_unwind(I)V
    iinc 69 1
    goto pj_db4_loop
pj_dbu5_ok:
    ldc 3
    anewarray java/lang/Object
    dup
    iconst_0
    ldc 2
    iload 69
    iadd
    iconst_1
    iadd
    invokestatic java/lang/Integer/valueOf(I)Ljava/lang/Integer;
    aastore
    dup
    ldc 1
    aload 0
    aastore
    dup
    ldc 2
    aload 1
    aastore
    areturn
pj_db4_miss:
    aconst_null
    areturn
.end method

; === queens/2 ========================================================
; Predicate method: p_FUNCTOR_ARITY(args..., cs) -> Object[]|null
; cs = continuation state: 0=first try, N=retry from clause N
.method static p_queens_2([Ljava/lang/Object;[Ljava/lang/Object;I)[Ljava/lang/Object;
    .limit stack 512
    .limit locals 77
    iconst_0
    istore 75
    iload 2
    istore 4
    iload 2 ; cs >= 0? → clause0
    ldc 0
    if_icmpge p_queens_2_clause0
    goto p_queens_2_omega
p_queens_2_clause0:
    iload 2
    ldc 0
    isub
    dup
    ifge p_queens_2_initcs_clamp_0
    pop
    iconst_0
p_queens_2_initcs_clamp_0:
    istore 4
    iconst_0
    istore 5
    invokestatic queens/pj_trail_mark()I
    istore 3
    aload 0
    astore 6
    aload 1
    astore 7
    invokestatic queens/pj_term_var()[Ljava/lang/Object;
    astore 8
    goto p_queens_2_beta_0
p_queens_2_alphafail_0:
    iload 3
    invokestatic queens/pj_trail_unwind(I)V
    goto p_queens_2_omega
p_queens_2_alpha_0:
    iload 3
    invokestatic queens/pj_trail_unwind(I)V
    aload 0
    astore 6
    aload 1
    astore 7
    invokestatic queens/pj_term_var()[Ljava/lang/Object;
    astore 8
p_queens_2_beta_0:
    aload 7
    aload 6
    invokestatic queens/pj_length_2(Ljava/lang/Object;Ljava/lang/Object;)Z
    ifeq dg6_omega
    goto dg6_gamma
dg6_gamma:
    iload 4
    istore 9
call7_alpha:
    invokestatic queens/pj_trail_mark()I
    istore 11
    aload 7
    aload 8
    ldc2_w 0
    invokestatic queens/pj_term_int(J)[Ljava/lang/Object;
    aload 6
    invokestatic queens/pj_term_var()[Ljava/lang/Object;
    invokestatic queens/pj_term_var()[Ljava/lang/Object;
    iload 9
    invokestatic queens/p_board_6([Ljava/lang/Object;[Ljava/lang/Object;[Ljava/lang/Object;[Ljava/lang/Object;[Ljava/lang/Object;[Ljava/lang/Object;I)[Ljava/lang/Object;
    dup
    astore 10
    ifnull call7_omega
    aload 10
    iconst_0
    aaload
    checkcast java/lang/Integer
    invokevirtual java/lang/Integer/intValue()I
    dup
    istore 5
    istore 9
    iconst_0
    istore 12
    iconst_0
    istore 13
    iload 12
    istore 14
call8_alpha:
    invokestatic queens/pj_trail_mark()I
    istore 16
    aload 8
    aload 7
    iload 14
    invokestatic queens/p_permutation_2([Ljava/lang/Object;[Ljava/lang/Object;I)[Ljava/lang/Object;
    dup
    astore 15
    ifnull call8_omega
    aload 15
    iconst_0
    aaload
    checkcast java/lang/Integer
    invokevirtual java/lang/Integer/intValue()I
    dup
    istore 13
    istore 14
    iconst_0
    istore 17
    iconst_0
    istore 18
    goto p_queens_2_gamma_0
call8_beta:
    iload 16
    invokestatic queens/pj_trail_unwind(I)V
    goto call8_alpha
call8_omega:
    iconst_0
    istore 14
    goto call7_beta
call7_beta:
    iload 11
    invokestatic queens/pj_trail_unwind(I)V
    goto call7_alpha
call7_omega:
    iconst_0
    istore 9
    goto p_queens_2_bodyfail_0
dg6_omega:
    goto p_queens_2_bodyfail_0
p_queens_2_bodyfail_0:
    iload 3
    invokestatic queens/pj_trail_unwind(I)V
    goto p_queens_2_omega
p_queens_2_gamma_0:
    iconst_1
    anewarray java/lang/Object
    dup
    iconst_0
    iload 5
    invokestatic java/lang/Integer/valueOf(I)Ljava/lang/Integer;
    aastore
    areturn
p_queens_2_cutgamma_0:
    iconst_1
    anewarray java/lang/Object
    dup
    iconst_0
    ldc 2147483647
    invokestatic java/lang/Integer/valueOf(I)Ljava/lang/Integer;
    aastore
    areturn
p_queens_2_omega:
    iload 2
    ldc 1
    isub
    dup
    ifge pj_db9_store
    pop
    iconst_0
pj_db9_store:
    istore 75
pj_db9_loop:
    ldc "queens/2"
    iload 75
    invokestatic queens/pj_db_query(Ljava/lang/String;I)Ljava/lang/Object;
    dup
    ifnonnull pj_db9_hit
    pop
    goto pj_db9_miss
pj_db9_hit:
    checkcast [Ljava/lang/Object;
    astore 76
    invokestatic queens/pj_trail_mark()I
    istore 3
    aload 0
    aload 76
    ldc 2
    aaload
    invokestatic queens/pj_unify(Ljava/lang/Object;Ljava/lang/Object;)Z
    ifeq pj_dbu10_fail
    aload 1
    aload 76
    ldc 3
    aaload
    invokestatic queens/pj_unify(Ljava/lang/Object;Ljava/lang/Object;)Z
    ifeq pj_dbu10_fail
    goto pj_dbu10_ok
pj_dbu10_fail:
    iload 3
    invokestatic queens/pj_trail_unwind(I)V
    iinc 75 1
    goto pj_db9_loop
pj_dbu10_ok:
    ldc 3
    anewarray java/lang/Object
    dup
    iconst_0
    ldc 1
    iload 75
    iadd
    iconst_1
    iadd
    invokestatic java/lang/Integer/valueOf(I)Ljava/lang/Integer;
    aastore
    dup
    ldc 1
    aload 0
    aastore
    dup
    ldc 2
    aload 1
    aastore
    areturn
pj_db9_miss:
    aconst_null
    areturn
.end method

; === board/6 =========================================================
; Predicate method: p_FUNCTOR_ARITY(args..., cs) -> Object[]|null
; cs = continuation state: 0=first try, N=retry from clause N
.method static p_board_6([Ljava/lang/Object;[Ljava/lang/Object;[Ljava/lang/Object;[Ljava/lang/Object;[Ljava/lang/Object;[Ljava/lang/Object;I)[Ljava/lang/Object;
    .limit stack 512
    .limit locals 81
    iconst_0
    istore 79
    iload 6
    istore 8
    iload 6 ; cs >= 1? → clause1
    ldc 1
    if_icmpge p_board_6_clause1
    iload 6 ; cs >= 0? → clause0
    ldc 0
    if_icmpge p_board_6_clause0
    goto p_board_6_omega
p_board_6_clause0:
    iload 6
    ldc 0
    isub
    dup
    ifge p_board_6_initcs_clamp_0
    pop
    iconst_0
p_board_6_initcs_clamp_0:
    istore 8
    iconst_0
    istore 9
    invokestatic queens/pj_trail_mark()I
    istore 7
    aload 2
    astore 10
    aload 0
    ldc "[]"
    invokestatic queens/pj_term_atom(Ljava/lang/String;)[Ljava/lang/Object;
    invokestatic queens/pj_unify(Ljava/lang/Object;Ljava/lang/Object;)Z
    ifeq p_board_6_alphafail_0
    aload 1
    ldc "[]"
    invokestatic queens/pj_term_atom(Ljava/lang/String;)[Ljava/lang/Object;
    invokestatic queens/pj_unify(Ljava/lang/Object;Ljava/lang/Object;)Z
    ifeq p_board_6_alphafail_0
    aload 3
    aload 10
    invokestatic queens/pj_unify(Ljava/lang/Object;Ljava/lang/Object;)Z
    ifeq p_board_6_alphafail_0
    goto p_board_6_beta_0
p_board_6_alphafail_0:
    iload 7
    invokestatic queens/pj_trail_unwind(I)V
    goto p_board_6_clause1
p_board_6_alpha_0:
    iload 7
    invokestatic queens/pj_trail_unwind(I)V
    aload 3
    astore 10
    aload 0
    ldc "[]"
    invokestatic queens/pj_term_atom(Ljava/lang/String;)[Ljava/lang/Object;
    invokestatic queens/pj_unify(Ljava/lang/Object;Ljava/lang/Object;)Z
    ifeq p_board_6_clause1
    aload 1
    ldc "[]"
    invokestatic queens/pj_term_atom(Ljava/lang/String;)[Ljava/lang/Object;
    invokestatic queens/pj_unify(Ljava/lang/Object;Ljava/lang/Object;)Z
    ifeq p_board_6_clause1
p_board_6_beta_0:
    goto p_board_6_gamma_0
p_board_6_bodyfail_0:
    iload 7
    invokestatic queens/pj_trail_unwind(I)V
    goto p_board_6_clause1
p_board_6_gamma_0:
    iconst_1
    anewarray java/lang/Object
    dup
    iconst_0
    ldc 0
    iload 8
    iadd
    iconst_1
    iadd
    invokestatic java/lang/Integer/valueOf(I)Ljava/lang/Integer;
    aastore
    areturn
p_board_6_cutgamma_0:
    iconst_1
    anewarray java/lang/Object
    dup
    iconst_0
    ldc 2147483647
    invokestatic java/lang/Integer/valueOf(I)Ljava/lang/Integer;
    aastore
    areturn
p_board_6_clause1:
    iload 6
    ldc 1
    isub
    dup
    ifge p_board_6_initcs_clamp_1
    pop
    iconst_0
p_board_6_initcs_clamp_1:
    istore 8
    iconst_0
    istore 9
    invokestatic queens/pj_trail_mark()I
    istore 7
    invokestatic queens/pj_term_var()[Ljava/lang/Object;
    astore 10
    invokestatic queens/pj_term_var()[Ljava/lang/Object;
    astore 11
    invokestatic queens/pj_term_var()[Ljava/lang/Object;
    astore 12
    aload 2
    astore 13
    aload 3
    astore 14
    invokestatic queens/pj_term_var()[Ljava/lang/Object;
    astore 15
    invokestatic queens/pj_term_var()[Ljava/lang/Object;
    astore 16
    invokestatic queens/pj_term_var()[Ljava/lang/Object;
    astore 17
    aload 0
    bipush 4
    anewarray java/lang/Object
    dup
    iconst_0
    ldc "compound"
    aastore
    dup
    iconst_1
    ldc "."
    aastore
    dup
    bipush 2
    invokestatic queens/pj_term_var()[Ljava/lang/Object;
    aastore
    dup
    bipush 3
    aload 10
    aastore
    invokestatic queens/pj_unify(Ljava/lang/Object;Ljava/lang/Object;)Z
    ifeq p_board_6_alphafail_1
    aload 1
    bipush 4
    anewarray java/lang/Object
    dup
    iconst_0
    ldc "compound"
    aastore
    dup
    iconst_1
    ldc "."
    aastore
    dup
    bipush 2
    aload 11
    aastore
    dup
    bipush 3
    aload 12
    aastore
    invokestatic queens/pj_unify(Ljava/lang/Object;Ljava/lang/Object;)Z
    ifeq p_board_6_alphafail_1
    aload 4
    bipush 4
    anewarray java/lang/Object
    dup
    iconst_0
    ldc "compound"
    aastore
    dup
    iconst_1
    ldc "."
    aastore
    dup
    bipush 2
    aload 13
    aastore
    dup
    bipush 3
    aload 15
    aastore
    invokestatic queens/pj_unify(Ljava/lang/Object;Ljava/lang/Object;)Z
    ifeq p_board_6_alphafail_1
    aload 5
    bipush 4
    anewarray java/lang/Object
    dup
    iconst_0
    ldc "compound"
    aastore
    dup
    iconst_1
    ldc "."
    aastore
    dup
    bipush 2
    aload 13
    aastore
    dup
    bipush 3
    aload 16
    aastore
    invokestatic queens/pj_unify(Ljava/lang/Object;Ljava/lang/Object;)Z
    ifeq p_board_6_alphafail_1
    goto p_board_6_beta_1
p_board_6_alphafail_1:
    iload 7
    invokestatic queens/pj_trail_unwind(I)V
    goto p_board_6_omega
p_board_6_alpha_1:
    iload 7
    invokestatic queens/pj_trail_unwind(I)V
    invokestatic queens/pj_term_var()[Ljava/lang/Object;
    astore 10
    invokestatic queens/pj_term_var()[Ljava/lang/Object;
    astore 11
    invokestatic queens/pj_term_var()[Ljava/lang/Object;
    astore 12
    aload 2
    astore 13
    aload 3
    astore 14
    invokestatic queens/pj_term_var()[Ljava/lang/Object;
    astore 15
    invokestatic queens/pj_term_var()[Ljava/lang/Object;
    astore 16
    invokestatic queens/pj_term_var()[Ljava/lang/Object;
    astore 17
    aload 0
    bipush 4
    anewarray java/lang/Object
    dup
    iconst_0
    ldc "compound"
    aastore
    dup
    iconst_1
    ldc "."
    aastore
    dup
    bipush 2
    invokestatic queens/pj_term_var()[Ljava/lang/Object;
    aastore
    dup
    bipush 3
    aload 10
    aastore
    invokestatic queens/pj_unify(Ljava/lang/Object;Ljava/lang/Object;)Z
    ifeq p_board_6_omega
    aload 1
    bipush 4
    anewarray java/lang/Object
    dup
    iconst_0
    ldc "compound"
    aastore
    dup
    iconst_1
    ldc "."
    aastore
    dup
    bipush 2
    aload 11
    aastore
    dup
    bipush 3
    aload 12
    aastore
    invokestatic queens/pj_unify(Ljava/lang/Object;Ljava/lang/Object;)Z
    ifeq p_board_6_omega
    aload 4
    bipush 4
    anewarray java/lang/Object
    dup
    iconst_0
    ldc "compound"
    aastore
    dup
    iconst_1
    ldc "."
    aastore
    dup
    bipush 2
    aload 13
    aastore
    dup
    bipush 3
    aload 15
    aastore
    invokestatic queens/pj_unify(Ljava/lang/Object;Ljava/lang/Object;)Z
    ifeq p_board_6_omega
    aload 5
    bipush 4
    anewarray java/lang/Object
    dup
    iconst_0
    ldc "compound"
    aastore
    dup
    iconst_1
    ldc "."
    aastore
    dup
    bipush 2
    aload 13
    aastore
    dup
    bipush 3
    aload 16
    aastore
    invokestatic queens/pj_unify(Ljava/lang/Object;Ljava/lang/Object;)Z
    ifeq p_board_6_omega
p_board_6_beta_1:
    aload 13
    invokestatic queens/pj_deref(Ljava/lang/Object;)Ljava/lang/Object;
    checkcast [Ljava/lang/Object;
    ldc2_w 1
    invokestatic queens/pj_term_int(J)[Ljava/lang/Object;
    invokestatic queens/pj_varnum_add([Ljava/lang/Object;[Ljava/lang/Object;)[Ljava/lang/Object;
    aload 17
    swap
    invokestatic queens/pj_unify(Ljava/lang/Object;Ljava/lang/Object;)Z
    ifeq dg11_omega
    goto dg11_gamma
dg11_gamma:
    iload 8
    istore 18
call12_alpha:
    invokestatic queens/pj_trail_mark()I
    istore 20
    aload 10
    aload 12
    aload 17
    aload 14
    aload 15
    aload 16
    iload 18
    invokestatic queens/p_board_6([Ljava/lang/Object;[Ljava/lang/Object;[Ljava/lang/Object;[Ljava/lang/Object;[Ljava/lang/Object;[Ljava/lang/Object;I)[Ljava/lang/Object;
    dup
    astore 19
    ifnull call12_omega
    aload 19
    iconst_0
    aaload
    checkcast java/lang/Integer
    invokevirtual java/lang/Integer/intValue()I
    dup
    istore 9
    istore 18
    iconst_0
    istore 21
    iconst_0
    istore 22
    goto p_board_6_gamma_1
call12_beta:
    iload 20
    invokestatic queens/pj_trail_unwind(I)V
    goto call12_alpha
call12_omega:
    iconst_0
    istore 18
    goto p_board_6_bodyfail_1
dg11_omega:
    goto p_board_6_bodyfail_1
p_board_6_bodyfail_1:
    iload 7
    invokestatic queens/pj_trail_unwind(I)V
    goto p_board_6_omega
p_board_6_gamma_1:
    iconst_1
    anewarray java/lang/Object
    dup
    iconst_0
    ldc 1
    iload 8
    iadd
    iconst_1
    iadd
    invokestatic java/lang/Integer/valueOf(I)Ljava/lang/Integer;
    aastore
    areturn
p_board_6_cutgamma_1:
    iconst_1
    anewarray java/lang/Object
    dup
    iconst_0
    ldc 2147483647
    invokestatic java/lang/Integer/valueOf(I)Ljava/lang/Integer;
    aastore
    areturn
p_board_6_omega:
    iload 6
    ldc 2
    isub
    dup
    ifge pj_db13_store
    pop
    iconst_0
pj_db13_store:
    istore 79
pj_db13_loop:
    ldc "board/6"
    iload 79
    invokestatic queens/pj_db_query(Ljava/lang/String;I)Ljava/lang/Object;
    dup
    ifnonnull pj_db13_hit
    pop
    goto pj_db13_miss
pj_db13_hit:
    checkcast [Ljava/lang/Object;
    astore 80
    invokestatic queens/pj_trail_mark()I
    istore 7
    aload 0
    aload 80
    ldc 2
    aaload
    invokestatic queens/pj_unify(Ljava/lang/Object;Ljava/lang/Object;)Z
    ifeq pj_dbu14_fail
    aload 1
    aload 80
    ldc 3
    aaload
    invokestatic queens/pj_unify(Ljava/lang/Object;Ljava/lang/Object;)Z
    ifeq pj_dbu14_fail
    aload 2
    aload 80
    ldc 4
    aaload
    invokestatic queens/pj_unify(Ljava/lang/Object;Ljava/lang/Object;)Z
    ifeq pj_dbu14_fail
    aload 3
    aload 80
    ldc 5
    aaload
    invokestatic queens/pj_unify(Ljava/lang/Object;Ljava/lang/Object;)Z
    ifeq pj_dbu14_fail
    aload 4
    aload 80
    ldc 6
    aaload
    invokestatic queens/pj_unify(Ljava/lang/Object;Ljava/lang/Object;)Z
    ifeq pj_dbu14_fail
    aload 5
    aload 80
    ldc 7
    aaload
    invokestatic queens/pj_unify(Ljava/lang/Object;Ljava/lang/Object;)Z
    ifeq pj_dbu14_fail
    goto pj_dbu14_ok
pj_dbu14_fail:
    iload 7
    invokestatic queens/pj_trail_unwind(I)V
    iinc 79 1
    goto pj_db13_loop
pj_dbu14_ok:
    ldc 7
    anewarray java/lang/Object
    dup
    iconst_0
    ldc 2
    iload 79
    iadd
    iconst_1
    iadd
    invokestatic java/lang/Integer/valueOf(I)Ljava/lang/Integer;
    aastore
    dup
    ldc 1
    aload 0
    aastore
    dup
    ldc 2
    aload 1
    aastore
    dup
    ldc 3
    aload 2
    aastore
    dup
    ldc 4
    aload 3
    aastore
    dup
    ldc 5
    aload 4
    aastore
    dup
    ldc 6
    aload 5
    aastore
    areturn
pj_db13_miss:
    aconst_null
    areturn
.end method

; === permutation/2 ===================================================
; Predicate method: p_FUNCTOR_ARITY(args..., cs) -> Object[]|null
; cs = continuation state: 0=first try, N=retry from clause N
.method static p_permutation_2([Ljava/lang/Object;[Ljava/lang/Object;I)[Ljava/lang/Object;
    .limit stack 512
    .limit locals 78
    iconst_0
    istore 76
    iload 2
    istore 4
    iload 2 ; cs >= 1? → clause1
    ldc 1
    if_icmpge p_permutation_2_clause1
    iload 2 ; cs >= 0? → clause0
    ldc 0
    if_icmpge p_permutation_2_clause0
    goto p_permutation_2_omega
p_permutation_2_clause0:
    iload 2
    ldc 0
    isub
    dup
    ifge p_permutation_2_initcs_clamp_0
    pop
    iconst_0
p_permutation_2_initcs_clamp_0:
    istore 4
    iconst_0
    istore 5
    invokestatic queens/pj_trail_mark()I
    istore 3
    aload 0
    ldc "[]"
    invokestatic queens/pj_term_atom(Ljava/lang/String;)[Ljava/lang/Object;
    invokestatic queens/pj_unify(Ljava/lang/Object;Ljava/lang/Object;)Z
    ifeq p_permutation_2_alphafail_0
    aload 1
    ldc "[]"
    invokestatic queens/pj_term_atom(Ljava/lang/String;)[Ljava/lang/Object;
    invokestatic queens/pj_unify(Ljava/lang/Object;Ljava/lang/Object;)Z
    ifeq p_permutation_2_alphafail_0
    goto p_permutation_2_beta_0
p_permutation_2_alphafail_0:
    iload 3
    invokestatic queens/pj_trail_unwind(I)V
    goto p_permutation_2_clause1
p_permutation_2_alpha_0:
    iload 3
    invokestatic queens/pj_trail_unwind(I)V
    aload 0
    ldc "[]"
    invokestatic queens/pj_term_atom(Ljava/lang/String;)[Ljava/lang/Object;
    invokestatic queens/pj_unify(Ljava/lang/Object;Ljava/lang/Object;)Z
    ifeq p_permutation_2_clause1
    aload 1
    ldc "[]"
    invokestatic queens/pj_term_atom(Ljava/lang/String;)[Ljava/lang/Object;
    invokestatic queens/pj_unify(Ljava/lang/Object;Ljava/lang/Object;)Z
    ifeq p_permutation_2_clause1
p_permutation_2_beta_0:
    goto p_permutation_2_gamma_0
p_permutation_2_bodyfail_0:
    iload 3
    invokestatic queens/pj_trail_unwind(I)V
    goto p_permutation_2_clause1
p_permutation_2_gamma_0:
    iconst_1
    anewarray java/lang/Object
    dup
    iconst_0
    ldc 0
    iload 4
    iadd
    iconst_1
    iadd
    invokestatic java/lang/Integer/valueOf(I)Ljava/lang/Integer;
    aastore
    areturn
p_permutation_2_cutgamma_0:
    iconst_1
    anewarray java/lang/Object
    dup
    iconst_0
    ldc 2147483647
    invokestatic java/lang/Integer/valueOf(I)Ljava/lang/Integer;
    aastore
    areturn
p_permutation_2_clause1:
    iload 2
    ldc 1
    isub
    dup
    ifge p_permutation_2_initcs_clamp_1
    pop
    iconst_0
p_permutation_2_initcs_clamp_1:
    istore 4
    iconst_0
    istore 5
    invokestatic queens/pj_trail_mark()I
    istore 3
    aload 0
    astore 6
    invokestatic queens/pj_term_var()[Ljava/lang/Object;
    astore 7
    invokestatic queens/pj_term_var()[Ljava/lang/Object;
    astore 8
    invokestatic queens/pj_term_var()[Ljava/lang/Object;
    astore 9
    aload 1
    bipush 4
    anewarray java/lang/Object
    dup
    iconst_0
    ldc "compound"
    aastore
    dup
    iconst_1
    ldc "."
    aastore
    dup
    bipush 2
    aload 7
    aastore
    dup
    bipush 3
    aload 8
    aastore
    invokestatic queens/pj_unify(Ljava/lang/Object;Ljava/lang/Object;)Z
    ifeq p_permutation_2_alphafail_1
    goto p_permutation_2_beta_1
p_permutation_2_alphafail_1:
    iload 3
    invokestatic queens/pj_trail_unwind(I)V
    goto p_permutation_2_omega
p_permutation_2_alpha_1:
    iload 3
    invokestatic queens/pj_trail_unwind(I)V
    aload 0
    astore 6
    invokestatic queens/pj_term_var()[Ljava/lang/Object;
    astore 7
    invokestatic queens/pj_term_var()[Ljava/lang/Object;
    astore 8
    invokestatic queens/pj_term_var()[Ljava/lang/Object;
    astore 9
    aload 1
    bipush 4
    anewarray java/lang/Object
    dup
    iconst_0
    ldc "compound"
    aastore
    dup
    iconst_1
    ldc "."
    aastore
    dup
    bipush 2
    aload 7
    aastore
    dup
    bipush 3
    aload 8
    aastore
    invokestatic queens/pj_unify(Ljava/lang/Object;Ljava/lang/Object;)Z
    ifeq p_permutation_2_omega
p_permutation_2_beta_1:
    iload 4
    istore 10
call15_alpha:
    invokestatic queens/pj_trail_mark()I
    istore 12
    aload 7
    aload 6
    aload 9
    iload 10
    invokestatic queens/p_select_3([Ljava/lang/Object;[Ljava/lang/Object;[Ljava/lang/Object;I)[Ljava/lang/Object;
    dup
    astore 11
    ifnull call15_omega
    aload 11
    iconst_0
    aaload
    checkcast java/lang/Integer
    invokevirtual java/lang/Integer/intValue()I
    dup
    istore 5
    istore 10
    iconst_0
    istore 13
    iconst_0
    istore 14
    iload 13
    istore 15
call16_alpha:
    invokestatic queens/pj_trail_mark()I
    istore 17
    aload 9
    aload 8
    iload 15
    invokestatic queens/p_permutation_2([Ljava/lang/Object;[Ljava/lang/Object;I)[Ljava/lang/Object;
    dup
    astore 16
    ifnull call16_omega
    aload 16
    iconst_0
    aaload
    checkcast java/lang/Integer
    invokevirtual java/lang/Integer/intValue()I
    dup
    istore 14
    istore 15
    iconst_0
    istore 18
    iconst_0
    istore 19
    goto p_permutation_2_gamma_1
call16_beta:
    iload 17
    invokestatic queens/pj_trail_unwind(I)V
    goto call16_alpha
call16_omega:
    iconst_0
    istore 15
    goto call15_beta
call15_beta:
    iload 12
    invokestatic queens/pj_trail_unwind(I)V
    goto call15_alpha
call15_omega:
    iconst_0
    istore 10
    goto p_permutation_2_bodyfail_1
p_permutation_2_bodyfail_1:
    iload 3
    invokestatic queens/pj_trail_unwind(I)V
    goto p_permutation_2_omega
p_permutation_2_gamma_1:
    iconst_1
    anewarray java/lang/Object
    dup
    iconst_0
    ldc 1
    iload 4
    iadd
    iconst_1
    iadd
    invokestatic java/lang/Integer/valueOf(I)Ljava/lang/Integer;
    aastore
    areturn
p_permutation_2_cutgamma_1:
    iconst_1
    anewarray java/lang/Object
    dup
    iconst_0
    ldc 2147483647
    invokestatic java/lang/Integer/valueOf(I)Ljava/lang/Integer;
    aastore
    areturn
p_permutation_2_omega:
    iload 2
    ldc 2
    isub
    dup
    ifge pj_db17_store
    pop
    iconst_0
pj_db17_store:
    istore 76
pj_db17_loop:
    ldc "permutation/2"
    iload 76
    invokestatic queens/pj_db_query(Ljava/lang/String;I)Ljava/lang/Object;
    dup
    ifnonnull pj_db17_hit
    pop
    goto pj_db17_miss
pj_db17_hit:
    checkcast [Ljava/lang/Object;
    astore 77
    invokestatic queens/pj_trail_mark()I
    istore 3
    aload 0
    aload 77
    ldc 2
    aaload
    invokestatic queens/pj_unify(Ljava/lang/Object;Ljava/lang/Object;)Z
    ifeq pj_dbu18_fail
    aload 1
    aload 77
    ldc 3
    aaload
    invokestatic queens/pj_unify(Ljava/lang/Object;Ljava/lang/Object;)Z
    ifeq pj_dbu18_fail
    goto pj_dbu18_ok
pj_dbu18_fail:
    iload 3
    invokestatic queens/pj_trail_unwind(I)V
    iinc 76 1
    goto pj_db17_loop
pj_dbu18_ok:
    ldc 3
    anewarray java/lang/Object
    dup
    iconst_0
    ldc 2
    iload 76
    iadd
    iconst_1
    iadd
    invokestatic java/lang/Integer/valueOf(I)Ljava/lang/Integer;
    aastore
    dup
    ldc 1
    aload 0
    aastore
    dup
    ldc 2
    aload 1
    aastore
    areturn
pj_db17_miss:
    aconst_null
    areturn
.end method

; === safe/1 ==========================================================
; Predicate method: p_FUNCTOR_ARITY(args..., cs) -> Object[]|null
; cs = continuation state: 0=first try, N=retry from clause N
.method static p_safe_1([Ljava/lang/Object;I)[Ljava/lang/Object;
    .limit stack 512
    .limit locals 75
    iconst_0
    istore 73
    iload 1
    istore 3
    iload 1 ; cs >= 1? → clause1
    ldc 1
    if_icmpge p_safe_1_clause1
    iload 1 ; cs >= 0? → clause0
    ldc 0
    if_icmpge p_safe_1_clause0
    goto p_safe_1_omega
p_safe_1_clause0:
    iload 1
    ldc 0
    isub
    dup
    ifge p_safe_1_initcs_clamp_0
    pop
    iconst_0
p_safe_1_initcs_clamp_0:
    istore 3
    iconst_0
    istore 4
    invokestatic queens/pj_trail_mark()I
    istore 2
    aload 0
    ldc "[]"
    invokestatic queens/pj_term_atom(Ljava/lang/String;)[Ljava/lang/Object;
    invokestatic queens/pj_unify(Ljava/lang/Object;Ljava/lang/Object;)Z
    ifeq p_safe_1_alphafail_0
    goto p_safe_1_beta_0
p_safe_1_alphafail_0:
    iload 2
    invokestatic queens/pj_trail_unwind(I)V
    goto p_safe_1_clause1
p_safe_1_alpha_0:
    iload 2
    invokestatic queens/pj_trail_unwind(I)V
    aload 0
    ldc "[]"
    invokestatic queens/pj_term_atom(Ljava/lang/String;)[Ljava/lang/Object;
    invokestatic queens/pj_unify(Ljava/lang/Object;Ljava/lang/Object;)Z
    ifeq p_safe_1_clause1
p_safe_1_beta_0:
    goto p_safe_1_gamma_0
p_safe_1_bodyfail_0:
    iload 2
    invokestatic queens/pj_trail_unwind(I)V
    goto p_safe_1_clause1
p_safe_1_gamma_0:
    iconst_1
    anewarray java/lang/Object
    dup
    iconst_0
    ldc 0
    iload 3
    iadd
    iconst_1
    iadd
    invokestatic java/lang/Integer/valueOf(I)Ljava/lang/Integer;
    aastore
    areturn
p_safe_1_cutgamma_0:
    iconst_1
    anewarray java/lang/Object
    dup
    iconst_0
    ldc 2147483647
    invokestatic java/lang/Integer/valueOf(I)Ljava/lang/Integer;
    aastore
    areturn
p_safe_1_clause1:
    iload 1
    ldc 1
    isub
    dup
    ifge p_safe_1_initcs_clamp_1
    pop
    iconst_0
p_safe_1_initcs_clamp_1:
    istore 3
    iconst_0
    istore 4
    invokestatic queens/pj_trail_mark()I
    istore 2
    invokestatic queens/pj_term_var()[Ljava/lang/Object;
    astore 5
    invokestatic queens/pj_term_var()[Ljava/lang/Object;
    astore 6
    aload 0
    bipush 4
    anewarray java/lang/Object
    dup
    iconst_0
    ldc "compound"
    aastore
    dup
    iconst_1
    ldc "."
    aastore
    dup
    bipush 2
    aload 5
    aastore
    dup
    bipush 3
    aload 6
    aastore
    invokestatic queens/pj_unify(Ljava/lang/Object;Ljava/lang/Object;)Z
    ifeq p_safe_1_alphafail_1
    goto p_safe_1_beta_1
p_safe_1_alphafail_1:
    iload 2
    invokestatic queens/pj_trail_unwind(I)V
    goto p_safe_1_omega
p_safe_1_alpha_1:
    iload 2
    invokestatic queens/pj_trail_unwind(I)V
    invokestatic queens/pj_term_var()[Ljava/lang/Object;
    astore 5
    invokestatic queens/pj_term_var()[Ljava/lang/Object;
    astore 6
    aload 0
    bipush 4
    anewarray java/lang/Object
    dup
    iconst_0
    ldc "compound"
    aastore
    dup
    iconst_1
    ldc "."
    aastore
    dup
    bipush 2
    aload 5
    aastore
    dup
    bipush 3
    aload 6
    aastore
    invokestatic queens/pj_unify(Ljava/lang/Object;Ljava/lang/Object;)Z
    ifeq p_safe_1_omega
p_safe_1_beta_1:
    iload 3
    istore 7
call19_alpha:
    invokestatic queens/pj_trail_mark()I
    istore 9
    aload 5
    aload 6
    ldc2_w 1
    invokestatic queens/pj_term_int(J)[Ljava/lang/Object;
    iload 7
    invokestatic queens/p_no_attack_3([Ljava/lang/Object;[Ljava/lang/Object;[Ljava/lang/Object;I)[Ljava/lang/Object;
    dup
    astore 8
    ifnull call19_omega
    aload 8
    iconst_0
    aaload
    checkcast java/lang/Integer
    invokevirtual java/lang/Integer/intValue()I
    dup
    istore 4
    istore 7
    iconst_0
    istore 10
    iconst_0
    istore 11
    iload 10
    istore 12
call20_alpha:
    invokestatic queens/pj_trail_mark()I
    istore 14
    aload 6
    iload 12
    invokestatic queens/p_safe_1([Ljava/lang/Object;I)[Ljava/lang/Object;
    dup
    astore 13
    ifnull call20_omega
    aload 13
    iconst_0
    aaload
    checkcast java/lang/Integer
    invokevirtual java/lang/Integer/intValue()I
    dup
    istore 11
    istore 12
    iconst_0
    istore 15
    iconst_0
    istore 16
    goto p_safe_1_gamma_1
call20_beta:
    iload 14
    invokestatic queens/pj_trail_unwind(I)V
    goto call20_alpha
call20_omega:
    iconst_0
    istore 12
    goto call19_beta
call19_beta:
    iload 9
    invokestatic queens/pj_trail_unwind(I)V
    goto call19_alpha
call19_omega:
    iconst_0
    istore 7
    goto p_safe_1_bodyfail_1
p_safe_1_bodyfail_1:
    iload 2
    invokestatic queens/pj_trail_unwind(I)V
    goto p_safe_1_omega
p_safe_1_gamma_1:
    iconst_1
    anewarray java/lang/Object
    dup
    iconst_0
    ldc 1
    iload 3
    iadd
    iconst_1
    iadd
    invokestatic java/lang/Integer/valueOf(I)Ljava/lang/Integer;
    aastore
    areturn
p_safe_1_cutgamma_1:
    iconst_1
    anewarray java/lang/Object
    dup
    iconst_0
    ldc 2147483647
    invokestatic java/lang/Integer/valueOf(I)Ljava/lang/Integer;
    aastore
    areturn
p_safe_1_omega:
    iload 1
    ldc 2
    isub
    dup
    ifge pj_db21_store
    pop
    iconst_0
pj_db21_store:
    istore 73
pj_db21_loop:
    ldc "safe/1"
    iload 73
    invokestatic queens/pj_db_query(Ljava/lang/String;I)Ljava/lang/Object;
    dup
    ifnonnull pj_db21_hit
    pop
    goto pj_db21_miss
pj_db21_hit:
    checkcast [Ljava/lang/Object;
    astore 74
    invokestatic queens/pj_trail_mark()I
    istore 2
    aload 0
    aload 74
    ldc 2
    aaload
    invokestatic queens/pj_unify(Ljava/lang/Object;Ljava/lang/Object;)Z
    ifeq pj_dbu22_fail
    goto pj_dbu22_ok
pj_dbu22_fail:
    iload 2
    invokestatic queens/pj_trail_unwind(I)V
    iinc 73 1
    goto pj_db21_loop
pj_dbu22_ok:
    ldc 2
    anewarray java/lang/Object
    dup
    iconst_0
    ldc 2
    iload 73
    iadd
    iconst_1
    iadd
    invokestatic java/lang/Integer/valueOf(I)Ljava/lang/Integer;
    aastore
    dup
    ldc 1
    aload 0
    aastore
    areturn
pj_db21_miss:
    aconst_null
    areturn
.end method

; === no_attack/3 =====================================================
; Predicate method: p_FUNCTOR_ARITY(args..., cs) -> Object[]|null
; cs = continuation state: 0=first try, N=retry from clause N
.method static p_no_attack_3([Ljava/lang/Object;[Ljava/lang/Object;[Ljava/lang/Object;I)[Ljava/lang/Object;
    .limit stack 512
    .limit locals 75
    iconst_0
    istore 73
    iload 3
    istore 5
    iload 3 ; cs >= 1? → clause1
    ldc 1
    if_icmpge p_no_attack_3_clause1
    iload 3 ; cs >= 0? → clause0
    ldc 0
    if_icmpge p_no_attack_3_clause0
    goto p_no_attack_3_omega
p_no_attack_3_clause0:
    iload 3
    ldc 0
    isub
    dup
    ifge p_no_attack_3_initcs_clamp_0
    pop
    iconst_0
p_no_attack_3_initcs_clamp_0:
    istore 5
    iconst_0
    istore 6
    invokestatic queens/pj_trail_mark()I
    istore 4
    aload 1
    ldc "[]"
    invokestatic queens/pj_term_atom(Ljava/lang/String;)[Ljava/lang/Object;
    invokestatic queens/pj_unify(Ljava/lang/Object;Ljava/lang/Object;)Z
    ifeq p_no_attack_3_alphafail_0
    goto p_no_attack_3_beta_0
p_no_attack_3_alphafail_0:
    iload 4
    invokestatic queens/pj_trail_unwind(I)V
    goto p_no_attack_3_clause1
p_no_attack_3_alpha_0:
    iload 4
    invokestatic queens/pj_trail_unwind(I)V
    aload 1
    ldc "[]"
    invokestatic queens/pj_term_atom(Ljava/lang/String;)[Ljava/lang/Object;
    invokestatic queens/pj_unify(Ljava/lang/Object;Ljava/lang/Object;)Z
    ifeq p_no_attack_3_clause1
p_no_attack_3_beta_0:
    goto p_no_attack_3_gamma_0
p_no_attack_3_bodyfail_0:
    iload 4
    invokestatic queens/pj_trail_unwind(I)V
    goto p_no_attack_3_clause1
p_no_attack_3_gamma_0:
    iconst_1
    anewarray java/lang/Object
    dup
    iconst_0
    ldc 0
    iload 5
    iadd
    iconst_1
    iadd
    invokestatic java/lang/Integer/valueOf(I)Ljava/lang/Integer;
    aastore
    areturn
p_no_attack_3_cutgamma_0:
    iconst_1
    anewarray java/lang/Object
    dup
    iconst_0
    ldc 2147483647
    invokestatic java/lang/Integer/valueOf(I)Ljava/lang/Integer;
    aastore
    areturn
p_no_attack_3_clause1:
    iload 3
    ldc 1
    isub
    dup
    ifge p_no_attack_3_initcs_clamp_1
    pop
    iconst_0
p_no_attack_3_initcs_clamp_1:
    istore 5
    iconst_0
    istore 6
    invokestatic queens/pj_trail_mark()I
    istore 4
    aload 0
    astore 7
    invokestatic queens/pj_term_var()[Ljava/lang/Object;
    astore 8
    invokestatic queens/pj_term_var()[Ljava/lang/Object;
    astore 9
    aload 2
    astore 10
    invokestatic queens/pj_term_var()[Ljava/lang/Object;
    astore 11
    aload 1
    bipush 4
    anewarray java/lang/Object
    dup
    iconst_0
    ldc "compound"
    aastore
    dup
    iconst_1
    ldc "."
    aastore
    dup
    bipush 2
    aload 8
    aastore
    dup
    bipush 3
    aload 9
    aastore
    invokestatic queens/pj_unify(Ljava/lang/Object;Ljava/lang/Object;)Z
    ifeq p_no_attack_3_alphafail_1
    goto p_no_attack_3_beta_1
p_no_attack_3_alphafail_1:
    iload 4
    invokestatic queens/pj_trail_unwind(I)V
    goto p_no_attack_3_omega
p_no_attack_3_alpha_1:
    iload 4
    invokestatic queens/pj_trail_unwind(I)V
    aload 0
    astore 7
    invokestatic queens/pj_term_var()[Ljava/lang/Object;
    astore 8
    invokestatic queens/pj_term_var()[Ljava/lang/Object;
    astore 9
    aload 2
    astore 10
    invokestatic queens/pj_term_var()[Ljava/lang/Object;
    astore 11
    aload 1
    bipush 4
    anewarray java/lang/Object
    dup
    iconst_0
    ldc "compound"
    aastore
    dup
    iconst_1
    ldc "."
    aastore
    dup
    bipush 2
    aload 8
    aastore
    dup
    bipush 3
    aload 9
    aastore
    invokestatic queens/pj_unify(Ljava/lang/Object;Ljava/lang/Object;)Z
    ifeq p_no_attack_3_omega
p_no_attack_3_beta_1:
    aload 8
    invokestatic queens/pj_deref(Ljava/lang/Object;)Ljava/lang/Object;
    checkcast [Ljava/lang/Object;
    aload 7
    invokestatic queens/pj_deref(Ljava/lang/Object;)Ljava/lang/Object;
    checkcast [Ljava/lang/Object;
    invokestatic queens/pj_varnum_sub([Ljava/lang/Object;[Ljava/lang/Object;)[Ljava/lang/Object;
    aload 10
    invokestatic queens/pj_deref(Ljava/lang/Object;)Ljava/lang/Object;
    checkcast [Ljava/lang/Object;
    invokestatic queens/pj_num_cmp([Ljava/lang/Object;[Ljava/lang/Object;)I
    ifeq dg23_omega
    goto dg23_gamma
dg23_gamma:
    aload 7
    invokestatic queens/pj_deref(Ljava/lang/Object;)Ljava/lang/Object;
    checkcast [Ljava/lang/Object;
    aload 8
    invokestatic queens/pj_deref(Ljava/lang/Object;)Ljava/lang/Object;
    checkcast [Ljava/lang/Object;
    invokestatic queens/pj_varnum_sub([Ljava/lang/Object;[Ljava/lang/Object;)[Ljava/lang/Object;
    aload 10
    invokestatic queens/pj_deref(Ljava/lang/Object;)Ljava/lang/Object;
    checkcast [Ljava/lang/Object;
    invokestatic queens/pj_num_cmp([Ljava/lang/Object;[Ljava/lang/Object;)I
    ifeq dg24_omega
    goto dg24_gamma
dg24_gamma:
    aload 10
    invokestatic queens/pj_deref(Ljava/lang/Object;)Ljava/lang/Object;
    checkcast [Ljava/lang/Object;
    ldc2_w 1
    invokestatic queens/pj_term_int(J)[Ljava/lang/Object;
    invokestatic queens/pj_varnum_add([Ljava/lang/Object;[Ljava/lang/Object;)[Ljava/lang/Object;
    aload 11
    swap
    invokestatic queens/pj_unify(Ljava/lang/Object;Ljava/lang/Object;)Z
    ifeq dg25_omega
    goto dg25_gamma
dg25_gamma:
    iload 5
    istore 12
call26_alpha:
    invokestatic queens/pj_trail_mark()I
    istore 14
    aload 7
    aload 9
    aload 11
    iload 12
    invokestatic queens/p_no_attack_3([Ljava/lang/Object;[Ljava/lang/Object;[Ljava/lang/Object;I)[Ljava/lang/Object;
    dup
    astore 13
    ifnull call26_omega
    aload 13
    iconst_0
    aaload
    checkcast java/lang/Integer
    invokevirtual java/lang/Integer/intValue()I
    dup
    istore 6
    istore 12
    iconst_0
    istore 15
    iconst_0
    istore 16
    goto p_no_attack_3_gamma_1
call26_beta:
    iload 14
    invokestatic queens/pj_trail_unwind(I)V
    goto call26_alpha
call26_omega:
    iconst_0
    istore 12
    goto p_no_attack_3_bodyfail_1
dg25_omega:
    goto p_no_attack_3_bodyfail_1
dg24_omega:
    goto p_no_attack_3_bodyfail_1
dg23_omega:
    goto p_no_attack_3_bodyfail_1
p_no_attack_3_bodyfail_1:
    iload 4
    invokestatic queens/pj_trail_unwind(I)V
    goto p_no_attack_3_omega
p_no_attack_3_gamma_1:
    iconst_1
    anewarray java/lang/Object
    dup
    iconst_0
    ldc 1
    iload 5
    iadd
    iconst_1
    iadd
    invokestatic java/lang/Integer/valueOf(I)Ljava/lang/Integer;
    aastore
    areturn
p_no_attack_3_cutgamma_1:
    iconst_1
    anewarray java/lang/Object
    dup
    iconst_0
    ldc 2147483647
    invokestatic java/lang/Integer/valueOf(I)Ljava/lang/Integer;
    aastore
    areturn
p_no_attack_3_omega:
    iload 3
    ldc 2
    isub
    dup
    ifge pj_db27_store
    pop
    iconst_0
pj_db27_store:
    istore 73
pj_db27_loop:
    ldc "no_attack/3"
    iload 73
    invokestatic queens/pj_db_query(Ljava/lang/String;I)Ljava/lang/Object;
    dup
    ifnonnull pj_db27_hit
    pop
    goto pj_db27_miss
pj_db27_hit:
    checkcast [Ljava/lang/Object;
    astore 74
    invokestatic queens/pj_trail_mark()I
    istore 4
    aload 0
    aload 74
    ldc 2
    aaload
    invokestatic queens/pj_unify(Ljava/lang/Object;Ljava/lang/Object;)Z
    ifeq pj_dbu28_fail
    aload 1
    aload 74
    ldc 3
    aaload
    invokestatic queens/pj_unify(Ljava/lang/Object;Ljava/lang/Object;)Z
    ifeq pj_dbu28_fail
    aload 2
    aload 74
    ldc 4
    aaload
    invokestatic queens/pj_unify(Ljava/lang/Object;Ljava/lang/Object;)Z
    ifeq pj_dbu28_fail
    goto pj_dbu28_ok
pj_dbu28_fail:
    iload 4
    invokestatic queens/pj_trail_unwind(I)V
    iinc 73 1
    goto pj_db27_loop
pj_dbu28_ok:
    ldc 4
    anewarray java/lang/Object
    dup
    iconst_0
    ldc 2
    iload 73
    iadd
    iconst_1
    iadd
    invokestatic java/lang/Integer/valueOf(I)Ljava/lang/Integer;
    aastore
    dup
    ldc 1
    aload 0
    aastore
    dup
    ldc 2
    aload 1
    aastore
    dup
    ldc 3
    aload 2
    aastore
    areturn
pj_db27_miss:
    aconst_null
    areturn
.end method

; === solution/2 ======================================================
; Predicate method: p_FUNCTOR_ARITY(args..., cs) -> Object[]|null
; cs = continuation state: 0=first try, N=retry from clause N
.method static p_solution_2([Ljava/lang/Object;[Ljava/lang/Object;I)[Ljava/lang/Object;
    .limit stack 512
    .limit locals 82
    iconst_0
    istore 80
    iload 2
    istore 4
    iload 2 ; cs >= 0? → clause0
    ldc 0
    if_icmpge p_solution_2_clause0
    goto p_solution_2_omega
p_solution_2_clause0:
    iload 2
    ldc 0
    isub
    dup
    ifge p_solution_2_initcs_clamp_0
    pop
    iconst_0
p_solution_2_initcs_clamp_0:
    istore 4
    iconst_0
    istore 5
    invokestatic queens/pj_trail_mark()I
    istore 3
    aload 0
    astore 6
    aload 1
    astore 7
    invokestatic queens/pj_term_var()[Ljava/lang/Object;
    astore 8
    goto p_solution_2_beta_0
p_solution_2_alphafail_0:
    iload 3
    invokestatic queens/pj_trail_unwind(I)V
    goto p_solution_2_omega
p_solution_2_alpha_0:
    iload 3
    invokestatic queens/pj_trail_unwind(I)V
    aload 0
    astore 6
    aload 1
    astore 7
    invokestatic queens/pj_term_var()[Ljava/lang/Object;
    astore 8
p_solution_2_beta_0:
    iload 4
    istore 9
call29_alpha:
    invokestatic queens/pj_trail_mark()I
    istore 11
    ldc2_w 1
    invokestatic queens/pj_term_int(J)[Ljava/lang/Object;
    aload 6
    aload 8
    iload 9
    invokestatic queens/p_numlist_3([Ljava/lang/Object;[Ljava/lang/Object;[Ljava/lang/Object;I)[Ljava/lang/Object;
    dup
    astore 10
    ifnull call29_omega
    aload 10
    iconst_0
    aaload
    checkcast java/lang/Integer
    invokevirtual java/lang/Integer/intValue()I
    dup
    istore 5
    istore 9
    iconst_0
    istore 12
    iconst_0
    istore 13
    iload 12
    istore 14
call30_alpha:
    invokestatic queens/pj_trail_mark()I
    istore 16
    aload 8
    aload 7
    iload 14
    invokestatic queens/p_permutation_2([Ljava/lang/Object;[Ljava/lang/Object;I)[Ljava/lang/Object;
    dup
    astore 15
    ifnull call30_omega
    aload 15
    iconst_0
    aaload
    checkcast java/lang/Integer
    invokevirtual java/lang/Integer/intValue()I
    dup
    istore 13
    istore 14
    iconst_0
    istore 17
    iconst_0
    istore 18
    iload 17
    istore 19
call31_alpha:
    invokestatic queens/pj_trail_mark()I
    istore 21
    aload 7
    iload 19
    invokestatic queens/p_safe_1([Ljava/lang/Object;I)[Ljava/lang/Object;
    dup
    astore 20
    ifnull call31_omega
    aload 20
    iconst_0
    aaload
    checkcast java/lang/Integer
    invokevirtual java/lang/Integer/intValue()I
    dup
    istore 18
    istore 19
    iconst_0
    istore 22
    iconst_0
    istore 23
    goto p_solution_2_gamma_0
call31_beta:
    iload 21
    invokestatic queens/pj_trail_unwind(I)V
    goto call31_alpha
call31_omega:
    iconst_0
    istore 19
    goto call30_beta
call30_beta:
    iload 16
    invokestatic queens/pj_trail_unwind(I)V
    goto call30_alpha
call30_omega:
    iconst_0
    istore 14
    goto call29_beta
call29_beta:
    iload 11
    invokestatic queens/pj_trail_unwind(I)V
    goto call29_alpha
call29_omega:
    iconst_0
    istore 9
    goto p_solution_2_bodyfail_0
p_solution_2_bodyfail_0:
    iload 3
    invokestatic queens/pj_trail_unwind(I)V
    goto p_solution_2_omega
p_solution_2_gamma_0:
    iconst_1
    anewarray java/lang/Object
    dup
    iconst_0
    iload 5
    invokestatic java/lang/Integer/valueOf(I)Ljava/lang/Integer;
    aastore
    areturn
p_solution_2_cutgamma_0:
    iconst_1
    anewarray java/lang/Object
    dup
    iconst_0
    ldc 2147483647
    invokestatic java/lang/Integer/valueOf(I)Ljava/lang/Integer;
    aastore
    areturn
p_solution_2_omega:
    iload 2
    ldc 1
    isub
    dup
    ifge pj_db32_store
    pop
    iconst_0
pj_db32_store:
    istore 80
pj_db32_loop:
    ldc "solution/2"
    iload 80
    invokestatic queens/pj_db_query(Ljava/lang/String;I)Ljava/lang/Object;
    dup
    ifnonnull pj_db32_hit
    pop
    goto pj_db32_miss
pj_db32_hit:
    checkcast [Ljava/lang/Object;
    astore 81
    invokestatic queens/pj_trail_mark()I
    istore 3
    aload 0
    aload 81
    ldc 2
    aaload
    invokestatic queens/pj_unify(Ljava/lang/Object;Ljava/lang/Object;)Z
    ifeq pj_dbu33_fail
    aload 1
    aload 81
    ldc 3
    aaload
    invokestatic queens/pj_unify(Ljava/lang/Object;Ljava/lang/Object;)Z
    ifeq pj_dbu33_fail
    goto pj_dbu33_ok
pj_dbu33_fail:
    iload 3
    invokestatic queens/pj_trail_unwind(I)V
    iinc 80 1
    goto pj_db32_loop
pj_dbu33_ok:
    ldc 3
    anewarray java/lang/Object
    dup
    iconst_0
    ldc 1
    iload 80
    iadd
    iconst_1
    iadd
    invokestatic java/lang/Integer/valueOf(I)Ljava/lang/Integer;
    aastore
    dup
    ldc 1
    aload 0
    aastore
    dup
    ldc 2
    aload 1
    aastore
    areturn
pj_db32_miss:
    aconst_null
    areturn
.end method

; === main/0 ==========================================================
; Predicate method: p_FUNCTOR_ARITY(args..., cs) -> Object[]|null
; cs = continuation state: 0=first try, N=retry from clause N
.method static p_main_0(I)[Ljava/lang/Object;
    .limit stack 512
    .limit locals 70
    iconst_0
    istore 68
    iload 0
    istore 2
    iload 0 ; cs >= 0? → clause0
    ldc 0
    if_icmpge p_main_0_clause0
    goto p_main_0_omega
p_main_0_clause0:
    iload 0
    ldc 0
    isub
    dup
    ifge p_main_0_initcs_clamp_0
    pop
    iconst_0
p_main_0_initcs_clamp_0:
    istore 2
    iconst_0
    istore 3
    invokestatic queens/pj_trail_mark()I
    istore 1
    invokestatic queens/pj_term_var()[Ljava/lang/Object;
    astore 4
    invokestatic queens/pj_term_var()[Ljava/lang/Object;
    astore 5
    invokestatic queens/pj_term_var()[Ljava/lang/Object;
    astore 6
    goto p_main_0_beta_0
p_main_0_alphafail_0:
    iload 1
    invokestatic queens/pj_trail_unwind(I)V
    goto p_main_0_omega
p_main_0_alpha_0:
    iload 1
    invokestatic queens/pj_trail_unwind(I)V
    invokestatic queens/pj_term_var()[Ljava/lang/Object;
    astore 4
    invokestatic queens/pj_term_var()[Ljava/lang/Object;
    astore 5
    invokestatic queens/pj_term_var()[Ljava/lang/Object;
    astore 6
p_main_0_beta_0:
    aload 4
    ldc2_w 6
    invokestatic queens/pj_term_int(J)[Ljava/lang/Object;
    invokestatic queens/pj_unify(Ljava/lang/Object;Ljava/lang/Object;)Z
    ifeq dg34_omega
    goto dg34_gamma
dg34_gamma:
    ldc "~w-Queens solutions:~n"
    invokestatic queens/pj_term_atom(Ljava/lang/String;)[Ljava/lang/Object;
    bipush 4
    anewarray java/lang/Object
    dup
    iconst_0
    ldc "compound"
    aastore
    dup
    iconst_1
    ldc "."
    aastore
    dup
    bipush 2
    aload 4
    aastore
    dup
    bipush 3
    ldc "[]"
    invokestatic queens/pj_term_atom(Ljava/lang/String;)[Ljava/lang/Object;
    aastore
    invokestatic queens/pj_format_2(Ljava/lang/Object;Ljava/lang/Object;)V
    goto dg35_gamma
dg35_gamma:
    ldc "count"
    invokestatic queens/pj_term_atom(Ljava/lang/String;)[Ljava/lang/Object;
    bipush 4
    anewarray java/lang/Object
    dup
    iconst_0
    ldc "compound"
    aastore
    dup
    iconst_1
    ldc "solution"
    aastore
    dup
    bipush 2
    aload 4
    aastore
    dup
    bipush 3
    invokestatic queens/pj_term_var()[Ljava/lang/Object;
    aastore
    aload 5
    iconst_0
    invokestatic queens/p_aggregate_all_3([Ljava/lang/Object;[Ljava/lang/Object;[Ljava/lang/Object;I)[Ljava/lang/Object;
    astore 7
    aload 7
    ifnull dg36_omega
    goto dg36_gamma
dg36_gamma:
    ldc "  ~w solutions~n"
    invokestatic queens/pj_term_atom(Ljava/lang/String;)[Ljava/lang/Object;
    bipush 4
    anewarray java/lang/Object
    dup
    iconst_0
    ldc "compound"
    aastore
    dup
    iconst_1
    ldc "."
    aastore
    dup
    bipush 2
    aload 5
    aastore
    dup
    bipush 3
    ldc "[]"
    invokestatic queens/pj_term_atom(Ljava/lang/String;)[Ljava/lang/Object;
    aastore
    invokestatic queens/pj_format_2(Ljava/lang/Object;Ljava/lang/Object;)V
    goto dg37_gamma
dg37_gamma:
    iload 2
    istore 8
call38_alpha:
    invokestatic queens/pj_trail_mark()I
    istore 10
    bipush 4
    anewarray java/lang/Object
    dup
    iconst_0
    ldc "compound"
    aastore
    dup
    iconst_1
    ldc "solution"
    aastore
    dup
    bipush 2
    aload 4
    aastore
    dup
    bipush 3
    aload 6
    aastore
    iload 8
    invokestatic queens/p_once_1([Ljava/lang/Object;I)[Ljava/lang/Object;
    dup
    astore 9
    ifnull call38_omega
    aload 9
    iconst_0
    aaload
    checkcast java/lang/Integer
    invokevirtual java/lang/Integer/intValue()I
    dup
    istore 3
    istore 8
    iconst_0
    istore 11
    iconst_0
    istore 12
    ldc "  first: ~w~n"
    invokestatic queens/pj_term_atom(Ljava/lang/String;)[Ljava/lang/Object;
    bipush 4
    anewarray java/lang/Object
    dup
    iconst_0
    ldc "compound"
    aastore
    dup
    iconst_1
    ldc "."
    aastore
    dup
    bipush 2
    aload 6
    aastore
    dup
    bipush 3
    ldc "[]"
    invokestatic queens/pj_term_atom(Ljava/lang/String;)[Ljava/lang/Object;
    aastore
    invokestatic queens/pj_format_2(Ljava/lang/Object;Ljava/lang/Object;)V
    goto dg39_gamma
dg39_gamma:
    goto p_main_0_gamma_0
dg39_omega:
    goto call38_beta
call38_beta:
    iload 10
    invokestatic queens/pj_trail_unwind(I)V
    goto call38_alpha
call38_omega:
    iconst_0
    istore 8
    goto p_main_0_bodyfail_0
dg37_omega:
    goto p_main_0_bodyfail_0
dg36_omega:
    goto p_main_0_bodyfail_0
dg35_omega:
    goto p_main_0_bodyfail_0
dg34_omega:
    goto p_main_0_bodyfail_0
p_main_0_bodyfail_0:
    iload 1
    invokestatic queens/pj_trail_unwind(I)V
    goto p_main_0_omega
p_main_0_gamma_0:
    iconst_1
    anewarray java/lang/Object
    dup
    iconst_0
    iload 3
    invokestatic java/lang/Integer/valueOf(I)Ljava/lang/Integer;
    aastore
    areturn
p_main_0_cutgamma_0:
    iconst_1
    anewarray java/lang/Object
    dup
    iconst_0
    ldc 2147483647
    invokestatic java/lang/Integer/valueOf(I)Ljava/lang/Integer;
    aastore
    areturn
p_main_0_omega:
    iload 0
    ldc 1
    isub
    dup
    ifge pj_db40_store
    pop
    iconst_0
pj_db40_store:
    istore 68
pj_db40_loop:
    ldc "main/0"
    iload 68
    invokestatic queens/pj_db_query(Ljava/lang/String;I)Ljava/lang/Object;
    dup
    ifnonnull pj_db40_hit
    pop
    goto pj_db40_miss
pj_db40_hit:
    pop
    ldc 1
    anewarray java/lang/Object
    dup
    iconst_0
    ldc 1
    iload 68
    iadd
    iconst_1
    iadd
    invokestatic java/lang/Integer/valueOf(I)Ljava/lang/Integer;
    aastore
    areturn
pj_db40_miss:
    aconst_null
    areturn
.end method

.method public static main([Ljava/lang/String;)V
    .limit stack 512
    .limit locals 4
    iconst_0
    invokestatic queens/p_main_0(I)[Ljava/lang/Object;
    pop
    return
.end method

