; Auto-generated by icon_emit_jvm.c — Tiny-ICON Byrd Box JVM
.bytecode 45.0
.class public family_icon
.super java/lang/Object

.field public static icn_failed B
.field public static icn_suspended B
.field public static icn_suspend_id I
.field public static icn_retval_obj Ljava/lang/Object;
.field public static icn_retval J
.field public static icn_retval_str Ljava/lang/String;
.field public static icn_pv_main_cnt Ljava/lang/String;
.field public static icn_gvar_cnt Ljava/lang/String;
.field public static icn_pv_main_raw Ljava/lang/String;
.field public static icn_gvar_raw Ljava/lang/String;
.field public static icn_pv_main_t Ljava/util/HashMap;
.field public static icn_pv_main_t_dflt Ljava/lang/Object;
.field public static icn_pv_main_line Ljava/lang/String;
.field public static icn_gvar_line Ljava/lang/String;
.field public static icn_pv_main_a Ljava/lang/String;
.field public static icn_gvar_a Ljava/lang/String;
.field public static icn_pv_main_b Ljava/lang/String;
.field public static icn_gvar_b Ljava/lang/String;
.field public static icn_pv_main_lo Ljava/lang/String;
.field public static icn_gvar_lo Ljava/lang/String;
.field public static icn_pv_main_hi Ljava/lang/String;
.field public static icn_gvar_hi Ljava/lang/String;
.field public static icn_pv_main_key Ljava/lang/String;
.field public static icn_gvar_key Ljava/lang/String;
.field public static icn_1_relop_lc J
.field public static icn_1_relop_rc J
.field public static icn_pv_main_n J
.field public static icn_pv_main_i J
.field public static icn_6_alt_gate I
.field public static icn_7_binop_lc J
.field public static icn_7_binop_rc J
.field public static icn_7_binop_bf I
.field public static icn_find_s1_10 Ljava/lang/String;
.field public static icn_find_s2_10 Ljava/lang/String;
.field public static icn_find_pos_10 I
.field public static icn_6_alt_val J
.field public static icn_pv_main_j J
.field public static icn_13_alt_gate I
.field public static icn_17_relop_lc J
.field public static icn_17_relop_rc J
.field public static icn_21_sec_s Ljava/lang/String;
.field public static icn_21_sec_lo I
.field public static icn_21_sec_hi I
.field public static icn_find_s1_26 Ljava/lang/String;
.field public static icn_find_s2_26 Ljava/lang/String;
.field public static icn_find_pos_26 I
.field public static icn_pv_main_pi J
.field public static icn_30_lc Ljava/lang/String;
.field public static icn_30_rc Ljava/lang/String;
.field public static icn_32_lc Ljava/lang/String;
.field public static icn_32_rc Ljava/lang/String;
.field public static icn_33_sec_s Ljava/lang/String;
.field public static icn_33_sec_lo I
.field public static icn_33_sec_hi I
.field public static icn_37_lc Ljava/lang/String;
.field public static icn_37_rc Ljava/lang/String;
.field public static icn_39_lc Ljava/lang/String;
.field public static icn_39_rc Ljava/lang/String;
.field public static icn_40_sec_s Ljava/lang/String;
.field public static icn_40_sec_lo I
.field public static icn_40_sec_hi I
.field public static icn_42_binop_lc J
.field public static icn_42_binop_rc J
.field public static icn_42_binop_bf I
.field public static icn_45_binop_lc J
.field public static icn_45_binop_rc J
.field public static icn_45_binop_bf I
.field public static icn_16_and_drain_0 J
.field public static icn_16_and_drain_1 Ljava/lang/String;
.field public static icn_16_and_drain_2 J
.field public static icn_13_alt_val J
.field public static icn_51_binop_lc J
.field public static icn_51_binop_rc J
.field public static icn_51_binop_bf I
.field public static icn_4_and_drain_0 J
.field public static icn_4_and_drain_1 J
.field public static icn_imp_arr_60 [Ljava/lang/Object;
.field public static icn_imp_sv_60_0 Ljava/lang/Object;
.field public static icn_67_relop_lc J
.field public static icn_67_relop_rc J
.field public static icn_72_alt_gate I
.field public static icn_73_binop_lc J
.field public static icn_73_binop_rc J
.field public static icn_73_binop_bf I
.field public static icn_find_s1_76 Ljava/lang/String;
.field public static icn_find_s2_76 Ljava/lang/String;
.field public static icn_find_pos_76 I
.field public static icn_72_alt_val J
.field public static icn_79_alt_gate I
.field public static icn_83_relop_lc J
.field public static icn_83_relop_rc J
.field public static icn_87_sec_s Ljava/lang/String;
.field public static icn_87_sec_lo I
.field public static icn_87_sec_hi I
.field public static icn_find_s1_92 Ljava/lang/String;
.field public static icn_find_s2_92 Ljava/lang/String;
.field public static icn_find_pos_92 I
.field public static icn_96_lc Ljava/lang/String;
.field public static icn_96_rc Ljava/lang/String;
.field public static icn_97_sec_s Ljava/lang/String;
.field public static icn_97_sec_lo I
.field public static icn_97_sec_hi I
.field public static icn_101_lc Ljava/lang/String;
.field public static icn_101_rc Ljava/lang/String;
.field public static icn_103_lc Ljava/lang/String;
.field public static icn_103_rc Ljava/lang/String;
.field public static icn_104_sec_s Ljava/lang/String;
.field public static icn_104_sec_lo I
.field public static icn_104_sec_hi I
.field public static icn_106_binop_lc J
.field public static icn_106_binop_rc J
.field public static icn_106_binop_bf I
.field public static icn_109_binop_lc J
.field public static icn_109_binop_rc J
.field public static icn_109_binop_bf I
.field public static icn_82_and_drain_0 J
.field public static icn_82_and_drain_1 Ljava/lang/String;
.field public static icn_82_and_drain_2 J
.field public static icn_79_alt_val J
.field public static icn_115_binop_lc J
.field public static icn_115_binop_rc J
.field public static icn_115_binop_bf I
.field public static icn_70_and_drain_0 J
.field public static icn_70_and_drain_1 J
.field public static icn_130_relop_lc J
.field public static icn_130_relop_rc J
.field public static icn_135_alt_gate I
.field public static icn_136_binop_lc J
.field public static icn_136_binop_rc J
.field public static icn_136_binop_bf I
.field public static icn_find_s1_139 Ljava/lang/String;
.field public static icn_find_s2_139 Ljava/lang/String;
.field public static icn_find_pos_139 I
.field public static icn_135_alt_val J
.field public static icn_142_alt_gate I
.field public static icn_146_relop_lc J
.field public static icn_146_relop_rc J
.field public static icn_150_sec_s Ljava/lang/String;
.field public static icn_150_sec_lo I
.field public static icn_150_sec_hi I
.field public static icn_find_s1_155 Ljava/lang/String;
.field public static icn_find_s2_155 Ljava/lang/String;
.field public static icn_find_pos_155 I
.field public static icn_159_sec_s Ljava/lang/String;
.field public static icn_159_sec_lo I
.field public static icn_159_sec_hi I
.field public static icn_164_sec_s Ljava/lang/String;
.field public static icn_164_sec_lo I
.field public static icn_164_sec_hi I
.field public static icn_166_binop_lc J
.field public static icn_166_binop_rc J
.field public static icn_166_binop_bf I
.field public static icn_169_binop_lc J
.field public static icn_169_binop_rc J
.field public static icn_169_binop_bf I
.field public static icn_173_alt_gate I
.field public static icn_174_and_drain_0 Ljava/lang/String;
.field public static icn_180_relop_lc Ljava/lang/String;
.field public static icn_180_relop_rc Ljava/lang/String;
.field public static icn_179_and_drain_0 Ljava/lang/String;
.field public static icn_179_and_drain_1 Ljava/lang/String;
.field public static icn_188_lc Ljava/lang/String;
.field public static icn_188_rc Ljava/lang/String;
.field public static icn_190_lc Ljava/lang/String;
.field public static icn_190_rc Ljava/lang/String;
.field public static icn_193_relop_lc Ljava/lang/String;
.field public static icn_193_relop_rc Ljava/lang/String;
.field public static icn_195_ts_tbl Ljava/util/HashMap;
.field public static icn_195_ts_key Ljava/lang/String;
.field public static icn_195_ts_kval J
.field public static icn_198_tsa_vl Ljava/lang/String;
.field public static icn_198_tsa_vo Ljava/lang/Object;
.field public static icn_198_tsa_ks Ljava/lang/String;
.field public static icn_202_lc Ljava/lang/String;
.field public static icn_202_rc Ljava/lang/String;
.field public static icn_204_lc Ljava/lang/String;
.field public static icn_204_rc Ljava/lang/String;
.field public static icn_206_lc Ljava/lang/String;
.field public static icn_206_rc Ljava/lang/String;
.field public static icn_208_lc Ljava/lang/String;
.field public static icn_208_rc Ljava/lang/String;
.field public static icn_145_and_drain_0 J
.field public static icn_145_and_drain_1 Ljava/lang/String;
.field public static icn_145_and_drain_2 J
.field public static icn_145_and_drain_3 Ljava/lang/String;
.field public static icn_145_and_drain_4 Ljava/lang/String;
.field public static icn_145_and_drain_5 Ljava/lang/String;
.field public static icn_145_and_drain_6 Ljava/lang/String;
.field public static icn_145_and_drain_7 Ljava/lang/String;
.field public static icn_145_and_drain_8 Ljava/lang/String;
.field public static icn_142_alt_val J
.field public static icn_212_binop_lc J
.field public static icn_212_binop_rc J
.field public static icn_212_binop_bf I
.field public static icn_133_and_drain_0 J
.field public static icn_133_and_drain_1 J
.field public static icn_221_tbl Ljava/util/HashMap;
.field public static icn_221_tdflt Ljava/lang/Object;
.field public static icn_230_relop_lc J
.field public static icn_230_relop_rc J
.field public static icn_235_alt_gate I
.field public static icn_236_binop_lc J
.field public static icn_236_binop_rc J
.field public static icn_236_binop_bf I
.field public static icn_find_s1_239 Ljava/lang/String;
.field public static icn_find_s2_239 Ljava/lang/String;
.field public static icn_find_pos_239 I
.field public static icn_235_alt_val J
.field public static icn_242_alt_gate I
.field public static icn_246_relop_lc J
.field public static icn_246_relop_rc J
.field public static icn_250_sec_s Ljava/lang/String;
.field public static icn_250_sec_lo I
.field public static icn_250_sec_hi I
.field public static icn_find_s1_255 Ljava/lang/String;
.field public static icn_find_s2_255 Ljava/lang/String;
.field public static icn_find_pos_255 I
.field public static icn_259_sec_s Ljava/lang/String;
.field public static icn_259_sec_lo I
.field public static icn_259_sec_hi I
.field public static icn_264_sec_s Ljava/lang/String;
.field public static icn_264_sec_lo I
.field public static icn_264_sec_hi I
.field public static icn_266_binop_lc J
.field public static icn_266_binop_rc J
.field public static icn_266_binop_bf I
.field public static icn_269_binop_lc J
.field public static icn_269_binop_rc J
.field public static icn_269_binop_bf I
.field public static icn_273_alt_gate I
.field public static icn_274_and_drain_0 Ljava/lang/String;
.field public static icn_280_relop_lc Ljava/lang/String;
.field public static icn_280_relop_rc Ljava/lang/String;
.field public static icn_279_and_drain_0 Ljava/lang/String;
.field public static icn_279_and_drain_1 Ljava/lang/String;
.field public static icn_288_lc Ljava/lang/String;
.field public static icn_288_rc Ljava/lang/String;
.field public static icn_290_lc Ljava/lang/String;
.field public static icn_290_rc Ljava/lang/String;
.field public static icn_293_relop_lc Ljava/lang/String;
.field public static icn_293_relop_rc Ljava/lang/String;
.field public static icn_295_ts_tbl Ljava/util/HashMap;
.field public static icn_295_ts_key Ljava/lang/String;
.field public static icn_295_ts_kval J
.field public static icn_298_tsa_vl Ljava/lang/String;
.field public static icn_298_tsa_vo Ljava/lang/Object;
.field public static icn_298_tsa_ks Ljava/lang/String;
.field public static icn_302_lc Ljava/lang/String;
.field public static icn_302_rc Ljava/lang/String;
.field public static icn_304_lc Ljava/lang/String;
.field public static icn_304_rc Ljava/lang/String;
.field public static icn_306_lc Ljava/lang/String;
.field public static icn_306_rc Ljava/lang/String;
.field public static icn_308_lc Ljava/lang/String;
.field public static icn_308_rc Ljava/lang/String;
.field public static icn_245_and_drain_0 J
.field public static icn_245_and_drain_1 Ljava/lang/String;
.field public static icn_245_and_drain_2 J
.field public static icn_245_and_drain_3 Ljava/lang/String;
.field public static icn_245_and_drain_4 Ljava/lang/String;
.field public static icn_245_and_drain_5 Ljava/lang/String;
.field public static icn_245_and_drain_6 Ljava/lang/String;
.field public static icn_245_and_drain_7 Ljava/lang/String;
.field public static icn_245_and_drain_8 Ljava/lang/String;
.field public static icn_242_alt_val J
.field public static icn_312_binop_lc J
.field public static icn_312_binop_rc J
.field public static icn_312_binop_bf I
.field public static icn_233_and_drain_0 J
.field public static icn_233_and_drain_1 J
.field public static icn_321_tbl Ljava/util/HashMap;
.field public static icn_321_tdflt Ljava/lang/Object;
.field public static icn_330_relop_lc J
.field public static icn_330_relop_rc J
.field public static icn_335_alt_gate I
.field public static icn_336_binop_lc J
.field public static icn_336_binop_rc J
.field public static icn_336_binop_bf I
.field public static icn_find_s1_339 Ljava/lang/String;
.field public static icn_find_s2_339 Ljava/lang/String;
.field public static icn_find_pos_339 I
.field public static icn_335_alt_val J
.field public static icn_342_alt_gate I
.field public static icn_346_relop_lc J
.field public static icn_346_relop_rc J
.field public static icn_350_lc Ljava/lang/String;
.field public static icn_350_rc Ljava/lang/String;
.field public static icn_351_sec_s Ljava/lang/String;
.field public static icn_351_sec_lo I
.field public static icn_351_sec_hi I
.field public static icn_345_and_drain_0 J
.field public static icn_342_alt_val J
.field public static icn_357_binop_lc J
.field public static icn_357_binop_rc J
.field public static icn_357_binop_bf I
.field public static icn_333_and_drain_0 J
.field public static icn_333_and_drain_1 J
.field public static icn_372_lc Ljava/lang/String;
.field public static icn_372_rc Ljava/lang/String;
.field public static icn_374_lc Ljava/lang/String;
.field public static icn_374_rc Ljava/lang/String;

.method public static main([Ljava/lang/String;)V
    .limit stack 4
    .limit locals 1
    invokestatic family_icon/icn_main()V
    return
.end method

.method public static icn_builtin_any(Ljava/lang/String;Ljava/lang/String;I)J
    .limit stack 4
    .limit locals 3
    ; if pos >= subj.length() → return -1
    aload_1
    invokevirtual java/lang/String/length()I
    iload_2
    if_icmpgt icn_any_inbounds
    ldc2_w -1
    lreturn
icn_any_inbounds:
    ; cs.indexOf(subj.charAt(pos)) >= 0?
    aload_0
    aload_1
    iload_2
    invokevirtual java/lang/String/charAt(I)C
    invokevirtual java/lang/String/indexOf(I)I
    ifge icn_any_match
    ldc2_w -1
    lreturn
icn_any_match:
    ; return pos+2 (new 1-based pos after consuming one char)
    iload_2
    iconst_2
    iadd
    i2l
    lreturn
.end method

.method public static icn_builtin_many(Ljava/lang/String;Ljava/lang/String;I)J
    .limit stack 4
    .limit locals 4
    ; check first char in cs — must match at least one
    aload_1
    invokevirtual java/lang/String/length()I
    iload_2
    if_icmpgt icn_many_first_ok
    ldc2_w -1
    lreturn
icn_many_first_ok:
    aload_0
    aload_1
    iload_2
    invokevirtual java/lang/String/charAt(I)C
    invokevirtual java/lang/String/indexOf(I)I
    ifge icn_many_loop_init
    ldc2_w -1
    lreturn
icn_many_loop_init:
    ; local 3 = pos (working)
    iload_2
    istore_3
icn_many_loop:
    iinc 3 1
    ; if pos3 >= length → done
    aload_1
    invokevirtual java/lang/String/length()I
    iload_3
    if_icmpgt icn_many_cont
    iload_3
    i2l
    lconst_1
    ladd
    lreturn
icn_many_cont:
    aload_0
    aload_1
    iload_3
    invokevirtual java/lang/String/charAt(I)C
    invokevirtual java/lang/String/indexOf(I)I
    ifge icn_many_loop
    ; stopped — return pos3+1 (1-based)
    iload_3
    iconst_1
    iadd
    i2l
    lreturn
.end method

.method public static icn_builtin_upto_step(Ljava/lang/String;Ljava/lang/String;I)J
    .limit stack 4
    .limit locals 4
    iload_2
    istore_3
icn_upto_scan:
    ; if pos3 >= length → -1
    aload_1
    invokevirtual java/lang/String/length()I
    iload_3
    if_icmpgt icn_upto_inbounds
    ldc2_w -1
    lreturn
icn_upto_inbounds:
    aload_0
    aload_1
    iload_3
    invokevirtual java/lang/String/charAt(I)C
    invokevirtual java/lang/String/indexOf(I)I
    ifge icn_upto_found
    iinc 3 1
    goto icn_upto_scan
icn_upto_found:
    ; return pos3+1 (1-based); caller sets icn_pos=result for next resume
    iload_3
    iconst_1
    iadd
    i2l
    lreturn
.end method

.method public static icn_builtin_find(Ljava/lang/String;Ljava/lang/String;I)J
    .limit stack 4
    .limit locals 3
    aload_1
    aload_0
    iload_2
    invokevirtual java/lang/String/indexOf(Ljava/lang/String;I)I
    dup
    ifge icn_find_ok
    pop
    ldc2_w -1
    lreturn
icn_find_ok:
    iconst_1
    iadd
    i2l
    lreturn
.end method

.method public static icn_builtin_match(Ljava/lang/String;Ljava/lang/String;I)J
    .limit stack 4
    .limit locals 3
    aload_1
    aload_0
    iload_2
    invokevirtual java/lang/String/startsWith(Ljava/lang/String;I)Z
    ifne icn_match_ok
    ldc2_w -1
    lreturn
icn_match_ok:
    iload_2
    aload_0
    invokevirtual java/lang/String/length()I
    iadd
    iconst_1
    iadd
    i2l
    lreturn
.end method

.method public static icn_builtin_tab_str(ILjava/lang/String;I)Ljava/lang/String;
    .limit stack 4
    .limit locals 4
    ; end = n-1 (0-based)
    iload_0
    iconst_1
    isub
    istore_3
    ; fail if end < pos
    iload_3
    iload_2
    if_icmpge icn_tab_posok
    aconst_null
    areturn
icn_tab_posok:
    ; fail if end > subj.length()
    aload_1
    invokevirtual java/lang/String/length()I
    iload_3
    if_icmpge icn_tab_lenok
    aconst_null
    areturn
icn_tab_lenok:
    ; update icn_pos = end (static field)
    iload_3
    putstatic family_icon/icn_pos I
    ; return subj.substring(pos, end)
    aload_1
    iload_2
    iload_3
    invokevirtual java/lang/String/substring(II)Ljava/lang/String;
    areturn
.end method

.method public static icn_builtin_move_str(ILjava/lang/String;I)Ljava/lang/String;
    .limit stack 4
    .limit locals 4
    ; end = pos+n
    iload_2
    iload_0
    iadd
    istore_3
    ; fail if end > subj.length()
    aload_1
    invokevirtual java/lang/String/length()I
    iload_3
    if_icmpge icn_move_ok
    aconst_null
    areturn
icn_move_ok:
    ; update icn_pos = end
    iload_3
    putstatic family_icon/icn_pos I
    ; return subj.substring(pos, end)
    aload_1
    iload_2
    iload_3
    invokevirtual java/lang/String/substring(II)Ljava/lang/String;
    areturn
.end method

.method public static icn_builtin_left(Ljava/lang/String;ILjava/lang/String;)Ljava/lang/String;
    .limit stack 4
    .limit locals 5
    aload_0
    invokevirtual java/lang/String/length()I
    iload_1
    if_icmplt icn_left_pad
    aload_0
    iconst_0
    iload_1
    invokevirtual java/lang/String/substring(II)Ljava/lang/String;
    areturn
icn_left_pad:
    new java/lang/StringBuilder
    dup
    aload_0
    invokespecial java/lang/StringBuilder/<init>(Ljava/lang/String;)V
    astore_3
icn_left_loop:
    aload_3
    invokevirtual java/lang/StringBuilder/length()I
    iload_1
    if_icmpge icn_left_done
    aload_3
    aload_2
    iconst_0
    invokevirtual java/lang/String/charAt(I)C
    invokevirtual java/lang/StringBuilder/append(C)Ljava/lang/StringBuilder;
    pop
    goto icn_left_loop
icn_left_done:
    aload_3
    invokevirtual java/lang/StringBuilder/toString()Ljava/lang/String;
    areturn
.end method

.method public static icn_builtin_right(Ljava/lang/String;ILjava/lang/String;)Ljava/lang/String;
    .limit stack 4
    .limit locals 5
    aload_0
    invokevirtual java/lang/String/length()I
    iload_1
    if_icmplt icn_right_pad
    aload_0
    invokevirtual java/lang/String/length()I
    iload_1
    isub
    aload_0
    swap
    invokevirtual java/lang/String/substring(I)Ljava/lang/String;
    areturn
icn_right_pad:
    new java/lang/StringBuilder
    dup
    invokespecial java/lang/StringBuilder/<init>()V
    astore_3
    iload_1
    aload_0
    invokevirtual java/lang/String/length()I
    isub
    istore 4
    iconst_0
icn_right_loop:
    dup
    iload 4
    if_icmpge icn_right_append
    aload_3
    aload_2
    iconst_0
    invokevirtual java/lang/String/charAt(I)C
    invokevirtual java/lang/StringBuilder/append(C)Ljava/lang/StringBuilder;
    pop
    iconst_1
    iadd
    goto icn_right_loop
icn_right_append:
    pop
    aload_3
    aload_0
    invokevirtual java/lang/StringBuilder/append(Ljava/lang/String;)Ljava/lang/StringBuilder;
    pop
    aload_3
    invokevirtual java/lang/StringBuilder/toString()Ljava/lang/String;
    areturn
.end method

.method public static icn_builtin_center(Ljava/lang/String;ILjava/lang/String;)Ljava/lang/String;
    .limit stack 5
    .limit locals 7
    aload_0
    invokevirtual java/lang/String/length()I
    iload_1
    if_icmplt icn_ctr_pad
    aload_0
    iconst_0
    iload_1
    invokevirtual java/lang/String/substring(II)Ljava/lang/String;
    areturn
icn_ctr_pad:
    iload_1
    aload_0
    invokevirtual java/lang/String/length()I
    isub
    istore_3
    iload_3
    iconst_2
    idiv
    istore 4
    iload_3
    iload 4
    isub
    istore 5
    new java/lang/StringBuilder
    dup
    invokespecial java/lang/StringBuilder/<init>()V
    astore 6
    iconst_0
icn_ctr_lloop:
    dup
    iload 4
    if_icmpge icn_ctr_mid
    aload 6
    aload_2
    iconst_0
    invokevirtual java/lang/String/charAt(I)C
    invokevirtual java/lang/StringBuilder/append(C)Ljava/lang/StringBuilder;
    pop
    iconst_1
    iadd
    goto icn_ctr_lloop
icn_ctr_mid:
    pop
    aload 6
    aload_0
    invokevirtual java/lang/StringBuilder/append(Ljava/lang/String;)Ljava/lang/StringBuilder;
    pop
    iconst_0
icn_ctr_rloop:
    dup
    iload 5
    if_icmpge icn_ctr_done
    aload 6
    aload_2
    iconst_0
    invokevirtual java/lang/String/charAt(I)C
    invokevirtual java/lang/StringBuilder/append(C)Ljava/lang/StringBuilder;
    pop
    iconst_1
    iadd
    goto icn_ctr_rloop
icn_ctr_done:
    pop
    aload 6
    invokevirtual java/lang/StringBuilder/toString()Ljava/lang/String;
    areturn
.end method

.method public static icn_builtin_trim(Ljava/lang/String;Ljava/lang/String;)Ljava/lang/String;
    .limit stack 4
    .limit locals 3
    aload_0
    invokevirtual java/lang/String/length()I
    istore_2
icn_trim_loop:
    iload_2
    ifle icn_trim_done
    aload_1
    aload_0
    iload_2
    iconst_1
    isub
    invokevirtual java/lang/String/charAt(I)C
    invokevirtual java/lang/String/indexOf(I)I
    iflt icn_trim_done
    iinc 2 -1
    goto icn_trim_loop
icn_trim_done:
    aload_0
    iconst_0
    iload_2
    invokevirtual java/lang/String/substring(II)Ljava/lang/String;
    areturn
.end method

.method public static icn_builtin_map(Ljava/lang/String;Ljava/lang/String;Ljava/lang/String;)Ljava/lang/String;
    .limit stack 5
    .limit locals 7
    new java/lang/StringBuilder
    dup
    invokespecial java/lang/StringBuilder/<init>()V
    astore_3
    iconst_0
    istore 4
icn_map_loop:
    iload 4
    aload_0
    invokevirtual java/lang/String/length()I
    if_icmpge icn_map_done
    aload_0
    iload 4
    invokevirtual java/lang/String/charAt(I)C
    istore 5
    aload_1
    iload 5
    invokevirtual java/lang/String/indexOf(I)I
    istore 6
    iload 6
    iflt icn_map_notfound
    iload 6
    aload_2
    invokevirtual java/lang/String/length()I
    if_icmpge icn_map_notfound
    aload_3
    aload_2
    iload 6
    invokevirtual java/lang/String/charAt(I)C
    invokevirtual java/lang/StringBuilder/append(C)Ljava/lang/StringBuilder;
    pop
    goto icn_map_next
icn_map_notfound:
    aload_3
    iload 5
    invokevirtual java/lang/StringBuilder/append(C)Ljava/lang/StringBuilder;
    pop
icn_map_next:
    iinc 4 1
    goto icn_map_loop
icn_map_done:
    aload_3
    invokevirtual java/lang/StringBuilder/toString()Ljava/lang/String;
    areturn
.end method

.method public static icn_builtin_numeric(Ljava/lang/String;)J
    .limit stack 2
    .limit locals 2
    .catch java/lang/NumberFormatException from icn_num_L0 to icn_num_L1 using icn_num_catch
icn_num_L0:
    aload_0
    invokestatic java/lang/Long/parseLong(Ljava/lang/String;)J
icn_num_L1:
    lreturn
icn_num_catch:
    pop
    ldc2_w -9223372036854775808
    lreturn
.end method

.method public static icn_builtin_sort(Ljava/util/ArrayList;)Ljava/util/ArrayList;
    .limit stack 6
    .limit locals 8
    new java/util/ArrayList
    dup
    aload_0
    invokespecial java/util/ArrayList/<init>(Ljava/util/Collection;)V
    astore_1
    iconst_1
    istore_2
icn_sort_outer:
    aload_1
    invokevirtual java/util/ArrayList/size()I
    iload_2
    if_icmple icn_sort_done
    aload_1
    iload_2
    invokevirtual java/util/ArrayList/get(I)Ljava/lang/Object;
    checkcast java/lang/Long
    invokevirtual java/lang/Long/longValue()J
    lstore 4
    iload_2
    iconst_1
    isub
    istore_3
icn_sort_inner:
    iload_3
    iflt icn_sort_insert
    aload_1
    iload_3
    invokevirtual java/util/ArrayList/get(I)Ljava/lang/Object;
    checkcast java/lang/Long
    invokevirtual java/lang/Long/longValue()J
    lload 4
    lcmp
    ifle icn_sort_insert
    aload_1
    iload_3
    iconst_1
    iadd
    aload_1
    iload_3
    invokevirtual java/util/ArrayList/get(I)Ljava/lang/Object;
    invokevirtual java/util/ArrayList/set(ILjava/lang/Object;)Ljava/lang/Object;
    pop
    iinc 3 -1
    goto icn_sort_inner
icn_sort_insert:
    aload_1
    iload_3
    iconst_1
    iadd
    lload 4
    invokestatic java/lang/Long/valueOf(J)Ljava/lang/Long;
    invokevirtual java/util/ArrayList/set(ILjava/lang/Object;)Ljava/lang/Object;
    pop
    iinc 2 1
    goto icn_sort_outer
icn_sort_done:
    aload_1
    areturn
.end method

.method public static icn_builtin_sortf(Ljava/util/ArrayList;I)Ljava/util/ArrayList;
    .limit stack 8
    .limit locals 10
    new java/util/ArrayList
    dup
    aload_0
    invokespecial java/util/ArrayList/<init>(Ljava/util/Collection;)V
    astore_2
    iconst_1
    istore_3
icn_sortf_outer:
    aload_2
    invokevirtual java/util/ArrayList/size()I
    iload_3
    if_icmple icn_sortf_done
    aload_2
    iload_3
    invokevirtual java/util/ArrayList/get(I)Ljava/lang/Object;
    astore 5
    iload_3
    iconst_1
    isub
    istore 4
icn_sortf_inner:
    iload 4
    iflt icn_sortf_insert
    aload_2
    iload 4
    invokevirtual java/util/ArrayList/get(I)Ljava/lang/Object;
    astore 6
    aload 6
    invokevirtual java/lang/Object/getClass()Ljava/lang/Class;
    invokevirtual java/lang/Class/getDeclaredFields()[Ljava/lang/reflect/Field;
    iload_1
    iconst_1
    isub
    aaload
    aload 6
    invokevirtual java/lang/reflect/Field/get(Ljava/lang/Object;)Ljava/lang/Object;
    astore 7
    aload 5
    invokevirtual java/lang/Object/getClass()Ljava/lang/Class;
    invokevirtual java/lang/Class/getDeclaredFields()[Ljava/lang/reflect/Field;
    iload_1
    iconst_1
    isub
    aaload
    aload 5
    invokevirtual java/lang/reflect/Field/get(Ljava/lang/Object;)Ljava/lang/Object;
    astore 8
    aload 7
    checkcast java/lang/Long
    aload 8
    checkcast java/lang/Long
    invokevirtual java/lang/Long/compareTo(Ljava/lang/Long;)I
    ifle icn_sortf_insert
    aload_2
    iload 4
    iconst_1
    iadd
    aload_2
    iload 4
    invokevirtual java/util/ArrayList/get(I)Ljava/lang/Object;
    invokevirtual java/util/ArrayList/set(ILjava/lang/Object;)Ljava/lang/Object;
    pop
    iinc 4 -1
    goto icn_sortf_inner
icn_sortf_insert:
    aload_2
    iload 4
    iconst_1
    iadd
    aload 5
    invokevirtual java/util/ArrayList/set(ILjava/lang/Object;)Ljava/lang/Object;
    pop
    iinc 3 1
    goto icn_sortf_outer
icn_sortf_done:
    aload_2
    areturn
.end method

.method public static icn_main()V
    .limit stack 16
    .limit locals 772
    lconst_0
    lstore 0
    lconst_0
    lstore 2
    lconst_0
    lstore 4
    lconst_0
    lstore 6
    lconst_0
    lstore 8
    lconst_0
    lstore 10
    lconst_0
    lstore 12
    lconst_0
    lstore 14
    lconst_0
    lstore 16
    lconst_0
    lstore 18
    lconst_0
    lstore 20
    lconst_0
    lstore 22
    lconst_0
    lstore 24
    lconst_0
    lstore 26
    lconst_0
    lstore 28
    lconst_0
    lstore 30
    lconst_0
    lstore 32
    lconst_0
    lstore 34
    lconst_0
    lstore 36
    lconst_0
    lstore 38
    lconst_0
    lstore 40
    lconst_0
    lstore 42
    lconst_0
    lstore 44
    lconst_0
    lstore 46
    lconst_0
    lstore 48
    lconst_0
    lstore 50
    lconst_0
    lstore 52
    lconst_0
    lstore 54
    lconst_0
    lstore 56
    lconst_0
    lstore 58
    lconst_0
    lstore 60
    lconst_0
    lstore 62
    iconst_0
    istore 84
    iconst_0
    istore 85
    iconst_0
    istore 86
    iconst_0
    istore 87
    iconst_0
    istore 88
    iconst_0
    istore 89
    iconst_0
    istore 90
    iconst_0
    istore 91
    iconst_0
    istore 92
    iconst_0
    istore 93
    iconst_0
    istore 94
    iconst_0
    istore 95
    iconst_0
    istore 96
    iconst_0
    istore 97
    iconst_0
    istore 98
    iconst_0
    istore 99
    iconst_0
    istore 100
    iconst_0
    istore 101
    iconst_0
    istore 102
    iconst_0
    istore 103
    iconst_0
    istore 104
    iconst_0
    istore 105
    iconst_0
    istore 106
    iconst_0
    istore 107
    iconst_0
    istore 108
    iconst_0
    istore 109
    iconst_0
    istore 110
    iconst_0
    istore 111
    iconst_0
    istore 112
    iconst_0
    istore 113
    iconst_0
    istore 114
    iconst_0
    istore 115
    iconst_0
    istore 116
    iconst_0
    istore 117
    iconst_0
    istore 118
    iconst_0
    istore 119
    iconst_0
    istore 120
    iconst_0
    istore 121
    iconst_0
    istore 122
    iconst_0
    istore 123
    iconst_0
    istore 124
    iconst_0
    istore 125
    iconst_0
    istore 126
    iconst_0
    istore 127
    iconst_0
    istore 128
    iconst_0
    istore 129
    iconst_0
    istore 130
    iconst_0
    istore 131
    iconst_0
    istore 132
    iconst_0
    istore 133
    iconst_0
    istore 134
    iconst_0
    istore 135
    iconst_0
    istore 136
    iconst_0
    istore 137
    iconst_0
    istore 138
    iconst_0
    istore 139
    iconst_0
    istore 140
    iconst_0
    istore 141
    iconst_0
    istore 142
    iconst_0
    istore 143
    iconst_0
    istore 144
    iconst_0
    istore 145
    iconst_0
    istore 146
    iconst_0
    istore 147
    iconst_0
    istore 148
    aconst_null
    astore 148
    aconst_null
    astore 149
    aconst_null
    astore 150
    aconst_null
    astore 151
    aconst_null
    astore 152
    aconst_null
    astore 153
    aconst_null
    astore 154
    aconst_null
    astore 155
    aconst_null
    astore 156
    aconst_null
    astore 157
    aconst_null
    astore 158
    aconst_null
    astore 159
    aconst_null
    astore 160
    aconst_null
    astore 161
    aconst_null
    astore 162
    aconst_null
    astore 163
    aconst_null
    astore 164
    aconst_null
    astore 165
    aconst_null
    astore 166
    aconst_null
    astore 167
    aconst_null
    astore 168
    aconst_null
    astore 169
    aconst_null
    astore 170
    aconst_null
    astore 171
    goto icn_379_α
;  VAR
icn_2_α:
    getstatic family_icon/icn_pv_main_n J
    goto icn_1_rrelay
icn_2_β:
    goto icn_1_lb
;  VAR
icn_3_α:
    getstatic family_icon/icn_pv_main_i J
    goto icn_1_lrelay
icn_3_β:
    goto icn_main_done
icn_1_lrelay:
    putstatic family_icon/icn_1_relop_lc J
    goto icn_1_lstore
icn_1_rrelay:
    putstatic family_icon/icn_1_relop_rc J
    goto icn_1_check
icn_1_lb:
    goto icn_3_β
icn_1_α:
    goto icn_3_α
icn_1_β:
    goto icn_2_β
icn_1_lstore:
    goto icn_2_α
icn_1_check:
    getstatic family_icon/icn_1_relop_lc J
    getstatic family_icon/icn_1_relop_rc J
    lcmp
    ifgt icn_2_β
    getstatic family_icon/icn_1_relop_rc J
    goto icn_0_condok
icn_0_condok:
    pop2
    goto icn_0_wbstart
;  INT
icn_8_α:
    ldc2_w 1
    goto icn_7_rrelay
icn_8_β:
    goto icn_7_lb
;  VAR
icn_9_α:
    getstatic family_icon/icn_pv_main_n J
    goto icn_7_lrelay
icn_9_β:
    goto icn_0_top
icn_7_lrelay:
    putstatic family_icon/icn_7_binop_lc J
    goto icn_7_lstore
icn_7_rrelay:
    putstatic family_icon/icn_7_binop_rc J
    goto icn_7_compute
icn_7_lb:
    goto icn_9_β
icn_7_α:
    iconst_0
    putstatic family_icon/icn_7_binop_bf I
    goto icn_9_α
icn_7_β:
    iconst_1
    putstatic family_icon/icn_7_binop_bf I
    goto icn_9_α
icn_7_lstore:
    getstatic family_icon/icn_7_binop_bf I
    ifeq icn_8_α
    goto icn_8_β
icn_7_compute:
    getstatic family_icon/icn_7_binop_lc J
    getstatic family_icon/icn_7_binop_rc J
    ladd
    goto icn_6_alt_g1
;  STR
icn_11_α:
    ldc "\n"
    goto icn_10_fa1
icn_11_β:
    goto icn_7_α
;  VAR
icn_12_α:
    getstatic family_icon/icn_pv_main_raw Ljava/lang/String;
    goto icn_10_fa2
icn_12_β:
    goto icn_7_α
icn_10_α:
    goto icn_11_α
icn_10_fa1:
    putstatic family_icon/icn_find_s1_10 Ljava/lang/String;
    goto icn_12_α
icn_10_fa2:
    putstatic family_icon/icn_find_s2_10 Ljava/lang/String;
    iconst_0
    putstatic family_icon/icn_find_pos_10 I
    goto icn_10_fchk
icn_10_β:
    getstatic family_icon/icn_find_pos_10 I
    putstatic family_icon/icn_find_pos_10 I
    goto icn_10_fchk
icn_10_fchk:
    getstatic family_icon/icn_find_s1_10 Ljava/lang/String;
    getstatic family_icon/icn_find_s2_10 Ljava/lang/String;
    getstatic family_icon/icn_find_pos_10 I
    invokestatic family_icon/icn_builtin_find(Ljava/lang/String;Ljava/lang/String;I)J
    dup2
    lconst_1
    lneg
    lcmp
    ifne icn_10_fok
    pop2
    goto icn_7_α
icn_10_fok:
;  find ok: store result as new pos, push result → γ
    dup2
    l2i
    putstatic family_icon/icn_find_pos_10 I
    goto icn_6_alt_g0
icn_6_alt_g0:
    putstatic family_icon/icn_6_alt_val J
    sipush 1
    putstatic family_icon/icn_6_alt_gate I
    getstatic family_icon/icn_6_alt_val J
    goto icn_5_store
icn_6_alt_g1:
    putstatic family_icon/icn_6_alt_val J
    sipush 2
    putstatic family_icon/icn_6_alt_gate I
    getstatic family_icon/icn_6_alt_val J
    goto icn_5_store
icn_6_α:
    iconst_0
    putstatic family_icon/icn_6_alt_gate I
    goto icn_10_α
icn_6_β:
    getstatic family_icon/icn_6_alt_gate I
    tableswitch 1 2
        icn_10_β
        icn_7_β
        default: icn_0_top
icn_5_α:
    goto icn_6_α
icn_5_β:
    goto icn_6_β
icn_5_store:
    putstatic family_icon/icn_pv_main_j J
    getstatic family_icon/icn_pv_main_j J
    goto icn_4_and_rg_0
;  VAR
icn_15_α:
    getstatic family_icon/icn_pv_main_i J
    goto icn_14_store
icn_15_β:
    goto icn_5_β
icn_14_α:
    goto icn_15_α
icn_14_β:
    goto icn_15_β
icn_14_store:
    putstatic family_icon/icn_pv_main_i J
    getstatic family_icon/icn_pv_main_i J
    goto icn_13_alt_g1
;  VAR
icn_18_α:
    getstatic family_icon/icn_pv_main_i J
    goto icn_17_rrelay
icn_18_β:
    goto icn_17_lb
;  VAR
icn_19_α:
    getstatic family_icon/icn_pv_main_j J
    goto icn_17_lrelay
icn_19_β:
    goto icn_14_α
icn_17_lrelay:
    putstatic family_icon/icn_17_relop_lc J
    goto icn_17_lstore
icn_17_rrelay:
    putstatic family_icon/icn_17_relop_rc J
    goto icn_17_check
icn_17_lb:
    goto icn_19_β
icn_17_α:
    goto icn_19_α
icn_17_β:
    goto icn_18_β
icn_17_lstore:
    goto icn_18_α
icn_17_check:
    getstatic family_icon/icn_17_relop_lc J
    getstatic family_icon/icn_17_relop_rc J
    lcmp
    ifle icn_18_β
    getstatic family_icon/icn_17_relop_rc J
    goto icn_16_and_rg_0
;  VAR
icn_22_α:
    getstatic family_icon/icn_pv_main_raw Ljava/lang/String;
    goto icn_21_sec_sr
icn_22_β:
    goto icn_17_β
;  VAR
icn_23_α:
    getstatic family_icon/icn_pv_main_i J
    goto icn_21_sec_lor
icn_23_β:
    goto icn_17_β
;  VAR
icn_24_α:
    getstatic family_icon/icn_pv_main_j J
    goto icn_21_sec_hir
icn_24_β:
    goto icn_17_β
icn_21_sec_lor:
    l2i
    istore 84
    iload 84
    ifgt icn_21_sec_lop
    iload 84
    iflt icn_21_sec_lon
icn_21_sec_loz:
    goto icn_17_β
icn_21_sec_lop:
    iload 84
    iconst_1
    isub
    putstatic family_icon/icn_21_sec_lo I
    goto icn_24_α
icn_21_sec_lon:
    getstatic family_icon/icn_21_sec_s Ljava/lang/String;
    invokevirtual java/lang/String/length()I
    iload 84
    iadd
    putstatic family_icon/icn_21_sec_lo I
    goto icn_24_α
icn_21_sec_hir:
    l2i
    istore 85
    iload 85
    ifgt icn_21_sec_hip
    iload 85
    iflt icn_21_sec_hin
icn_21_sec_hiz:
    goto icn_17_β
icn_21_sec_hip:
    iload 85
    iconst_1
    isub
    putstatic family_icon/icn_21_sec_hi I
    goto icn_21_sec_cmp
icn_21_sec_hin:
    getstatic family_icon/icn_21_sec_s Ljava/lang/String;
    invokevirtual java/lang/String/length()I
    iload 85
    iadd
    putstatic family_icon/icn_21_sec_hi I
    goto icn_21_sec_cmp
icn_21_sec_cmp:
    getstatic family_icon/icn_21_sec_lo I
    iflt icn_17_β
    getstatic family_icon/icn_21_sec_hi I
    iflt icn_17_β
    getstatic family_icon/icn_21_sec_s Ljava/lang/String;
    invokevirtual java/lang/String/length()I
    getstatic family_icon/icn_21_sec_lo I
    if_icmplt icn_17_β
    getstatic family_icon/icn_21_sec_s Ljava/lang/String;
    invokevirtual java/lang/String/length()I
    istore 86
    getstatic family_icon/icn_21_sec_hi I
    iload 86
    if_icmple icn_21_sec_hiok
    iload 86
    putstatic family_icon/icn_21_sec_hi I
icn_21_sec_hiok:
    getstatic family_icon/icn_21_sec_s Ljava/lang/String;
    getstatic family_icon/icn_21_sec_lo I
    getstatic family_icon/icn_21_sec_hi I
    invokevirtual java/lang/String/substring(II)Ljava/lang/String;
    goto icn_20_store
icn_21_α:
    goto icn_22_α
icn_21_sec_sr:
    putstatic family_icon/icn_21_sec_s Ljava/lang/String;
    goto icn_23_α
icn_21_β:
    goto icn_17_β
icn_20_α:
    goto icn_21_α
icn_20_β:
    goto icn_21_β
icn_20_store:
    putstatic family_icon/icn_pv_main_line Ljava/lang/String;
    getstatic family_icon/icn_pv_main_line Ljava/lang/String;
    goto icn_16_and_rg_1
;  STR
icn_27_α:
    ldc "|"
    goto icn_26_fa1
icn_27_β:
    goto icn_20_β
;  VAR
icn_28_α:
    getstatic family_icon/icn_pv_main_line Ljava/lang/String;
    goto icn_26_fa2
icn_28_β:
    goto icn_20_β
icn_26_α:
    goto icn_27_α
icn_26_fa1:
    putstatic family_icon/icn_find_s1_26 Ljava/lang/String;
    goto icn_28_α
icn_26_fa2:
    putstatic family_icon/icn_find_s2_26 Ljava/lang/String;
    iconst_0
    putstatic family_icon/icn_find_pos_26 I
    goto icn_26_fchk
icn_26_β:
    getstatic family_icon/icn_find_pos_26 I
    putstatic family_icon/icn_find_pos_26 I
    goto icn_26_fchk
icn_26_fchk:
    getstatic family_icon/icn_find_s1_26 Ljava/lang/String;
    getstatic family_icon/icn_find_s2_26 Ljava/lang/String;
    getstatic family_icon/icn_find_pos_26 I
    invokestatic family_icon/icn_builtin_find(Ljava/lang/String;Ljava/lang/String;I)J
    dup2
    lconst_1
    lneg
    lcmp
    ifne icn_26_fok
    pop2
    goto icn_20_β
icn_26_fok:
;  find ok: store result as new pos, push result → γ
    dup2
    l2i
    putstatic family_icon/icn_find_pos_26 I
    goto icn_25_store
icn_25_α:
    goto icn_26_α
icn_25_β:
    goto icn_26_β
icn_25_store:
    putstatic family_icon/icn_pv_main_pi J
    getstatic family_icon/icn_pv_main_pi J
    goto icn_16_and_rg_2
;  STR
icn_31_α:
    ldc ")"
    goto icn_30_rrelay
icn_31_β:
    goto icn_30_lb
;  VAR
icn_34_α:
    getstatic family_icon/icn_pv_main_line Ljava/lang/String;
    goto icn_33_sec_sr
icn_34_β:
    goto icn_32_lb
;  INT
icn_35_α:
    ldc2_w 1
    goto icn_33_sec_lor
icn_35_β:
    goto icn_32_lb
;  VAR
icn_36_α:
    getstatic family_icon/icn_pv_main_pi J
    goto icn_33_sec_hir
icn_36_β:
    goto icn_32_lb
icn_33_sec_lor:
    l2i
    istore 89
    iload 89
    ifgt icn_33_sec_lop
    iload 89
    iflt icn_33_sec_lon
icn_33_sec_loz:
    goto icn_32_lb
icn_33_sec_lop:
    iload 89
    iconst_1
    isub
    putstatic family_icon/icn_33_sec_lo I
    goto icn_36_α
icn_33_sec_lon:
    getstatic family_icon/icn_33_sec_s Ljava/lang/String;
    invokevirtual java/lang/String/length()I
    iload 89
    iadd
    putstatic family_icon/icn_33_sec_lo I
    goto icn_36_α
icn_33_sec_hir:
    l2i
    istore 90
    iload 90
    ifgt icn_33_sec_hip
    iload 90
    iflt icn_33_sec_hin
icn_33_sec_hiz:
    goto icn_32_lb
icn_33_sec_hip:
    iload 90
    iconst_1
    isub
    putstatic family_icon/icn_33_sec_hi I
    goto icn_33_sec_cmp
icn_33_sec_hin:
    getstatic family_icon/icn_33_sec_s Ljava/lang/String;
    invokevirtual java/lang/String/length()I
    iload 90
    iadd
    putstatic family_icon/icn_33_sec_hi I
    goto icn_33_sec_cmp
icn_33_sec_cmp:
    getstatic family_icon/icn_33_sec_lo I
    iflt icn_32_lb
    getstatic family_icon/icn_33_sec_hi I
    iflt icn_32_lb
    getstatic family_icon/icn_33_sec_s Ljava/lang/String;
    invokevirtual java/lang/String/length()I
    getstatic family_icon/icn_33_sec_lo I
    if_icmplt icn_32_lb
    getstatic family_icon/icn_33_sec_s Ljava/lang/String;
    invokevirtual java/lang/String/length()I
    istore 91
    getstatic family_icon/icn_33_sec_hi I
    iload 91
    if_icmple icn_33_sec_hiok
    iload 91
    putstatic family_icon/icn_33_sec_hi I
icn_33_sec_hiok:
    getstatic family_icon/icn_33_sec_s Ljava/lang/String;
    getstatic family_icon/icn_33_sec_lo I
    getstatic family_icon/icn_33_sec_hi I
    invokevirtual java/lang/String/substring(II)Ljava/lang/String;
    goto icn_32_rrelay
icn_33_α:
    goto icn_34_α
icn_33_sec_sr:
    putstatic family_icon/icn_33_sec_s Ljava/lang/String;
    goto icn_35_α
icn_33_β:
    goto icn_32_lb
;  STR
icn_38_α:
    ldc " (generation "
    goto icn_37_rrelay
icn_38_β:
    goto icn_37_lb
;  VAR
icn_41_α:
    getstatic family_icon/icn_pv_main_line Ljava/lang/String;
    goto icn_40_sec_sr
icn_41_β:
    goto icn_39_lb
;  INT
icn_43_α:
    ldc2_w 1
    goto icn_42_rrelay
icn_43_β:
    goto icn_42_lb
;  VAR
icn_44_α:
    getstatic family_icon/icn_pv_main_pi J
    goto icn_42_lrelay
icn_44_β:
    goto icn_39_lb
icn_42_lrelay:
    putstatic family_icon/icn_42_binop_lc J
    goto icn_42_lstore
icn_42_rrelay:
    putstatic family_icon/icn_42_binop_rc J
    goto icn_42_compute
icn_42_lb:
    goto icn_44_β
icn_42_α:
    iconst_0
    putstatic family_icon/icn_42_binop_bf I
    goto icn_44_α
icn_42_β:
    iconst_1
    putstatic family_icon/icn_42_binop_bf I
    goto icn_44_α
icn_42_lstore:
    getstatic family_icon/icn_42_binop_bf I
    ifeq icn_43_α
    goto icn_43_β
icn_42_compute:
    getstatic family_icon/icn_42_binop_lc J
    getstatic family_icon/icn_42_binop_rc J
    ladd
    goto icn_40_sec_lor
;  INT
icn_46_α:
    ldc2_w 1
    goto icn_45_rrelay
icn_46_β:
    goto icn_45_lb
;  VAR
icn_48_α:
    getstatic family_icon/icn_pv_main_line Ljava/lang/String;
    goto icn_47_relay
icn_48_β:
    goto icn_39_lb
icn_47_α:
    goto icn_48_α
icn_47_β:
    goto icn_48_β
icn_47_relay:
    invokevirtual java/lang/String/length()I
    i2l
    goto icn_45_lrelay
icn_45_lrelay:
    putstatic family_icon/icn_45_binop_lc J
    goto icn_45_lstore
icn_45_rrelay:
    putstatic family_icon/icn_45_binop_rc J
    goto icn_45_compute
icn_45_lb:
    goto icn_47_β
icn_45_α:
    iconst_0
    putstatic family_icon/icn_45_binop_bf I
    goto icn_47_α
icn_45_β:
    goto icn_46_β
icn_45_lstore:
    getstatic family_icon/icn_45_binop_bf I
    ifeq icn_46_α
    goto icn_46_β
icn_45_compute:
    getstatic family_icon/icn_45_binop_lc J
    getstatic family_icon/icn_45_binop_rc J
    ladd
    goto icn_40_sec_hir
icn_40_sec_lor:
    l2i
    istore 94
    iload 94
    ifgt icn_40_sec_lop
    iload 94
    iflt icn_40_sec_lon
icn_40_sec_loz:
    goto icn_39_lb
icn_40_sec_lop:
    iload 94
    iconst_1
    isub
    putstatic family_icon/icn_40_sec_lo I
    goto icn_45_α
icn_40_sec_lon:
    getstatic family_icon/icn_40_sec_s Ljava/lang/String;
    invokevirtual java/lang/String/length()I
    iload 94
    iadd
    putstatic family_icon/icn_40_sec_lo I
    goto icn_45_α
icn_40_sec_hir:
    l2i
    istore 95
    iload 95
    ifgt icn_40_sec_hip
    iload 95
    iflt icn_40_sec_hin
icn_40_sec_hiz:
    goto icn_39_lb
icn_40_sec_hip:
    iload 95
    iconst_1
    isub
    putstatic family_icon/icn_40_sec_hi I
    goto icn_40_sec_cmp
icn_40_sec_hin:
    getstatic family_icon/icn_40_sec_s Ljava/lang/String;
    invokevirtual java/lang/String/length()I
    iload 95
    iadd
    putstatic family_icon/icn_40_sec_hi I
    goto icn_40_sec_cmp
icn_40_sec_cmp:
    getstatic family_icon/icn_40_sec_lo I
    iflt icn_39_lb
    getstatic family_icon/icn_40_sec_hi I
    iflt icn_39_lb
    getstatic family_icon/icn_40_sec_s Ljava/lang/String;
    invokevirtual java/lang/String/length()I
    getstatic family_icon/icn_40_sec_lo I
    if_icmplt icn_39_lb
    getstatic family_icon/icn_40_sec_s Ljava/lang/String;
    invokevirtual java/lang/String/length()I
    istore 96
    getstatic family_icon/icn_40_sec_hi I
    iload 96
    if_icmple icn_40_sec_hiok
    iload 96
    putstatic family_icon/icn_40_sec_hi I
icn_40_sec_hiok:
    getstatic family_icon/icn_40_sec_s Ljava/lang/String;
    getstatic family_icon/icn_40_sec_lo I
    getstatic family_icon/icn_40_sec_hi I
    invokevirtual java/lang/String/substring(II)Ljava/lang/String;
    goto icn_39_rrelay
icn_40_α:
    goto icn_41_α
icn_40_sec_sr:
    putstatic family_icon/icn_40_sec_s Ljava/lang/String;
    goto icn_42_α
icn_40_β:
    goto icn_39_lb
;  STR
icn_49_α:
    ldc "  "
    goto icn_39_lrelay
icn_49_β:
    goto icn_25_β
icn_39_lrelay:
    putstatic family_icon/icn_39_lc Ljava/lang/String;
    goto icn_39_lstore
icn_39_rrelay:
    putstatic family_icon/icn_39_rc Ljava/lang/String;
    goto icn_39_compute
icn_39_lb:
    goto icn_49_β
icn_39_α:
    iconst_0
    istore 93
    goto icn_49_α
icn_39_β:
    iconst_1
    istore 93
    goto icn_49_α
icn_39_lstore:
    iload 93
    ifeq icn_40_α
    goto icn_40_β
icn_39_compute:
    getstatic family_icon/icn_39_lc Ljava/lang/String;
    getstatic family_icon/icn_39_rc Ljava/lang/String;
    invokevirtual java/lang/String/concat(Ljava/lang/String;)Ljava/lang/String;
    goto icn_37_lrelay
icn_37_lrelay:
    putstatic family_icon/icn_37_lc Ljava/lang/String;
    goto icn_37_lstore
icn_37_rrelay:
    putstatic family_icon/icn_37_rc Ljava/lang/String;
    goto icn_37_compute
icn_37_lb:
    goto icn_39_β
icn_37_α:
    iconst_0
    istore 92
    goto icn_39_α
icn_37_β:
    iconst_1
    istore 92
    goto icn_39_α
icn_37_lstore:
    iload 92
    ifeq icn_38_α
    goto icn_38_β
icn_37_compute:
    getstatic family_icon/icn_37_lc Ljava/lang/String;
    getstatic family_icon/icn_37_rc Ljava/lang/String;
    invokevirtual java/lang/String/concat(Ljava/lang/String;)Ljava/lang/String;
    goto icn_32_lrelay
icn_32_lrelay:
    putstatic family_icon/icn_32_lc Ljava/lang/String;
    goto icn_32_lstore
icn_32_rrelay:
    putstatic family_icon/icn_32_rc Ljava/lang/String;
    goto icn_32_compute
icn_32_lb:
    goto icn_37_β
icn_32_α:
    iconst_0
    istore 88
    goto icn_37_α
icn_32_β:
    iconst_1
    istore 88
    goto icn_37_α
icn_32_lstore:
    iload 88
    ifeq icn_33_α
    goto icn_33_β
icn_32_compute:
    getstatic family_icon/icn_32_lc Ljava/lang/String;
    getstatic family_icon/icn_32_rc Ljava/lang/String;
    invokevirtual java/lang/String/concat(Ljava/lang/String;)Ljava/lang/String;
    goto icn_30_lrelay
icn_30_lrelay:
    putstatic family_icon/icn_30_lc Ljava/lang/String;
    goto icn_30_lstore
icn_30_rrelay:
    putstatic family_icon/icn_30_rc Ljava/lang/String;
    goto icn_30_compute
icn_30_lb:
    goto icn_32_β
icn_30_α:
    iconst_0
    istore 87
    goto icn_32_α
icn_30_β:
    iconst_1
    istore 87
    goto icn_32_α
icn_30_lstore:
    iload 87
    ifeq icn_31_α
    goto icn_31_β
icn_30_compute:
    getstatic family_icon/icn_30_lc Ljava/lang/String;
    getstatic family_icon/icn_30_rc Ljava/lang/String;
    invokevirtual java/lang/String/concat(Ljava/lang/String;)Ljava/lang/String;
    goto icn_29_call
icn_29_α:
    goto icn_30_α
icn_29_β:
    goto icn_30_β
icn_29_call:
    astore 148
    getstatic java/lang/System/out Ljava/io/PrintStream;
    aload 148
    invokevirtual java/io/PrintStream/println(Ljava/lang/String;)V
    aload 148
    goto icn_13_alt_g0
    goto icn_16_α
icn_16_and_rg_0:
    putstatic family_icon/icn_16_and_drain_0 J
    goto icn_20_α
icn_16_and_rg_1:
    putstatic family_icon/icn_16_and_drain_1 Ljava/lang/String;
    goto icn_25_α
icn_16_and_rg_2:
    putstatic family_icon/icn_16_and_drain_2 J
    goto icn_29_α
icn_16_α:
    goto icn_17_α
icn_16_β:
    goto icn_29_β
icn_13_alt_g0:
    pop
    lconst_0
    putstatic family_icon/icn_13_alt_val J
    sipush 1
    putstatic family_icon/icn_13_alt_gate I
    getstatic family_icon/icn_13_alt_val J
    goto icn_4_and_rg_1
icn_13_alt_g1:
    putstatic family_icon/icn_13_alt_val J
    sipush 2
    putstatic family_icon/icn_13_alt_gate I
    getstatic family_icon/icn_13_alt_val J
    goto icn_4_and_rg_1
icn_13_α:
    iconst_0
    putstatic family_icon/icn_13_alt_gate I
    goto icn_16_α
icn_13_β:
    getstatic family_icon/icn_13_alt_gate I
    tableswitch 1 2
        icn_16_β
        icn_14_β
        default: icn_5_β
;  INT
icn_52_α:
    ldc2_w 1
    goto icn_51_rrelay
icn_52_β:
    goto icn_51_lb
;  VAR
icn_53_α:
    getstatic family_icon/icn_pv_main_j J
    goto icn_51_lrelay
icn_53_β:
    goto icn_13_β
icn_51_lrelay:
    putstatic family_icon/icn_51_binop_lc J
    goto icn_51_lstore
icn_51_rrelay:
    putstatic family_icon/icn_51_binop_rc J
    goto icn_51_compute
icn_51_lb:
    goto icn_53_β
icn_51_α:
    iconst_0
    putstatic family_icon/icn_51_binop_bf I
    goto icn_53_α
icn_51_β:
    iconst_1
    putstatic family_icon/icn_51_binop_bf I
    goto icn_53_α
icn_51_lstore:
    getstatic family_icon/icn_51_binop_bf I
    ifeq icn_52_α
    goto icn_52_β
icn_51_compute:
    getstatic family_icon/icn_51_binop_lc J
    getstatic family_icon/icn_51_binop_rc J
    ladd
    goto icn_50_store
icn_50_α:
    goto icn_51_α
icn_50_β:
    goto icn_51_β
icn_50_store:
    putstatic family_icon/icn_pv_main_i J
    getstatic family_icon/icn_pv_main_i J
    goto icn_0_wbdrain
    goto icn_4_α
icn_4_and_rg_0:
    putstatic family_icon/icn_4_and_drain_0 J
    goto icn_13_α
icn_4_and_rg_1:
    putstatic family_icon/icn_4_and_drain_1 J
    goto icn_50_α
icn_4_α:
    goto icn_5_α
icn_4_β:
    goto icn_50_β
icn_0_wbstart:
    goto icn_4_α
icn_0_wbdrain:
    pop2
icn_0_top:
    goto icn_1_α
icn_0_α:
    goto icn_1_α
icn_0_β:
    goto icn_main_done
;  INT
icn_55_α:
    ldc2_w 1
    goto icn_54_store
icn_55_β:
    goto icn_0_α
icn_54_α:
    goto icn_55_α
icn_54_β:
    goto icn_55_β
icn_54_store:
    putstatic family_icon/icn_pv_main_i J
    getstatic family_icon/icn_pv_main_i J
    goto icn_main_s34_sdrain
icn_main_s34_sdrain:
    pop2
    goto icn_0_α
;  VAR
icn_58_α:
    getstatic family_icon/icn_pv_main_raw Ljava/lang/String;
    goto icn_57_relay
icn_58_β:
    goto icn_54_α
icn_57_α:
    goto icn_58_α
icn_57_β:
    goto icn_58_β
icn_57_relay:
    invokevirtual java/lang/String/length()I
    i2l
    goto icn_56_store
icn_56_α:
    goto icn_57_α
icn_56_β:
    goto icn_57_β
icn_56_store:
    putstatic family_icon/icn_pv_main_n J
    getstatic family_icon/icn_pv_main_n J
    goto icn_main_s33_sdrain
icn_main_s33_sdrain:
    pop2
    goto icn_54_α
icn_60_α:
icn_60_β:
    ldc 1
    anewarray java/lang/Object
    putstatic family_icon/icn_imp_arr_60 [Ljava/lang/Object;
    goto icn_60_imp_s0
;  STR
icn_61_α:
    ldc "U008"
    goto icn_60_imp_r0
icn_61_β:
    goto icn_56_α
icn_60_imp_r0:
    putstatic family_icon/icn_imp_sv_60_0 Ljava/lang/Object;
    goto icn_60_imp_d0
icn_60_imp_s0:
    goto icn_61_α
icn_60_imp_d0:
    getstatic family_icon/icn_imp_arr_60 [Ljava/lang/Object;
    ldc 0
    getstatic family_icon/icn_imp_sv_60_0 Ljava/lang/Object;
    aastore
icn_60_imp_pack:
    getstatic family_icon/icn_imp_arr_60 [Ljava/lang/Object;
    aconst_null
    aconst_null
    invokestatic family_prolog/query_ancestors([Ljava/lang/Object;Ljava/lang/Runnable;Ljava/lang/Runnable;)V
    getstatic ByrdBoxLinkage/RESULT Ljava/util/concurrent/atomic/AtomicReference;
    invokevirtual java/util/concurrent/atomic/AtomicReference/get()Ljava/lang/Object;
    putstatic family_icon/icn_retval_obj Ljava/lang/Object;
    getstatic family_icon/icn_retval_obj Ljava/lang/Object;
    checkcast java/lang/String
    goto icn_59_store
icn_59_α:
    goto icn_60_α
icn_59_β:
    goto icn_60_β
icn_59_store:
    putstatic family_icon/icn_pv_main_raw Ljava/lang/String;
    getstatic family_icon/icn_pv_main_raw Ljava/lang/String;
    goto icn_main_s32_sdrain
icn_main_s32_sdrain:
    pop
    goto icn_56_α
;  STR
icn_63_α:
    ldc "=== Ancestors of James (U008) ==="
    goto icn_62_call
icn_63_β:
    goto icn_59_α
icn_62_α:
    goto icn_63_α
icn_62_β:
    goto icn_63_β
icn_62_call:
    astore 149
    getstatic java/lang/System/out Ljava/io/PrintStream;
    aload 149
    invokevirtual java/io/PrintStream/println(Ljava/lang/String;)V
    aload 149
    goto icn_main_s31_sdrain
icn_main_s31_sdrain:
    pop
    goto icn_59_α
;  STR
icn_65_α:
    ldc ""
    goto icn_64_call
icn_65_β:
    goto icn_62_α
icn_64_α:
    goto icn_65_α
icn_64_β:
    goto icn_65_β
icn_64_call:
    astore 150
    getstatic java/lang/System/out Ljava/io/PrintStream;
    aload 150
    invokevirtual java/io/PrintStream/println(Ljava/lang/String;)V
    aload 150
    goto icn_main_s30_sdrain
icn_main_s30_sdrain:
    pop
    goto icn_62_α
;  VAR
icn_68_α:
    getstatic family_icon/icn_pv_main_n J
    goto icn_67_rrelay
icn_68_β:
    goto icn_67_lb
;  VAR
icn_69_α:
    getstatic family_icon/icn_pv_main_i J
    goto icn_67_lrelay
icn_69_β:
    goto icn_64_α
icn_67_lrelay:
    putstatic family_icon/icn_67_relop_lc J
    goto icn_67_lstore
icn_67_rrelay:
    putstatic family_icon/icn_67_relop_rc J
    goto icn_67_check
icn_67_lb:
    goto icn_69_β
icn_67_α:
    goto icn_69_α
icn_67_β:
    goto icn_68_β
icn_67_lstore:
    goto icn_68_α
icn_67_check:
    getstatic family_icon/icn_67_relop_lc J
    getstatic family_icon/icn_67_relop_rc J
    lcmp
    ifgt icn_68_β
    getstatic family_icon/icn_67_relop_rc J
    goto icn_66_condok
icn_66_condok:
    pop2
    goto icn_66_wbstart
;  INT
icn_74_α:
    ldc2_w 1
    goto icn_73_rrelay
icn_74_β:
    goto icn_73_lb
;  VAR
icn_75_α:
    getstatic family_icon/icn_pv_main_n J
    goto icn_73_lrelay
icn_75_β:
    goto icn_66_top
icn_73_lrelay:
    putstatic family_icon/icn_73_binop_lc J
    goto icn_73_lstore
icn_73_rrelay:
    putstatic family_icon/icn_73_binop_rc J
    goto icn_73_compute
icn_73_lb:
    goto icn_75_β
icn_73_α:
    iconst_0
    putstatic family_icon/icn_73_binop_bf I
    goto icn_75_α
icn_73_β:
    iconst_1
    putstatic family_icon/icn_73_binop_bf I
    goto icn_75_α
icn_73_lstore:
    getstatic family_icon/icn_73_binop_bf I
    ifeq icn_74_α
    goto icn_74_β
icn_73_compute:
    getstatic family_icon/icn_73_binop_lc J
    getstatic family_icon/icn_73_binop_rc J
    ladd
    goto icn_72_alt_g1
;  STR
icn_77_α:
    ldc "\n"
    goto icn_76_fa1
icn_77_β:
    goto icn_73_α
;  VAR
icn_78_α:
    getstatic family_icon/icn_pv_main_raw Ljava/lang/String;
    goto icn_76_fa2
icn_78_β:
    goto icn_73_α
icn_76_α:
    goto icn_77_α
icn_76_fa1:
    putstatic family_icon/icn_find_s1_76 Ljava/lang/String;
    goto icn_78_α
icn_76_fa2:
    putstatic family_icon/icn_find_s2_76 Ljava/lang/String;
    iconst_0
    putstatic family_icon/icn_find_pos_76 I
    goto icn_76_fchk
icn_76_β:
    getstatic family_icon/icn_find_pos_76 I
    putstatic family_icon/icn_find_pos_76 I
    goto icn_76_fchk
icn_76_fchk:
    getstatic family_icon/icn_find_s1_76 Ljava/lang/String;
    getstatic family_icon/icn_find_s2_76 Ljava/lang/String;
    getstatic family_icon/icn_find_pos_76 I
    invokestatic family_icon/icn_builtin_find(Ljava/lang/String;Ljava/lang/String;I)J
    dup2
    lconst_1
    lneg
    lcmp
    ifne icn_76_fok
    pop2
    goto icn_73_α
icn_76_fok:
;  find ok: store result as new pos, push result → γ
    dup2
    l2i
    putstatic family_icon/icn_find_pos_76 I
    goto icn_72_alt_g0
icn_72_alt_g0:
    putstatic family_icon/icn_72_alt_val J
    sipush 1
    putstatic family_icon/icn_72_alt_gate I
    getstatic family_icon/icn_72_alt_val J
    goto icn_71_store
icn_72_alt_g1:
    putstatic family_icon/icn_72_alt_val J
    sipush 2
    putstatic family_icon/icn_72_alt_gate I
    getstatic family_icon/icn_72_alt_val J
    goto icn_71_store
icn_72_α:
    iconst_0
    putstatic family_icon/icn_72_alt_gate I
    goto icn_76_α
icn_72_β:
    getstatic family_icon/icn_72_alt_gate I
    tableswitch 1 2
        icn_76_β
        icn_73_β
        default: icn_66_top
icn_71_α:
    goto icn_72_α
icn_71_β:
    goto icn_72_β
icn_71_store:
    putstatic family_icon/icn_pv_main_j J
    getstatic family_icon/icn_pv_main_j J
    goto icn_70_and_rg_0
;  VAR
icn_81_α:
    getstatic family_icon/icn_pv_main_i J
    goto icn_80_store
icn_81_β:
    goto icn_71_β
icn_80_α:
    goto icn_81_α
icn_80_β:
    goto icn_81_β
icn_80_store:
    putstatic family_icon/icn_pv_main_i J
    getstatic family_icon/icn_pv_main_i J
    goto icn_79_alt_g1
;  VAR
icn_84_α:
    getstatic family_icon/icn_pv_main_i J
    goto icn_83_rrelay
icn_84_β:
    goto icn_83_lb
;  VAR
icn_85_α:
    getstatic family_icon/icn_pv_main_j J
    goto icn_83_lrelay
icn_85_β:
    goto icn_80_α
icn_83_lrelay:
    putstatic family_icon/icn_83_relop_lc J
    goto icn_83_lstore
icn_83_rrelay:
    putstatic family_icon/icn_83_relop_rc J
    goto icn_83_check
icn_83_lb:
    goto icn_85_β
icn_83_α:
    goto icn_85_α
icn_83_β:
    goto icn_84_β
icn_83_lstore:
    goto icn_84_α
icn_83_check:
    getstatic family_icon/icn_83_relop_lc J
    getstatic family_icon/icn_83_relop_rc J
    lcmp
    ifle icn_84_β
    getstatic family_icon/icn_83_relop_rc J
    goto icn_82_and_rg_0
;  VAR
icn_88_α:
    getstatic family_icon/icn_pv_main_raw Ljava/lang/String;
    goto icn_87_sec_sr
icn_88_β:
    goto icn_83_β
;  VAR
icn_89_α:
    getstatic family_icon/icn_pv_main_i J
    goto icn_87_sec_lor
icn_89_β:
    goto icn_83_β
;  VAR
icn_90_α:
    getstatic family_icon/icn_pv_main_j J
    goto icn_87_sec_hir
icn_90_β:
    goto icn_83_β
icn_87_sec_lor:
    l2i
    istore 97
    iload 97
    ifgt icn_87_sec_lop
    iload 97
    iflt icn_87_sec_lon
icn_87_sec_loz:
    goto icn_83_β
icn_87_sec_lop:
    iload 97
    iconst_1
    isub
    putstatic family_icon/icn_87_sec_lo I
    goto icn_90_α
icn_87_sec_lon:
    getstatic family_icon/icn_87_sec_s Ljava/lang/String;
    invokevirtual java/lang/String/length()I
    iload 97
    iadd
    putstatic family_icon/icn_87_sec_lo I
    goto icn_90_α
icn_87_sec_hir:
    l2i
    istore 98
    iload 98
    ifgt icn_87_sec_hip
    iload 98
    iflt icn_87_sec_hin
icn_87_sec_hiz:
    goto icn_83_β
icn_87_sec_hip:
    iload 98
    iconst_1
    isub
    putstatic family_icon/icn_87_sec_hi I
    goto icn_87_sec_cmp
icn_87_sec_hin:
    getstatic family_icon/icn_87_sec_s Ljava/lang/String;
    invokevirtual java/lang/String/length()I
    iload 98
    iadd
    putstatic family_icon/icn_87_sec_hi I
    goto icn_87_sec_cmp
icn_87_sec_cmp:
    getstatic family_icon/icn_87_sec_lo I
    iflt icn_83_β
    getstatic family_icon/icn_87_sec_hi I
    iflt icn_83_β
    getstatic family_icon/icn_87_sec_s Ljava/lang/String;
    invokevirtual java/lang/String/length()I
    getstatic family_icon/icn_87_sec_lo I
    if_icmplt icn_83_β
    getstatic family_icon/icn_87_sec_s Ljava/lang/String;
    invokevirtual java/lang/String/length()I
    istore 99
    getstatic family_icon/icn_87_sec_hi I
    iload 99
    if_icmple icn_87_sec_hiok
    iload 99
    putstatic family_icon/icn_87_sec_hi I
icn_87_sec_hiok:
    getstatic family_icon/icn_87_sec_s Ljava/lang/String;
    getstatic family_icon/icn_87_sec_lo I
    getstatic family_icon/icn_87_sec_hi I
    invokevirtual java/lang/String/substring(II)Ljava/lang/String;
    goto icn_86_store
icn_87_α:
    goto icn_88_α
icn_87_sec_sr:
    putstatic family_icon/icn_87_sec_s Ljava/lang/String;
    goto icn_89_α
icn_87_β:
    goto icn_83_β
icn_86_α:
    goto icn_87_α
icn_86_β:
    goto icn_87_β
icn_86_store:
    putstatic family_icon/icn_pv_main_line Ljava/lang/String;
    getstatic family_icon/icn_pv_main_line Ljava/lang/String;
    goto icn_82_and_rg_1
;  STR
icn_93_α:
    ldc "|"
    goto icn_92_fa1
icn_93_β:
    goto icn_86_β
;  VAR
icn_94_α:
    getstatic family_icon/icn_pv_main_line Ljava/lang/String;
    goto icn_92_fa2
icn_94_β:
    goto icn_86_β
icn_92_α:
    goto icn_93_α
icn_92_fa1:
    putstatic family_icon/icn_find_s1_92 Ljava/lang/String;
    goto icn_94_α
icn_92_fa2:
    putstatic family_icon/icn_find_s2_92 Ljava/lang/String;
    iconst_0
    putstatic family_icon/icn_find_pos_92 I
    goto icn_92_fchk
icn_92_β:
    getstatic family_icon/icn_find_pos_92 I
    putstatic family_icon/icn_find_pos_92 I
    goto icn_92_fchk
icn_92_fchk:
    getstatic family_icon/icn_find_s1_92 Ljava/lang/String;
    getstatic family_icon/icn_find_s2_92 Ljava/lang/String;
    getstatic family_icon/icn_find_pos_92 I
    invokestatic family_icon/icn_builtin_find(Ljava/lang/String;Ljava/lang/String;I)J
    dup2
    lconst_1
    lneg
    lcmp
    ifne icn_92_fok
    pop2
    goto icn_86_β
icn_92_fok:
;  find ok: store result as new pos, push result → γ
    dup2
    l2i
    putstatic family_icon/icn_find_pos_92 I
    goto icn_91_store
icn_91_α:
    goto icn_92_α
icn_91_β:
    goto icn_92_β
icn_91_store:
    putstatic family_icon/icn_pv_main_pi J
    getstatic family_icon/icn_pv_main_pi J
    goto icn_82_and_rg_2
;  VAR
icn_98_α:
    getstatic family_icon/icn_pv_main_line Ljava/lang/String;
    goto icn_97_sec_sr
icn_98_β:
    goto icn_96_lb
;  INT
icn_99_α:
    ldc2_w 1
    goto icn_97_sec_lor
icn_99_β:
    goto icn_96_lb
;  VAR
icn_100_α:
    getstatic family_icon/icn_pv_main_pi J
    goto icn_97_sec_hir
icn_100_β:
    goto icn_96_lb
icn_97_sec_lor:
    l2i
    istore 101
    iload 101
    ifgt icn_97_sec_lop
    iload 101
    iflt icn_97_sec_lon
icn_97_sec_loz:
    goto icn_96_lb
icn_97_sec_lop:
    iload 101
    iconst_1
    isub
    putstatic family_icon/icn_97_sec_lo I
    goto icn_100_α
icn_97_sec_lon:
    getstatic family_icon/icn_97_sec_s Ljava/lang/String;
    invokevirtual java/lang/String/length()I
    iload 101
    iadd
    putstatic family_icon/icn_97_sec_lo I
    goto icn_100_α
icn_97_sec_hir:
    l2i
    istore 102
    iload 102
    ifgt icn_97_sec_hip
    iload 102
    iflt icn_97_sec_hin
icn_97_sec_hiz:
    goto icn_96_lb
icn_97_sec_hip:
    iload 102
    iconst_1
    isub
    putstatic family_icon/icn_97_sec_hi I
    goto icn_97_sec_cmp
icn_97_sec_hin:
    getstatic family_icon/icn_97_sec_s Ljava/lang/String;
    invokevirtual java/lang/String/length()I
    iload 102
    iadd
    putstatic family_icon/icn_97_sec_hi I
    goto icn_97_sec_cmp
icn_97_sec_cmp:
    getstatic family_icon/icn_97_sec_lo I
    iflt icn_96_lb
    getstatic family_icon/icn_97_sec_hi I
    iflt icn_96_lb
    getstatic family_icon/icn_97_sec_s Ljava/lang/String;
    invokevirtual java/lang/String/length()I
    getstatic family_icon/icn_97_sec_lo I
    if_icmplt icn_96_lb
    getstatic family_icon/icn_97_sec_s Ljava/lang/String;
    invokevirtual java/lang/String/length()I
    istore 103
    getstatic family_icon/icn_97_sec_hi I
    iload 103
    if_icmple icn_97_sec_hiok
    iload 103
    putstatic family_icon/icn_97_sec_hi I
icn_97_sec_hiok:
    getstatic family_icon/icn_97_sec_s Ljava/lang/String;
    getstatic family_icon/icn_97_sec_lo I
    getstatic family_icon/icn_97_sec_hi I
    invokevirtual java/lang/String/substring(II)Ljava/lang/String;
    goto icn_96_rrelay
icn_97_α:
    goto icn_98_α
icn_97_sec_sr:
    putstatic family_icon/icn_97_sec_s Ljava/lang/String;
    goto icn_99_α
icn_97_β:
    goto icn_96_lb
;  STR
icn_102_α:
    ldc " : generation "
    goto icn_101_rrelay
icn_102_β:
    goto icn_101_lb
;  VAR
icn_105_α:
    getstatic family_icon/icn_pv_main_line Ljava/lang/String;
    goto icn_104_sec_sr
icn_105_β:
    goto icn_103_lb
;  INT
icn_107_α:
    ldc2_w 1
    goto icn_106_rrelay
icn_107_β:
    goto icn_106_lb
;  VAR
icn_108_α:
    getstatic family_icon/icn_pv_main_pi J
    goto icn_106_lrelay
icn_108_β:
    goto icn_103_lb
icn_106_lrelay:
    putstatic family_icon/icn_106_binop_lc J
    goto icn_106_lstore
icn_106_rrelay:
    putstatic family_icon/icn_106_binop_rc J
    goto icn_106_compute
icn_106_lb:
    goto icn_108_β
icn_106_α:
    iconst_0
    putstatic family_icon/icn_106_binop_bf I
    goto icn_108_α
icn_106_β:
    iconst_1
    putstatic family_icon/icn_106_binop_bf I
    goto icn_108_α
icn_106_lstore:
    getstatic family_icon/icn_106_binop_bf I
    ifeq icn_107_α
    goto icn_107_β
icn_106_compute:
    getstatic family_icon/icn_106_binop_lc J
    getstatic family_icon/icn_106_binop_rc J
    ladd
    goto icn_104_sec_lor
;  INT
icn_110_α:
    ldc2_w 1
    goto icn_109_rrelay
icn_110_β:
    goto icn_109_lb
;  VAR
icn_112_α:
    getstatic family_icon/icn_pv_main_line Ljava/lang/String;
    goto icn_111_relay
icn_112_β:
    goto icn_103_lb
icn_111_α:
    goto icn_112_α
icn_111_β:
    goto icn_112_β
icn_111_relay:
    invokevirtual java/lang/String/length()I
    i2l
    goto icn_109_lrelay
icn_109_lrelay:
    putstatic family_icon/icn_109_binop_lc J
    goto icn_109_lstore
icn_109_rrelay:
    putstatic family_icon/icn_109_binop_rc J
    goto icn_109_compute
icn_109_lb:
    goto icn_111_β
icn_109_α:
    iconst_0
    putstatic family_icon/icn_109_binop_bf I
    goto icn_111_α
icn_109_β:
    goto icn_110_β
icn_109_lstore:
    getstatic family_icon/icn_109_binop_bf I
    ifeq icn_110_α
    goto icn_110_β
icn_109_compute:
    getstatic family_icon/icn_109_binop_lc J
    getstatic family_icon/icn_109_binop_rc J
    ladd
    goto icn_104_sec_hir
icn_104_sec_lor:
    l2i
    istore 106
    iload 106
    ifgt icn_104_sec_lop
    iload 106
    iflt icn_104_sec_lon
icn_104_sec_loz:
    goto icn_103_lb
icn_104_sec_lop:
    iload 106
    iconst_1
    isub
    putstatic family_icon/icn_104_sec_lo I
    goto icn_109_α
icn_104_sec_lon:
    getstatic family_icon/icn_104_sec_s Ljava/lang/String;
    invokevirtual java/lang/String/length()I
    iload 106
    iadd
    putstatic family_icon/icn_104_sec_lo I
    goto icn_109_α
icn_104_sec_hir:
    l2i
    istore 107
    iload 107
    ifgt icn_104_sec_hip
    iload 107
    iflt icn_104_sec_hin
icn_104_sec_hiz:
    goto icn_103_lb
icn_104_sec_hip:
    iload 107
    iconst_1
    isub
    putstatic family_icon/icn_104_sec_hi I
    goto icn_104_sec_cmp
icn_104_sec_hin:
    getstatic family_icon/icn_104_sec_s Ljava/lang/String;
    invokevirtual java/lang/String/length()I
    iload 107
    iadd
    putstatic family_icon/icn_104_sec_hi I
    goto icn_104_sec_cmp
icn_104_sec_cmp:
    getstatic family_icon/icn_104_sec_lo I
    iflt icn_103_lb
    getstatic family_icon/icn_104_sec_hi I
    iflt icn_103_lb
    getstatic family_icon/icn_104_sec_s Ljava/lang/String;
    invokevirtual java/lang/String/length()I
    getstatic family_icon/icn_104_sec_lo I
    if_icmplt icn_103_lb
    getstatic family_icon/icn_104_sec_s Ljava/lang/String;
    invokevirtual java/lang/String/length()I
    istore 108
    getstatic family_icon/icn_104_sec_hi I
    iload 108
    if_icmple icn_104_sec_hiok
    iload 108
    putstatic family_icon/icn_104_sec_hi I
icn_104_sec_hiok:
    getstatic family_icon/icn_104_sec_s Ljava/lang/String;
    getstatic family_icon/icn_104_sec_lo I
    getstatic family_icon/icn_104_sec_hi I
    invokevirtual java/lang/String/substring(II)Ljava/lang/String;
    goto icn_103_rrelay
icn_104_α:
    goto icn_105_α
icn_104_sec_sr:
    putstatic family_icon/icn_104_sec_s Ljava/lang/String;
    goto icn_106_α
icn_104_β:
    goto icn_103_lb
;  STR
icn_113_α:
    ldc "  "
    goto icn_103_lrelay
icn_113_β:
    goto icn_91_β
icn_103_lrelay:
    putstatic family_icon/icn_103_lc Ljava/lang/String;
    goto icn_103_lstore
icn_103_rrelay:
    putstatic family_icon/icn_103_rc Ljava/lang/String;
    goto icn_103_compute
icn_103_lb:
    goto icn_113_β
icn_103_α:
    iconst_0
    istore 105
    goto icn_113_α
icn_103_β:
    iconst_1
    istore 105
    goto icn_113_α
icn_103_lstore:
    iload 105
    ifeq icn_104_α
    goto icn_104_β
icn_103_compute:
    getstatic family_icon/icn_103_lc Ljava/lang/String;
    getstatic family_icon/icn_103_rc Ljava/lang/String;
    invokevirtual java/lang/String/concat(Ljava/lang/String;)Ljava/lang/String;
    goto icn_101_lrelay
icn_101_lrelay:
    putstatic family_icon/icn_101_lc Ljava/lang/String;
    goto icn_101_lstore
icn_101_rrelay:
    putstatic family_icon/icn_101_rc Ljava/lang/String;
    goto icn_101_compute
icn_101_lb:
    goto icn_103_β
icn_101_α:
    iconst_0
    istore 104
    goto icn_103_α
icn_101_β:
    iconst_1
    istore 104
    goto icn_103_α
icn_101_lstore:
    iload 104
    ifeq icn_102_α
    goto icn_102_β
icn_101_compute:
    getstatic family_icon/icn_101_lc Ljava/lang/String;
    getstatic family_icon/icn_101_rc Ljava/lang/String;
    invokevirtual java/lang/String/concat(Ljava/lang/String;)Ljava/lang/String;
    goto icn_96_lrelay
icn_96_lrelay:
    putstatic family_icon/icn_96_lc Ljava/lang/String;
    goto icn_96_lstore
icn_96_rrelay:
    putstatic family_icon/icn_96_rc Ljava/lang/String;
    goto icn_96_compute
icn_96_lb:
    goto icn_101_β
icn_96_α:
    iconst_0
    istore 100
    goto icn_101_α
icn_96_β:
    iconst_1
    istore 100
    goto icn_101_α
icn_96_lstore:
    iload 100
    ifeq icn_97_α
    goto icn_97_β
icn_96_compute:
    getstatic family_icon/icn_96_lc Ljava/lang/String;
    getstatic family_icon/icn_96_rc Ljava/lang/String;
    invokevirtual java/lang/String/concat(Ljava/lang/String;)Ljava/lang/String;
    goto icn_95_call
icn_95_α:
    goto icn_96_α
icn_95_β:
    goto icn_96_β
icn_95_call:
    astore 151
    getstatic java/lang/System/out Ljava/io/PrintStream;
    aload 151
    invokevirtual java/io/PrintStream/println(Ljava/lang/String;)V
    aload 151
    goto icn_79_alt_g0
    goto icn_82_α
icn_82_and_rg_0:
    putstatic family_icon/icn_82_and_drain_0 J
    goto icn_86_α
icn_82_and_rg_1:
    putstatic family_icon/icn_82_and_drain_1 Ljava/lang/String;
    goto icn_91_α
icn_82_and_rg_2:
    putstatic family_icon/icn_82_and_drain_2 J
    goto icn_95_α
icn_82_α:
    goto icn_83_α
icn_82_β:
    goto icn_95_β
icn_79_alt_g0:
    pop
    lconst_0
    putstatic family_icon/icn_79_alt_val J
    sipush 1
    putstatic family_icon/icn_79_alt_gate I
    getstatic family_icon/icn_79_alt_val J
    goto icn_70_and_rg_1
icn_79_alt_g1:
    putstatic family_icon/icn_79_alt_val J
    sipush 2
    putstatic family_icon/icn_79_alt_gate I
    getstatic family_icon/icn_79_alt_val J
    goto icn_70_and_rg_1
icn_79_α:
    iconst_0
    putstatic family_icon/icn_79_alt_gate I
    goto icn_82_α
icn_79_β:
    getstatic family_icon/icn_79_alt_gate I
    tableswitch 1 2
        icn_82_β
        icn_80_β
        default: icn_71_β
;  INT
icn_116_α:
    ldc2_w 1
    goto icn_115_rrelay
icn_116_β:
    goto icn_115_lb
;  VAR
icn_117_α:
    getstatic family_icon/icn_pv_main_j J
    goto icn_115_lrelay
icn_117_β:
    goto icn_79_β
icn_115_lrelay:
    putstatic family_icon/icn_115_binop_lc J
    goto icn_115_lstore
icn_115_rrelay:
    putstatic family_icon/icn_115_binop_rc J
    goto icn_115_compute
icn_115_lb:
    goto icn_117_β
icn_115_α:
    iconst_0
    putstatic family_icon/icn_115_binop_bf I
    goto icn_117_α
icn_115_β:
    iconst_1
    putstatic family_icon/icn_115_binop_bf I
    goto icn_117_α
icn_115_lstore:
    getstatic family_icon/icn_115_binop_bf I
    ifeq icn_116_α
    goto icn_116_β
icn_115_compute:
    getstatic family_icon/icn_115_binop_lc J
    getstatic family_icon/icn_115_binop_rc J
    ladd
    goto icn_114_store
icn_114_α:
    goto icn_115_α
icn_114_β:
    goto icn_115_β
icn_114_store:
    putstatic family_icon/icn_pv_main_i J
    getstatic family_icon/icn_pv_main_i J
    goto icn_66_wbdrain
    goto icn_70_α
icn_70_and_rg_0:
    putstatic family_icon/icn_70_and_drain_0 J
    goto icn_79_α
icn_70_and_rg_1:
    putstatic family_icon/icn_70_and_drain_1 J
    goto icn_114_α
icn_70_α:
    goto icn_71_α
icn_70_β:
    goto icn_114_β
icn_66_wbstart:
    goto icn_70_α
icn_66_wbdrain:
    pop2
icn_66_top:
    goto icn_67_α
icn_66_α:
    goto icn_67_α
icn_66_β:
    goto icn_64_α
;  INT
icn_119_α:
    ldc2_w 1
    goto icn_118_store
icn_119_β:
    goto icn_66_α
icn_118_α:
    goto icn_119_α
icn_118_β:
    goto icn_119_β
icn_118_store:
    putstatic family_icon/icn_pv_main_i J
    getstatic family_icon/icn_pv_main_i J
    goto icn_main_s28_sdrain
icn_main_s28_sdrain:
    pop2
    goto icn_66_α
;  VAR
icn_122_α:
    getstatic family_icon/icn_pv_main_raw Ljava/lang/String;
    goto icn_121_relay
icn_122_β:
    goto icn_118_α
icn_121_α:
    goto icn_122_α
icn_121_β:
    goto icn_122_β
icn_121_relay:
    invokevirtual java/lang/String/length()I
    i2l
    goto icn_120_store
icn_120_α:
    goto icn_121_α
icn_120_β:
    goto icn_121_β
icn_120_store:
    putstatic family_icon/icn_pv_main_n J
    getstatic family_icon/icn_pv_main_n J
    goto icn_main_s27_sdrain
icn_main_s27_sdrain:
    pop2
    goto icn_118_α
icn_124_α:
icn_124_β:
    aconst_null
    aconst_null
    aconst_null
    invokestatic family_prolog/query_generations([Ljava/lang/Object;Ljava/lang/Runnable;Ljava/lang/Runnable;)V
    getstatic ByrdBoxLinkage/RESULT Ljava/util/concurrent/atomic/AtomicReference;
    invokevirtual java/util/concurrent/atomic/AtomicReference/get()Ljava/lang/Object;
    putstatic family_icon/icn_retval_obj Ljava/lang/Object;
    getstatic family_icon/icn_retval_obj Ljava/lang/Object;
    checkcast java/lang/String
    goto icn_123_store
icn_123_α:
    goto icn_124_α
icn_123_β:
    goto icn_124_β
icn_123_store:
    putstatic family_icon/icn_pv_main_raw Ljava/lang/String;
    getstatic family_icon/icn_pv_main_raw Ljava/lang/String;
    goto icn_main_s26_sdrain
icn_main_s26_sdrain:
    pop
    goto icn_120_α
;  STR
icn_126_α:
    ldc "=== Generations (root=0) ==="
    goto icn_125_call
icn_126_β:
    goto icn_123_α
icn_125_α:
    goto icn_126_α
icn_125_β:
    goto icn_126_β
icn_125_call:
    astore 152
    getstatic java/lang/System/out Ljava/io/PrintStream;
    aload 152
    invokevirtual java/io/PrintStream/println(Ljava/lang/String;)V
    aload 152
    goto icn_main_s25_sdrain
icn_main_s25_sdrain:
    pop
    goto icn_123_α
;  STR
icn_128_α:
    ldc ""
    goto icn_127_call
icn_128_β:
    goto icn_125_α
icn_127_α:
    goto icn_128_α
icn_127_β:
    goto icn_128_β
icn_127_call:
    astore 153
    getstatic java/lang/System/out Ljava/io/PrintStream;
    aload 153
    invokevirtual java/io/PrintStream/println(Ljava/lang/String;)V
    aload 153
    goto icn_main_s24_sdrain
icn_main_s24_sdrain:
    pop
    goto icn_125_α
;  VAR
icn_131_α:
    getstatic family_icon/icn_pv_main_n J
    goto icn_130_rrelay
icn_131_β:
    goto icn_130_lb
;  VAR
icn_132_α:
    getstatic family_icon/icn_pv_main_i J
    goto icn_130_lrelay
icn_132_β:
    goto icn_127_α
icn_130_lrelay:
    putstatic family_icon/icn_130_relop_lc J
    goto icn_130_lstore
icn_130_rrelay:
    putstatic family_icon/icn_130_relop_rc J
    goto icn_130_check
icn_130_lb:
    goto icn_132_β
icn_130_α:
    goto icn_132_α
icn_130_β:
    goto icn_131_β
icn_130_lstore:
    goto icn_131_α
icn_130_check:
    getstatic family_icon/icn_130_relop_lc J
    getstatic family_icon/icn_130_relop_rc J
    lcmp
    ifgt icn_131_β
    getstatic family_icon/icn_130_relop_rc J
    goto icn_129_condok
icn_129_condok:
    pop2
    goto icn_129_wbstart
;  INT
icn_137_α:
    ldc2_w 1
    goto icn_136_rrelay
icn_137_β:
    goto icn_136_lb
;  VAR
icn_138_α:
    getstatic family_icon/icn_pv_main_n J
    goto icn_136_lrelay
icn_138_β:
    goto icn_129_top
icn_136_lrelay:
    putstatic family_icon/icn_136_binop_lc J
    goto icn_136_lstore
icn_136_rrelay:
    putstatic family_icon/icn_136_binop_rc J
    goto icn_136_compute
icn_136_lb:
    goto icn_138_β
icn_136_α:
    iconst_0
    putstatic family_icon/icn_136_binop_bf I
    goto icn_138_α
icn_136_β:
    iconst_1
    putstatic family_icon/icn_136_binop_bf I
    goto icn_138_α
icn_136_lstore:
    getstatic family_icon/icn_136_binop_bf I
    ifeq icn_137_α
    goto icn_137_β
icn_136_compute:
    getstatic family_icon/icn_136_binop_lc J
    getstatic family_icon/icn_136_binop_rc J
    ladd
    goto icn_135_alt_g1
;  STR
icn_140_α:
    ldc "\n"
    goto icn_139_fa1
icn_140_β:
    goto icn_136_α
;  VAR
icn_141_α:
    getstatic family_icon/icn_pv_main_raw Ljava/lang/String;
    goto icn_139_fa2
icn_141_β:
    goto icn_136_α
icn_139_α:
    goto icn_140_α
icn_139_fa1:
    putstatic family_icon/icn_find_s1_139 Ljava/lang/String;
    goto icn_141_α
icn_139_fa2:
    putstatic family_icon/icn_find_s2_139 Ljava/lang/String;
    iconst_0
    putstatic family_icon/icn_find_pos_139 I
    goto icn_139_fchk
icn_139_β:
    getstatic family_icon/icn_find_pos_139 I
    putstatic family_icon/icn_find_pos_139 I
    goto icn_139_fchk
icn_139_fchk:
    getstatic family_icon/icn_find_s1_139 Ljava/lang/String;
    getstatic family_icon/icn_find_s2_139 Ljava/lang/String;
    getstatic family_icon/icn_find_pos_139 I
    invokestatic family_icon/icn_builtin_find(Ljava/lang/String;Ljava/lang/String;I)J
    dup2
    lconst_1
    lneg
    lcmp
    ifne icn_139_fok
    pop2
    goto icn_136_α
icn_139_fok:
;  find ok: store result as new pos, push result → γ
    dup2
    l2i
    putstatic family_icon/icn_find_pos_139 I
    goto icn_135_alt_g0
icn_135_alt_g0:
    putstatic family_icon/icn_135_alt_val J
    sipush 1
    putstatic family_icon/icn_135_alt_gate I
    getstatic family_icon/icn_135_alt_val J
    goto icn_134_store
icn_135_alt_g1:
    putstatic family_icon/icn_135_alt_val J
    sipush 2
    putstatic family_icon/icn_135_alt_gate I
    getstatic family_icon/icn_135_alt_val J
    goto icn_134_store
icn_135_α:
    iconst_0
    putstatic family_icon/icn_135_alt_gate I
    goto icn_139_α
icn_135_β:
    getstatic family_icon/icn_135_alt_gate I
    tableswitch 1 2
        icn_139_β
        icn_136_β
        default: icn_129_top
icn_134_α:
    goto icn_135_α
icn_134_β:
    goto icn_135_β
icn_134_store:
    putstatic family_icon/icn_pv_main_j J
    getstatic family_icon/icn_pv_main_j J
    goto icn_133_and_rg_0
;  VAR
icn_144_α:
    getstatic family_icon/icn_pv_main_i J
    goto icn_143_store
icn_144_β:
    goto icn_134_β
icn_143_α:
    goto icn_144_α
icn_143_β:
    goto icn_144_β
icn_143_store:
    putstatic family_icon/icn_pv_main_i J
    getstatic family_icon/icn_pv_main_i J
    goto icn_142_alt_g1
;  VAR
icn_147_α:
    getstatic family_icon/icn_pv_main_i J
    goto icn_146_rrelay
icn_147_β:
    goto icn_146_lb
;  VAR
icn_148_α:
    getstatic family_icon/icn_pv_main_j J
    goto icn_146_lrelay
icn_148_β:
    goto icn_143_α
icn_146_lrelay:
    putstatic family_icon/icn_146_relop_lc J
    goto icn_146_lstore
icn_146_rrelay:
    putstatic family_icon/icn_146_relop_rc J
    goto icn_146_check
icn_146_lb:
    goto icn_148_β
icn_146_α:
    goto icn_148_α
icn_146_β:
    goto icn_147_β
icn_146_lstore:
    goto icn_147_α
icn_146_check:
    getstatic family_icon/icn_146_relop_lc J
    getstatic family_icon/icn_146_relop_rc J
    lcmp
    ifle icn_147_β
    getstatic family_icon/icn_146_relop_rc J
    goto icn_145_and_rg_0
;  VAR
icn_151_α:
    getstatic family_icon/icn_pv_main_raw Ljava/lang/String;
    goto icn_150_sec_sr
icn_151_β:
    goto icn_146_β
;  VAR
icn_152_α:
    getstatic family_icon/icn_pv_main_i J
    goto icn_150_sec_lor
icn_152_β:
    goto icn_146_β
;  VAR
icn_153_α:
    getstatic family_icon/icn_pv_main_j J
    goto icn_150_sec_hir
icn_153_β:
    goto icn_146_β
icn_150_sec_lor:
    l2i
    istore 109
    iload 109
    ifgt icn_150_sec_lop
    iload 109
    iflt icn_150_sec_lon
icn_150_sec_loz:
    goto icn_146_β
icn_150_sec_lop:
    iload 109
    iconst_1
    isub
    putstatic family_icon/icn_150_sec_lo I
    goto icn_153_α
icn_150_sec_lon:
    getstatic family_icon/icn_150_sec_s Ljava/lang/String;
    invokevirtual java/lang/String/length()I
    iload 109
    iadd
    putstatic family_icon/icn_150_sec_lo I
    goto icn_153_α
icn_150_sec_hir:
    l2i
    istore 110
    iload 110
    ifgt icn_150_sec_hip
    iload 110
    iflt icn_150_sec_hin
icn_150_sec_hiz:
    goto icn_146_β
icn_150_sec_hip:
    iload 110
    iconst_1
    isub
    putstatic family_icon/icn_150_sec_hi I
    goto icn_150_sec_cmp
icn_150_sec_hin:
    getstatic family_icon/icn_150_sec_s Ljava/lang/String;
    invokevirtual java/lang/String/length()I
    iload 110
    iadd
    putstatic family_icon/icn_150_sec_hi I
    goto icn_150_sec_cmp
icn_150_sec_cmp:
    getstatic family_icon/icn_150_sec_lo I
    iflt icn_146_β
    getstatic family_icon/icn_150_sec_hi I
    iflt icn_146_β
    getstatic family_icon/icn_150_sec_s Ljava/lang/String;
    invokevirtual java/lang/String/length()I
    getstatic family_icon/icn_150_sec_lo I
    if_icmplt icn_146_β
    getstatic family_icon/icn_150_sec_s Ljava/lang/String;
    invokevirtual java/lang/String/length()I
    istore 111
    getstatic family_icon/icn_150_sec_hi I
    iload 111
    if_icmple icn_150_sec_hiok
    iload 111
    putstatic family_icon/icn_150_sec_hi I
icn_150_sec_hiok:
    getstatic family_icon/icn_150_sec_s Ljava/lang/String;
    getstatic family_icon/icn_150_sec_lo I
    getstatic family_icon/icn_150_sec_hi I
    invokevirtual java/lang/String/substring(II)Ljava/lang/String;
    goto icn_149_store
icn_150_α:
    goto icn_151_α
icn_150_sec_sr:
    putstatic family_icon/icn_150_sec_s Ljava/lang/String;
    goto icn_152_α
icn_150_β:
    goto icn_146_β
icn_149_α:
    goto icn_150_α
icn_149_β:
    goto icn_150_β
icn_149_store:
    putstatic family_icon/icn_pv_main_line Ljava/lang/String;
    getstatic family_icon/icn_pv_main_line Ljava/lang/String;
    goto icn_145_and_rg_1
;  STR
icn_156_α:
    ldc "|"
    goto icn_155_fa1
icn_156_β:
    goto icn_149_β
;  VAR
icn_157_α:
    getstatic family_icon/icn_pv_main_line Ljava/lang/String;
    goto icn_155_fa2
icn_157_β:
    goto icn_149_β
icn_155_α:
    goto icn_156_α
icn_155_fa1:
    putstatic family_icon/icn_find_s1_155 Ljava/lang/String;
    goto icn_157_α
icn_155_fa2:
    putstatic family_icon/icn_find_s2_155 Ljava/lang/String;
    iconst_0
    putstatic family_icon/icn_find_pos_155 I
    goto icn_155_fchk
icn_155_β:
    getstatic family_icon/icn_find_pos_155 I
    putstatic family_icon/icn_find_pos_155 I
    goto icn_155_fchk
icn_155_fchk:
    getstatic family_icon/icn_find_s1_155 Ljava/lang/String;
    getstatic family_icon/icn_find_s2_155 Ljava/lang/String;
    getstatic family_icon/icn_find_pos_155 I
    invokestatic family_icon/icn_builtin_find(Ljava/lang/String;Ljava/lang/String;I)J
    dup2
    lconst_1
    lneg
    lcmp
    ifne icn_155_fok
    pop2
    goto icn_149_β
icn_155_fok:
;  find ok: store result as new pos, push result → γ
    dup2
    l2i
    putstatic family_icon/icn_find_pos_155 I
    goto icn_154_store
icn_154_α:
    goto icn_155_α
icn_154_β:
    goto icn_155_β
icn_154_store:
    putstatic family_icon/icn_pv_main_pi J
    getstatic family_icon/icn_pv_main_pi J
    goto icn_145_and_rg_2
;  VAR
icn_160_α:
    getstatic family_icon/icn_pv_main_line Ljava/lang/String;
    goto icn_159_sec_sr
icn_160_β:
    goto icn_154_β
;  INT
icn_161_α:
    ldc2_w 1
    goto icn_159_sec_lor
icn_161_β:
    goto icn_154_β
;  VAR
icn_162_α:
    getstatic family_icon/icn_pv_main_pi J
    goto icn_159_sec_hir
icn_162_β:
    goto icn_154_β
icn_159_sec_lor:
    l2i
    istore 112
    iload 112
    ifgt icn_159_sec_lop
    iload 112
    iflt icn_159_sec_lon
icn_159_sec_loz:
    goto icn_154_β
icn_159_sec_lop:
    iload 112
    iconst_1
    isub
    putstatic family_icon/icn_159_sec_lo I
    goto icn_162_α
icn_159_sec_lon:
    getstatic family_icon/icn_159_sec_s Ljava/lang/String;
    invokevirtual java/lang/String/length()I
    iload 112
    iadd
    putstatic family_icon/icn_159_sec_lo I
    goto icn_162_α
icn_159_sec_hir:
    l2i
    istore 113
    iload 113
    ifgt icn_159_sec_hip
    iload 113
    iflt icn_159_sec_hin
icn_159_sec_hiz:
    goto icn_154_β
icn_159_sec_hip:
    iload 113
    iconst_1
    isub
    putstatic family_icon/icn_159_sec_hi I
    goto icn_159_sec_cmp
icn_159_sec_hin:
    getstatic family_icon/icn_159_sec_s Ljava/lang/String;
    invokevirtual java/lang/String/length()I
    iload 113
    iadd
    putstatic family_icon/icn_159_sec_hi I
    goto icn_159_sec_cmp
icn_159_sec_cmp:
    getstatic family_icon/icn_159_sec_lo I
    iflt icn_154_β
    getstatic family_icon/icn_159_sec_hi I
    iflt icn_154_β
    getstatic family_icon/icn_159_sec_s Ljava/lang/String;
    invokevirtual java/lang/String/length()I
    getstatic family_icon/icn_159_sec_lo I
    if_icmplt icn_154_β
    getstatic family_icon/icn_159_sec_s Ljava/lang/String;
    invokevirtual java/lang/String/length()I
    istore 114
    getstatic family_icon/icn_159_sec_hi I
    iload 114
    if_icmple icn_159_sec_hiok
    iload 114
    putstatic family_icon/icn_159_sec_hi I
icn_159_sec_hiok:
    getstatic family_icon/icn_159_sec_s Ljava/lang/String;
    getstatic family_icon/icn_159_sec_lo I
    getstatic family_icon/icn_159_sec_hi I
    invokevirtual java/lang/String/substring(II)Ljava/lang/String;
    goto icn_158_store
icn_159_α:
    goto icn_160_α
icn_159_sec_sr:
    putstatic family_icon/icn_159_sec_s Ljava/lang/String;
    goto icn_161_α
icn_159_β:
    goto icn_154_β
icn_158_α:
    goto icn_159_α
icn_158_β:
    goto icn_159_β
icn_158_store:
    putstatic family_icon/icn_pv_main_a Ljava/lang/String;
    getstatic family_icon/icn_pv_main_a Ljava/lang/String;
    goto icn_145_and_rg_3
;  VAR
icn_165_α:
    getstatic family_icon/icn_pv_main_line Ljava/lang/String;
    goto icn_164_sec_sr
icn_165_β:
    goto icn_158_β
;  INT
icn_167_α:
    ldc2_w 1
    goto icn_166_rrelay
icn_167_β:
    goto icn_166_lb
;  VAR
icn_168_α:
    getstatic family_icon/icn_pv_main_pi J
    goto icn_166_lrelay
icn_168_β:
    goto icn_158_β
icn_166_lrelay:
    putstatic family_icon/icn_166_binop_lc J
    goto icn_166_lstore
icn_166_rrelay:
    putstatic family_icon/icn_166_binop_rc J
    goto icn_166_compute
icn_166_lb:
    goto icn_168_β
icn_166_α:
    iconst_0
    putstatic family_icon/icn_166_binop_bf I
    goto icn_168_α
icn_166_β:
    iconst_1
    putstatic family_icon/icn_166_binop_bf I
    goto icn_168_α
icn_166_lstore:
    getstatic family_icon/icn_166_binop_bf I
    ifeq icn_167_α
    goto icn_167_β
icn_166_compute:
    getstatic family_icon/icn_166_binop_lc J
    getstatic family_icon/icn_166_binop_rc J
    ladd
    goto icn_164_sec_lor
;  INT
icn_170_α:
    ldc2_w 1
    goto icn_169_rrelay
icn_170_β:
    goto icn_169_lb
;  VAR
icn_172_α:
    getstatic family_icon/icn_pv_main_line Ljava/lang/String;
    goto icn_171_relay
icn_172_β:
    goto icn_158_β
icn_171_α:
    goto icn_172_α
icn_171_β:
    goto icn_172_β
icn_171_relay:
    invokevirtual java/lang/String/length()I
    i2l
    goto icn_169_lrelay
icn_169_lrelay:
    putstatic family_icon/icn_169_binop_lc J
    goto icn_169_lstore
icn_169_rrelay:
    putstatic family_icon/icn_169_binop_rc J
    goto icn_169_compute
icn_169_lb:
    goto icn_171_β
icn_169_α:
    iconst_0
    putstatic family_icon/icn_169_binop_bf I
    goto icn_171_α
icn_169_β:
    goto icn_170_β
icn_169_lstore:
    getstatic family_icon/icn_169_binop_bf I
    ifeq icn_170_α
    goto icn_170_β
icn_169_compute:
    getstatic family_icon/icn_169_binop_lc J
    getstatic family_icon/icn_169_binop_rc J
    ladd
    goto icn_164_sec_hir
icn_164_sec_lor:
    l2i
    istore 115
    iload 115
    ifgt icn_164_sec_lop
    iload 115
    iflt icn_164_sec_lon
icn_164_sec_loz:
    goto icn_158_β
icn_164_sec_lop:
    iload 115
    iconst_1
    isub
    putstatic family_icon/icn_164_sec_lo I
    goto icn_169_α
icn_164_sec_lon:
    getstatic family_icon/icn_164_sec_s Ljava/lang/String;
    invokevirtual java/lang/String/length()I
    iload 115
    iadd
    putstatic family_icon/icn_164_sec_lo I
    goto icn_169_α
icn_164_sec_hir:
    l2i
    istore 116
    iload 116
    ifgt icn_164_sec_hip
    iload 116
    iflt icn_164_sec_hin
icn_164_sec_hiz:
    goto icn_158_β
icn_164_sec_hip:
    iload 116
    iconst_1
    isub
    putstatic family_icon/icn_164_sec_hi I
    goto icn_164_sec_cmp
icn_164_sec_hin:
    getstatic family_icon/icn_164_sec_s Ljava/lang/String;
    invokevirtual java/lang/String/length()I
    iload 116
    iadd
    putstatic family_icon/icn_164_sec_hi I
    goto icn_164_sec_cmp
icn_164_sec_cmp:
    getstatic family_icon/icn_164_sec_lo I
    iflt icn_158_β
    getstatic family_icon/icn_164_sec_hi I
    iflt icn_158_β
    getstatic family_icon/icn_164_sec_s Ljava/lang/String;
    invokevirtual java/lang/String/length()I
    getstatic family_icon/icn_164_sec_lo I
    if_icmplt icn_158_β
    getstatic family_icon/icn_164_sec_s Ljava/lang/String;
    invokevirtual java/lang/String/length()I
    istore 117
    getstatic family_icon/icn_164_sec_hi I
    iload 117
    if_icmple icn_164_sec_hiok
    iload 117
    putstatic family_icon/icn_164_sec_hi I
icn_164_sec_hiok:
    getstatic family_icon/icn_164_sec_s Ljava/lang/String;
    getstatic family_icon/icn_164_sec_lo I
    getstatic family_icon/icn_164_sec_hi I
    invokevirtual java/lang/String/substring(II)Ljava/lang/String;
    goto icn_163_store
icn_164_α:
    goto icn_165_α
icn_164_sec_sr:
    putstatic family_icon/icn_164_sec_s Ljava/lang/String;
    goto icn_166_α
icn_164_β:
    goto icn_158_β
icn_163_α:
    goto icn_164_α
icn_163_β:
    goto icn_164_β
icn_163_store:
    putstatic family_icon/icn_pv_main_b Ljava/lang/String;
    getstatic family_icon/icn_pv_main_b Ljava/lang/String;
    goto icn_145_and_rg_4
;  VAR
icn_176_α:
    getstatic family_icon/icn_pv_main_a Ljava/lang/String;
    goto icn_175_store
icn_176_β:
    goto icn_163_β
icn_175_α:
    goto icn_176_α
icn_175_β:
    goto icn_176_β
icn_175_store:
    putstatic family_icon/icn_pv_main_lo Ljava/lang/String;
    getstatic family_icon/icn_pv_main_lo Ljava/lang/String;
    goto icn_174_and_rg_0
;  VAR
icn_178_α:
    getstatic family_icon/icn_pv_main_b Ljava/lang/String;
    goto icn_177_store
icn_178_β:
    goto icn_175_β
icn_177_α:
    goto icn_178_α
icn_177_β:
    goto icn_178_β
icn_177_store:
    putstatic family_icon/icn_pv_main_hi Ljava/lang/String;
    getstatic family_icon/icn_pv_main_hi Ljava/lang/String;
    goto icn_173_alt_g1
    goto icn_174_α
icn_174_and_rg_0:
    putstatic family_icon/icn_174_and_drain_0 Ljava/lang/String;
    goto icn_177_α
icn_174_α:
    goto icn_175_α
icn_174_β:
    goto icn_177_β
;  VAR
icn_181_α:
    getstatic family_icon/icn_pv_main_b Ljava/lang/String;
    goto icn_180_rrelay
icn_181_β:
    goto icn_180_lb
;  VAR
icn_182_α:
    getstatic family_icon/icn_pv_main_a Ljava/lang/String;
    goto icn_180_lrelay
icn_182_β:
    goto icn_174_α
icn_180_lrelay:
    putstatic family_icon/icn_180_relop_lc Ljava/lang/String;
    goto icn_180_lstore
icn_180_rrelay:
    putstatic family_icon/icn_180_relop_rc Ljava/lang/String;
    goto icn_180_check
icn_180_lb:
    goto icn_182_β
icn_180_α:
    goto icn_182_α
icn_180_β:
    goto icn_181_β
icn_180_lstore:
    goto icn_181_α
icn_180_check:
    getstatic family_icon/icn_180_relop_lc Ljava/lang/String;
    getstatic family_icon/icn_180_relop_rc Ljava/lang/String;
    invokevirtual java/lang/String/compareTo(Ljava/lang/String;)I
    ifle icn_181_β
    getstatic family_icon/icn_180_relop_rc Ljava/lang/String;
    goto icn_179_and_rg_0
;  VAR
icn_184_α:
    getstatic family_icon/icn_pv_main_b Ljava/lang/String;
    goto icn_183_store
icn_184_β:
    goto icn_180_β
icn_183_α:
    goto icn_184_α
icn_183_β:
    goto icn_184_β
icn_183_store:
    putstatic family_icon/icn_pv_main_lo Ljava/lang/String;
    getstatic family_icon/icn_pv_main_lo Ljava/lang/String;
    goto icn_179_and_rg_1
;  VAR
icn_186_α:
    getstatic family_icon/icn_pv_main_a Ljava/lang/String;
    goto icn_185_store
icn_186_β:
    goto icn_183_β
icn_185_α:
    goto icn_186_α
icn_185_β:
    goto icn_186_β
icn_185_store:
    putstatic family_icon/icn_pv_main_hi Ljava/lang/String;
    getstatic family_icon/icn_pv_main_hi Ljava/lang/String;
    goto icn_173_alt_g0
    goto icn_179_α
icn_179_and_rg_0:
    putstatic family_icon/icn_179_and_drain_0 Ljava/lang/String;
    goto icn_183_α
icn_179_and_rg_1:
    putstatic family_icon/icn_179_and_drain_1 Ljava/lang/String;
    goto icn_185_α
icn_179_α:
    goto icn_180_α
icn_179_β:
    goto icn_185_β
icn_173_alt_g0:
    astore 154
    sipush 1
    putstatic family_icon/icn_173_alt_gate I
    aload 154
    goto icn_145_and_rg_5
icn_173_alt_g1:
    astore 155
    sipush 2
    putstatic family_icon/icn_173_alt_gate I
    aload 155
    goto icn_145_and_rg_5
icn_173_α:
    iconst_0
    putstatic family_icon/icn_173_alt_gate I
    goto icn_179_α
icn_173_β:
    getstatic family_icon/icn_173_alt_gate I
    tableswitch 1 2
        icn_179_β
        icn_174_β
        default: icn_163_β
;  VAR
icn_189_α:
    getstatic family_icon/icn_pv_main_hi Ljava/lang/String;
    goto icn_188_rrelay
icn_189_β:
    goto icn_188_lb
;  STR
icn_191_α:
    ldc "|"
    goto icn_190_rrelay
icn_191_β:
    goto icn_190_lb
;  VAR
icn_192_α:
    getstatic family_icon/icn_pv_main_lo Ljava/lang/String;
    goto icn_190_lrelay
icn_192_β:
    goto icn_173_β
icn_190_lrelay:
    putstatic family_icon/icn_190_lc Ljava/lang/String;
    goto icn_190_lstore
icn_190_rrelay:
    putstatic family_icon/icn_190_rc Ljava/lang/String;
    goto icn_190_compute
icn_190_lb:
    goto icn_192_β
icn_190_α:
    iconst_0
    istore 119
    goto icn_192_α
icn_190_β:
    iconst_1
    istore 119
    goto icn_192_α
icn_190_lstore:
    iload 119
    ifeq icn_191_α
    goto icn_191_β
icn_190_compute:
    getstatic family_icon/icn_190_lc Ljava/lang/String;
    getstatic family_icon/icn_190_rc Ljava/lang/String;
    invokevirtual java/lang/String/concat(Ljava/lang/String;)Ljava/lang/String;
    goto icn_188_lrelay
icn_188_lrelay:
    putstatic family_icon/icn_188_lc Ljava/lang/String;
    goto icn_188_lstore
icn_188_rrelay:
    putstatic family_icon/icn_188_rc Ljava/lang/String;
    goto icn_188_compute
icn_188_lb:
    goto icn_190_β
icn_188_α:
    iconst_0
    istore 118
    goto icn_190_α
icn_188_β:
    iconst_1
    istore 118
    goto icn_190_α
icn_188_lstore:
    iload 118
    ifeq icn_189_α
    goto icn_189_β
icn_188_compute:
    getstatic family_icon/icn_188_lc Ljava/lang/String;
    getstatic family_icon/icn_188_rc Ljava/lang/String;
    invokevirtual java/lang/String/concat(Ljava/lang/String;)Ljava/lang/String;
    goto icn_187_store
icn_187_α:
    goto icn_188_α
icn_187_β:
    goto icn_188_β
icn_187_store:
    putstatic family_icon/icn_pv_main_key Ljava/lang/String;
    getstatic family_icon/icn_pv_main_key Ljava/lang/String;
    goto icn_145_and_rg_6
;  STR
icn_194_α:
    ldc "0"
    goto icn_193_rrelay
icn_194_β:
    goto icn_193_lb
;  VAR
icn_196_α:
    getstatic family_icon/icn_pv_main_t Ljava/util/HashMap;
    goto icn_195_ts_tr
icn_196_β:
    goto icn_187_β
;  VAR
icn_197_α:
    getstatic family_icon/icn_pv_main_key Ljava/lang/String;
    goto icn_195_ts_kr
icn_197_β:
    goto icn_187_β
icn_195_α:
    goto icn_196_α
icn_195_β:
    goto icn_197_β
icn_195_ts_tr:
    putstatic family_icon/icn_195_ts_tbl Ljava/util/HashMap;
    goto icn_197_α
icn_195_ts_kr:
    dup
    putstatic family_icon/icn_195_ts_key Ljava/lang/String;
    lconst_0
    putstatic family_icon/icn_195_ts_kval J
    getstatic family_icon/icn_195_ts_tbl Ljava/util/HashMap;
    getstatic family_icon/icn_195_ts_key Ljava/lang/String;
    invokevirtual java/util/HashMap/get(Ljava/lang/Object;)Ljava/lang/Object;
    dup
    ifnonnull icn_195_ts_got
    pop
    getstatic family_icon/icn_pv_main_t_dflt Ljava/lang/Object;
    checkcast java/lang/String
    goto icn_193_lrelay
icn_195_ts_got:
    checkcast java/lang/String
    goto icn_193_lrelay
icn_193_lrelay:
    putstatic family_icon/icn_193_relop_lc Ljava/lang/String;
    goto icn_193_lstore
icn_193_rrelay:
    putstatic family_icon/icn_193_relop_rc Ljava/lang/String;
    goto icn_193_check
icn_193_lb:
    goto icn_195_β
icn_193_α:
    goto icn_195_α
icn_193_β:
    goto icn_194_β
icn_193_lstore:
    goto icn_194_α
icn_193_check:
    getstatic family_icon/icn_193_relop_lc Ljava/lang/String;
    getstatic family_icon/icn_193_relop_rc Ljava/lang/String;
    invokevirtual java/lang/String/compareTo(Ljava/lang/String;)I
    ifne icn_194_β
    getstatic family_icon/icn_193_relop_rc Ljava/lang/String;
    goto icn_145_and_rg_7
;  STR
icn_199_α:
    ldc "1"
    goto icn_198_tsa_vr
icn_199_β:
    goto icn_193_β
;  VAR
icn_200_α:
    getstatic family_icon/icn_pv_main_key Ljava/lang/String;
    goto icn_198_tsa_kr
icn_200_β:
    goto icn_193_β
icn_198_α:
    goto icn_199_α
icn_198_β:
    goto icn_193_β
icn_198_tsa_vr:
    dup
    putstatic family_icon/icn_198_tsa_vl Ljava/lang/String;
    goto icn_200_α
icn_198_tsa_kr:
    putstatic family_icon/icn_198_tsa_ks Ljava/lang/String;
    goto icn_198_tsa_put
icn_198_tsa_put:
    getstatic family_icon/icn_pv_main_t Ljava/util/HashMap;
    getstatic family_icon/icn_198_tsa_ks Ljava/lang/String;
    getstatic family_icon/icn_198_tsa_vl Ljava/lang/String;
    invokevirtual java/util/HashMap/put(Ljava/lang/Object;Ljava/lang/Object;)Ljava/lang/Object;
    pop
    getstatic family_icon/icn_198_tsa_vl Ljava/lang/String;
    goto icn_145_and_rg_8
;  STR
icn_203_α:
    ldc " are cousins"
    goto icn_202_rrelay
icn_203_β:
    goto icn_202_lb
;  VAR
icn_205_α:
    getstatic family_icon/icn_pv_main_b Ljava/lang/String;
    goto icn_204_rrelay
icn_205_β:
    goto icn_204_lb
;  STR
icn_207_α:
    ldc " and "
    goto icn_206_rrelay
icn_207_β:
    goto icn_206_lb
;  VAR
icn_209_α:
    getstatic family_icon/icn_pv_main_a Ljava/lang/String;
    goto icn_208_rrelay
icn_209_β:
    goto icn_208_lb
;  STR
icn_210_α:
    ldc "  "
    goto icn_208_lrelay
icn_210_β:
    goto icn_198_β
icn_208_lrelay:
    putstatic family_icon/icn_208_lc Ljava/lang/String;
    goto icn_208_lstore
icn_208_rrelay:
    putstatic family_icon/icn_208_rc Ljava/lang/String;
    goto icn_208_compute
icn_208_lb:
    goto icn_210_β
icn_208_α:
    iconst_0
    istore 123
    goto icn_210_α
icn_208_β:
    iconst_1
    istore 123
    goto icn_210_α
icn_208_lstore:
    iload 123
    ifeq icn_209_α
    goto icn_209_β
icn_208_compute:
    getstatic family_icon/icn_208_lc Ljava/lang/String;
    getstatic family_icon/icn_208_rc Ljava/lang/String;
    invokevirtual java/lang/String/concat(Ljava/lang/String;)Ljava/lang/String;
    goto icn_206_lrelay
icn_206_lrelay:
    putstatic family_icon/icn_206_lc Ljava/lang/String;
    goto icn_206_lstore
icn_206_rrelay:
    putstatic family_icon/icn_206_rc Ljava/lang/String;
    goto icn_206_compute
icn_206_lb:
    goto icn_208_β
icn_206_α:
    iconst_0
    istore 122
    goto icn_208_α
icn_206_β:
    iconst_1
    istore 122
    goto icn_208_α
icn_206_lstore:
    iload 122
    ifeq icn_207_α
    goto icn_207_β
icn_206_compute:
    getstatic family_icon/icn_206_lc Ljava/lang/String;
    getstatic family_icon/icn_206_rc Ljava/lang/String;
    invokevirtual java/lang/String/concat(Ljava/lang/String;)Ljava/lang/String;
    goto icn_204_lrelay
icn_204_lrelay:
    putstatic family_icon/icn_204_lc Ljava/lang/String;
    goto icn_204_lstore
icn_204_rrelay:
    putstatic family_icon/icn_204_rc Ljava/lang/String;
    goto icn_204_compute
icn_204_lb:
    goto icn_206_β
icn_204_α:
    iconst_0
    istore 121
    goto icn_206_α
icn_204_β:
    iconst_1
    istore 121
    goto icn_206_α
icn_204_lstore:
    iload 121
    ifeq icn_205_α
    goto icn_205_β
icn_204_compute:
    getstatic family_icon/icn_204_lc Ljava/lang/String;
    getstatic family_icon/icn_204_rc Ljava/lang/String;
    invokevirtual java/lang/String/concat(Ljava/lang/String;)Ljava/lang/String;
    goto icn_202_lrelay
icn_202_lrelay:
    putstatic family_icon/icn_202_lc Ljava/lang/String;
    goto icn_202_lstore
icn_202_rrelay:
    putstatic family_icon/icn_202_rc Ljava/lang/String;
    goto icn_202_compute
icn_202_lb:
    goto icn_204_β
icn_202_α:
    iconst_0
    istore 120
    goto icn_204_α
icn_202_β:
    iconst_1
    istore 120
    goto icn_204_α
icn_202_lstore:
    iload 120
    ifeq icn_203_α
    goto icn_203_β
icn_202_compute:
    getstatic family_icon/icn_202_lc Ljava/lang/String;
    getstatic family_icon/icn_202_rc Ljava/lang/String;
    invokevirtual java/lang/String/concat(Ljava/lang/String;)Ljava/lang/String;
    goto icn_201_call
icn_201_α:
    goto icn_202_α
icn_201_β:
    goto icn_202_β
icn_201_call:
    astore 156
    getstatic java/lang/System/out Ljava/io/PrintStream;
    aload 156
    invokevirtual java/io/PrintStream/println(Ljava/lang/String;)V
    aload 156
    goto icn_142_alt_g0
    goto icn_145_α
icn_145_and_rg_0:
    putstatic family_icon/icn_145_and_drain_0 J
    goto icn_149_α
icn_145_and_rg_1:
    putstatic family_icon/icn_145_and_drain_1 Ljava/lang/String;
    goto icn_154_α
icn_145_and_rg_2:
    putstatic family_icon/icn_145_and_drain_2 J
    goto icn_158_α
icn_145_and_rg_3:
    putstatic family_icon/icn_145_and_drain_3 Ljava/lang/String;
    goto icn_163_α
icn_145_and_rg_4:
    putstatic family_icon/icn_145_and_drain_4 Ljava/lang/String;
    goto icn_173_α
icn_145_and_rg_5:
    putstatic family_icon/icn_145_and_drain_5 Ljava/lang/String;
    goto icn_187_α
icn_145_and_rg_6:
    putstatic family_icon/icn_145_and_drain_6 Ljava/lang/String;
    goto icn_193_α
icn_145_and_rg_7:
    putstatic family_icon/icn_145_and_drain_7 Ljava/lang/String;
    goto icn_198_α
icn_145_and_rg_8:
    putstatic family_icon/icn_145_and_drain_8 Ljava/lang/String;
    goto icn_201_α
icn_145_α:
    goto icn_146_α
icn_145_β:
    goto icn_201_β
icn_142_alt_g0:
    pop
    lconst_0
    putstatic family_icon/icn_142_alt_val J
    sipush 1
    putstatic family_icon/icn_142_alt_gate I
    getstatic family_icon/icn_142_alt_val J
    goto icn_133_and_rg_1
icn_142_alt_g1:
    putstatic family_icon/icn_142_alt_val J
    sipush 2
    putstatic family_icon/icn_142_alt_gate I
    getstatic family_icon/icn_142_alt_val J
    goto icn_133_and_rg_1
icn_142_α:
    iconst_0
    putstatic family_icon/icn_142_alt_gate I
    goto icn_145_α
icn_142_β:
    getstatic family_icon/icn_142_alt_gate I
    tableswitch 1 2
        icn_145_β
        icn_143_β
        default: icn_134_β
;  INT
icn_213_α:
    ldc2_w 1
    goto icn_212_rrelay
icn_213_β:
    goto icn_212_lb
;  VAR
icn_214_α:
    getstatic family_icon/icn_pv_main_j J
    goto icn_212_lrelay
icn_214_β:
    goto icn_142_β
icn_212_lrelay:
    putstatic family_icon/icn_212_binop_lc J
    goto icn_212_lstore
icn_212_rrelay:
    putstatic family_icon/icn_212_binop_rc J
    goto icn_212_compute
icn_212_lb:
    goto icn_214_β
icn_212_α:
    iconst_0
    putstatic family_icon/icn_212_binop_bf I
    goto icn_214_α
icn_212_β:
    iconst_1
    putstatic family_icon/icn_212_binop_bf I
    goto icn_214_α
icn_212_lstore:
    getstatic family_icon/icn_212_binop_bf I
    ifeq icn_213_α
    goto icn_213_β
icn_212_compute:
    getstatic family_icon/icn_212_binop_lc J
    getstatic family_icon/icn_212_binop_rc J
    ladd
    goto icn_211_store
icn_211_α:
    goto icn_212_α
icn_211_β:
    goto icn_212_β
icn_211_store:
    putstatic family_icon/icn_pv_main_i J
    getstatic family_icon/icn_pv_main_i J
    goto icn_129_wbdrain
    goto icn_133_α
icn_133_and_rg_0:
    putstatic family_icon/icn_133_and_drain_0 J
    goto icn_142_α
icn_133_and_rg_1:
    putstatic family_icon/icn_133_and_drain_1 J
    goto icn_211_α
icn_133_α:
    goto icn_134_α
icn_133_β:
    goto icn_211_β
icn_129_wbstart:
    goto icn_133_α
icn_129_wbdrain:
    pop2
icn_129_top:
    goto icn_130_α
icn_129_α:
    goto icn_130_α
icn_129_β:
    goto icn_127_α
;  INT
icn_216_α:
    ldc2_w 1
    goto icn_215_store
icn_216_β:
    goto icn_129_α
icn_215_α:
    goto icn_216_α
icn_215_β:
    goto icn_216_β
icn_215_store:
    putstatic family_icon/icn_pv_main_i J
    getstatic family_icon/icn_pv_main_i J
    goto icn_main_s22_sdrain
icn_main_s22_sdrain:
    pop2
    goto icn_129_α
;  VAR
icn_219_α:
    getstatic family_icon/icn_pv_main_raw Ljava/lang/String;
    goto icn_218_relay
icn_219_β:
    goto icn_215_α
icn_218_α:
    goto icn_219_α
icn_218_β:
    goto icn_219_β
icn_218_relay:
    invokevirtual java/lang/String/length()I
    i2l
    goto icn_217_store
icn_217_α:
    goto icn_218_α
icn_217_β:
    goto icn_218_β
icn_217_store:
    putstatic family_icon/icn_pv_main_n J
    getstatic family_icon/icn_pv_main_n J
    goto icn_main_s21_sdrain
icn_main_s21_sdrain:
    pop2
    goto icn_215_α
;  STR
icn_222_α:
    ldc "0"
    goto icn_221_tdr
icn_222_β:
    goto icn_217_α
icn_221_α:
    goto icn_222_α
icn_221_β:
    goto icn_217_α
icn_221_tdr:
    putstatic family_icon/icn_221_tdflt Ljava/lang/Object;
    new java/util/HashMap
    dup
    invokespecial java/util/HashMap/<init>()V
    putstatic family_icon/icn_221_tbl Ljava/util/HashMap;
    getstatic family_icon/icn_221_tbl Ljava/util/HashMap;
    goto icn_220_store
icn_220_α:
    goto icn_221_α
icn_220_β:
    goto icn_221_β
icn_220_store:
    putstatic family_icon/icn_pv_main_t Ljava/util/HashMap;
    getstatic family_icon/icn_221_tdflt Ljava/lang/Object;
    putstatic family_icon/icn_pv_main_t_dflt Ljava/lang/Object;
    getstatic family_icon/icn_pv_main_t Ljava/util/HashMap;
    goto icn_main_s20_sdrain
icn_main_s20_sdrain:
    pop
    goto icn_217_α
icn_224_α:
icn_224_β:
    aconst_null
    aconst_null
    aconst_null
    invokestatic family_prolog/query_cousins([Ljava/lang/Object;Ljava/lang/Runnable;Ljava/lang/Runnable;)V
    getstatic ByrdBoxLinkage/RESULT Ljava/util/concurrent/atomic/AtomicReference;
    invokevirtual java/util/concurrent/atomic/AtomicReference/get()Ljava/lang/Object;
    putstatic family_icon/icn_retval_obj Ljava/lang/Object;
    getstatic family_icon/icn_retval_obj Ljava/lang/Object;
    checkcast java/lang/String
    goto icn_223_store
icn_223_α:
    goto icn_224_α
icn_223_β:
    goto icn_224_β
icn_223_store:
    putstatic family_icon/icn_pv_main_raw Ljava/lang/String;
    getstatic family_icon/icn_pv_main_raw Ljava/lang/String;
    goto icn_main_s19_sdrain
icn_main_s19_sdrain:
    pop
    goto icn_220_α
;  STR
icn_226_α:
    ldc "=== Cousins ==="
    goto icn_225_call
icn_226_β:
    goto icn_223_α
icn_225_α:
    goto icn_226_α
icn_225_β:
    goto icn_226_β
icn_225_call:
    astore 157
    getstatic java/lang/System/out Ljava/io/PrintStream;
    aload 157
    invokevirtual java/io/PrintStream/println(Ljava/lang/String;)V
    aload 157
    goto icn_main_s18_sdrain
icn_main_s18_sdrain:
    pop
    goto icn_223_α
;  STR
icn_228_α:
    ldc ""
    goto icn_227_call
icn_228_β:
    goto icn_225_α
icn_227_α:
    goto icn_228_α
icn_227_β:
    goto icn_228_β
icn_227_call:
    astore 158
    getstatic java/lang/System/out Ljava/io/PrintStream;
    aload 158
    invokevirtual java/io/PrintStream/println(Ljava/lang/String;)V
    aload 158
    goto icn_main_s17_sdrain
icn_main_s17_sdrain:
    pop
    goto icn_225_α
;  VAR
icn_231_α:
    getstatic family_icon/icn_pv_main_n J
    goto icn_230_rrelay
icn_231_β:
    goto icn_230_lb
;  VAR
icn_232_α:
    getstatic family_icon/icn_pv_main_i J
    goto icn_230_lrelay
icn_232_β:
    goto icn_227_α
icn_230_lrelay:
    putstatic family_icon/icn_230_relop_lc J
    goto icn_230_lstore
icn_230_rrelay:
    putstatic family_icon/icn_230_relop_rc J
    goto icn_230_check
icn_230_lb:
    goto icn_232_β
icn_230_α:
    goto icn_232_α
icn_230_β:
    goto icn_231_β
icn_230_lstore:
    goto icn_231_α
icn_230_check:
    getstatic family_icon/icn_230_relop_lc J
    getstatic family_icon/icn_230_relop_rc J
    lcmp
    ifgt icn_231_β
    getstatic family_icon/icn_230_relop_rc J
    goto icn_229_condok
icn_229_condok:
    pop2
    goto icn_229_wbstart
;  INT
icn_237_α:
    ldc2_w 1
    goto icn_236_rrelay
icn_237_β:
    goto icn_236_lb
;  VAR
icn_238_α:
    getstatic family_icon/icn_pv_main_n J
    goto icn_236_lrelay
icn_238_β:
    goto icn_229_top
icn_236_lrelay:
    putstatic family_icon/icn_236_binop_lc J
    goto icn_236_lstore
icn_236_rrelay:
    putstatic family_icon/icn_236_binop_rc J
    goto icn_236_compute
icn_236_lb:
    goto icn_238_β
icn_236_α:
    iconst_0
    putstatic family_icon/icn_236_binop_bf I
    goto icn_238_α
icn_236_β:
    iconst_1
    putstatic family_icon/icn_236_binop_bf I
    goto icn_238_α
icn_236_lstore:
    getstatic family_icon/icn_236_binop_bf I
    ifeq icn_237_α
    goto icn_237_β
icn_236_compute:
    getstatic family_icon/icn_236_binop_lc J
    getstatic family_icon/icn_236_binop_rc J
    ladd
    goto icn_235_alt_g1
;  STR
icn_240_α:
    ldc "\n"
    goto icn_239_fa1
icn_240_β:
    goto icn_236_α
;  VAR
icn_241_α:
    getstatic family_icon/icn_pv_main_raw Ljava/lang/String;
    goto icn_239_fa2
icn_241_β:
    goto icn_236_α
icn_239_α:
    goto icn_240_α
icn_239_fa1:
    putstatic family_icon/icn_find_s1_239 Ljava/lang/String;
    goto icn_241_α
icn_239_fa2:
    putstatic family_icon/icn_find_s2_239 Ljava/lang/String;
    iconst_0
    putstatic family_icon/icn_find_pos_239 I
    goto icn_239_fchk
icn_239_β:
    getstatic family_icon/icn_find_pos_239 I
    putstatic family_icon/icn_find_pos_239 I
    goto icn_239_fchk
icn_239_fchk:
    getstatic family_icon/icn_find_s1_239 Ljava/lang/String;
    getstatic family_icon/icn_find_s2_239 Ljava/lang/String;
    getstatic family_icon/icn_find_pos_239 I
    invokestatic family_icon/icn_builtin_find(Ljava/lang/String;Ljava/lang/String;I)J
    dup2
    lconst_1
    lneg
    lcmp
    ifne icn_239_fok
    pop2
    goto icn_236_α
icn_239_fok:
;  find ok: store result as new pos, push result → γ
    dup2
    l2i
    putstatic family_icon/icn_find_pos_239 I
    goto icn_235_alt_g0
icn_235_alt_g0:
    putstatic family_icon/icn_235_alt_val J
    sipush 1
    putstatic family_icon/icn_235_alt_gate I
    getstatic family_icon/icn_235_alt_val J
    goto icn_234_store
icn_235_alt_g1:
    putstatic family_icon/icn_235_alt_val J
    sipush 2
    putstatic family_icon/icn_235_alt_gate I
    getstatic family_icon/icn_235_alt_val J
    goto icn_234_store
icn_235_α:
    iconst_0
    putstatic family_icon/icn_235_alt_gate I
    goto icn_239_α
icn_235_β:
    getstatic family_icon/icn_235_alt_gate I
    tableswitch 1 2
        icn_239_β
        icn_236_β
        default: icn_229_top
icn_234_α:
    goto icn_235_α
icn_234_β:
    goto icn_235_β
icn_234_store:
    putstatic family_icon/icn_pv_main_j J
    getstatic family_icon/icn_pv_main_j J
    goto icn_233_and_rg_0
;  VAR
icn_244_α:
    getstatic family_icon/icn_pv_main_i J
    goto icn_243_store
icn_244_β:
    goto icn_234_β
icn_243_α:
    goto icn_244_α
icn_243_β:
    goto icn_244_β
icn_243_store:
    putstatic family_icon/icn_pv_main_i J
    getstatic family_icon/icn_pv_main_i J
    goto icn_242_alt_g1
;  VAR
icn_247_α:
    getstatic family_icon/icn_pv_main_i J
    goto icn_246_rrelay
icn_247_β:
    goto icn_246_lb
;  VAR
icn_248_α:
    getstatic family_icon/icn_pv_main_j J
    goto icn_246_lrelay
icn_248_β:
    goto icn_243_α
icn_246_lrelay:
    putstatic family_icon/icn_246_relop_lc J
    goto icn_246_lstore
icn_246_rrelay:
    putstatic family_icon/icn_246_relop_rc J
    goto icn_246_check
icn_246_lb:
    goto icn_248_β
icn_246_α:
    goto icn_248_α
icn_246_β:
    goto icn_247_β
icn_246_lstore:
    goto icn_247_α
icn_246_check:
    getstatic family_icon/icn_246_relop_lc J
    getstatic family_icon/icn_246_relop_rc J
    lcmp
    ifle icn_247_β
    getstatic family_icon/icn_246_relop_rc J
    goto icn_245_and_rg_0
;  VAR
icn_251_α:
    getstatic family_icon/icn_pv_main_raw Ljava/lang/String;
    goto icn_250_sec_sr
icn_251_β:
    goto icn_246_β
;  VAR
icn_252_α:
    getstatic family_icon/icn_pv_main_i J
    goto icn_250_sec_lor
icn_252_β:
    goto icn_246_β
;  VAR
icn_253_α:
    getstatic family_icon/icn_pv_main_j J
    goto icn_250_sec_hir
icn_253_β:
    goto icn_246_β
icn_250_sec_lor:
    l2i
    istore 124
    iload 124
    ifgt icn_250_sec_lop
    iload 124
    iflt icn_250_sec_lon
icn_250_sec_loz:
    goto icn_246_β
icn_250_sec_lop:
    iload 124
    iconst_1
    isub
    putstatic family_icon/icn_250_sec_lo I
    goto icn_253_α
icn_250_sec_lon:
    getstatic family_icon/icn_250_sec_s Ljava/lang/String;
    invokevirtual java/lang/String/length()I
    iload 124
    iadd
    putstatic family_icon/icn_250_sec_lo I
    goto icn_253_α
icn_250_sec_hir:
    l2i
    istore 125
    iload 125
    ifgt icn_250_sec_hip
    iload 125
    iflt icn_250_sec_hin
icn_250_sec_hiz:
    goto icn_246_β
icn_250_sec_hip:
    iload 125
    iconst_1
    isub
    putstatic family_icon/icn_250_sec_hi I
    goto icn_250_sec_cmp
icn_250_sec_hin:
    getstatic family_icon/icn_250_sec_s Ljava/lang/String;
    invokevirtual java/lang/String/length()I
    iload 125
    iadd
    putstatic family_icon/icn_250_sec_hi I
    goto icn_250_sec_cmp
icn_250_sec_cmp:
    getstatic family_icon/icn_250_sec_lo I
    iflt icn_246_β
    getstatic family_icon/icn_250_sec_hi I
    iflt icn_246_β
    getstatic family_icon/icn_250_sec_s Ljava/lang/String;
    invokevirtual java/lang/String/length()I
    getstatic family_icon/icn_250_sec_lo I
    if_icmplt icn_246_β
    getstatic family_icon/icn_250_sec_s Ljava/lang/String;
    invokevirtual java/lang/String/length()I
    istore 126
    getstatic family_icon/icn_250_sec_hi I
    iload 126
    if_icmple icn_250_sec_hiok
    iload 126
    putstatic family_icon/icn_250_sec_hi I
icn_250_sec_hiok:
    getstatic family_icon/icn_250_sec_s Ljava/lang/String;
    getstatic family_icon/icn_250_sec_lo I
    getstatic family_icon/icn_250_sec_hi I
    invokevirtual java/lang/String/substring(II)Ljava/lang/String;
    goto icn_249_store
icn_250_α:
    goto icn_251_α
icn_250_sec_sr:
    putstatic family_icon/icn_250_sec_s Ljava/lang/String;
    goto icn_252_α
icn_250_β:
    goto icn_246_β
icn_249_α:
    goto icn_250_α
icn_249_β:
    goto icn_250_β
icn_249_store:
    putstatic family_icon/icn_pv_main_line Ljava/lang/String;
    getstatic family_icon/icn_pv_main_line Ljava/lang/String;
    goto icn_245_and_rg_1
;  STR
icn_256_α:
    ldc "|"
    goto icn_255_fa1
icn_256_β:
    goto icn_249_β
;  VAR
icn_257_α:
    getstatic family_icon/icn_pv_main_line Ljava/lang/String;
    goto icn_255_fa2
icn_257_β:
    goto icn_249_β
icn_255_α:
    goto icn_256_α
icn_255_fa1:
    putstatic family_icon/icn_find_s1_255 Ljava/lang/String;
    goto icn_257_α
icn_255_fa2:
    putstatic family_icon/icn_find_s2_255 Ljava/lang/String;
    iconst_0
    putstatic family_icon/icn_find_pos_255 I
    goto icn_255_fchk
icn_255_β:
    getstatic family_icon/icn_find_pos_255 I
    putstatic family_icon/icn_find_pos_255 I
    goto icn_255_fchk
icn_255_fchk:
    getstatic family_icon/icn_find_s1_255 Ljava/lang/String;
    getstatic family_icon/icn_find_s2_255 Ljava/lang/String;
    getstatic family_icon/icn_find_pos_255 I
    invokestatic family_icon/icn_builtin_find(Ljava/lang/String;Ljava/lang/String;I)J
    dup2
    lconst_1
    lneg
    lcmp
    ifne icn_255_fok
    pop2
    goto icn_249_β
icn_255_fok:
;  find ok: store result as new pos, push result → γ
    dup2
    l2i
    putstatic family_icon/icn_find_pos_255 I
    goto icn_254_store
icn_254_α:
    goto icn_255_α
icn_254_β:
    goto icn_255_β
icn_254_store:
    putstatic family_icon/icn_pv_main_pi J
    getstatic family_icon/icn_pv_main_pi J
    goto icn_245_and_rg_2
;  VAR
icn_260_α:
    getstatic family_icon/icn_pv_main_line Ljava/lang/String;
    goto icn_259_sec_sr
icn_260_β:
    goto icn_254_β
;  INT
icn_261_α:
    ldc2_w 1
    goto icn_259_sec_lor
icn_261_β:
    goto icn_254_β
;  VAR
icn_262_α:
    getstatic family_icon/icn_pv_main_pi J
    goto icn_259_sec_hir
icn_262_β:
    goto icn_254_β
icn_259_sec_lor:
    l2i
    istore 127
    iload 127
    ifgt icn_259_sec_lop
    iload 127
    iflt icn_259_sec_lon
icn_259_sec_loz:
    goto icn_254_β
icn_259_sec_lop:
    iload 127
    iconst_1
    isub
    putstatic family_icon/icn_259_sec_lo I
    goto icn_262_α
icn_259_sec_lon:
    getstatic family_icon/icn_259_sec_s Ljava/lang/String;
    invokevirtual java/lang/String/length()I
    iload 127
    iadd
    putstatic family_icon/icn_259_sec_lo I
    goto icn_262_α
icn_259_sec_hir:
    l2i
    istore 128
    iload 128
    ifgt icn_259_sec_hip
    iload 128
    iflt icn_259_sec_hin
icn_259_sec_hiz:
    goto icn_254_β
icn_259_sec_hip:
    iload 128
    iconst_1
    isub
    putstatic family_icon/icn_259_sec_hi I
    goto icn_259_sec_cmp
icn_259_sec_hin:
    getstatic family_icon/icn_259_sec_s Ljava/lang/String;
    invokevirtual java/lang/String/length()I
    iload 128
    iadd
    putstatic family_icon/icn_259_sec_hi I
    goto icn_259_sec_cmp
icn_259_sec_cmp:
    getstatic family_icon/icn_259_sec_lo I
    iflt icn_254_β
    getstatic family_icon/icn_259_sec_hi I
    iflt icn_254_β
    getstatic family_icon/icn_259_sec_s Ljava/lang/String;
    invokevirtual java/lang/String/length()I
    getstatic family_icon/icn_259_sec_lo I
    if_icmplt icn_254_β
    getstatic family_icon/icn_259_sec_s Ljava/lang/String;
    invokevirtual java/lang/String/length()I
    istore 129
    getstatic family_icon/icn_259_sec_hi I
    iload 129
    if_icmple icn_259_sec_hiok
    iload 129
    putstatic family_icon/icn_259_sec_hi I
icn_259_sec_hiok:
    getstatic family_icon/icn_259_sec_s Ljava/lang/String;
    getstatic family_icon/icn_259_sec_lo I
    getstatic family_icon/icn_259_sec_hi I
    invokevirtual java/lang/String/substring(II)Ljava/lang/String;
    goto icn_258_store
icn_259_α:
    goto icn_260_α
icn_259_sec_sr:
    putstatic family_icon/icn_259_sec_s Ljava/lang/String;
    goto icn_261_α
icn_259_β:
    goto icn_254_β
icn_258_α:
    goto icn_259_α
icn_258_β:
    goto icn_259_β
icn_258_store:
    putstatic family_icon/icn_pv_main_a Ljava/lang/String;
    getstatic family_icon/icn_pv_main_a Ljava/lang/String;
    goto icn_245_and_rg_3
;  VAR
icn_265_α:
    getstatic family_icon/icn_pv_main_line Ljava/lang/String;
    goto icn_264_sec_sr
icn_265_β:
    goto icn_258_β
;  INT
icn_267_α:
    ldc2_w 1
    goto icn_266_rrelay
icn_267_β:
    goto icn_266_lb
;  VAR
icn_268_α:
    getstatic family_icon/icn_pv_main_pi J
    goto icn_266_lrelay
icn_268_β:
    goto icn_258_β
icn_266_lrelay:
    putstatic family_icon/icn_266_binop_lc J
    goto icn_266_lstore
icn_266_rrelay:
    putstatic family_icon/icn_266_binop_rc J
    goto icn_266_compute
icn_266_lb:
    goto icn_268_β
icn_266_α:
    iconst_0
    putstatic family_icon/icn_266_binop_bf I
    goto icn_268_α
icn_266_β:
    iconst_1
    putstatic family_icon/icn_266_binop_bf I
    goto icn_268_α
icn_266_lstore:
    getstatic family_icon/icn_266_binop_bf I
    ifeq icn_267_α
    goto icn_267_β
icn_266_compute:
    getstatic family_icon/icn_266_binop_lc J
    getstatic family_icon/icn_266_binop_rc J
    ladd
    goto icn_264_sec_lor
;  INT
icn_270_α:
    ldc2_w 1
    goto icn_269_rrelay
icn_270_β:
    goto icn_269_lb
;  VAR
icn_272_α:
    getstatic family_icon/icn_pv_main_line Ljava/lang/String;
    goto icn_271_relay
icn_272_β:
    goto icn_258_β
icn_271_α:
    goto icn_272_α
icn_271_β:
    goto icn_272_β
icn_271_relay:
    invokevirtual java/lang/String/length()I
    i2l
    goto icn_269_lrelay
icn_269_lrelay:
    putstatic family_icon/icn_269_binop_lc J
    goto icn_269_lstore
icn_269_rrelay:
    putstatic family_icon/icn_269_binop_rc J
    goto icn_269_compute
icn_269_lb:
    goto icn_271_β
icn_269_α:
    iconst_0
    putstatic family_icon/icn_269_binop_bf I
    goto icn_271_α
icn_269_β:
    goto icn_270_β
icn_269_lstore:
    getstatic family_icon/icn_269_binop_bf I
    ifeq icn_270_α
    goto icn_270_β
icn_269_compute:
    getstatic family_icon/icn_269_binop_lc J
    getstatic family_icon/icn_269_binop_rc J
    ladd
    goto icn_264_sec_hir
icn_264_sec_lor:
    l2i
    istore 130
    iload 130
    ifgt icn_264_sec_lop
    iload 130
    iflt icn_264_sec_lon
icn_264_sec_loz:
    goto icn_258_β
icn_264_sec_lop:
    iload 130
    iconst_1
    isub
    putstatic family_icon/icn_264_sec_lo I
    goto icn_269_α
icn_264_sec_lon:
    getstatic family_icon/icn_264_sec_s Ljava/lang/String;
    invokevirtual java/lang/String/length()I
    iload 130
    iadd
    putstatic family_icon/icn_264_sec_lo I
    goto icn_269_α
icn_264_sec_hir:
    l2i
    istore 131
    iload 131
    ifgt icn_264_sec_hip
    iload 131
    iflt icn_264_sec_hin
icn_264_sec_hiz:
    goto icn_258_β
icn_264_sec_hip:
    iload 131
    iconst_1
    isub
    putstatic family_icon/icn_264_sec_hi I
    goto icn_264_sec_cmp
icn_264_sec_hin:
    getstatic family_icon/icn_264_sec_s Ljava/lang/String;
    invokevirtual java/lang/String/length()I
    iload 131
    iadd
    putstatic family_icon/icn_264_sec_hi I
    goto icn_264_sec_cmp
icn_264_sec_cmp:
    getstatic family_icon/icn_264_sec_lo I
    iflt icn_258_β
    getstatic family_icon/icn_264_sec_hi I
    iflt icn_258_β
    getstatic family_icon/icn_264_sec_s Ljava/lang/String;
    invokevirtual java/lang/String/length()I
    getstatic family_icon/icn_264_sec_lo I
    if_icmplt icn_258_β
    getstatic family_icon/icn_264_sec_s Ljava/lang/String;
    invokevirtual java/lang/String/length()I
    istore 132
    getstatic family_icon/icn_264_sec_hi I
    iload 132
    if_icmple icn_264_sec_hiok
    iload 132
    putstatic family_icon/icn_264_sec_hi I
icn_264_sec_hiok:
    getstatic family_icon/icn_264_sec_s Ljava/lang/String;
    getstatic family_icon/icn_264_sec_lo I
    getstatic family_icon/icn_264_sec_hi I
    invokevirtual java/lang/String/substring(II)Ljava/lang/String;
    goto icn_263_store
icn_264_α:
    goto icn_265_α
icn_264_sec_sr:
    putstatic family_icon/icn_264_sec_s Ljava/lang/String;
    goto icn_266_α
icn_264_β:
    goto icn_258_β
icn_263_α:
    goto icn_264_α
icn_263_β:
    goto icn_264_β
icn_263_store:
    putstatic family_icon/icn_pv_main_b Ljava/lang/String;
    getstatic family_icon/icn_pv_main_b Ljava/lang/String;
    goto icn_245_and_rg_4
;  VAR
icn_276_α:
    getstatic family_icon/icn_pv_main_a Ljava/lang/String;
    goto icn_275_store
icn_276_β:
    goto icn_263_β
icn_275_α:
    goto icn_276_α
icn_275_β:
    goto icn_276_β
icn_275_store:
    putstatic family_icon/icn_pv_main_lo Ljava/lang/String;
    getstatic family_icon/icn_pv_main_lo Ljava/lang/String;
    goto icn_274_and_rg_0
;  VAR
icn_278_α:
    getstatic family_icon/icn_pv_main_b Ljava/lang/String;
    goto icn_277_store
icn_278_β:
    goto icn_275_β
icn_277_α:
    goto icn_278_α
icn_277_β:
    goto icn_278_β
icn_277_store:
    putstatic family_icon/icn_pv_main_hi Ljava/lang/String;
    getstatic family_icon/icn_pv_main_hi Ljava/lang/String;
    goto icn_273_alt_g1
    goto icn_274_α
icn_274_and_rg_0:
    putstatic family_icon/icn_274_and_drain_0 Ljava/lang/String;
    goto icn_277_α
icn_274_α:
    goto icn_275_α
icn_274_β:
    goto icn_277_β
;  VAR
icn_281_α:
    getstatic family_icon/icn_pv_main_b Ljava/lang/String;
    goto icn_280_rrelay
icn_281_β:
    goto icn_280_lb
;  VAR
icn_282_α:
    getstatic family_icon/icn_pv_main_a Ljava/lang/String;
    goto icn_280_lrelay
icn_282_β:
    goto icn_274_α
icn_280_lrelay:
    putstatic family_icon/icn_280_relop_lc Ljava/lang/String;
    goto icn_280_lstore
icn_280_rrelay:
    putstatic family_icon/icn_280_relop_rc Ljava/lang/String;
    goto icn_280_check
icn_280_lb:
    goto icn_282_β
icn_280_α:
    goto icn_282_α
icn_280_β:
    goto icn_281_β
icn_280_lstore:
    goto icn_281_α
icn_280_check:
    getstatic family_icon/icn_280_relop_lc Ljava/lang/String;
    getstatic family_icon/icn_280_relop_rc Ljava/lang/String;
    invokevirtual java/lang/String/compareTo(Ljava/lang/String;)I
    ifle icn_281_β
    getstatic family_icon/icn_280_relop_rc Ljava/lang/String;
    goto icn_279_and_rg_0
;  VAR
icn_284_α:
    getstatic family_icon/icn_pv_main_b Ljava/lang/String;
    goto icn_283_store
icn_284_β:
    goto icn_280_β
icn_283_α:
    goto icn_284_α
icn_283_β:
    goto icn_284_β
icn_283_store:
    putstatic family_icon/icn_pv_main_lo Ljava/lang/String;
    getstatic family_icon/icn_pv_main_lo Ljava/lang/String;
    goto icn_279_and_rg_1
;  VAR
icn_286_α:
    getstatic family_icon/icn_pv_main_a Ljava/lang/String;
    goto icn_285_store
icn_286_β:
    goto icn_283_β
icn_285_α:
    goto icn_286_α
icn_285_β:
    goto icn_286_β
icn_285_store:
    putstatic family_icon/icn_pv_main_hi Ljava/lang/String;
    getstatic family_icon/icn_pv_main_hi Ljava/lang/String;
    goto icn_273_alt_g0
    goto icn_279_α
icn_279_and_rg_0:
    putstatic family_icon/icn_279_and_drain_0 Ljava/lang/String;
    goto icn_283_α
icn_279_and_rg_1:
    putstatic family_icon/icn_279_and_drain_1 Ljava/lang/String;
    goto icn_285_α
icn_279_α:
    goto icn_280_α
icn_279_β:
    goto icn_285_β
icn_273_alt_g0:
    astore 159
    sipush 1
    putstatic family_icon/icn_273_alt_gate I
    aload 159
    goto icn_245_and_rg_5
icn_273_alt_g1:
    astore 160
    sipush 2
    putstatic family_icon/icn_273_alt_gate I
    aload 160
    goto icn_245_and_rg_5
icn_273_α:
    iconst_0
    putstatic family_icon/icn_273_alt_gate I
    goto icn_279_α
icn_273_β:
    getstatic family_icon/icn_273_alt_gate I
    tableswitch 1 2
        icn_279_β
        icn_274_β
        default: icn_263_β
;  VAR
icn_289_α:
    getstatic family_icon/icn_pv_main_hi Ljava/lang/String;
    goto icn_288_rrelay
icn_289_β:
    goto icn_288_lb
;  STR
icn_291_α:
    ldc "|"
    goto icn_290_rrelay
icn_291_β:
    goto icn_290_lb
;  VAR
icn_292_α:
    getstatic family_icon/icn_pv_main_lo Ljava/lang/String;
    goto icn_290_lrelay
icn_292_β:
    goto icn_273_β
icn_290_lrelay:
    putstatic family_icon/icn_290_lc Ljava/lang/String;
    goto icn_290_lstore
icn_290_rrelay:
    putstatic family_icon/icn_290_rc Ljava/lang/String;
    goto icn_290_compute
icn_290_lb:
    goto icn_292_β
icn_290_α:
    iconst_0
    istore 134
    goto icn_292_α
icn_290_β:
    iconst_1
    istore 134
    goto icn_292_α
icn_290_lstore:
    iload 134
    ifeq icn_291_α
    goto icn_291_β
icn_290_compute:
    getstatic family_icon/icn_290_lc Ljava/lang/String;
    getstatic family_icon/icn_290_rc Ljava/lang/String;
    invokevirtual java/lang/String/concat(Ljava/lang/String;)Ljava/lang/String;
    goto icn_288_lrelay
icn_288_lrelay:
    putstatic family_icon/icn_288_lc Ljava/lang/String;
    goto icn_288_lstore
icn_288_rrelay:
    putstatic family_icon/icn_288_rc Ljava/lang/String;
    goto icn_288_compute
icn_288_lb:
    goto icn_290_β
icn_288_α:
    iconst_0
    istore 133
    goto icn_290_α
icn_288_β:
    iconst_1
    istore 133
    goto icn_290_α
icn_288_lstore:
    iload 133
    ifeq icn_289_α
    goto icn_289_β
icn_288_compute:
    getstatic family_icon/icn_288_lc Ljava/lang/String;
    getstatic family_icon/icn_288_rc Ljava/lang/String;
    invokevirtual java/lang/String/concat(Ljava/lang/String;)Ljava/lang/String;
    goto icn_287_store
icn_287_α:
    goto icn_288_α
icn_287_β:
    goto icn_288_β
icn_287_store:
    putstatic family_icon/icn_pv_main_key Ljava/lang/String;
    getstatic family_icon/icn_pv_main_key Ljava/lang/String;
    goto icn_245_and_rg_6
;  STR
icn_294_α:
    ldc "0"
    goto icn_293_rrelay
icn_294_β:
    goto icn_293_lb
;  VAR
icn_296_α:
    getstatic family_icon/icn_pv_main_t Ljava/util/HashMap;
    goto icn_295_ts_tr
icn_296_β:
    goto icn_287_β
;  VAR
icn_297_α:
    getstatic family_icon/icn_pv_main_key Ljava/lang/String;
    goto icn_295_ts_kr
icn_297_β:
    goto icn_287_β
icn_295_α:
    goto icn_296_α
icn_295_β:
    goto icn_297_β
icn_295_ts_tr:
    putstatic family_icon/icn_295_ts_tbl Ljava/util/HashMap;
    goto icn_297_α
icn_295_ts_kr:
    dup
    putstatic family_icon/icn_295_ts_key Ljava/lang/String;
    lconst_0
    putstatic family_icon/icn_295_ts_kval J
    getstatic family_icon/icn_295_ts_tbl Ljava/util/HashMap;
    getstatic family_icon/icn_295_ts_key Ljava/lang/String;
    invokevirtual java/util/HashMap/get(Ljava/lang/Object;)Ljava/lang/Object;
    dup
    ifnonnull icn_295_ts_got
    pop
    getstatic family_icon/icn_pv_main_t_dflt Ljava/lang/Object;
    checkcast java/lang/String
    goto icn_293_lrelay
icn_295_ts_got:
    checkcast java/lang/String
    goto icn_293_lrelay
icn_293_lrelay:
    putstatic family_icon/icn_293_relop_lc Ljava/lang/String;
    goto icn_293_lstore
icn_293_rrelay:
    putstatic family_icon/icn_293_relop_rc Ljava/lang/String;
    goto icn_293_check
icn_293_lb:
    goto icn_295_β
icn_293_α:
    goto icn_295_α
icn_293_β:
    goto icn_294_β
icn_293_lstore:
    goto icn_294_α
icn_293_check:
    getstatic family_icon/icn_293_relop_lc Ljava/lang/String;
    getstatic family_icon/icn_293_relop_rc Ljava/lang/String;
    invokevirtual java/lang/String/compareTo(Ljava/lang/String;)I
    ifne icn_294_β
    getstatic family_icon/icn_293_relop_rc Ljava/lang/String;
    goto icn_245_and_rg_7
;  STR
icn_299_α:
    ldc "1"
    goto icn_298_tsa_vr
icn_299_β:
    goto icn_293_β
;  VAR
icn_300_α:
    getstatic family_icon/icn_pv_main_key Ljava/lang/String;
    goto icn_298_tsa_kr
icn_300_β:
    goto icn_293_β
icn_298_α:
    goto icn_299_α
icn_298_β:
    goto icn_293_β
icn_298_tsa_vr:
    dup
    putstatic family_icon/icn_298_tsa_vl Ljava/lang/String;
    goto icn_300_α
icn_298_tsa_kr:
    putstatic family_icon/icn_298_tsa_ks Ljava/lang/String;
    goto icn_298_tsa_put
icn_298_tsa_put:
    getstatic family_icon/icn_pv_main_t Ljava/util/HashMap;
    getstatic family_icon/icn_298_tsa_ks Ljava/lang/String;
    getstatic family_icon/icn_298_tsa_vl Ljava/lang/String;
    invokevirtual java/util/HashMap/put(Ljava/lang/Object;Ljava/lang/Object;)Ljava/lang/Object;
    pop
    getstatic family_icon/icn_298_tsa_vl Ljava/lang/String;
    goto icn_245_and_rg_8
;  STR
icn_303_α:
    ldc " are siblings"
    goto icn_302_rrelay
icn_303_β:
    goto icn_302_lb
;  VAR
icn_305_α:
    getstatic family_icon/icn_pv_main_b Ljava/lang/String;
    goto icn_304_rrelay
icn_305_β:
    goto icn_304_lb
;  STR
icn_307_α:
    ldc " and "
    goto icn_306_rrelay
icn_307_β:
    goto icn_306_lb
;  VAR
icn_309_α:
    getstatic family_icon/icn_pv_main_a Ljava/lang/String;
    goto icn_308_rrelay
icn_309_β:
    goto icn_308_lb
;  STR
icn_310_α:
    ldc "  "
    goto icn_308_lrelay
icn_310_β:
    goto icn_298_β
icn_308_lrelay:
    putstatic family_icon/icn_308_lc Ljava/lang/String;
    goto icn_308_lstore
icn_308_rrelay:
    putstatic family_icon/icn_308_rc Ljava/lang/String;
    goto icn_308_compute
icn_308_lb:
    goto icn_310_β
icn_308_α:
    iconst_0
    istore 138
    goto icn_310_α
icn_308_β:
    iconst_1
    istore 138
    goto icn_310_α
icn_308_lstore:
    iload 138
    ifeq icn_309_α
    goto icn_309_β
icn_308_compute:
    getstatic family_icon/icn_308_lc Ljava/lang/String;
    getstatic family_icon/icn_308_rc Ljava/lang/String;
    invokevirtual java/lang/String/concat(Ljava/lang/String;)Ljava/lang/String;
    goto icn_306_lrelay
icn_306_lrelay:
    putstatic family_icon/icn_306_lc Ljava/lang/String;
    goto icn_306_lstore
icn_306_rrelay:
    putstatic family_icon/icn_306_rc Ljava/lang/String;
    goto icn_306_compute
icn_306_lb:
    goto icn_308_β
icn_306_α:
    iconst_0
    istore 137
    goto icn_308_α
icn_306_β:
    iconst_1
    istore 137
    goto icn_308_α
icn_306_lstore:
    iload 137
    ifeq icn_307_α
    goto icn_307_β
icn_306_compute:
    getstatic family_icon/icn_306_lc Ljava/lang/String;
    getstatic family_icon/icn_306_rc Ljava/lang/String;
    invokevirtual java/lang/String/concat(Ljava/lang/String;)Ljava/lang/String;
    goto icn_304_lrelay
icn_304_lrelay:
    putstatic family_icon/icn_304_lc Ljava/lang/String;
    goto icn_304_lstore
icn_304_rrelay:
    putstatic family_icon/icn_304_rc Ljava/lang/String;
    goto icn_304_compute
icn_304_lb:
    goto icn_306_β
icn_304_α:
    iconst_0
    istore 136
    goto icn_306_α
icn_304_β:
    iconst_1
    istore 136
    goto icn_306_α
icn_304_lstore:
    iload 136
    ifeq icn_305_α
    goto icn_305_β
icn_304_compute:
    getstatic family_icon/icn_304_lc Ljava/lang/String;
    getstatic family_icon/icn_304_rc Ljava/lang/String;
    invokevirtual java/lang/String/concat(Ljava/lang/String;)Ljava/lang/String;
    goto icn_302_lrelay
icn_302_lrelay:
    putstatic family_icon/icn_302_lc Ljava/lang/String;
    goto icn_302_lstore
icn_302_rrelay:
    putstatic family_icon/icn_302_rc Ljava/lang/String;
    goto icn_302_compute
icn_302_lb:
    goto icn_304_β
icn_302_α:
    iconst_0
    istore 135
    goto icn_304_α
icn_302_β:
    iconst_1
    istore 135
    goto icn_304_α
icn_302_lstore:
    iload 135
    ifeq icn_303_α
    goto icn_303_β
icn_302_compute:
    getstatic family_icon/icn_302_lc Ljava/lang/String;
    getstatic family_icon/icn_302_rc Ljava/lang/String;
    invokevirtual java/lang/String/concat(Ljava/lang/String;)Ljava/lang/String;
    goto icn_301_call
icn_301_α:
    goto icn_302_α
icn_301_β:
    goto icn_302_β
icn_301_call:
    astore 161
    getstatic java/lang/System/out Ljava/io/PrintStream;
    aload 161
    invokevirtual java/io/PrintStream/println(Ljava/lang/String;)V
    aload 161
    goto icn_242_alt_g0
    goto icn_245_α
icn_245_and_rg_0:
    putstatic family_icon/icn_245_and_drain_0 J
    goto icn_249_α
icn_245_and_rg_1:
    putstatic family_icon/icn_245_and_drain_1 Ljava/lang/String;
    goto icn_254_α
icn_245_and_rg_2:
    putstatic family_icon/icn_245_and_drain_2 J
    goto icn_258_α
icn_245_and_rg_3:
    putstatic family_icon/icn_245_and_drain_3 Ljava/lang/String;
    goto icn_263_α
icn_245_and_rg_4:
    putstatic family_icon/icn_245_and_drain_4 Ljava/lang/String;
    goto icn_273_α
icn_245_and_rg_5:
    putstatic family_icon/icn_245_and_drain_5 Ljava/lang/String;
    goto icn_287_α
icn_245_and_rg_6:
    putstatic family_icon/icn_245_and_drain_6 Ljava/lang/String;
    goto icn_293_α
icn_245_and_rg_7:
    putstatic family_icon/icn_245_and_drain_7 Ljava/lang/String;
    goto icn_298_α
icn_245_and_rg_8:
    putstatic family_icon/icn_245_and_drain_8 Ljava/lang/String;
    goto icn_301_α
icn_245_α:
    goto icn_246_α
icn_245_β:
    goto icn_301_β
icn_242_alt_g0:
    pop
    lconst_0
    putstatic family_icon/icn_242_alt_val J
    sipush 1
    putstatic family_icon/icn_242_alt_gate I
    getstatic family_icon/icn_242_alt_val J
    goto icn_233_and_rg_1
icn_242_alt_g1:
    putstatic family_icon/icn_242_alt_val J
    sipush 2
    putstatic family_icon/icn_242_alt_gate I
    getstatic family_icon/icn_242_alt_val J
    goto icn_233_and_rg_1
icn_242_α:
    iconst_0
    putstatic family_icon/icn_242_alt_gate I
    goto icn_245_α
icn_242_β:
    getstatic family_icon/icn_242_alt_gate I
    tableswitch 1 2
        icn_245_β
        icn_243_β
        default: icn_234_β
;  INT
icn_313_α:
    ldc2_w 1
    goto icn_312_rrelay
icn_313_β:
    goto icn_312_lb
;  VAR
icn_314_α:
    getstatic family_icon/icn_pv_main_j J
    goto icn_312_lrelay
icn_314_β:
    goto icn_242_β
icn_312_lrelay:
    putstatic family_icon/icn_312_binop_lc J
    goto icn_312_lstore
icn_312_rrelay:
    putstatic family_icon/icn_312_binop_rc J
    goto icn_312_compute
icn_312_lb:
    goto icn_314_β
icn_312_α:
    iconst_0
    putstatic family_icon/icn_312_binop_bf I
    goto icn_314_α
icn_312_β:
    iconst_1
    putstatic family_icon/icn_312_binop_bf I
    goto icn_314_α
icn_312_lstore:
    getstatic family_icon/icn_312_binop_bf I
    ifeq icn_313_α
    goto icn_313_β
icn_312_compute:
    getstatic family_icon/icn_312_binop_lc J
    getstatic family_icon/icn_312_binop_rc J
    ladd
    goto icn_311_store
icn_311_α:
    goto icn_312_α
icn_311_β:
    goto icn_312_β
icn_311_store:
    putstatic family_icon/icn_pv_main_i J
    getstatic family_icon/icn_pv_main_i J
    goto icn_229_wbdrain
    goto icn_233_α
icn_233_and_rg_0:
    putstatic family_icon/icn_233_and_drain_0 J
    goto icn_242_α
icn_233_and_rg_1:
    putstatic family_icon/icn_233_and_drain_1 J
    goto icn_311_α
icn_233_α:
    goto icn_234_α
icn_233_β:
    goto icn_311_β
icn_229_wbstart:
    goto icn_233_α
icn_229_wbdrain:
    pop2
icn_229_top:
    goto icn_230_α
icn_229_α:
    goto icn_230_α
icn_229_β:
    goto icn_227_α
;  INT
icn_316_α:
    ldc2_w 1
    goto icn_315_store
icn_316_β:
    goto icn_229_α
icn_315_α:
    goto icn_316_α
icn_315_β:
    goto icn_316_β
icn_315_store:
    putstatic family_icon/icn_pv_main_i J
    getstatic family_icon/icn_pv_main_i J
    goto icn_main_s15_sdrain
icn_main_s15_sdrain:
    pop2
    goto icn_229_α
;  VAR
icn_319_α:
    getstatic family_icon/icn_pv_main_raw Ljava/lang/String;
    goto icn_318_relay
icn_319_β:
    goto icn_315_α
icn_318_α:
    goto icn_319_α
icn_318_β:
    goto icn_319_β
icn_318_relay:
    invokevirtual java/lang/String/length()I
    i2l
    goto icn_317_store
icn_317_α:
    goto icn_318_α
icn_317_β:
    goto icn_318_β
icn_317_store:
    putstatic family_icon/icn_pv_main_n J
    getstatic family_icon/icn_pv_main_n J
    goto icn_main_s14_sdrain
icn_main_s14_sdrain:
    pop2
    goto icn_315_α
;  STR
icn_322_α:
    ldc "0"
    goto icn_321_tdr
icn_322_β:
    goto icn_317_α
icn_321_α:
    goto icn_322_α
icn_321_β:
    goto icn_317_α
icn_321_tdr:
    putstatic family_icon/icn_321_tdflt Ljava/lang/Object;
    new java/util/HashMap
    dup
    invokespecial java/util/HashMap/<init>()V
    putstatic family_icon/icn_321_tbl Ljava/util/HashMap;
    getstatic family_icon/icn_321_tbl Ljava/util/HashMap;
    goto icn_320_store
icn_320_α:
    goto icn_321_α
icn_320_β:
    goto icn_321_β
icn_320_store:
    putstatic family_icon/icn_pv_main_t Ljava/util/HashMap;
    getstatic family_icon/icn_321_tdflt Ljava/lang/Object;
    putstatic family_icon/icn_pv_main_t_dflt Ljava/lang/Object;
    getstatic family_icon/icn_pv_main_t Ljava/util/HashMap;
    goto icn_main_s13_sdrain
icn_main_s13_sdrain:
    pop
    goto icn_317_α
icn_324_α:
icn_324_β:
    aconst_null
    aconst_null
    aconst_null
    invokestatic family_prolog/query_siblings([Ljava/lang/Object;Ljava/lang/Runnable;Ljava/lang/Runnable;)V
    getstatic ByrdBoxLinkage/RESULT Ljava/util/concurrent/atomic/AtomicReference;
    invokevirtual java/util/concurrent/atomic/AtomicReference/get()Ljava/lang/Object;
    putstatic family_icon/icn_retval_obj Ljava/lang/Object;
    getstatic family_icon/icn_retval_obj Ljava/lang/Object;
    checkcast java/lang/String
    goto icn_323_store
icn_323_α:
    goto icn_324_α
icn_323_β:
    goto icn_324_β
icn_323_store:
    putstatic family_icon/icn_pv_main_raw Ljava/lang/String;
    getstatic family_icon/icn_pv_main_raw Ljava/lang/String;
    goto icn_main_s12_sdrain
icn_main_s12_sdrain:
    pop
    goto icn_320_α
;  STR
icn_326_α:
    ldc "=== Siblings ==="
    goto icn_325_call
icn_326_β:
    goto icn_323_α
icn_325_α:
    goto icn_326_α
icn_325_β:
    goto icn_326_β
icn_325_call:
    astore 162
    getstatic java/lang/System/out Ljava/io/PrintStream;
    aload 162
    invokevirtual java/io/PrintStream/println(Ljava/lang/String;)V
    aload 162
    goto icn_main_s11_sdrain
icn_main_s11_sdrain:
    pop
    goto icn_323_α
;  STR
icn_328_α:
    ldc ""
    goto icn_327_call
icn_328_β:
    goto icn_325_α
icn_327_α:
    goto icn_328_α
icn_327_β:
    goto icn_328_β
icn_327_call:
    astore 163
    getstatic java/lang/System/out Ljava/io/PrintStream;
    aload 163
    invokevirtual java/io/PrintStream/println(Ljava/lang/String;)V
    aload 163
    goto icn_main_s10_sdrain
icn_main_s10_sdrain:
    pop
    goto icn_325_α
;  VAR
icn_331_α:
    getstatic family_icon/icn_pv_main_n J
    goto icn_330_rrelay
icn_331_β:
    goto icn_330_lb
;  VAR
icn_332_α:
    getstatic family_icon/icn_pv_main_i J
    goto icn_330_lrelay
icn_332_β:
    goto icn_327_α
icn_330_lrelay:
    putstatic family_icon/icn_330_relop_lc J
    goto icn_330_lstore
icn_330_rrelay:
    putstatic family_icon/icn_330_relop_rc J
    goto icn_330_check
icn_330_lb:
    goto icn_332_β
icn_330_α:
    goto icn_332_α
icn_330_β:
    goto icn_331_β
icn_330_lstore:
    goto icn_331_α
icn_330_check:
    getstatic family_icon/icn_330_relop_lc J
    getstatic family_icon/icn_330_relop_rc J
    lcmp
    ifgt icn_331_β
    getstatic family_icon/icn_330_relop_rc J
    goto icn_329_condok
icn_329_condok:
    pop2
    goto icn_329_wbstart
;  INT
icn_337_α:
    ldc2_w 1
    goto icn_336_rrelay
icn_337_β:
    goto icn_336_lb
;  VAR
icn_338_α:
    getstatic family_icon/icn_pv_main_n J
    goto icn_336_lrelay
icn_338_β:
    goto icn_329_top
icn_336_lrelay:
    putstatic family_icon/icn_336_binop_lc J
    goto icn_336_lstore
icn_336_rrelay:
    putstatic family_icon/icn_336_binop_rc J
    goto icn_336_compute
icn_336_lb:
    goto icn_338_β
icn_336_α:
    iconst_0
    putstatic family_icon/icn_336_binop_bf I
    goto icn_338_α
icn_336_β:
    iconst_1
    putstatic family_icon/icn_336_binop_bf I
    goto icn_338_α
icn_336_lstore:
    getstatic family_icon/icn_336_binop_bf I
    ifeq icn_337_α
    goto icn_337_β
icn_336_compute:
    getstatic family_icon/icn_336_binop_lc J
    getstatic family_icon/icn_336_binop_rc J
    ladd
    goto icn_335_alt_g1
;  STR
icn_340_α:
    ldc "\n"
    goto icn_339_fa1
icn_340_β:
    goto icn_336_α
;  VAR
icn_341_α:
    getstatic family_icon/icn_pv_main_raw Ljava/lang/String;
    goto icn_339_fa2
icn_341_β:
    goto icn_336_α
icn_339_α:
    goto icn_340_α
icn_339_fa1:
    putstatic family_icon/icn_find_s1_339 Ljava/lang/String;
    goto icn_341_α
icn_339_fa2:
    putstatic family_icon/icn_find_s2_339 Ljava/lang/String;
    iconst_0
    putstatic family_icon/icn_find_pos_339 I
    goto icn_339_fchk
icn_339_β:
    getstatic family_icon/icn_find_pos_339 I
    putstatic family_icon/icn_find_pos_339 I
    goto icn_339_fchk
icn_339_fchk:
    getstatic family_icon/icn_find_s1_339 Ljava/lang/String;
    getstatic family_icon/icn_find_s2_339 Ljava/lang/String;
    getstatic family_icon/icn_find_pos_339 I
    invokestatic family_icon/icn_builtin_find(Ljava/lang/String;Ljava/lang/String;I)J
    dup2
    lconst_1
    lneg
    lcmp
    ifne icn_339_fok
    pop2
    goto icn_336_α
icn_339_fok:
;  find ok: store result as new pos, push result → γ
    dup2
    l2i
    putstatic family_icon/icn_find_pos_339 I
    goto icn_335_alt_g0
icn_335_alt_g0:
    putstatic family_icon/icn_335_alt_val J
    sipush 1
    putstatic family_icon/icn_335_alt_gate I
    getstatic family_icon/icn_335_alt_val J
    goto icn_334_store
icn_335_alt_g1:
    putstatic family_icon/icn_335_alt_val J
    sipush 2
    putstatic family_icon/icn_335_alt_gate I
    getstatic family_icon/icn_335_alt_val J
    goto icn_334_store
icn_335_α:
    iconst_0
    putstatic family_icon/icn_335_alt_gate I
    goto icn_339_α
icn_335_β:
    getstatic family_icon/icn_335_alt_gate I
    tableswitch 1 2
        icn_339_β
        icn_336_β
        default: icn_329_top
icn_334_α:
    goto icn_335_α
icn_334_β:
    goto icn_335_β
icn_334_store:
    putstatic family_icon/icn_pv_main_j J
    getstatic family_icon/icn_pv_main_j J
    goto icn_333_and_rg_0
;  VAR
icn_344_α:
    getstatic family_icon/icn_pv_main_i J
    goto icn_343_store
icn_344_β:
    goto icn_334_β
icn_343_α:
    goto icn_344_α
icn_343_β:
    goto icn_344_β
icn_343_store:
    putstatic family_icon/icn_pv_main_i J
    getstatic family_icon/icn_pv_main_i J
    goto icn_342_alt_g1
;  VAR
icn_347_α:
    getstatic family_icon/icn_pv_main_i J
    goto icn_346_rrelay
icn_347_β:
    goto icn_346_lb
;  VAR
icn_348_α:
    getstatic family_icon/icn_pv_main_j J
    goto icn_346_lrelay
icn_348_β:
    goto icn_343_α
icn_346_lrelay:
    putstatic family_icon/icn_346_relop_lc J
    goto icn_346_lstore
icn_346_rrelay:
    putstatic family_icon/icn_346_relop_rc J
    goto icn_346_check
icn_346_lb:
    goto icn_348_β
icn_346_α:
    goto icn_348_α
icn_346_β:
    goto icn_347_β
icn_346_lstore:
    goto icn_347_α
icn_346_check:
    getstatic family_icon/icn_346_relop_lc J
    getstatic family_icon/icn_346_relop_rc J
    lcmp
    ifle icn_347_β
    getstatic family_icon/icn_346_relop_rc J
    goto icn_345_and_rg_0
;  VAR
icn_352_α:
    getstatic family_icon/icn_pv_main_raw Ljava/lang/String;
    goto icn_351_sec_sr
icn_352_β:
    goto icn_350_lb
;  VAR
icn_353_α:
    getstatic family_icon/icn_pv_main_i J
    goto icn_351_sec_lor
icn_353_β:
    goto icn_350_lb
;  VAR
icn_354_α:
    getstatic family_icon/icn_pv_main_j J
    goto icn_351_sec_hir
icn_354_β:
    goto icn_350_lb
icn_351_sec_lor:
    l2i
    istore 140
    iload 140
    ifgt icn_351_sec_lop
    iload 140
    iflt icn_351_sec_lon
icn_351_sec_loz:
    goto icn_350_lb
icn_351_sec_lop:
    iload 140
    iconst_1
    isub
    putstatic family_icon/icn_351_sec_lo I
    goto icn_354_α
icn_351_sec_lon:
    getstatic family_icon/icn_351_sec_s Ljava/lang/String;
    invokevirtual java/lang/String/length()I
    iload 140
    iadd
    putstatic family_icon/icn_351_sec_lo I
    goto icn_354_α
icn_351_sec_hir:
    l2i
    istore 141
    iload 141
    ifgt icn_351_sec_hip
    iload 141
    iflt icn_351_sec_hin
icn_351_sec_hiz:
    goto icn_350_lb
icn_351_sec_hip:
    iload 141
    iconst_1
    isub
    putstatic family_icon/icn_351_sec_hi I
    goto icn_351_sec_cmp
icn_351_sec_hin:
    getstatic family_icon/icn_351_sec_s Ljava/lang/String;
    invokevirtual java/lang/String/length()I
    iload 141
    iadd
    putstatic family_icon/icn_351_sec_hi I
    goto icn_351_sec_cmp
icn_351_sec_cmp:
    getstatic family_icon/icn_351_sec_lo I
    iflt icn_350_lb
    getstatic family_icon/icn_351_sec_hi I
    iflt icn_350_lb
    getstatic family_icon/icn_351_sec_s Ljava/lang/String;
    invokevirtual java/lang/String/length()I
    getstatic family_icon/icn_351_sec_lo I
    if_icmplt icn_350_lb
    getstatic family_icon/icn_351_sec_s Ljava/lang/String;
    invokevirtual java/lang/String/length()I
    istore 142
    getstatic family_icon/icn_351_sec_hi I
    iload 142
    if_icmple icn_351_sec_hiok
    iload 142
    putstatic family_icon/icn_351_sec_hi I
icn_351_sec_hiok:
    getstatic family_icon/icn_351_sec_s Ljava/lang/String;
    getstatic family_icon/icn_351_sec_lo I
    getstatic family_icon/icn_351_sec_hi I
    invokevirtual java/lang/String/substring(II)Ljava/lang/String;
    goto icn_350_rrelay
icn_351_α:
    goto icn_352_α
icn_351_sec_sr:
    putstatic family_icon/icn_351_sec_s Ljava/lang/String;
    goto icn_353_α
icn_351_β:
    goto icn_350_lb
;  STR
icn_355_α:
    ldc "  "
    goto icn_350_lrelay
icn_355_β:
    goto icn_346_β
icn_350_lrelay:
    putstatic family_icon/icn_350_lc Ljava/lang/String;
    goto icn_350_lstore
icn_350_rrelay:
    putstatic family_icon/icn_350_rc Ljava/lang/String;
    goto icn_350_compute
icn_350_lb:
    goto icn_355_β
icn_350_α:
    iconst_0
    istore 139
    goto icn_355_α
icn_350_β:
    iconst_1
    istore 139
    goto icn_355_α
icn_350_lstore:
    iload 139
    ifeq icn_351_α
    goto icn_351_β
icn_350_compute:
    getstatic family_icon/icn_350_lc Ljava/lang/String;
    getstatic family_icon/icn_350_rc Ljava/lang/String;
    invokevirtual java/lang/String/concat(Ljava/lang/String;)Ljava/lang/String;
    goto icn_349_call
icn_349_α:
    goto icn_350_α
icn_349_β:
    goto icn_350_β
icn_349_call:
    astore 164
    getstatic java/lang/System/out Ljava/io/PrintStream;
    aload 164
    invokevirtual java/io/PrintStream/println(Ljava/lang/String;)V
    aload 164
    goto icn_342_alt_g0
    goto icn_345_α
icn_345_and_rg_0:
    putstatic family_icon/icn_345_and_drain_0 J
    goto icn_349_α
icn_345_α:
    goto icn_346_α
icn_345_β:
    goto icn_349_β
icn_342_alt_g0:
    pop
    lconst_0
    putstatic family_icon/icn_342_alt_val J
    sipush 1
    putstatic family_icon/icn_342_alt_gate I
    getstatic family_icon/icn_342_alt_val J
    goto icn_333_and_rg_1
icn_342_alt_g1:
    putstatic family_icon/icn_342_alt_val J
    sipush 2
    putstatic family_icon/icn_342_alt_gate I
    getstatic family_icon/icn_342_alt_val J
    goto icn_333_and_rg_1
icn_342_α:
    iconst_0
    putstatic family_icon/icn_342_alt_gate I
    goto icn_345_α
icn_342_β:
    getstatic family_icon/icn_342_alt_gate I
    tableswitch 1 2
        icn_345_β
        icn_343_β
        default: icn_334_β
;  INT
icn_358_α:
    ldc2_w 1
    goto icn_357_rrelay
icn_358_β:
    goto icn_357_lb
;  VAR
icn_359_α:
    getstatic family_icon/icn_pv_main_j J
    goto icn_357_lrelay
icn_359_β:
    goto icn_342_β
icn_357_lrelay:
    putstatic family_icon/icn_357_binop_lc J
    goto icn_357_lstore
icn_357_rrelay:
    putstatic family_icon/icn_357_binop_rc J
    goto icn_357_compute
icn_357_lb:
    goto icn_359_β
icn_357_α:
    iconst_0
    putstatic family_icon/icn_357_binop_bf I
    goto icn_359_α
icn_357_β:
    iconst_1
    putstatic family_icon/icn_357_binop_bf I
    goto icn_359_α
icn_357_lstore:
    getstatic family_icon/icn_357_binop_bf I
    ifeq icn_358_α
    goto icn_358_β
icn_357_compute:
    getstatic family_icon/icn_357_binop_lc J
    getstatic family_icon/icn_357_binop_rc J
    ladd
    goto icn_356_store
icn_356_α:
    goto icn_357_α
icn_356_β:
    goto icn_357_β
icn_356_store:
    putstatic family_icon/icn_pv_main_i J
    getstatic family_icon/icn_pv_main_i J
    goto icn_329_wbdrain
    goto icn_333_α
icn_333_and_rg_0:
    putstatic family_icon/icn_333_and_drain_0 J
    goto icn_342_α
icn_333_and_rg_1:
    putstatic family_icon/icn_333_and_drain_1 J
    goto icn_356_α
icn_333_α:
    goto icn_334_α
icn_333_β:
    goto icn_356_β
icn_329_wbstart:
    goto icn_333_α
icn_329_wbdrain:
    pop2
icn_329_top:
    goto icn_330_α
icn_329_α:
    goto icn_330_α
icn_329_β:
    goto icn_327_α
;  INT
icn_361_α:
    ldc2_w 1
    goto icn_360_store
icn_361_β:
    goto icn_329_α
icn_360_α:
    goto icn_361_α
icn_360_β:
    goto icn_361_β
icn_360_store:
    putstatic family_icon/icn_pv_main_i J
    getstatic family_icon/icn_pv_main_i J
    goto icn_main_s8_sdrain
icn_main_s8_sdrain:
    pop2
    goto icn_329_α
;  VAR
icn_364_α:
    getstatic family_icon/icn_pv_main_raw Ljava/lang/String;
    goto icn_363_relay
icn_364_β:
    goto icn_360_α
icn_363_α:
    goto icn_364_α
icn_363_β:
    goto icn_364_β
icn_363_relay:
    invokevirtual java/lang/String/length()I
    i2l
    goto icn_362_store
icn_362_α:
    goto icn_363_α
icn_362_β:
    goto icn_363_β
icn_362_store:
    putstatic family_icon/icn_pv_main_n J
    getstatic family_icon/icn_pv_main_n J
    goto icn_main_s7_sdrain
icn_main_s7_sdrain:
    pop2
    goto icn_360_α
icn_366_α:
icn_366_β:
    aconst_null
    aconst_null
    aconst_null
    invokestatic family_prolog/query_grandparents([Ljava/lang/Object;Ljava/lang/Runnable;Ljava/lang/Runnable;)V
    getstatic ByrdBoxLinkage/RESULT Ljava/util/concurrent/atomic/AtomicReference;
    invokevirtual java/util/concurrent/atomic/AtomicReference/get()Ljava/lang/Object;
    putstatic family_icon/icn_retval_obj Ljava/lang/Object;
    getstatic family_icon/icn_retval_obj Ljava/lang/Object;
    checkcast java/lang/String
    goto icn_365_store
icn_365_α:
    goto icn_366_α
icn_365_β:
    goto icn_366_β
icn_365_store:
    putstatic family_icon/icn_pv_main_raw Ljava/lang/String;
    getstatic family_icon/icn_pv_main_raw Ljava/lang/String;
    goto icn_main_s6_sdrain
icn_main_s6_sdrain:
    pop
    goto icn_362_α
;  STR
icn_368_α:
    ldc "=== Grandparent relationships ==="
    goto icn_367_call
icn_368_β:
    goto icn_365_α
icn_367_α:
    goto icn_368_α
icn_367_β:
    goto icn_368_β
icn_367_call:
    astore 165
    getstatic java/lang/System/out Ljava/io/PrintStream;
    aload 165
    invokevirtual java/io/PrintStream/println(Ljava/lang/String;)V
    aload 165
    goto icn_main_s5_sdrain
icn_main_s5_sdrain:
    pop
    goto icn_365_α
;  STR
icn_370_α:
    ldc ""
    goto icn_369_call
icn_370_β:
    goto icn_367_α
icn_369_α:
    goto icn_370_α
icn_369_β:
    goto icn_370_β
icn_369_call:
    astore 166
    getstatic java/lang/System/out Ljava/io/PrintStream;
    aload 166
    invokevirtual java/io/PrintStream/println(Ljava/lang/String;)V
    aload 166
    goto icn_main_s4_sdrain
icn_main_s4_sdrain:
    pop
    goto icn_367_α
;  STR
icn_373_α:
    ldc " family members."
    goto icn_372_rrelay
icn_373_β:
    goto icn_372_lb
;  VAR
icn_375_α:
    getstatic family_icon/icn_pv_main_cnt Ljava/lang/String;
    goto icn_374_rrelay
icn_375_β:
    goto icn_374_lb
;  STR
icn_376_α:
    ldc "Parsed "
    goto icn_374_lrelay
icn_376_β:
    goto icn_369_α
icn_374_lrelay:
    putstatic family_icon/icn_374_lc Ljava/lang/String;
    goto icn_374_lstore
icn_374_rrelay:
    putstatic family_icon/icn_374_rc Ljava/lang/String;
    goto icn_374_compute
icn_374_lb:
    goto icn_376_β
icn_374_α:
    iconst_0
    istore 144
    goto icn_376_α
icn_374_β:
    iconst_1
    istore 144
    goto icn_376_α
icn_374_lstore:
    iload 144
    ifeq icn_375_α
    goto icn_375_β
icn_374_compute:
    getstatic family_icon/icn_374_lc Ljava/lang/String;
    getstatic family_icon/icn_374_rc Ljava/lang/String;
    invokevirtual java/lang/String/concat(Ljava/lang/String;)Ljava/lang/String;
    goto icn_372_lrelay
icn_372_lrelay:
    putstatic family_icon/icn_372_lc Ljava/lang/String;
    goto icn_372_lstore
icn_372_rrelay:
    putstatic family_icon/icn_372_rc Ljava/lang/String;
    goto icn_372_compute
icn_372_lb:
    goto icn_374_β
icn_372_α:
    iconst_0
    istore 143
    goto icn_374_α
icn_372_β:
    iconst_1
    istore 143
    goto icn_374_α
icn_372_lstore:
    iload 143
    ifeq icn_373_α
    goto icn_373_β
icn_372_compute:
    getstatic family_icon/icn_372_lc Ljava/lang/String;
    getstatic family_icon/icn_372_rc Ljava/lang/String;
    invokevirtual java/lang/String/concat(Ljava/lang/String;)Ljava/lang/String;
    goto icn_371_call
icn_371_α:
    goto icn_372_α
icn_371_β:
    goto icn_372_β
icn_371_call:
    astore 167
    getstatic java/lang/System/out Ljava/io/PrintStream;
    aload 167
    invokevirtual java/io/PrintStream/println(Ljava/lang/String;)V
    aload 167
    goto icn_main_s3_sdrain
icn_main_s3_sdrain:
    pop
    goto icn_369_α
icn_378_α:
icn_378_β:
    aconst_null
    aconst_null
    aconst_null
    invokestatic family_prolog/query_count([Ljava/lang/Object;Ljava/lang/Runnable;Ljava/lang/Runnable;)V
    getstatic ByrdBoxLinkage/RESULT Ljava/util/concurrent/atomic/AtomicReference;
    invokevirtual java/util/concurrent/atomic/AtomicReference/get()Ljava/lang/Object;
    putstatic family_icon/icn_retval_obj Ljava/lang/Object;
    getstatic family_icon/icn_retval_obj Ljava/lang/Object;
    checkcast java/lang/String
    goto icn_377_store
icn_377_α:
    goto icn_378_α
icn_377_β:
    goto icn_378_β
icn_377_store:
    putstatic family_icon/icn_pv_main_cnt Ljava/lang/String;
    getstatic family_icon/icn_pv_main_cnt Ljava/lang/String;
    goto icn_main_s2_sdrain
icn_main_s2_sdrain:
    pop
    goto icn_371_α
icn_379_α:
icn_379_β:
    aconst_null
    aconst_null
    aconst_null
    invokestatic family_snobol4/parse_csv([Ljava/lang/Object;Ljava/lang/Runnable;Ljava/lang/Runnable;)V
    getstatic ByrdBoxLinkage/RESULT Ljava/util/concurrent/atomic/AtomicReference;
    invokevirtual java/util/concurrent/atomic/AtomicReference/get()Ljava/lang/Object;
    putstatic family_icon/icn_retval_obj Ljava/lang/Object;
    getstatic family_icon/icn_retval_obj Ljava/lang/Object;
    checkcast java/lang/String
    goto icn_main_s1_sdrain
icn_main_s1_sdrain:
    pop
    goto icn_377_α
icn_main_done:
    return
.end method

