; Generated by scrip-cc -jvm
; Assemble: java -jar jasmin.jar <file>.j -d .
; Run:      java <classname>

.class public coverage_sno_nodes
.super java/lang/Object

; Runtime fields
.field static sno_stdout Ljava/io/PrintStream;
.field static sno_input_br Ljava/io/BufferedReader;
.field static sno_kw_TRIM I
.field static sno_kw_ANCHOR I
.field static sno_kw_STNO I
.field static sno_kw_STLIMIT I
.field static sno_kw_STCOUNT I
.field static sno_vars Ljava/util/HashMap;
.field static sno_arrays Ljava/util/HashMap;
.field static sno_data_types Ljava/util/HashMap;
.field static sno_mon_fd Ljava/io/OutputStream;
.field static sno_mon_go_fd Ljava/io/InputStream;
.field static sno_var_X Ljava/lang/String;
.field static sno_var_A Ljava/lang/String;
.field static sno_var_N Ljava/lang/String;
.field static sno_var_S Ljava/lang/String;
.field static sno_var_CAPT Ljava/lang/String;
.field static sno_var_S2 Ljava/lang/String;
.field static sno_var_S3 Ljava/lang/String;
.field static sno_var_S4 Ljava/lang/String;
.field static sno_var_PART Ljava/lang/String;
.field static sno_var_S5 Ljava/lang/String;
.field static sno_var_TRAIL Ljava/lang/String;
.field static sno_var_S6 Ljava/lang/String;
.field static sno_var_POS1 Ljava/lang/String;
.field static sno_var_S7 Ljava/lang/String;
.field static sno_var_ARB Ljava/lang/String;
.field static sno_var_S8 Ljava/lang/String;
.field static sno_var_PAT Ljava/lang/String;
.field static sno_var_S9 Ljava/lang/String;
.field static sno_var_VNAME Ljava/lang/String;
.field static sno_var_T Ljava/lang/String;
.field static sno_var_UNDEF Ljava/lang/String;

.method static <clinit>()V
    .limit stack 67
    .limit locals 0
    getstatic       java/lang/System/out Ljava/io/PrintStream;
    putstatic       coverage_sno_nodes/sno_stdout Ljava/io/PrintStream;
    iconst_0
    putstatic       coverage_sno_nodes/sno_kw_TRIM I
    iconst_0
    putstatic       coverage_sno_nodes/sno_kw_ANCHOR I
    iconst_0
    putstatic       coverage_sno_nodes/sno_kw_STNO I
    iconst_m1
    putstatic       coverage_sno_nodes/sno_kw_STLIMIT I
    iconst_0
    putstatic       coverage_sno_nodes/sno_kw_STCOUNT I
    new java/util/HashMap
    dup
    invokespecial java/util/HashMap/<init>()V
    putstatic       coverage_sno_nodes/sno_vars Ljava/util/HashMap;
    new java/util/HashMap
    dup
    invokespecial java/util/HashMap/<init>()V
    putstatic       coverage_sno_nodes/sno_arrays Ljava/util/HashMap;
    new java/util/HashMap
    dup
    invokespecial java/util/HashMap/<init>()V
    putstatic       coverage_sno_nodes/sno_data_types Ljava/util/HashMap;
    ldc             ""
    putstatic       coverage_sno_nodes/sno_var_X Ljava/lang/String;
    getstatic       coverage_sno_nodes/sno_vars Ljava/util/HashMap;
    ldc             "X"
    ldc             ""
    invokevirtual   java/util/HashMap/put(Ljava/lang/Object;Ljava/lang/Object;)Ljava/lang/Object;
    pop
    ldc             ""
    putstatic       coverage_sno_nodes/sno_var_A Ljava/lang/String;
    getstatic       coverage_sno_nodes/sno_vars Ljava/util/HashMap;
    ldc             "A"
    ldc             ""
    invokevirtual   java/util/HashMap/put(Ljava/lang/Object;Ljava/lang/Object;)Ljava/lang/Object;
    pop
    ldc             ""
    putstatic       coverage_sno_nodes/sno_var_N Ljava/lang/String;
    getstatic       coverage_sno_nodes/sno_vars Ljava/util/HashMap;
    ldc             "N"
    ldc             ""
    invokevirtual   java/util/HashMap/put(Ljava/lang/Object;Ljava/lang/Object;)Ljava/lang/Object;
    pop
    ldc             ""
    putstatic       coverage_sno_nodes/sno_var_S Ljava/lang/String;
    getstatic       coverage_sno_nodes/sno_vars Ljava/util/HashMap;
    ldc             "S"
    ldc             ""
    invokevirtual   java/util/HashMap/put(Ljava/lang/Object;Ljava/lang/Object;)Ljava/lang/Object;
    pop
    ldc             ""
    putstatic       coverage_sno_nodes/sno_var_CAPT Ljava/lang/String;
    getstatic       coverage_sno_nodes/sno_vars Ljava/util/HashMap;
    ldc             "CAPT"
    ldc             ""
    invokevirtual   java/util/HashMap/put(Ljava/lang/Object;Ljava/lang/Object;)Ljava/lang/Object;
    pop
    ldc             ""
    putstatic       coverage_sno_nodes/sno_var_S2 Ljava/lang/String;
    getstatic       coverage_sno_nodes/sno_vars Ljava/util/HashMap;
    ldc             "S2"
    ldc             ""
    invokevirtual   java/util/HashMap/put(Ljava/lang/Object;Ljava/lang/Object;)Ljava/lang/Object;
    pop
    ldc             ""
    putstatic       coverage_sno_nodes/sno_var_S3 Ljava/lang/String;
    getstatic       coverage_sno_nodes/sno_vars Ljava/util/HashMap;
    ldc             "S3"
    ldc             ""
    invokevirtual   java/util/HashMap/put(Ljava/lang/Object;Ljava/lang/Object;)Ljava/lang/Object;
    pop
    ldc             ""
    putstatic       coverage_sno_nodes/sno_var_S4 Ljava/lang/String;
    getstatic       coverage_sno_nodes/sno_vars Ljava/util/HashMap;
    ldc             "S4"
    ldc             ""
    invokevirtual   java/util/HashMap/put(Ljava/lang/Object;Ljava/lang/Object;)Ljava/lang/Object;
    pop
    ldc             ""
    putstatic       coverage_sno_nodes/sno_var_PART Ljava/lang/String;
    getstatic       coverage_sno_nodes/sno_vars Ljava/util/HashMap;
    ldc             "PART"
    ldc             ""
    invokevirtual   java/util/HashMap/put(Ljava/lang/Object;Ljava/lang/Object;)Ljava/lang/Object;
    pop
    ldc             ""
    putstatic       coverage_sno_nodes/sno_var_S5 Ljava/lang/String;
    getstatic       coverage_sno_nodes/sno_vars Ljava/util/HashMap;
    ldc             "S5"
    ldc             ""
    invokevirtual   java/util/HashMap/put(Ljava/lang/Object;Ljava/lang/Object;)Ljava/lang/Object;
    pop
    ldc             ""
    putstatic       coverage_sno_nodes/sno_var_TRAIL Ljava/lang/String;
    getstatic       coverage_sno_nodes/sno_vars Ljava/util/HashMap;
    ldc             "TRAIL"
    ldc             ""
    invokevirtual   java/util/HashMap/put(Ljava/lang/Object;Ljava/lang/Object;)Ljava/lang/Object;
    pop
    ldc             ""
    putstatic       coverage_sno_nodes/sno_var_S6 Ljava/lang/String;
    getstatic       coverage_sno_nodes/sno_vars Ljava/util/HashMap;
    ldc             "S6"
    ldc             ""
    invokevirtual   java/util/HashMap/put(Ljava/lang/Object;Ljava/lang/Object;)Ljava/lang/Object;
    pop
    ldc             ""
    putstatic       coverage_sno_nodes/sno_var_POS1 Ljava/lang/String;
    getstatic       coverage_sno_nodes/sno_vars Ljava/util/HashMap;
    ldc             "POS1"
    ldc             ""
    invokevirtual   java/util/HashMap/put(Ljava/lang/Object;Ljava/lang/Object;)Ljava/lang/Object;
    pop
    ldc             ""
    putstatic       coverage_sno_nodes/sno_var_S7 Ljava/lang/String;
    getstatic       coverage_sno_nodes/sno_vars Ljava/util/HashMap;
    ldc             "S7"
    ldc             ""
    invokevirtual   java/util/HashMap/put(Ljava/lang/Object;Ljava/lang/Object;)Ljava/lang/Object;
    pop
    ldc             ""
    putstatic       coverage_sno_nodes/sno_var_ARB Ljava/lang/String;
    getstatic       coverage_sno_nodes/sno_vars Ljava/util/HashMap;
    ldc             "ARB"
    ldc             ""
    invokevirtual   java/util/HashMap/put(Ljava/lang/Object;Ljava/lang/Object;)Ljava/lang/Object;
    pop
    ldc             ""
    putstatic       coverage_sno_nodes/sno_var_S8 Ljava/lang/String;
    getstatic       coverage_sno_nodes/sno_vars Ljava/util/HashMap;
    ldc             "S8"
    ldc             ""
    invokevirtual   java/util/HashMap/put(Ljava/lang/Object;Ljava/lang/Object;)Ljava/lang/Object;
    pop
    ldc             ""
    putstatic       coverage_sno_nodes/sno_var_PAT Ljava/lang/String;
    getstatic       coverage_sno_nodes/sno_vars Ljava/util/HashMap;
    ldc             "PAT"
    ldc             ""
    invokevirtual   java/util/HashMap/put(Ljava/lang/Object;Ljava/lang/Object;)Ljava/lang/Object;
    pop
    ldc             ""
    putstatic       coverage_sno_nodes/sno_var_S9 Ljava/lang/String;
    getstatic       coverage_sno_nodes/sno_vars Ljava/util/HashMap;
    ldc             "S9"
    ldc             ""
    invokevirtual   java/util/HashMap/put(Ljava/lang/Object;Ljava/lang/Object;)Ljava/lang/Object;
    pop
    ldc             ""
    putstatic       coverage_sno_nodes/sno_var_VNAME Ljava/lang/String;
    getstatic       coverage_sno_nodes/sno_vars Ljava/util/HashMap;
    ldc             "VNAME"
    ldc             ""
    invokevirtual   java/util/HashMap/put(Ljava/lang/Object;Ljava/lang/Object;)Ljava/lang/Object;
    pop
    ldc             ""
    putstatic       coverage_sno_nodes/sno_var_T Ljava/lang/String;
    getstatic       coverage_sno_nodes/sno_vars Ljava/util/HashMap;
    ldc             "T"
    ldc             ""
    invokevirtual   java/util/HashMap/put(Ljava/lang/Object;Ljava/lang/Object;)Ljava/lang/Object;
    pop
    ldc             ""
    putstatic       coverage_sno_nodes/sno_var_UNDEF Ljava/lang/String;
    getstatic       coverage_sno_nodes/sno_vars Ljava/util/HashMap;
    ldc             "UNDEF"
    ldc             ""
    invokevirtual   java/util/HashMap/put(Ljava/lang/Object;Ljava/lang/Object;)Ljava/lang/Object;
    pop
    return
.end method

.method static sno_mon_init()V
    .limit stack 6
    .limit locals 2
    ldc "MONITOR_READY_PIPE"
    invokestatic java/lang/System/getenv(Ljava/lang/String;)Ljava/lang/String;
    astore_0
    aload_0
    ifnull Lsmi_done
    aload_0
    invokevirtual java/lang/String/isEmpty()Z
    ifne Lsmi_done
    new java/io/FileOutputStream
    dup
    aload_0
    iconst_1
    invokespecial java/io/FileOutputStream/<init>(Ljava/lang/String;Z)V
    putstatic coverage_sno_nodes/sno_mon_fd Ljava/io/OutputStream;
    ldc "MONITOR_GO_PIPE"
    invokestatic java/lang/System/getenv(Ljava/lang/String;)Ljava/lang/String;
    astore_1
    aload_1
    ifnull Lsmi_done
    aload_1
    invokevirtual java/lang/String/isEmpty()Z
    ifne Lsmi_done
    new java/io/FileInputStream
    dup
    aload_1
    invokespecial java/io/FileInputStream/<init>(Ljava/lang/String;)V
    putstatic coverage_sno_nodes/sno_mon_go_fd Ljava/io/InputStream;
Lsmi_done:
    return
.end method

.method public static main([Ljava/lang/String;)V
    .limit stack 16
    .limit locals 32

    invokestatic coverage_sno_nodes/sno_mon_init()V
    getstatic coverage_sno_nodes/sno_kw_STNO I
    iconst_1
    iadd
    putstatic coverage_sno_nodes/sno_kw_STNO I
    invokestatic coverage_sno_nodes/sno_stcount_tick()V
    ldc "hello"
    dup
    ifnonnull Lout_ok_0
    pop
    goto Lout_fail_0
Lout_ok_0:
    getstatic coverage_sno_nodes/sno_stdout Ljava/io/PrintStream;
    swap
    invokevirtual java/io/PrintStream/println(Ljava/lang/String;)V
Lout_fail_0:
    getstatic coverage_sno_nodes/sno_kw_STNO I
    iconst_1
    iadd
    putstatic coverage_sno_nodes/sno_kw_STNO I
    invokestatic coverage_sno_nodes/sno_stcount_tick()V
    ldc "42"
    dup
    ifnonnull Lout_ok_1
    pop
    goto Lout_fail_1
Lout_ok_1:
    getstatic coverage_sno_nodes/sno_stdout Ljava/io/PrintStream;
    swap
    invokevirtual java/io/PrintStream/println(Ljava/lang/String;)V
Lout_fail_1:
    getstatic coverage_sno_nodes/sno_kw_STNO I
    iconst_1
    iadd
    putstatic coverage_sno_nodes/sno_kw_STNO I
    invokestatic coverage_sno_nodes/sno_stcount_tick()V
    ldc "1.5"
    dup
    ifnonnull Lvar_ok_0
    pop
    goto Lvar_fail_0
Lvar_ok_0:
    ldc "X"
    swap
    invokestatic coverage_sno_nodes/sno_var_put(Ljava/lang/String;Ljava/lang/String;)V
Lvar_fail_0:
    getstatic coverage_sno_nodes/sno_kw_STNO I
    iconst_1
    iadd
    putstatic coverage_sno_nodes/sno_kw_STNO I
    invokestatic coverage_sno_nodes/sno_stcount_tick()V
    ldc "X"
    invokestatic coverage_sno_nodes/sno_indr_get(Ljava/lang/String;)Ljava/lang/String;
    dup
    ifnonnull Lout_ok_2
    pop
    goto Lout_fail_2
Lout_ok_2:
    getstatic coverage_sno_nodes/sno_stdout Ljava/io/PrintStream;
    swap
    invokevirtual java/io/PrintStream/println(Ljava/lang/String;)V
Lout_fail_2:
    getstatic coverage_sno_nodes/sno_kw_STNO I
    iconst_1
    iadd
    putstatic coverage_sno_nodes/sno_kw_STNO I
    invokestatic coverage_sno_nodes/sno_stcount_tick()V
    ldc "world"
    dup
    ifnonnull Lvar_ok_1
    pop
    goto Lvar_fail_1
Lvar_ok_1:
    ldc "A"
    swap
    invokestatic coverage_sno_nodes/sno_var_put(Ljava/lang/String;Ljava/lang/String;)V
Lvar_fail_1:
    getstatic coverage_sno_nodes/sno_kw_STNO I
    iconst_1
    iadd
    putstatic coverage_sno_nodes/sno_kw_STNO I
    invokestatic coverage_sno_nodes/sno_stcount_tick()V
    ldc "A"
    invokestatic coverage_sno_nodes/sno_indr_get(Ljava/lang/String;)Ljava/lang/String;
    dup
    ifnonnull Lout_ok_3
    pop
    goto Lout_fail_3
Lout_ok_3:
    getstatic coverage_sno_nodes/sno_stdout Ljava/io/PrintStream;
    swap
    invokevirtual java/io/PrintStream/println(Ljava/lang/String;)V
Lout_fail_3:
    getstatic coverage_sno_nodes/sno_kw_STNO I
    iconst_1
    iadd
    putstatic coverage_sno_nodes/sno_kw_STNO I
    invokestatic coverage_sno_nodes/sno_stcount_tick()V
    ldc "ALPHABET"
    invokestatic coverage_sno_nodes/sno_kw_get(Ljava/lang/String;)Ljava/lang/String;
    dup
    ifnonnull Lout_ok_4
    pop
    goto Lout_fail_4
Lout_ok_4:
    getstatic coverage_sno_nodes/sno_stdout Ljava/io/PrintStream;
    swap
    invokevirtual java/io/PrintStream/println(Ljava/lang/String;)V
Lout_fail_4:
    getstatic coverage_sno_nodes/sno_kw_STNO I
    iconst_1
    iadd
    putstatic coverage_sno_nodes/sno_kw_STNO I
    invokestatic coverage_sno_nodes/sno_stcount_tick()V
    ldc "3"
    invokestatic coverage_sno_nodes/sno_to_double(Ljava/lang/String;)D
    ldc "4"
    invokestatic coverage_sno_nodes/sno_to_double(Ljava/lang/String;)D
    dadd
    dstore 2
    dload 2
    d2l
    lstore 4
    lload 4
    l2d
    dload 2
    dcmpl
    ifne Larf_0
    lload 4
    invokestatic java/lang/Long/toString(J)Ljava/lang/String;
    goto Lard_0
Larf_0:
    dload 2
    invokestatic java/lang/Double/toString(D)Ljava/lang/String;
Lard_0:
    dup
    ifnonnull Lout_ok_5
    pop
    goto Lout_fail_5
Lout_ok_5:
    getstatic coverage_sno_nodes/sno_stdout Ljava/io/PrintStream;
    swap
    invokevirtual java/io/PrintStream/println(Ljava/lang/String;)V
Lout_fail_5:
    getstatic coverage_sno_nodes/sno_kw_STNO I
    iconst_1
    iadd
    putstatic coverage_sno_nodes/sno_kw_STNO I
    invokestatic coverage_sno_nodes/sno_stcount_tick()V
    ldc "10"
    invokestatic coverage_sno_nodes/sno_to_double(Ljava/lang/String;)D
    ldc "3"
    invokestatic coverage_sno_nodes/sno_to_double(Ljava/lang/String;)D
    dsub
    dstore 2
    dload 2
    d2l
    lstore 4
    lload 4
    l2d
    dload 2
    dcmpl
    ifne Larf_1
    lload 4
    invokestatic java/lang/Long/toString(J)Ljava/lang/String;
    goto Lard_1
Larf_1:
    dload 2
    invokestatic java/lang/Double/toString(D)Ljava/lang/String;
Lard_1:
    dup
    ifnonnull Lout_ok_6
    pop
    goto Lout_fail_6
Lout_ok_6:
    getstatic coverage_sno_nodes/sno_stdout Ljava/io/PrintStream;
    swap
    invokevirtual java/io/PrintStream/println(Ljava/lang/String;)V
Lout_fail_6:
    getstatic coverage_sno_nodes/sno_kw_STNO I
    iconst_1
    iadd
    putstatic coverage_sno_nodes/sno_kw_STNO I
    invokestatic coverage_sno_nodes/sno_stcount_tick()V
    ldc "3"
    invokestatic coverage_sno_nodes/sno_to_double(Ljava/lang/String;)D
    ldc "4"
    invokestatic coverage_sno_nodes/sno_to_double(Ljava/lang/String;)D
    dmul
    dstore 2
    dload 2
    d2l
    lstore 4
    lload 4
    l2d
    dload 2
    dcmpl
    ifne Larf_2
    lload 4
    invokestatic java/lang/Long/toString(J)Ljava/lang/String;
    goto Lard_2
Larf_2:
    dload 2
    invokestatic java/lang/Double/toString(D)Ljava/lang/String;
Lard_2:
    dup
    ifnonnull Lout_ok_7
    pop
    goto Lout_fail_7
Lout_ok_7:
    getstatic coverage_sno_nodes/sno_stdout Ljava/io/PrintStream;
    swap
    invokevirtual java/io/PrintStream/println(Ljava/lang/String;)V
Lout_fail_7:
    getstatic coverage_sno_nodes/sno_kw_STNO I
    iconst_1
    iadd
    putstatic coverage_sno_nodes/sno_kw_STNO I
    invokestatic coverage_sno_nodes/sno_stcount_tick()V
    ldc "10"
    astore 6
    ldc "2"
    astore 7
    aload 6
    invokestatic coverage_sno_nodes/sno_is_integer(Ljava/lang/String;)Z
    ifeq Ldivf_0
    aload 7
    invokestatic coverage_sno_nodes/sno_is_integer(Ljava/lang/String;)Z
    ifeq Ldivf_0
    aload 6
    invokestatic java/lang/Long/parseLong(Ljava/lang/String;)J
    aload 7
    invokestatic java/lang/Long/parseLong(Ljava/lang/String;)J
    ldiv
    invokestatic java/lang/Long/toString(J)Ljava/lang/String;
    goto Ldivd_0
Ldivf_0:
    aload 6
    invokestatic coverage_sno_nodes/sno_to_double(Ljava/lang/String;)D
    aload 7
    invokestatic coverage_sno_nodes/sno_to_double(Ljava/lang/String;)D
    ddiv
    dstore 2
    dload 2
    d2l
    lstore 4
    lload 4
    l2d
    dload 2
    dcmpl
    ifne Ldivfr_0
    lload 4
    invokestatic java/lang/Long/toString(J)Ljava/lang/String;
    goto Ldivd_0
Ldivfr_0:
    dload 2
    invokestatic java/lang/Double/toString(D)Ljava/lang/String;
Ldivd_0:
    dup
    ifnonnull Lout_ok_8
    pop
    goto Lout_fail_8
Lout_ok_8:
    getstatic coverage_sno_nodes/sno_stdout Ljava/io/PrintStream;
    swap
    invokevirtual java/io/PrintStream/println(Ljava/lang/String;)V
Lout_fail_8:
    getstatic coverage_sno_nodes/sno_kw_STNO I
    iconst_1
    iadd
    putstatic coverage_sno_nodes/sno_kw_STNO I
    invokestatic coverage_sno_nodes/sno_stcount_tick()V
    ldc "5"
    invokestatic coverage_sno_nodes/sno_to_double(Ljava/lang/String;)D
    dneg
    dstore 2
    dload 2
    d2l
    lstore 4
    lload 4
    l2d
    dload 2
    dcmpl
    ifne Lmnsf_0
    lload 4
    invokestatic java/lang/Long/toString(J)Ljava/lang/String;
    goto Lmnsd_0
Lmnsf_0:
    dload 2
    invokestatic java/lang/Double/toString(D)Ljava/lang/String;
Lmnsd_0:
    dup
    ifnonnull Lvar_ok_2
    pop
    goto Lvar_fail_2
Lvar_ok_2:
    ldc "N"
    swap
    invokestatic coverage_sno_nodes/sno_var_put(Ljava/lang/String;Ljava/lang/String;)V
Lvar_fail_2:
    getstatic coverage_sno_nodes/sno_kw_STNO I
    iconst_1
    iadd
    putstatic coverage_sno_nodes/sno_kw_STNO I
    invokestatic coverage_sno_nodes/sno_stcount_tick()V
    ldc "N"
    invokestatic coverage_sno_nodes/sno_indr_get(Ljava/lang/String;)Ljava/lang/String;
    dup
    ifnonnull Lout_ok_9
    pop
    goto Lout_fail_9
Lout_ok_9:
    getstatic coverage_sno_nodes/sno_stdout Ljava/io/PrintStream;
    swap
    invokevirtual java/io/PrintStream/println(Ljava/lang/String;)V
Lout_fail_9:
    getstatic coverage_sno_nodes/sno_kw_STNO I
    iconst_1
    iadd
    putstatic coverage_sno_nodes/sno_kw_STNO I
    invokestatic coverage_sno_nodes/sno_stcount_tick()V
    ldc "2"
    invokestatic coverage_sno_nodes/sno_to_double(Ljava/lang/String;)D
    ldc "8"
    invokestatic coverage_sno_nodes/sno_to_double(Ljava/lang/String;)D
    invokestatic java/lang/Math/pow(DD)D
    dstore 2
    dload 2
    d2l
    lstore 4
    lload 4
    l2d
    dload 2
    dcmpl
    ifne Larf_3
    lload 4
    invokestatic java/lang/Long/toString(J)Ljava/lang/String;
    goto Lard_3
Larf_3:
    dload 2
    invokestatic java/lang/Double/toString(D)Ljava/lang/String;
Lard_3:
    dup
    ifnonnull Lout_ok_10
    pop
    goto Lout_fail_10
Lout_ok_10:
    getstatic coverage_sno_nodes/sno_stdout Ljava/io/PrintStream;
    swap
    invokevirtual java/io/PrintStream/println(Ljava/lang/String;)V
Lout_fail_10:
    getstatic coverage_sno_nodes/sno_kw_STNO I
    iconst_1
    iadd
    putstatic coverage_sno_nodes/sno_kw_STNO I
    invokestatic coverage_sno_nodes/sno_stcount_tick()V
    new java/lang/StringBuilder
    dup
    invokespecial java/lang/StringBuilder/<init>()V
    ldc "foo"
    dup
    ifnonnull Lconc_ok_0_0
    pop
    pop
    aconst_null
    goto Lconc_done_0
Lconc_ok_0_0:
    invokevirtual java/lang/StringBuilder/append(Ljava/lang/String;)Ljava/lang/StringBuilder;
    ldc "bar"
    dup
    ifnonnull Lconc_ok_0_1
    pop
    pop
    aconst_null
    goto Lconc_done_0
Lconc_ok_0_1:
    invokevirtual java/lang/StringBuilder/append(Ljava/lang/String;)Ljava/lang/StringBuilder;
    invokevirtual java/lang/StringBuilder/toString()Ljava/lang/String;
Lconc_done_0:
    dup
    ifnonnull Lout_ok_11
    pop
    goto Lout_fail_11
Lout_ok_11:
    getstatic coverage_sno_nodes/sno_stdout Ljava/io/PrintStream;
    swap
    invokevirtual java/io/PrintStream/println(Ljava/lang/String;)V
Lout_fail_11:
    getstatic coverage_sno_nodes/sno_kw_STNO I
    iconst_1
    iadd
    putstatic coverage_sno_nodes/sno_kw_STNO I
    invokestatic coverage_sno_nodes/sno_stcount_tick()V
    ldc "hello world"
    dup
    ifnonnull Lvar_ok_3
    pop
    goto Lvar_fail_3
Lvar_ok_3:
    ldc "S"
    swap
    invokestatic coverage_sno_nodes/sno_var_put(Ljava/lang/String;Ljava/lang/String;)V
Lvar_fail_3:
    getstatic coverage_sno_nodes/sno_kw_STNO I
    iconst_1
    iadd
    putstatic coverage_sno_nodes/sno_kw_STNO I
    invokestatic coverage_sno_nodes/sno_stcount_tick()V
; --- pattern match statement ---
    ldc "S"
    invokestatic coverage_sno_nodes/sno_indr_get(Ljava/lang/String;)Ljava/lang/String;
    astore 6
    iconst_0
    istore 7
    aload 6
    invokevirtual java/lang/String/length()I
    istore 8
Jpat0_retry:
    iload 7
    istore 9
    ; STUB: unhandled pattern node kind 44
    goto Jpat0_tok
Jpat0_tok:
    goto Jpat0_success
Jpat0_tfail:
    getstatic coverage_sno_nodes/sno_kw_ANCHOR I
    ifeq Jpat0_askip
    goto Jpat0_fail
Jpat0_askip:
    iinc 7 1
    iload 7
    iload 8
    if_icmple Jpat0_retry
    goto Jpat0_fail
Jpat0_success:
Jpat0_fail:
    getstatic coverage_sno_nodes/sno_kw_STNO I
    iconst_1
    iadd
    putstatic coverage_sno_nodes/sno_kw_STNO I
    invokestatic coverage_sno_nodes/sno_stcount_tick()V
    ldc "CAPT"
    invokestatic coverage_sno_nodes/sno_indr_get(Ljava/lang/String;)Ljava/lang/String;
    dup
    ifnonnull Lout_ok_12
    pop
    goto Lout_fail_12
Lout_ok_12:
    getstatic coverage_sno_nodes/sno_stdout Ljava/io/PrintStream;
    swap
    invokevirtual java/io/PrintStream/println(Ljava/lang/String;)V
Lout_fail_12:
    getstatic coverage_sno_nodes/sno_kw_STNO I
    iconst_1
    iadd
    putstatic coverage_sno_nodes/sno_kw_STNO I
    invokestatic coverage_sno_nodes/sno_stcount_tick()V
    ldc "abcd"
    dup
    ifnonnull Lvar_ok_4
    pop
    goto Lvar_fail_4
Lvar_ok_4:
    ldc "S2"
    swap
    invokestatic coverage_sno_nodes/sno_var_put(Ljava/lang/String;Ljava/lang/String;)V
Lvar_fail_4:
    getstatic coverage_sno_nodes/sno_kw_STNO I
    iconst_1
    iadd
    putstatic coverage_sno_nodes/sno_kw_STNO I
    invokestatic coverage_sno_nodes/sno_stcount_tick()V
; --- pattern match statement ---
    ldc "S2"
    invokestatic coverage_sno_nodes/sno_indr_get(Ljava/lang/String;)Ljava/lang/String;
    astore 6
    iconst_0
    istore 7
    aload 6
    invokevirtual java/lang/String/length()I
    istore 8
Jpat1_retry:
    iload 7
    istore 9
    aload 6
    iload 7
    ldc "ab"
    iconst_0
    ldc 2
    invokevirtual java/lang/String/regionMatches(ILjava/lang/String;II)Z
    ifeq Jpat1_tfail
    iinc 7 2
    goto Jn1_seq_mid
Jn1_seq_mid:
    aload 6
    iload 7
    ldc "cd"
    iconst_0
    ldc 2
    invokevirtual java/lang/String/regionMatches(ILjava/lang/String;II)Z
    ifeq Jpat1_tfail
    iinc 7 2
    goto Jpat1_tok
Jpat1_tok:
    goto Jpat1_success
Jpat1_tfail:
    getstatic coverage_sno_nodes/sno_kw_ANCHOR I
    ifeq Jpat1_askip
    goto Jpat1_fail
Jpat1_askip:
    iinc 7 1
    iload 7
    iload 8
    if_icmple Jpat1_retry
    goto Jpat1_fail
Jpat1_success:
Jpat1_fail:
    getstatic coverage_sno_nodes/sno_kw_STNO I
    iconst_1
    iadd
    putstatic coverage_sno_nodes/sno_kw_STNO I
    invokestatic coverage_sno_nodes/sno_stcount_tick()V
    ldc "seq ok"
    dup
    ifnonnull Lout_ok_13
    pop
    goto Lout_fail_13
Lout_ok_13:
    getstatic coverage_sno_nodes/sno_stdout Ljava/io/PrintStream;
    swap
    invokevirtual java/io/PrintStream/println(Ljava/lang/String;)V
Lout_fail_13:
    getstatic coverage_sno_nodes/sno_kw_STNO I
    iconst_1
    iadd
    putstatic coverage_sno_nodes/sno_kw_STNO I
    invokestatic coverage_sno_nodes/sno_stcount_tick()V
    ldc "cat"
    dup
    ifnonnull Lvar_ok_5
    pop
    goto Lvar_fail_5
Lvar_ok_5:
    ldc "S3"
    swap
    invokestatic coverage_sno_nodes/sno_var_put(Ljava/lang/String;Ljava/lang/String;)V
Lvar_fail_5:
    getstatic coverage_sno_nodes/sno_kw_STNO I
    iconst_1
    iadd
    putstatic coverage_sno_nodes/sno_kw_STNO I
    invokestatic coverage_sno_nodes/sno_stcount_tick()V
; --- pattern match statement ---
    ldc "S3"
    invokestatic coverage_sno_nodes/sno_indr_get(Ljava/lang/String;)Ljava/lang/String;
    astore 6
    iconst_0
    istore 7
    aload 6
    invokevirtual java/lang/String/length()I
    istore 8
Jpat2_retry:
    iload 7
    istore 9
    iload 7
    istore 10
    aload 6
    iload 7
    ldc "dog"
    iconst_0
    ldc 3
    invokevirtual java/lang/String/regionMatches(ILjava/lang/String;II)Z
    ifeq Jn4_alt_right
    iinc 7 3
    goto Jpat2_tok
Jn4_alt_right:
    iload 10
    istore 7
    aload 6
    iload 7
    ldc "cat"
    iconst_0
    ldc 3
    invokevirtual java/lang/String/regionMatches(ILjava/lang/String;II)Z
    ifeq Jpat2_tfail
    iinc 7 3
    goto Jpat2_tok
Jpat2_tok:
    goto Jpat2_success
Jpat2_tfail:
    getstatic coverage_sno_nodes/sno_kw_ANCHOR I
    ifeq Jpat2_askip
    goto Jpat2_fail
Jpat2_askip:
    iinc 7 1
    iload 7
    iload 8
    if_icmple Jpat2_retry
    goto Jpat2_fail
Jpat2_success:
Jpat2_fail:
    getstatic coverage_sno_nodes/sno_kw_STNO I
    iconst_1
    iadd
    putstatic coverage_sno_nodes/sno_kw_STNO I
    invokestatic coverage_sno_nodes/sno_stcount_tick()V
    ldc "alt ok"
    dup
    ifnonnull Lout_ok_14
    pop
    goto Lout_fail_14
Lout_ok_14:
    getstatic coverage_sno_nodes/sno_stdout Ljava/io/PrintStream;
    swap
    invokevirtual java/io/PrintStream/println(Ljava/lang/String;)V
Lout_fail_14:
    getstatic coverage_sno_nodes/sno_kw_STNO I
    iconst_1
    iadd
    putstatic coverage_sno_nodes/sno_kw_STNO I
    invokestatic coverage_sno_nodes/sno_stcount_tick()V
    ldc "hello"
    dup
    ifnonnull Lvar_ok_6
    pop
    goto Lvar_fail_6
Lvar_ok_6:
    ldc "S4"
    swap
    invokestatic coverage_sno_nodes/sno_var_put(Ljava/lang/String;Ljava/lang/String;)V
Lvar_fail_6:
    getstatic coverage_sno_nodes/sno_kw_STNO I
    iconst_1
    iadd
    putstatic coverage_sno_nodes/sno_kw_STNO I
    invokestatic coverage_sno_nodes/sno_stcount_tick()V
; --- pattern match statement ---
    ldc "S4"
    invokestatic coverage_sno_nodes/sno_indr_get(Ljava/lang/String;)Ljava/lang/String;
    astore 6
    iconst_0
    istore 7
    aload 6
    invokevirtual java/lang/String/length()I
    istore 8
Jpat3_retry:
    iload 7
    istore 9
    iload 7
    istore 10
    ldc "3"
    invokestatic java/lang/Integer/parseInt(Ljava/lang/String;)I
    istore 11
    iload 7
    iload 11
    iadd
    iload 8
    if_icmpgt Jpat3_tfail
    iload 7
    iload 11
    iadd
    istore 7
    goto Jn7_nam_ok
Jn7_nam_ok:
    ldc "PART"
    aload 6
    iload 10
    iload 7
    invokevirtual java/lang/String/substring(II)Ljava/lang/String;
    invokestatic coverage_sno_nodes/sno_var_put(Ljava/lang/String;Ljava/lang/String;)V
    goto Jpat3_tok
Jpat3_tok:
    goto Jpat3_success
Jpat3_tfail:
    getstatic coverage_sno_nodes/sno_kw_ANCHOR I
    ifeq Jpat3_askip
    goto Jpat3_fail
Jpat3_askip:
    iinc 7 1
    iload 7
    iload 8
    if_icmple Jpat3_retry
    goto Jpat3_fail
Jpat3_success:
Jpat3_fail:
    getstatic coverage_sno_nodes/sno_kw_STNO I
    iconst_1
    iadd
    putstatic coverage_sno_nodes/sno_kw_STNO I
    invokestatic coverage_sno_nodes/sno_stcount_tick()V
    ldc "PART"
    invokestatic coverage_sno_nodes/sno_indr_get(Ljava/lang/String;)Ljava/lang/String;
    dup
    ifnonnull Lout_ok_15
    pop
    goto Lout_fail_15
Lout_ok_15:
    getstatic coverage_sno_nodes/sno_stdout Ljava/io/PrintStream;
    swap
    invokevirtual java/io/PrintStream/println(Ljava/lang/String;)V
Lout_fail_15:
    getstatic coverage_sno_nodes/sno_kw_STNO I
    iconst_1
    iadd
    putstatic coverage_sno_nodes/sno_kw_STNO I
    invokestatic coverage_sno_nodes/sno_stcount_tick()V
    ldc "hello world"
    dup
    ifnonnull Lvar_ok_7
    pop
    goto Lvar_fail_7
Lvar_ok_7:
    ldc "S5"
    swap
    invokestatic coverage_sno_nodes/sno_var_put(Ljava/lang/String;Ljava/lang/String;)V
Lvar_fail_7:
    getstatic coverage_sno_nodes/sno_kw_STNO I
    iconst_1
    iadd
    putstatic coverage_sno_nodes/sno_kw_STNO I
    invokestatic coverage_sno_nodes/sno_stcount_tick()V
; --- pattern match statement ---
    ldc "S5"
    invokestatic coverage_sno_nodes/sno_indr_get(Ljava/lang/String;)Ljava/lang/String;
    astore 6
    iconst_0
    istore 7
    aload 6
    invokevirtual java/lang/String/length()I
    istore 8
Jpat4_retry:
    iload 7
    istore 9
    iload 7
    istore 10
    aload 6
    iload 7
    ldc "world"
    iconst_0
    ldc 5
    invokevirtual java/lang/String/regionMatches(ILjava/lang/String;II)Z
    ifeq Jpat4_tfail
    iinc 7 5
    goto Jn9_dol_ok
Jn9_dol_ok:
    ldc "TRAIL"
    aload 6
    iload 10
    iload 7
    invokevirtual java/lang/String/substring(II)Ljava/lang/String;
    invokestatic coverage_sno_nodes/sno_var_put(Ljava/lang/String;Ljava/lang/String;)V
    goto Jpat4_tok
Jpat4_tok:
    goto Jpat4_success
Jpat4_tfail:
    getstatic coverage_sno_nodes/sno_kw_ANCHOR I
    ifeq Jpat4_askip
    goto Jpat4_fail
Jpat4_askip:
    iinc 7 1
    iload 7
    iload 8
    if_icmple Jpat4_retry
    goto Jpat4_fail
Jpat4_success:
Jpat4_fail:
    getstatic coverage_sno_nodes/sno_kw_STNO I
    iconst_1
    iadd
    putstatic coverage_sno_nodes/sno_kw_STNO I
    invokestatic coverage_sno_nodes/sno_stcount_tick()V
    ldc "TRAIL"
    invokestatic coverage_sno_nodes/sno_indr_get(Ljava/lang/String;)Ljava/lang/String;
    dup
    ifnonnull Lout_ok_16
    pop
    goto Lout_fail_16
Lout_ok_16:
    getstatic coverage_sno_nodes/sno_stdout Ljava/io/PrintStream;
    swap
    invokevirtual java/io/PrintStream/println(Ljava/lang/String;)V
Lout_fail_16:
    getstatic coverage_sno_nodes/sno_kw_STNO I
    iconst_1
    iadd
    putstatic coverage_sno_nodes/sno_kw_STNO I
    invokestatic coverage_sno_nodes/sno_stcount_tick()V
    ldc "abcdef"
    dup
    ifnonnull Lvar_ok_8
    pop
    goto Lvar_fail_8
Lvar_ok_8:
    ldc "S6"
    swap
    invokestatic coverage_sno_nodes/sno_var_put(Ljava/lang/String;Ljava/lang/String;)V
Lvar_fail_8:
    getstatic coverage_sno_nodes/sno_kw_STNO I
    iconst_1
    iadd
    putstatic coverage_sno_nodes/sno_kw_STNO I
    invokestatic coverage_sno_nodes/sno_stcount_tick()V
; --- pattern match statement ---
    ldc "S6"
    invokestatic coverage_sno_nodes/sno_indr_get(Ljava/lang/String;)Ljava/lang/String;
    astore 6
    iconst_0
    istore 7
    aload 6
    invokevirtual java/lang/String/length()I
    istore 8
Jpat5_retry:
    iload 7
    istore 9
    ldc "abc"
    iload 7
    invokestatic java/lang/Integer/toString(I)Ljava/lang/String;
    invokestatic coverage_sno_nodes/sno_var_put(Ljava/lang/String;Ljava/lang/String;)V
    goto Jpat5_tok
Jpat5_tok:
    goto Jpat5_success
Jpat5_tfail:
    getstatic coverage_sno_nodes/sno_kw_ANCHOR I
    ifeq Jpat5_askip
    goto Jpat5_fail
Jpat5_askip:
    iinc 7 1
    iload 7
    iload 8
    if_icmple Jpat5_retry
    goto Jpat5_fail
Jpat5_success:
Jpat5_fail:
    getstatic coverage_sno_nodes/sno_kw_STNO I
    iconst_1
    iadd
    putstatic coverage_sno_nodes/sno_kw_STNO I
    invokestatic coverage_sno_nodes/sno_stcount_tick()V
    ldc "POS1"
    invokestatic coverage_sno_nodes/sno_indr_get(Ljava/lang/String;)Ljava/lang/String;
    dup
    ifnonnull Lout_ok_17
    pop
    goto Lout_fail_17
Lout_ok_17:
    getstatic coverage_sno_nodes/sno_stdout Ljava/io/PrintStream;
    swap
    invokevirtual java/io/PrintStream/println(Ljava/lang/String;)V
Lout_fail_17:
    getstatic coverage_sno_nodes/sno_kw_STNO I
    iconst_1
    iadd
    putstatic coverage_sno_nodes/sno_kw_STNO I
    invokestatic coverage_sno_nodes/sno_stcount_tick()V
    ldc "xaby"
    dup
    ifnonnull Lvar_ok_9
    pop
    goto Lvar_fail_9
Lvar_ok_9:
    ldc "S7"
    swap
    invokestatic coverage_sno_nodes/sno_var_put(Ljava/lang/String;Ljava/lang/String;)V
Lvar_fail_9:
    getstatic coverage_sno_nodes/sno_kw_STNO I
    iconst_1
    iadd
    putstatic coverage_sno_nodes/sno_kw_STNO I
    invokestatic coverage_sno_nodes/sno_stcount_tick()V
; --- pattern match statement ---
    ldc "S7"
    invokestatic coverage_sno_nodes/sno_indr_get(Ljava/lang/String;)Ljava/lang/String;
    astore 6
    iconst_0
    istore 7
    aload 6
    invokevirtual java/lang/String/length()I
    istore 8
Jpat6_retry:
    iload 7
    istore 9
Jn12_arb_loop:
    iload 7
    istore 10
    ldc 0
    istore 11
Jn12_arb_retry:
    iload 10
    iload 11
    iadd
    iload 8
    if_icmpgt Jpat6_tfail
    iload 10
    iload 11
    iadd
    istore 7
    aload 6
    iload 7
    ldc "b"
    iconst_0
    ldc 1
    invokevirtual java/lang/String/regionMatches(ILjava/lang/String;II)Z
    ifeq Jn12_arb_decr
    iinc 7 1
    goto Jpat6_tok
Jn12_arb_decr:
    iinc 11 1
    goto Jn12_arb_retry
Jpat6_tok:
    goto Jpat6_success
Jpat6_tfail:
    getstatic coverage_sno_nodes/sno_kw_ANCHOR I
    ifeq Jpat6_askip
    goto Jpat6_fail
Jpat6_askip:
    iinc 7 1
    iload 7
    iload 8
    if_icmple Jpat6_retry
    goto Jpat6_fail
Jpat6_success:
Jpat6_fail:
    getstatic coverage_sno_nodes/sno_kw_STNO I
    iconst_1
    iadd
    putstatic coverage_sno_nodes/sno_kw_STNO I
    invokestatic coverage_sno_nodes/sno_stcount_tick()V
    ldc "arb ok"
    dup
    ifnonnull Lout_ok_18
    pop
    goto Lout_fail_18
Lout_ok_18:
    getstatic coverage_sno_nodes/sno_stdout Ljava/io/PrintStream;
    swap
    invokevirtual java/io/PrintStream/println(Ljava/lang/String;)V
Lout_fail_18:
    getstatic coverage_sno_nodes/sno_kw_STNO I
    iconst_1
    iadd
    putstatic coverage_sno_nodes/sno_kw_STNO I
    invokestatic coverage_sno_nodes/sno_stcount_tick()V
    ldc "aaab"
    dup
    ifnonnull Lvar_ok_10
    pop
    goto Lvar_fail_10
Lvar_ok_10:
    ldc "S8"
    swap
    invokestatic coverage_sno_nodes/sno_var_put(Ljava/lang/String;Ljava/lang/String;)V
Lvar_fail_10:
    getstatic coverage_sno_nodes/sno_kw_STNO I
    iconst_1
    iadd
    putstatic coverage_sno_nodes/sno_kw_STNO I
    invokestatic coverage_sno_nodes/sno_stcount_tick()V
; --- pattern match statement ---
    ldc "S8"
    invokestatic coverage_sno_nodes/sno_indr_get(Ljava/lang/String;)Ljava/lang/String;
    astore 6
    iconst_0
    istore 7
    aload 6
    invokevirtual java/lang/String/length()I
    istore 8
Jpat7_retry:
    iload 7
    istore 9
Jn15_arb_loop:
    iload 7
    istore 10
    aload 6
    iload 7
    ldc "a"
    iconst_0
    ldc 1
    invokevirtual java/lang/String/regionMatches(ILjava/lang/String;II)Z
    ifeq Jn15_arb_cfail
    iinc 7 1
    goto Jn15_arb_cok
Jn15_arb_cok:
    iload 7
    iload 10
    if_icmpeq Jn15_arb_done
    goto Jn15_arb_loop
Jn15_arb_cfail:
    iload 10
    istore 7
Jn15_arb_done:
    goto Jn14_seq_mid
Jn14_seq_mid:
    aload 6
    iload 7
    ldc "b"
    iconst_0
    ldc 1
    invokevirtual java/lang/String/regionMatches(ILjava/lang/String;II)Z
    ifeq Jpat7_tfail
    iinc 7 1
    goto Jpat7_tok
Jpat7_tok:
    goto Jpat7_success
Jpat7_tfail:
    getstatic coverage_sno_nodes/sno_kw_ANCHOR I
    ifeq Jpat7_askip
    goto Jpat7_fail
Jpat7_askip:
    iinc 7 1
    iload 7
    iload 8
    if_icmple Jpat7_retry
    goto Jpat7_fail
Jpat7_success:
Jpat7_fail:
    getstatic coverage_sno_nodes/sno_kw_STNO I
    iconst_1
    iadd
    putstatic coverage_sno_nodes/sno_kw_STNO I
    invokestatic coverage_sno_nodes/sno_stcount_tick()V
    ldc "arbno ok"
    dup
    ifnonnull Lout_ok_19
    pop
    goto Lout_fail_19
Lout_ok_19:
    getstatic coverage_sno_nodes/sno_stdout Ljava/io/PrintStream;
    swap
    invokevirtual java/io/PrintStream/println(Ljava/lang/String;)V
Lout_fail_19:
    getstatic coverage_sno_nodes/sno_kw_STNO I
    iconst_1
    iadd
    putstatic coverage_sno_nodes/sno_kw_STNO I
    invokestatic coverage_sno_nodes/sno_stcount_tick()V
    ldc ""
    dup
    ifnonnull Lvar_ok_11
    pop
    goto Lvar_fail_11
Lvar_ok_11:
    ldc "PAT"
    swap
    invokestatic coverage_sno_nodes/sno_var_put(Ljava/lang/String;Ljava/lang/String;)V
Lvar_fail_11:
    getstatic coverage_sno_nodes/sno_kw_STNO I
    iconst_1
    iadd
    putstatic coverage_sno_nodes/sno_kw_STNO I
    invokestatic coverage_sno_nodes/sno_stcount_tick()V
    ldc "abcd"
    dup
    ifnonnull Lvar_ok_12
    pop
    goto Lvar_fail_12
Lvar_ok_12:
    ldc "S9"
    swap
    invokestatic coverage_sno_nodes/sno_var_put(Ljava/lang/String;Ljava/lang/String;)V
Lvar_fail_12:
    getstatic coverage_sno_nodes/sno_kw_STNO I
    iconst_1
    iadd
    putstatic coverage_sno_nodes/sno_kw_STNO I
    invokestatic coverage_sno_nodes/sno_stcount_tick()V
; --- pattern match statement ---
    ldc "S9"
    invokestatic coverage_sno_nodes/sno_indr_get(Ljava/lang/String;)Ljava/lang/String;
    astore 6
    iconst_0
    istore 7
    aload 6
    invokevirtual java/lang/String/length()I
    istore 8
Jpat8_retry:
    iload 7
    istore 9
    ; STUB: unhandled pattern node kind 8
    goto Jpat8_tok
Jpat8_tok:
    goto Jpat8_success
Jpat8_tfail:
    getstatic coverage_sno_nodes/sno_kw_ANCHOR I
    ifeq Jpat8_askip
    goto Jpat8_fail
Jpat8_askip:
    iinc 7 1
    iload 7
    iload 8
    if_icmple Jpat8_retry
    goto Jpat8_fail
Jpat8_success:
Jpat8_fail:
    getstatic coverage_sno_nodes/sno_kw_STNO I
    iconst_1
    iadd
    putstatic coverage_sno_nodes/sno_kw_STNO I
    invokestatic coverage_sno_nodes/sno_stcount_tick()V
    ldc "star ok"
    dup
    ifnonnull Lout_ok_20
    pop
    goto Lout_fail_20
Lout_ok_20:
    getstatic coverage_sno_nodes/sno_stdout Ljava/io/PrintStream;
    swap
    invokevirtual java/io/PrintStream/println(Ljava/lang/String;)V
Lout_fail_20:
    getstatic coverage_sno_nodes/sno_kw_STNO I
    iconst_1
    iadd
    putstatic coverage_sno_nodes/sno_kw_STNO I
    invokestatic coverage_sno_nodes/sno_stcount_tick()V
    ldc "A"
    dup
    ifnonnull Lvar_ok_13
    pop
    goto Lvar_fail_13
Lvar_ok_13:
    ldc "VNAME"
    swap
    invokestatic coverage_sno_nodes/sno_var_put(Ljava/lang/String;Ljava/lang/String;)V
Lvar_fail_13:
    getstatic coverage_sno_nodes/sno_kw_STNO I
    iconst_1
    iadd
    putstatic coverage_sno_nodes/sno_kw_STNO I
    invokestatic coverage_sno_nodes/sno_stcount_tick()V
    ldc "VNAME"
    invokestatic coverage_sno_nodes/sno_indr_get(Ljava/lang/String;)Ljava/lang/String;
    invokestatic coverage_sno_nodes/sno_indr_get(Ljava/lang/String;)Ljava/lang/String;
    dup
    ifnonnull Lout_ok_21
    pop
    goto Lout_fail_21
Lout_ok_21:
    getstatic coverage_sno_nodes/sno_stdout Ljava/io/PrintStream;
    swap
    invokevirtual java/io/PrintStream/println(Ljava/lang/String;)V
Lout_fail_21:
    getstatic coverage_sno_nodes/sno_kw_STNO I
    iconst_1
    iadd
    putstatic coverage_sno_nodes/sno_kw_STNO I
    invokestatic coverage_sno_nodes/sno_stcount_tick()V
    ldc "hello"
    invokevirtual java/lang/String/length()I
    i2l
    invokestatic java/lang/Long/toString(J)Ljava/lang/String;
    dup
    ifnonnull Lout_ok_22
    pop
    goto Lout_fail_22
Lout_ok_22:
    getstatic coverage_sno_nodes/sno_stdout Ljava/io/PrintStream;
    swap
    invokevirtual java/io/PrintStream/println(Ljava/lang/String;)V
Lout_fail_22:
    getstatic coverage_sno_nodes/sno_kw_STNO I
    iconst_1
    iadd
    putstatic coverage_sno_nodes/sno_kw_STNO I
    invokestatic coverage_sno_nodes/sno_stcount_tick()V
    invokestatic coverage_sno_nodes/sno_table_new()Ljava/lang/String;
    dup
    ifnonnull Lvar_ok_14
    pop
    goto Lvar_fail_14
Lvar_ok_14:
    ldc "T"
    swap
    invokestatic coverage_sno_nodes/sno_var_put(Ljava/lang/String;Ljava/lang/String;)V
Lvar_fail_14:
    getstatic coverage_sno_nodes/sno_kw_STNO I
    iconst_1
    iadd
    putstatic coverage_sno_nodes/sno_kw_STNO I
    invokestatic coverage_sno_nodes/sno_stcount_tick()V
    ldc "T"
    invokestatic coverage_sno_nodes/sno_indr_get(Ljava/lang/String;)Ljava/lang/String;
    ldc "key"
    ldc "val"
    invokestatic coverage_sno_nodes/sno_array_put(Ljava/lang/String;Ljava/lang/String;Ljava/lang/String;)V
; unhandled stmt form
    nop
    getstatic coverage_sno_nodes/sno_kw_STNO I
    iconst_1
    iadd
    putstatic coverage_sno_nodes/sno_kw_STNO I
    invokestatic coverage_sno_nodes/sno_stcount_tick()V
    ldc "T"
    invokestatic coverage_sno_nodes/sno_indr_get(Ljava/lang/String;)Ljava/lang/String;
    ldc "key"
    invokestatic coverage_sno_nodes/sno_array_get(Ljava/lang/String;Ljava/lang/String;)Ljava/lang/String;
    dup
    ifnonnull Lout_ok_23
    pop
    goto Lout_fail_23
Lout_ok_23:
    getstatic coverage_sno_nodes/sno_stdout Ljava/io/PrintStream;
    swap
    invokevirtual java/io/PrintStream/println(Ljava/lang/String;)V
Lout_fail_23:
    getstatic coverage_sno_nodes/sno_kw_STNO I
    iconst_1
    iadd
    putstatic coverage_sno_nodes/sno_kw_STNO I
    invokestatic coverage_sno_nodes/sno_stcount_tick()V
    ldc "UNDEF"
    invokestatic coverage_sno_nodes/sno_indr_get(Ljava/lang/String;)Ljava/lang/String;
    dup
    ifnonnull Lident_n_0
    pop
    ldc ""
Lident_n_0:
    ldc ""
    dup
    ifnonnull Lident_n2_0
    pop
    ldc ""
Lident_n2_0:
    invokevirtual java/lang/String/equals(Ljava/lang/Object;)Z
    ifeq Lident_f_0
    ldc "UNDEF"
    invokestatic coverage_sno_nodes/sno_indr_get(Ljava/lang/String;)Ljava/lang/String;
    dup
    ifnonnull Lident_n3_0
    pop
    ldc ""
Lident_n3_0:
    goto Lident_d_0
Lident_f_0:
    aconst_null
Lident_d_0:
    dup
    ifnonnull Lout_ok_24
    pop
    goto Lout_fail_24
Lout_ok_24:
    getstatic coverage_sno_nodes/sno_stdout Ljava/io/PrintStream;
    swap
    invokevirtual java/io/PrintStream/println(Ljava/lang/String;)V
    goto L_NULLOK
Lout_fail_24:
    getstatic coverage_sno_nodes/sno_kw_STNO I
    iconst_1
    iadd
    putstatic coverage_sno_nodes/sno_kw_STNO I
    invokestatic coverage_sno_nodes/sno_stcount_tick()V
    ldc "not null"
    dup
    ifnonnull Lout_ok_25
    pop
    goto Lout_fail_25
Lout_ok_25:
    getstatic coverage_sno_nodes/sno_stdout Ljava/io/PrintStream;
    swap
    invokevirtual java/io/PrintStream/println(Ljava/lang/String;)V
    goto L_DONE
Lout_fail_25:
    goto L_DONE
; === NULLOK ==========================================================
L_NULLOK:
    getstatic coverage_sno_nodes/sno_kw_STNO I
    iconst_1
    iadd
    putstatic coverage_sno_nodes/sno_kw_STNO I
    invokestatic coverage_sno_nodes/sno_stcount_tick()V
    ldc "null ok"
    dup
    ifnonnull Lout_ok_26
    pop
    goto Lout_fail_26
Lout_ok_26:
    getstatic coverage_sno_nodes/sno_stdout Ljava/io/PrintStream;
    swap
    invokevirtual java/io/PrintStream/println(Ljava/lang/String;)V
Lout_fail_26:
; === DONE ============================================================
L_DONE:
    getstatic coverage_sno_nodes/sno_kw_STNO I
    iconst_1
    iadd
    putstatic coverage_sno_nodes/sno_kw_STNO I
    invokestatic coverage_sno_nodes/sno_stcount_tick()V
    ldc ""
    pop
    getstatic coverage_sno_nodes/sno_kw_STNO I
    iconst_1
    iadd
    putstatic coverage_sno_nodes/sno_kw_STNO I
    invokestatic coverage_sno_nodes/sno_stcount_tick()V
    ldc ""
    dup
    ifnonnull Lout_ok_27
    pop
    goto Lout_fail_27
Lout_ok_27:
    getstatic coverage_sno_nodes/sno_stdout Ljava/io/PrintStream;
    swap
    invokevirtual java/io/PrintStream/println(Ljava/lang/String;)V
Lout_fail_27:
; === END =============================================================
L_END:
    nop
; program end
    return
.end method
.method static sno_to_double(Ljava/lang/String;)D
    .limit stack 4
    .limit locals 1
    aload_0
    ifnull Lsno_pd_zero
    aload_0
    invokevirtual java/lang/String/trim()Ljava/lang/String;
    invokevirtual java/lang/String/isEmpty()Z
    ifne Lsno_pd_zero
    aload_0
    invokestatic java/lang/Double/parseDouble(Ljava/lang/String;)D
    dreturn
Lsno_pd_zero:
    dconst_0
    dreturn
.end method

.method static sno_str_eq(Ljava/lang/String;Ljava/lang/String;)Z
    .limit stack 4
    .limit locals 2
    aload_0
    ifnull Lstreq_false
    aload_1
    ifnull Lstreq_false
    aload_0
    aload_1
    invokevirtual java/lang/String/equalsIgnoreCase(Ljava/lang/String;)Z
    ireturn
Lstreq_false:
    iconst_0
    ireturn
.end method

.method static sno_kw_get(Ljava/lang/String;)Ljava/lang/String;
    .limit stack 4
    .limit locals 3
    aload_0
    ldc "ALPHABET"
    invokevirtual java/lang/String/equalsIgnoreCase(Ljava/lang/String;)Z
    ifeq Lkwg_not_alphabet
    new java/lang/StringBuilder
    dup
    invokespecial java/lang/StringBuilder/<init>()V
    astore_1
    iconst_0
    istore_2
Lkwg_alpha_loop:
    iload_2
    sipush 256
    if_icmpge Lkwg_alpha_done
    aload_1
    iload_2
    i2c
    invokevirtual java/lang/StringBuilder/append(C)Ljava/lang/StringBuilder;
    pop
    iinc 2 1
    goto Lkwg_alpha_loop
Lkwg_alpha_done:
    aload_1
    invokevirtual java/lang/StringBuilder/toString()Ljava/lang/String;
    areturn
Lkwg_not_alphabet:
    aload_0
    ldc "UCASE"
    invokevirtual java/lang/String/equalsIgnoreCase(Ljava/lang/String;)Z
    ifeq Lkwg_not_ucase
    ldc "ABCDEFGHIJKLMNOPQRSTUVWXYZ"
    areturn
Lkwg_not_ucase:
    aload_0
    ldc "LCASE"
    invokevirtual java/lang/String/equalsIgnoreCase(Ljava/lang/String;)Z
    ifeq Lkwg_not_lcase
    ldc "abcdefghijklmnopqrstuvwxyz"
    areturn
Lkwg_not_lcase:
    aload_0
    ldc "STNO"
    invokevirtual java/lang/String/equalsIgnoreCase(Ljava/lang/String;)Z
    ifeq Lkwg_not_stno
    getstatic coverage_sno_nodes/sno_kw_STNO I
    invokestatic java/lang/Integer/toString(I)Ljava/lang/String;
    areturn
Lkwg_not_stno:
    aload_0
    ldc "TRIM"
    invokevirtual java/lang/String/equalsIgnoreCase(Ljava/lang/String;)Z
    ifeq Lkwg_not_trim
    getstatic coverage_sno_nodes/sno_kw_TRIM I
    invokestatic java/lang/Integer/toString(I)Ljava/lang/String;
    areturn
Lkwg_not_trim:
    aload_0
    ldc "ANCHOR"
    invokevirtual java/lang/String/equalsIgnoreCase(Ljava/lang/String;)Z
    ifeq Lkwg_not_anchor
    getstatic coverage_sno_nodes/sno_kw_ANCHOR I
    invokestatic java/lang/Integer/toString(I)Ljava/lang/String;
    areturn
Lkwg_not_anchor:
    aload_0
    ldc "STLIMIT"
    invokevirtual java/lang/String/equalsIgnoreCase(Ljava/lang/String;)Z
    ifeq Lkwg_not_stlimit
    getstatic coverage_sno_nodes/sno_kw_STLIMIT I
    invokestatic java/lang/Integer/toString(I)Ljava/lang/String;
    areturn
Lkwg_not_stlimit:
    aload_0
    ldc "STCOUNT"
    invokevirtual java/lang/String/equalsIgnoreCase(Ljava/lang/String;)Z
    ifeq Lkwg_not_stcount
    getstatic coverage_sno_nodes/sno_kw_STCOUNT I
    invokestatic java/lang/Integer/toString(I)Ljava/lang/String;
    areturn
Lkwg_not_stcount:
    ldc ""
    areturn
.end method

.method static sno_kw_set(Ljava/lang/String;Ljava/lang/String;)V
    .limit stack 4
    .limit locals 2
    aload_0
    ldc "TRIM"
    invokevirtual java/lang/String/equalsIgnoreCase(Ljava/lang/String;)Z
    ifeq Lkws_not_trim
    aload_1
    invokestatic java/lang/Integer/parseInt(Ljava/lang/String;)I
    putstatic coverage_sno_nodes/sno_kw_TRIM I
    return
Lkws_not_trim:
    aload_0
    ldc "ANCHOR"
    invokevirtual java/lang/String/equalsIgnoreCase(Ljava/lang/String;)Z
    ifeq Lkws_not_anchor
    aload_1
    invokestatic java/lang/Integer/parseInt(Ljava/lang/String;)I
    putstatic coverage_sno_nodes/sno_kw_ANCHOR I
    return
Lkws_not_anchor:
    aload_0
    ldc "STNO"
    invokevirtual java/lang/String/equalsIgnoreCase(Ljava/lang/String;)Z
    ifeq Lkws_not_stno
    aload_1
    invokestatic java/lang/Integer/parseInt(Ljava/lang/String;)I
    putstatic coverage_sno_nodes/sno_kw_STNO I
    return
Lkws_not_stno:
    aload_0
    ldc "STLIMIT"
    invokevirtual java/lang/String/equalsIgnoreCase(Ljava/lang/String;)Z
    ifeq Lkws_not_stlimit
    aload_1
    invokestatic java/lang/Integer/parseInt(Ljava/lang/String;)I
    putstatic coverage_sno_nodes/sno_kw_STLIMIT I
    return
Lkws_not_stlimit:
    aload_0
    ldc "STCOUNT"
    invokevirtual java/lang/String/equalsIgnoreCase(Ljava/lang/String;)Z
    ifeq Lkws_not_stcount
    aload_1
    invokestatic java/lang/Integer/parseInt(Ljava/lang/String;)I
    putstatic coverage_sno_nodes/sno_kw_STCOUNT I
    return
Lkws_not_stcount:
    return
.end method

.method static sno_var_put(Ljava/lang/String;Ljava/lang/String;)V
    .limit stack 4
    .limit locals 2
    aload_0
    ldc "OUTPUT"
    invokevirtual java/lang/String/equalsIgnoreCase(Ljava/lang/String;)Z
    ifeq Lsvp_not_output
    getstatic coverage_sno_nodes/sno_stdout Ljava/io/PrintStream;
    aload_1
    invokevirtual java/io/PrintStream/println(Ljava/lang/String;)V
    return
Lsvp_not_output:
    getstatic coverage_sno_nodes/sno_vars Ljava/util/HashMap;
    aload_0
    aload_1
    invokevirtual java/util/HashMap/put(Ljava/lang/Object;Ljava/lang/Object;)Ljava/lang/Object;
    pop
    aload_0
    aload_1
    invokestatic coverage_sno_nodes/sno_mon_var(Ljava/lang/String;Ljava/lang/String;)V
    return
.end method

.method static sno_mon_var(Ljava/lang/String;Ljava/lang/String;)V
    .limit stack 6
    .limit locals 3
    getstatic coverage_sno_nodes/sno_mon_fd Ljava/io/OutputStream;
    ifnull Lsmv_done
    new java/lang/StringBuilder
    dup
    invokespecial java/lang/StringBuilder/<init>()V
    ldc "VALUE"
    invokevirtual java/lang/StringBuilder/append(Ljava/lang/String;)Ljava/lang/StringBuilder;
    bipush 30
    invokevirtual java/lang/StringBuilder/append(C)Ljava/lang/StringBuilder;
    aload_0
    invokevirtual java/lang/StringBuilder/append(Ljava/lang/String;)Ljava/lang/StringBuilder;
    bipush 31
    invokevirtual java/lang/StringBuilder/append(C)Ljava/lang/StringBuilder;
    aload_1
    invokevirtual java/lang/StringBuilder/append(Ljava/lang/String;)Ljava/lang/StringBuilder;
    bipush 30
    invokevirtual java/lang/StringBuilder/append(C)Ljava/lang/StringBuilder;
    invokevirtual java/lang/StringBuilder/toString()Ljava/lang/String;
    ldc "UTF-8"
    invokevirtual java/lang/String/getBytes(Ljava/lang/String;)[B
    astore_2
    getstatic coverage_sno_nodes/sno_mon_fd Ljava/io/OutputStream;
    aload_2
    invokevirtual java/io/OutputStream/write([B)V
    getstatic coverage_sno_nodes/sno_mon_go_fd Ljava/io/InputStream;
    ifnull Lsmv_done
    getstatic coverage_sno_nodes/sno_mon_go_fd Ljava/io/InputStream;
    invokevirtual java/io/InputStream/read()I
    istore_2
    iload_2
    bipush 71
    if_icmpeq Lsmv_done
    iconst_0
    invokestatic SnoRuntime/sno_exit(I)V
Lsmv_done:
    return
.end method

.method static sno_stcount_tick()V
    .limit stack 4
    .limit locals 0
    getstatic coverage_sno_nodes/sno_kw_STCOUNT I
    iconst_1
    iadd
    putstatic coverage_sno_nodes/sno_kw_STCOUNT I
    getstatic coverage_sno_nodes/sno_kw_STLIMIT I
    iflt Lstick_ok
    getstatic coverage_sno_nodes/sno_kw_STCOUNT I
    getstatic coverage_sno_nodes/sno_kw_STLIMIT I
    if_icmple Lstick_ok
    getstatic java/lang/System/err Ljava/io/PrintStream;
    ldc "Termination: statement limit"
    invokevirtual java/io/PrintStream/println(Ljava/lang/String;)V
    iconst_1
    invokestatic SnoRuntime/sno_exit(I)V
Lstick_ok:
    return
.end method

.method static sno_indr_get(Ljava/lang/String;)Ljava/lang/String;
    .limit stack 4
    .limit locals 1
    getstatic coverage_sno_nodes/sno_vars Ljava/util/HashMap;
    aload_0
    invokevirtual java/util/HashMap/get(Ljava/lang/Object;)Ljava/lang/Object;
    checkcast java/lang/String
    dup
    ifnonnull Lsig_done_indr
    pop
    ldc ""
Lsig_done_indr:
    areturn
.end method

.method static sno_indr_set(Ljava/lang/String;Ljava/lang/String;)V
    .limit stack 4
    .limit locals 2
    getstatic coverage_sno_nodes/sno_vars Ljava/util/HashMap;
    aload_0
    aload_1
    invokevirtual java/util/HashMap/put(Ljava/lang/Object;Ljava/lang/Object;)Ljava/lang/Object;
    pop
    return
.end method

.method static sno_is_integer(Ljava/lang/String;)Z
    .limit stack 4
    .limit locals 1
    aload_0
    ifnull Lisi_false
    aload_0
    invokevirtual java/lang/String/trim()Ljava/lang/String;
    invokevirtual java/lang/String/isEmpty()Z
    ifne Lisi_false
    aload_0
    invokevirtual java/lang/String/trim()Ljava/lang/String;
    ldc "-?[0-9]+"
    invokevirtual java/lang/String/matches(Ljava/lang/String;)Z
    ireturn
Lisi_false:
    iconst_0
    ireturn
.end method

.method static sno_array_new(Ljava/lang/String;)Ljava/lang/String;
    .limit stack 6
    .limit locals 2
    new java/util/HashMap
    dup
    invokespecial java/util/HashMap/<init>()V
    astore_1
    aload_1
    invokestatic java/lang/System/identityHashCode(Ljava/lang/Object;)I
    invokestatic java/lang/Integer/toString(I)Ljava/lang/String;
    dup
    getstatic coverage_sno_nodes/sno_arrays Ljava/util/HashMap;
    swap
    aload_1
    invokevirtual java/util/HashMap/put(Ljava/lang/Object;Ljava/lang/Object;)Ljava/lang/Object;
    pop
    areturn
.end method

.method static sno_array_new2(Ljava/lang/String;Ljava/lang/String;)Ljava/lang/String;
    .limit stack 8
    .limit locals 6
    new java/util/HashMap
    dup
    invokespecial java/util/HashMap/<init>()V
    astore_2
    aload_2
    invokestatic java/lang/System/identityHashCode(Ljava/lang/Object;)I
    invokestatic java/lang/Integer/toString(I)Ljava/lang/String;
    astore_3
    getstatic coverage_sno_nodes/sno_arrays Ljava/util/HashMap;
    aload_3
    aload_2
    invokevirtual java/util/HashMap/put(Ljava/lang/Object;Ljava/lang/Object;)Ljava/lang/Object;
    pop
    aload_0
    invokestatic java/lang/Double/parseDouble(Ljava/lang/String;)D
    d2i
    istore 4
    aload_1
    invokevirtual java/lang/String/isEmpty()Z
    ifne La2_done
    iconst_1
    istore 5
La2_loop:
    iload 5
    iload 4
    if_icmpgt La2_done
    aload_2
    iload 5
    invokestatic java/lang/Integer/toString(I)Ljava/lang/String;
    aload_1
    invokevirtual java/util/HashMap/put(Ljava/lang/Object;Ljava/lang/Object;)Ljava/lang/Object;
    pop
    iinc 5 1
    goto La2_loop
La2_done:
    aload_3
    areturn
.end method

.method static sno_table_new()Ljava/lang/String;
    .limit stack 6
    .limit locals 2
    new java/util/HashMap
    dup
    invokespecial java/util/HashMap/<init>()V
    astore_0
    aload_0
    invokestatic java/lang/System/identityHashCode(Ljava/lang/Object;)I
    invokestatic java/lang/Integer/toString(I)Ljava/lang/String;
    dup
    getstatic coverage_sno_nodes/sno_arrays Ljava/util/HashMap;
    swap
    aload_0
    invokevirtual java/util/HashMap/put(Ljava/lang/Object;Ljava/lang/Object;)Ljava/lang/Object;
    pop
    areturn
.end method

.method static sno_array_get(Ljava/lang/String;Ljava/lang/String;)Ljava/lang/String;
    .limit stack 4
    .limit locals 3
    getstatic coverage_sno_nodes/sno_arrays Ljava/util/HashMap;
    aload_0
    invokevirtual java/util/HashMap/get(Ljava/lang/Object;)Ljava/lang/Object;
    checkcast java/util/HashMap
    astore_2
    aload_2
    ifnull Lag_null
    aload_2
    aload_1
    invokevirtual java/util/HashMap/get(Ljava/lang/Object;)Ljava/lang/Object;
    checkcast java/lang/String
    areturn
Lag_null:
    aconst_null
    areturn
.end method

.method static sno_array_put(Ljava/lang/String;Ljava/lang/String;Ljava/lang/String;)V
    .limit stack 4
    .limit locals 4
    getstatic coverage_sno_nodes/sno_arrays Ljava/util/HashMap;
    aload_0
    invokevirtual java/util/HashMap/get(Ljava/lang/Object;)Ljava/lang/Object;
    checkcast java/util/HashMap
    astore_3
    aload_3
    ifnull Lap_done
    aload_3
    aload_1
    aload_2
    invokevirtual java/util/HashMap/put(Ljava/lang/Object;Ljava/lang/Object;)Ljava/lang/Object;
    pop
Lap_done:
    return
.end method

